Workbook

Sheet 使い方
B2: SQLフォルダパス
B3: T:\運用作業\0230.年次\年度繁忙進捗集計クエリv2.1
B5: クエリ実行後、「SQLデータ」シートのA1セルに貼り付け

Sheet SQLデータ
A1: 申請番号 | B1: 申請職員番号 | C1: 申請日 | D1: 申請種別 | E1: ステータス | F1: 案件状況 | G1: 届出事由 | H1: 届出事由区分 | I1: 扶養手当 | J1: 共済 | K1: 税控除 | L1: 共済ありフラグ | M1: 扶養ありフラグ | N1: 税のみフラグ | O1: 本人税のみフラグ | P1: 集計対象フラグ | Q1: 責任職対象外 | R1: 一般職対象外
A2: 202510000793 | B2: 1111083 | C2: 45866 | D2: 給与口座 | E2: ＯＰ確認中 | F2: 添付待ち | G2: NULL | L2: =IF(ISBLANK(J2),0,1) -> 0 | M2: =IF(AND(L2=0,I2<>""),1,0) -> 0 | N2: =IF(AND(L2=0,M2=0,K2<>""),1,0) -> 0 | O2: =IF(COUNTIF(L2:N2,0)=3,1,0) -> 1 | P2: =IF(D2<>"扶養","",IF(E2<>"確認待ち",1,IF(OR(AND(G2="本人の結婚",O2=1),AND(H2="減",OR(N2=1,O2=1))),1,0))) | Q2: =COUNTIF('責任職 企業局→市長部局'!A:A,SQLデータ!B2) -> 0 | R2: =COUNTIF('一般職員 企業局→市長部局'!A:F,SQLデータ!B2) -> 0
A3: 202510001619 | B3: 1122110 | C3: 46016 | D3: 給与口座 | E3: ＳＶ確認中 | F3: オペレータ保留 | G3: NULL | L3: =IF(ISBLANK(J3),0,1) -> 0 | M3: =IF(AND(L3=0,I3<>""),1,0) -> 0 | N3: =IF(AND(L3=0,M3=0,K3<>""),1,0) -> 0 | O3: =IF(COUNTIF(L3:N3,0)=3,1,0) -> 1 | P3: =IF(D3<>"扶養","",IF(E3<>"確認待ち",1,IF(OR(AND(G3="本人の結婚",O3=1),AND(H3="減",OR(N3=1,O3=1))),1,0))) | Q3: =COUNTIF('責任職 企業局→市長部局'!A:A,SQLデータ!B3) -> 0 | R3: =COUNTIF('一般職員 企業局→市長部局'!A:F,SQLデータ!B3) -> 0
A4: 202510001748 | B4: 1256125 | C4: 46057 | D4: 給与口座 | E4: ＯＰ確認中 | F4: 添付待ち | G4: NULL | L4: =IF(ISBLANK(J4),0,1) -> 0 | M4: =IF(AND(L4=0,I4<>""),1,0) -> 0 | N4: =IF(AND(L4=0,M4=0,K4<>""),1,0) -> 0 | O4: =IF(COUNTIF(L4:N4,0)=3,1,0) -> 1 | P4: =IF(D4<>"扶養","",IF(E4<>"確認待ち",1,IF(OR(AND(G4="本人の結婚",O4=1),AND(H4="減",OR(N4=1,O4=1))),1,0))) | Q4: =COUNTIF('責任職 企業局→市長部局'!A:A,SQLデータ!B4) -> 0 | R4: =COUNTIF('一般職員 企業局→市長部局'!A:F,SQLデータ!B4) -> 0
A5: 202510001923 | B5: 1211445 | C5: 46069 | D5: 給与口座 | E5: ＯＰ確認中 | F5: 添付待ち | G5: NULL | L5: =IF(ISBLANK(J5),0,1) -> 0 | M5: =IF(AND(L5=0,I5<>""),1,0) -> 0 | N5: =IF(AND(L5=0,M5=0,K5<>""),1,0) -> 0 | O5: =IF(COUNTIF(L5:N5,0)=3,1,0) -> 1 | P5: =IF(D5<>"扶養","",IF(E5<>"確認待ち",1,IF(OR(AND(G5="本人の結婚",O5=1),AND(H5="減",OR(N5=1,O5=1))),1,0))) | Q5: =COUNTIF('責任職 企業局→市長部局'!A:A,SQLデータ!B5) -> 0 | R5: =COUNTIF('一般職員 企業局→市長部局'!A:F,SQLデータ!B5) -> 0
A6: 202510002028 | B6: 1256115 | C6: 46084 | D6: 給与口座 | E6: ＯＰ確認中 | F6: 添付待ち | G6: NULL | L6: =IF(ISBLANK(J6),0,1) -> 0 | M6: =IF(AND(L6=0,I6<>""),1,0) -> 0 | N6: =IF(AND(L6=0,M6=0,K6<>""),1,0) -> 0 | O6: =IF(COUNTIF(L6:N6,0)=3,1,0) -> 1 | P6: =IF(D6<>"扶養","",IF(E6<>"確認待ち",1,IF(OR(AND(G6="本人の結婚",O6=1),AND(H6="減",OR(N6=1,O6=1))),1,0))) | Q6: =COUNTIF('責任職 企業局→市長部局'!A:A,SQLデータ!B6) -> 0 | R6: =COUNTIF('一般職員 企業局→市長部局'!A:F,SQLデータ!B6) -> 0
A7: 202510002029 | B7: 1256115 | C7: 46084 | D7: 給与口座 | E7: ＯＰ確認中 | F7: 添付待ち | G7: NULL | L7: =IF(ISBLANK(J7),0,1) -> 0 | M7: =IF(AND(L7=0,I7<>""),1,0) -> 0 | N7: =IF(AND(L7=0,M7=0,K7<>""),1,0) -> 0 | O7: =IF(COUNTIF(L7:N7,0)=3,1,0) -> 1 | P7: =IF(D7<>"扶養","",IF(E7<>"確認待ち",1,IF(OR(AND(G7="本人の結婚",O7=1),AND(H7="減",OR(N7=1,O7=1))),1,0))) | Q7: =COUNTIF('責任職 企業局→市長部局'!A:A,SQLデータ!B7) -> 0 | R7: =COUNTIF('一般職員 企業局→市長部局'!A:F,SQLデータ!B7) -> 0
A8: 202510002056 | B8: 1176101 | C8: 46128 | D8: 給与口座 | E8: 確認待ち | G8: NULL | L8: =IF(ISBLANK(J8),0,1) -> 0 | M8: =IF(AND(L8=0,I8<>""),1,0) -> 0 | N8: =IF(AND(L8=0,M8=0,K8<>""),1,0) -> 0 | O8: =IF(COUNTIF(L8:N8,0)=3,1,0) -> 1 | P8: =IF(D8<>"扶養","",IF(E8<>"確認待ち",1,IF(OR(AND(G8="本人の結婚",O8=1),AND(H8="減",OR(N8=1,O8=1))),1,0))) | Q8: =COUNTIF('責任職 企業局→市長部局'!A:A,SQLデータ!B8) -> 0 | R8: =COUNTIF('一般職員 企業局→市長部局'!A:F,SQLデータ!B8) -> 0
A9: 202510002069 | B9: 1182055 | C9: 46090 | D9: 給与口座 | E9: ＯＰ確認中 | F9: 添付待ち | G9: NULL | L9: =IF(ISBLANK(J9),0,1) -> 0 | M9: =IF(AND(L9=0,I9<>""),1,0) -> 0 | N9: =IF(AND(L9=0,M9=0,K9<>""),1,0) -> 0 | O9: =IF(COUNTIF(L9:N9,0)=3,1,0) -> 1 | P9: =IF(D9<>"扶養","",IF(E9<>"確認待ち",1,IF(OR(AND(G9="本人の結婚",O9=1),AND(H9="減",OR(N9=1,O9=1))),1,0))) | Q9: =COUNTIF('責任職 企業局→市長部局'!A:A,SQLデータ!B9) -> 0 | R9: =COUNTIF('一般職員 企業局→市長部局'!A:F,SQLデータ!B9) -> 0
A10: 202510002115 | B10: 1201456 | C10: 46097 | D10: 給与口座 | E10: ＯＰ確認中 | F10: 添付待ち | G10: NULL | L10: =IF(ISBLANK(J10),0,1) -> 0 | M10: =IF(AND(L10=0,I10<>""),1,0) -> 0 | N10: =IF(AND(L10=0,M10=0,K10<>""),1,0) -> 0 | O10: =IF(COUNTIF(L10:N10,0)=3,1,0) -> 1 | P10: =IF(D10<>"扶養","",IF(E10<>"確認待ち",1,IF(OR(AND(G10="本人の結婚",O10=1),AND(H10="減",OR(N10=1,O10=1))),1,0))) | Q10: =COUNTIF('責任職 企業局→市長部局'!A:A,SQLデータ!B10) -> 0 | R10: =COUNTIF('一般職員 企業局→市長部局'!A:F,SQLデータ!B10) -> 0
A11: 202510002128 | B11: 1111168 | C11: 46099 | D11: 給与口座 | E11: ＯＰ確認中 | F11: 添付待ち | G11: NULL | L11: =IF(ISBLANK(J11),0,1) -> 0 | M11: =IF(AND(L11=0,I11<>""),1,0) -> 0 | N11: =IF(AND(L11=0,M11=0,K11<>""),1,0) -> 0 | O11: =IF(COUNTIF(L11:N11,0)=3,1,0) -> 1 | P11: =IF(D11<>"扶養","",IF(E11<>"確認待ち",1,IF(OR(AND(G11="本人の結婚",O11=1),AND(H11="減",OR(N11=1,O11=1))),1,0))) | Q11: =COUNTIF('責任職 企業局→市長部局'!A:A,SQLデータ!B11) -> 0 | R11: =COUNTIF('一般職員 企業局→市長部局'!A:F,SQLデータ!B11) -> 0
A12: 202510002155 | B12: 1126064 | C12: 46104 | D12: 給与口座 | E12: 確認済 | G12: NULL | L12: =IF(ISBLANK(J12),0,1) -> 0 | M12: =IF(AND(L12=0,I12<>""),1,0) -> 0 | N12: =IF(AND(L12=0,M12=0,K12<>""),1,0) -> 0 | O12: =IF(COUNTIF(L12:N12,0)=3,1,0) -> 1 | P12: =IF(D12<>"扶養","",IF(E12<>"確認待ち",1,IF(OR(AND(G12="本人の結婚",O12=1),AND(H12="減",OR(N12=1,O12=1))),1,0))) | Q12: =COUNTIF('責任職 企業局→市長部局'!A:A,SQLデータ!B12) -> 0 | R12: =COUNTIF('一般職員 企業局→市長部局'!A:F,SQLデータ!B12) -> 0
A13: 202510002164 | B13: 1081458 | C13: 46105 | D13: 給与口座 | E13: ＯＰ確認中 | F13: 添付待ち | G13: NULL | L13: =IF(ISBLANK(J13),0,1) -> 0 | M13: =IF(AND(L13=0,I13<>""),1,0) -> 0 | N13: =IF(AND(L13=0,M13=0,K13<>""),1,0) -> 0 | O13: =IF(COUNTIF(L13:N13,0)=3,1,0) -> 1 | P13: =IF(D13<>"扶養","",IF(E13<>"確認待ち",1,IF(OR(AND(G13="本人の結婚",O13=1),AND(H13="減",OR(N13=1,O13=1))),1,0))) | Q13: =COUNTIF('責任職 企業局→市長部局'!A:A,SQLデータ!B13) -> 0 | R13: =COUNTIF('一般職員 企業局→市長部局'!A:F,SQLデータ!B13) -> 0
A14: 202510002216 | B14: 1122110 | C14: 46111 | D14: 給与口座 | E14: ＳＶ確認中 | F14: 保留中 | G14: NULL | L14: =IF(ISBLANK(J14),0,1) -> 0 | M14: =IF(AND(L14=0,I14<>""),1,0) -> 0 | N14: =IF(AND(L14=0,M14=0,K14<>""),1,0) -> 0 | O14: =IF(COUNTIF(L14:N14,0)=3,1,0) -> 1 | P14: =IF(D14<>"扶養","",IF(E14<>"確認待ち",1,IF(OR(AND(G14="本人の結婚",O14=1),AND(H14="減",OR(N14=1,O14=1))),1,0))) | Q14: =COUNTIF('責任職 企業局→市長部局'!A:A,SQLデータ!B14) -> 0 | R14: =COUNTIF('一般職員 企業局→市長部局'!A:F,SQLデータ!B14) -> 0
A15: 202520000560 | B15: 1186140 | C15: 46053 | D15: 児童（認定） | E15: ＯＰ確認中 | F15: オペレータ保留 | G15: NULL | L15: =IF(ISBLANK(J15),0,1) -> 0 | M15: =IF(AND(L15=0,I15<>""),1,0) -> 0 | N15: =IF(AND(L15=0,M15=0,K15<>""),1,0) -> 0 | O15: =IF(COUNTIF(L15:N15,0)=3,1,0) -> 1 | P15: =IF(D15<>"扶養","",IF(E15<>"確認待ち",1,IF(OR(AND(G15="本人の結婚",O15=1),AND(H15="減",OR(N15=1,O15=1))),1,0))) | Q15: =COUNTIF('責任職 企業局→市長部局'!A:A,SQLデータ!B15) -> 0 | R15: =COUNTIF('一般職員 企業局→市長部局'!A:F,SQLデータ!B15) -> 0
A16: 202520000561 | B16: 1156002 | C16: 46059 | D16: 児童（認定） | E16: 確認済 | G16: NULL | L16: =IF(ISBLANK(J16),0,1) -> 0 | M16: =IF(AND(L16=0,I16<>""),1,0) -> 0 | N16: =IF(AND(L16=0,M16=0,K16<>""),1,0) -> 0 | O16: =IF(COUNTIF(L16:N16,0)=3,1,0) -> 1 | P16: =IF(D16<>"扶養","",IF(E16<>"確認待ち",1,IF(OR(AND(G16="本人の結婚",O16=1),AND(H16="減",OR(N16=1,O16=1))),1,0))) | Q16: =COUNTIF('責任職 企業局→市長部局'!A:A,SQLデータ!B16) -> 0 | R16: =COUNTIF('一般職員 企業局→市長部局'!A:F,SQLデータ!B16) -> 0
A17: 202520000585 | B17: 1251245 | C17: 46079 | D17: 児童（認定） | E17: 確認待ち | F17: 添付待ち | G17: NULL | L17: =IF(ISBLANK(J17),0,1) -> 0 | M17: =IF(AND(L17=0,I17<>""),1,0) -> 0 | N17: =IF(AND(L17=0,M17=0,K17<>""),1,0) -> 0 | O17: =IF(COUNTIF(L17:N17,0)=3,1,0) -> 1 | P17: =IF(D17<>"扶養","",IF(E17<>"確認待ち",1,IF(OR(AND(G17="本人の結婚",O17=1),AND(H17="減",OR(N17=1,O17=1))),1,0))) | Q17: =COUNTIF('責任職 企業局→市長部局'!A:A,SQLデータ!B17) -> 0 | R17: =COUNTIF('一般職員 企業局→市長部局'!A:F,SQLデータ!B17) -> 0
A18: 202520000591 | B18: 1192017 | C18: 46084 | D18: 児童（認定） | E18: 確認済 | F18: オペレータ保留 | G18: NULL | L18: =IF(ISBLANK(J18),0,1) -> 0 | M18: =IF(AND(L18=0,I18<>""),1,0) -> 0 | N18: =IF(AND(L18=0,M18=0,K18<>""),1,0) -> 0 | O18: =IF(COUNTIF(L18:N18,0)=3,1,0) -> 1 | P18: =IF(D18<>"扶養","",IF(E18<>"確認待ち",1,IF(OR(AND(G18="本人の結婚",O18=1),AND(H18="減",OR(N18=1,O18=1))),1,0))) | Q18: =COUNTIF('責任職 企業局→市長部局'!A:A,SQLデータ!B18) -> 0 | R18: =COUNTIF('一般職員 企業局→市長部局'!A:F,SQLデータ!B18) -> 0
A19: 202520000600 | B19: 1211166 | C19: 46091 | D19: 児童（認定） | E19: ＯＰ確認中 | F19: オペレータ保留 | G19: NULL | L19: =IF(ISBLANK(J19),0,1) -> 0 | M19: =IF(AND(L19=0,I19<>""),1,0) -> 0 | N19: =IF(AND(L19=0,M19=0,K19<>""),1,0) -> 0 | O19: =IF(COUNTIF(L19:N19,0)=3,1,0) -> 1 | P19: =IF(D19<>"扶養","",IF(E19<>"確認待ち",1,IF(OR(AND(G19="本人の結婚",O19=1),AND(H19="減",OR(N19=1,O19=1))),1,0))) | Q19: =COUNTIF('責任職 企業局→市長部局'!A:A,SQLデータ!B19) -> 0 | R19: =COUNTIF('一般職員 企業局→市長部局'!A:F,SQLデータ!B19) -> 0
A20: 202520000603 | B20: 920331 | C20: 46091 | D20: 児童（認定） | E20: 確認済 | G20: NULL | L20: =IF(ISBLANK(J20),0,1) -> 0 | M20: =IF(AND(L20=0,I20<>""),1,0) -> 0 | N20: =IF(AND(L20=0,M20=0,K20<>""),1,0) -> 0 | O20: =IF(COUNTIF(L20:N20,0)=3,1,0) -> 1 | P20: =IF(D20<>"扶養","",IF(E20<>"確認待ち",1,IF(OR(AND(G20="本人の結婚",O20=1),AND(H20="減",OR(N20=1,O20=1))),1,0))) | Q20: =COUNTIF('責任職 企業局→市長部局'!A:A,SQLデータ!B20) -> 0 | R20: =COUNTIF('一般職員 企業局→市長部局'!A:F,SQLデータ!B20) -> 0
A21: 202520000605 | B21: 1161250 | C21: 46092 | D21: 児童（認定） | E21: 確認済 | F21: オペレータ保留 | G21: NULL | L21: =IF(ISBLANK(J21),0,1) -> 0 | M21: =IF(AND(L21=0,I21<>""),1,0) -> 0 | N21: =IF(AND(L21=0,M21=0,K21<>""),1,0) -> 0 | O21: =IF(COUNTIF(L21:N21,0)=3,1,0) -> 1 | P21: =IF(D21<>"扶養","",IF(E21<>"確認待ち",1,IF(OR(AND(G21="本人の結婚",O21=1),AND(H21="減",OR(N21=1,O21=1))),1,0))) | Q21: =COUNTIF('責任職 企業局→市長部局'!A:A,SQLデータ!B21) -> 0 | R21: =COUNTIF('一般職員 企業局→市長部局'!A:F,SQLデータ!B21) -> 0
A22: 202520000616 | B22: 1111437 | C22: 46104 | D22: 児童（認定） | E22: ＳＶ確認中 | F22: 1,7 | G22: NULL | L22: =IF(ISBLANK(J22),0,1) -> 0 | M22: =IF(AND(L22=0,I22<>""),1,0) -> 0 | N22: =IF(AND(L22=0,M22=0,K22<>""),1,0) -> 0 | O22: =IF(COUNTIF(L22:N22,0)=3,1,0) -> 1 | P22: =IF(D22<>"扶養","",IF(E22<>"確認待ち",1,IF(OR(AND(G22="本人の結婚",O22=1),AND(H22="減",OR(N22=1,O22=1))),1,0))) | Q22: =COUNTIF('責任職 企業局→市長部局'!A:A,SQLデータ!B22) -> 0 | R22: =COUNTIF('一般職員 企業局→市長部局'!A:F,SQLデータ!B22) -> 0
A23: 202520000617 | B23: 1156093 | C23: 46106 | D23: 児童（認定） | E23: 確認待ち | F23: 添付待ち | G23: NULL | L23: =IF(ISBLANK(J23),0,1) -> 0 | M23: =IF(AND(L23=0,I23<>""),1,0) -> 0 | N23: =IF(AND(L23=0,M23=0,K23<>""),1,0) -> 0 | O23: =IF(COUNTIF(L23:N23,0)=3,1,0) -> 1 | P23: =IF(D23<>"扶養","",IF(E23<>"確認待ち",1,IF(OR(AND(G23="本人の結婚",O23=1),AND(H23="減",OR(N23=1,O23=1))),1,0))) | Q23: =COUNTIF('責任職 企業局→市長部局'!A:A,SQLデータ!B23) -> 0 | R23: =COUNTIF('一般職員 企業局→市長部局'!A:F,SQLデータ!B23) -> 0
A24: 202520000618 | B24: 1206045 | C24: 46107 | D24: 児童（認定） | E24: 確認待ち | F24: 添付待ち | G24: NULL | L24: =IF(ISBLANK(J24),0,1) -> 0 | M24: =IF(AND(L24=0,I24<>""),1,0) -> 0 | N24: =IF(AND(L24=0,M24=0,K24<>""),1,0) -> 0 | O24: =IF(COUNTIF(L24:N24,0)=3,1,0) -> 1 | P24: =IF(D24<>"扶養","",IF(E24<>"確認待ち",1,IF(OR(AND(G24="本人の結婚",O24=1),AND(H24="減",OR(N24=1,O24=1))),1,0))) | Q24: =COUNTIF('責任職 企業局→市長部局'!A:A,SQLデータ!B24) -> 0 | R24: =COUNTIF('一般職員 企業局→市長部局'!A:F,SQLデータ!B24) -> 0
A25: 202520000621 | B25: 1151461 | C25: 46127 | D25: 児童（認定） | E25: 確認待ち | G25: NULL | L25: =IF(ISBLANK(J25),0,1) -> 0 | M25: =IF(AND(L25=0,I25<>""),1,0) -> 0 | N25: =IF(AND(L25=0,M25=0,K25<>""),1,0) -> 0 | O25: =IF(COUNTIF(L25:N25,0)=3,1,0) -> 1 | P25: =IF(D25<>"扶養","",IF(E25<>"確認待ち",1,IF(OR(AND(G25="本人の結婚",O25=1),AND(H25="減",OR(N25=1,O25=1))),1,0))) | Q25: =COUNTIF('責任職 企業局→市長部局'!A:A,SQLデータ!B25) -> 0 | R25: =COUNTIF('一般職員 企業局→市長部局'!A:F,SQLデータ!B25) -> 0
A26: 202520000622 | B26: 1194097 | C26: 46118 | D26: 児童（認定） | E26: 確認済 | F26: オペレータ保留 | G26: NULL | L26: =IF(ISBLANK(J26),0,1) -> 0 | M26: =IF(AND(L26=0,I26<>""),1,0) -> 0 | N26: =IF(AND(L26=0,M26=0,K26<>""),1,0) -> 0 | O26: =IF(COUNTIF(L26:N26,0)=3,1,0) -> 1 | P26: =IF(D26<>"扶養","",IF(E26<>"確認待ち",1,IF(OR(AND(G26="本人の結婚",O26=1),AND(H26="減",OR(N26=1,O26=1))),1,0))) | Q26: =COUNTIF('責任職 企業局→市長部局'!A:A,SQLデータ!B26) -> 0 | R26: =COUNTIF('一般職員 企業局→市長部局'!A:F,SQLデータ!B26) -> 0
A27: 202520000623 | B27: 1131048 | C27: 46111 | D27: 児童（認定） | E27: 確認済 | F27: オペレータ保留 | G27: NULL | L27: =IF(ISBLANK(J27),0,1) -> 0 | M27: =IF(AND(L27=0,I27<>""),1,0) -> 0 | N27: =IF(AND(L27=0,M27=0,K27<>""),1,0) -> 0 | O27: =IF(COUNTIF(L27:N27,0)=3,1,0) -> 1 | P27: =IF(D27<>"扶養","",IF(E27<>"確認待ち",1,IF(OR(AND(G27="本人の結婚",O27=1),AND(H27="減",OR(N27=1,O27=1))),1,0))) | Q27: =COUNTIF('責任職 企業局→市長部局'!A:A,SQLデータ!B27) -> 0 | R27: =COUNTIF('一般職員 企業局→市長部局'!A:F,SQLデータ!B27) -> 0
A28: 202530000153 | B28: 1071006 | C28: 45804 | D28: 児童（改定） | E28: 確認済 | G28: NULL | L28: =IF(ISBLANK(J28),0,1) -> 0 | M28: =IF(AND(L28=0,I28<>""),1,0) -> 0 | N28: =IF(AND(L28=0,M28=0,K28<>""),1,0) -> 0 | O28: =IF(COUNTIF(L28:N28,0)=3,1,0) -> 1 | P28: =IF(D28<>"扶養","",IF(E28<>"確認待ち",1,IF(OR(AND(G28="本人の結婚",O28=1),AND(H28="減",OR(N28=1,O28=1))),1,0))) | Q28: =COUNTIF('責任職 企業局→市長部局'!A:A,SQLデータ!B28) -> 0 | R28: =COUNTIF('一般職員 企業局→市長部局'!A:F,SQLデータ!B28) -> 0
A29: 202530000259 | B29: 1034029 | C29: 45863 | D29: 児童（改定） | E29: 申請受付 | F29: 保留中 | G29: NULL | L29: =IF(ISBLANK(J29),0,1) -> 0 | M29: =IF(AND(L29=0,I29<>""),1,0) -> 0 | N29: =IF(AND(L29=0,M29=0,K29<>""),1,0) -> 0 | O29: =IF(COUNTIF(L29:N29,0)=3,1,0) -> 1 | P29: =IF(D29<>"扶養","",IF(E29<>"確認待ち",1,IF(OR(AND(G29="本人の結婚",O29=1),AND(H29="減",OR(N29=1,O29=1))),1,0))) | Q29: =COUNTIF('責任職 企業局→市長部局'!A:A,SQLデータ!B29) -> 0 | R29: =COUNTIF('一般職員 企業局→市長部局'!A:F,SQLデータ!B29) -> 0
A30: 202530000456 | B30: 1146122 | C30: 46099 | D30: 児童（改定） | E30: 確認済 | F30: オペレータ保留 | G30: NULL | L30: =IF(ISBLANK(J30),0,1) -> 0 | M30: =IF(AND(L30=0,I30<>""),1,0) -> 0 | N30: =IF(AND(L30=0,M30=0,K30<>""),1,0) -> 0 | O30: =IF(COUNTIF(L30:N30,0)=3,1,0) -> 1 | P30: =IF(D30<>"扶養","",IF(E30<>"確認待ち",1,IF(OR(AND(G30="本人の結婚",O30=1),AND(H30="減",OR(N30=1,O30=1))),1,0))) | Q30: =COUNTIF('責任職 企業局→市長部局'!A:A,SQLデータ!B30) -> 0 | R30: =COUNTIF('一般職員 企業局→市長部局'!A:F,SQLデータ!B30) -> 0
A31: 202530000458 | B31: 1186125 | C31: 46090 | D31: 児童（改定） | E31: 確認済 | F31: オペレータ保留 | G31: NULL | L31: =IF(ISBLANK(J31),0,1) -> 0 | M31: =IF(AND(L31=0,I31<>""),1,0) -> 0 | N31: =IF(AND(L31=0,M31=0,K31<>""),1,0) -> 0 | O31: =IF(COUNTIF(L31:N31,0)=3,1,0) -> 1 | P31: =IF(D31<>"扶養","",IF(E31<>"確認待ち",1,IF(OR(AND(G31="本人の結婚",O31=1),AND(H31="減",OR(N31=1,O31=1))),1,0))) | Q31: =COUNTIF('責任職 企業局→市長部局'!A:A,SQLデータ!B31) -> 0 | R31: =COUNTIF('一般職員 企業局→市長部局'!A:F,SQLデータ!B31) -> 0
A32: 202530000459 | B32: 1082041 | C32: 46080 | D32: 児童（改定） | E32: 確認済 | G32: NULL | L32: =IF(ISBLANK(J32),0,1) -> 0 | M32: =IF(AND(L32=0,I32<>""),1,0) -> 0 | N32: =IF(AND(L32=0,M32=0,K32<>""),1,0) -> 0 | O32: =IF(COUNTIF(L32:N32,0)=3,1,0) -> 1 | P32: =IF(D32<>"扶養","",IF(E32<>"確認待ち",1,IF(OR(AND(G32="本人の結婚",O32=1),AND(H32="減",OR(N32=1,O32=1))),1,0))) | Q32: =COUNTIF('責任職 企業局→市長部局'!A:A,SQLデータ!B32) -> 0 | R32: =COUNTIF('一般職員 企業局→市長部局'!A:F,SQLデータ!B32) -> 0
A33: 202530000462 | B33: 1126005 | C33: 46092 | D33: 児童（改定） | E33: 確認済 | G33: NULL | L33: =IF(ISBLANK(J33),0,1) -> 0 | M33: =IF(AND(L33=0,I33<>""),1,0) -> 0 | N33: =IF(AND(L33=0,M33=0,K33<>""),1,0) -> 0 | O33: =IF(COUNTIF(L33:N33,0)=3,1,0) -> 1 | P33: =IF(D33<>"扶養","",IF(E33<>"確認待ち",1,IF(OR(AND(G33="本人の結婚",O33=1),AND(H33="減",OR(N33=1,O33=1))),1,0))) | Q33: =COUNTIF('責任職 企業局→市長部局'!A:A,SQLデータ!B33) -> 0 | R33: =COUNTIF('一般職員 企業局→市長部局'!A:F,SQLデータ!B33) -> 0
A34: 202530000464 | B34: 1126011 | C34: 46097 | D34: 児童（改定） | E34: 確認済 | F34: オペレータ保留 | G34: NULL | L34: =IF(ISBLANK(J34),0,1) -> 0 | M34: =IF(AND(L34=0,I34<>""),1,0) -> 0 | N34: =IF(AND(L34=0,M34=0,K34<>""),1,0) -> 0 | O34: =IF(COUNTIF(L34:N34,0)=3,1,0) -> 1 | P34: =IF(D34<>"扶養","",IF(E34<>"確認待ち",1,IF(OR(AND(G34="本人の結婚",O34=1),AND(H34="減",OR(N34=1,O34=1))),1,0))) | Q34: =COUNTIF('責任職 企業局→市長部局'!A:A,SQLデータ!B34) -> 0 | R34: =COUNTIF('一般職員 企業局→市長部局'!A:F,SQLデータ!B34) -> 0
A35: 202530000465 | B35: 1191466 | C35: 46099 | D35: 児童（改定） | E35: ＳＶ確認中 | G35: NULL | L35: =IF(ISBLANK(J35),0,1) -> 0 | M35: =IF(AND(L35=0,I35<>""),1,0) -> 0 | N35: =IF(AND(L35=0,M35=0,K35<>""),1,0) -> 0 | O35: =IF(COUNTIF(L35:N35,0)=3,1,0) -> 1 | P35: =IF(D35<>"扶養","",IF(E35<>"確認待ち",1,IF(OR(AND(G35="本人の結婚",O35=1),AND(H35="減",OR(N35=1,O35=1))),1,0))) | Q35: =COUNTIF('責任職 企業局→市長部局'!A:A,SQLデータ!B35) -> 0 | R35: =COUNTIF('一般職員 企業局→市長部局'!A:F,SQLデータ!B35) -> 0
A36: 202530000468 | B36: 1193025 | C36: 46099 | D36: 児童（改定） | E36: 確認済 | F36: オペレータ保留 | G36: NULL | L36: =IF(ISBLANK(J36),0,1) -> 0 | M36: =IF(AND(L36=0,I36<>""),1,0) -> 0 | N36: =IF(AND(L36=0,M36=0,K36<>""),1,0) -> 0 | O36: =IF(COUNTIF(L36:N36,0)=3,1,0) -> 1 | P36: =IF(D36<>"扶養","",IF(E36<>"確認待ち",1,IF(OR(AND(G36="本人の結婚",O36=1),AND(H36="減",OR(N36=1,O36=1))),1,0))) | Q36: =COUNTIF('責任職 企業局→市長部局'!A:A,SQLデータ!B36) -> 0 | R36: =COUNTIF('一般職員 企業局→市長部局'!A:F,SQLデータ!B36) -> 0
A37: 202530000469 | B37: 974169 | C37: 46115 | D37: 児童（改定） | E37: 確認待ち | G37: NULL | L37: =IF(ISBLANK(J37),0,1) -> 0 | M37: =IF(AND(L37=0,I37<>""),1,0) -> 0 | N37: =IF(AND(L37=0,M37=0,K37<>""),1,0) -> 0 | O37: =IF(COUNTIF(L37:N37,0)=3,1,0) -> 1 | P37: =IF(D37<>"扶養","",IF(E37<>"確認待ち",1,IF(OR(AND(G37="本人の結婚",O37=1),AND(H37="減",OR(N37=1,O37=1))),1,0))) | Q37: =COUNTIF('責任職 企業局→市長部局'!A:A,SQLデータ!B37) -> 0 | R37: =COUNTIF('一般職員 企業局→市長部局'!A:F,SQLデータ!B37) -> 0
A38: 202530000470 | B38: 1162079 | C38: 46105 | D38: 児童（改定） | E38: 確認済 | G38: NULL | L38: =IF(ISBLANK(J38),0,1) -> 0 | M38: =IF(AND(L38=0,I38<>""),1,0) -> 0 | N38: =IF(AND(L38=0,M38=0,K38<>""),1,0) -> 0 | O38: =IF(COUNTIF(L38:N38,0)=3,1,0) -> 1 | P38: =IF(D38<>"扶養","",IF(E38<>"確認待ち",1,IF(OR(AND(G38="本人の結婚",O38=1),AND(H38="減",OR(N38=1,O38=1))),1,0))) | Q38: =COUNTIF('責任職 企業局→市長部局'!A:A,SQLデータ!B38) -> 0 | R38: =COUNTIF('一般職員 企業局→市長部局'!A:F,SQLデータ!B38) -> 0
A39: 202530000471 | B39: 1176039 | C39: 46104 | D39: 児童（改定） | E39: ＯＰ確認中 | F39: オペレータ保留 | G39: NULL | L39: =IF(ISBLANK(J39),0,1) -> 0 | M39: =IF(AND(L39=0,I39<>""),1,0) -> 0 | N39: =IF(AND(L39=0,M39=0,K39<>""),1,0) -> 0 | O39: =IF(COUNTIF(L39:N39,0)=3,1,0) -> 1 | P39: =IF(D39<>"扶養","",IF(E39<>"確認待ち",1,IF(OR(AND(G39="本人の結婚",O39=1),AND(H39="減",OR(N39=1,O39=1))),1,0))) | Q39: =COUNTIF('責任職 企業局→市長部局'!A:A,SQLデータ!B39) -> 0 | R39: =COUNTIF('一般職員 企業局→市長部局'!A:F,SQLデータ!B39) -> 0
A40: 202530000475 | B40: 1201040 | C40: 46108 | D40: 児童（改定） | E40: 確認済 | F40: オペレータ保留 | G40: NULL | L40: =IF(ISBLANK(J40),0,1) -> 0 | M40: =IF(AND(L40=0,I40<>""),1,0) -> 0 | N40: =IF(AND(L40=0,M40=0,K40<>""),1,0) -> 0 | O40: =IF(COUNTIF(L40:N40,0)=3,1,0) -> 1 | P40: =IF(D40<>"扶養","",IF(E40<>"確認待ち",1,IF(OR(AND(G40="本人の結婚",O40=1),AND(H40="減",OR(N40=1,O40=1))),1,0))) | Q40: =COUNTIF('責任職 企業局→市長部局'!A:A,SQLデータ!B40) -> 0 | R40: =COUNTIF('一般職員 企業局→市長部局'!A:F,SQLデータ!B40) -> 0
A41: 202530000476 | B41: 996031 | C41: 46108 | D41: 児童（改定） | E41: 確認待ち | F41: オペレータ保留 | G41: NULL | L41: =IF(ISBLANK(J41),0,1) -> 0 | M41: =IF(AND(L41=0,I41<>""),1,0) -> 0 | N41: =IF(AND(L41=0,M41=0,K41<>""),1,0) -> 0 | O41: =IF(COUNTIF(L41:N41,0)=3,1,0) -> 1 | P41: =IF(D41<>"扶養","",IF(E41<>"確認待ち",1,IF(OR(AND(G41="本人の結婚",O41=1),AND(H41="減",OR(N41=1,O41=1))),1,0))) | Q41: =COUNTIF('責任職 企業局→市長部局'!A:A,SQLデータ!B41) -> 0 | R41: =COUNTIF('一般職員 企業局→市長部局'!A:F,SQLデータ!B41) -> 0
A42: 202530000478 | B42: 1176067 | C42: 46107 | D42: 児童（改定） | E42: ＯＰ確認中 | F42: オペレータ保留 | G42: NULL | L42: =IF(ISBLANK(J42),0,1) -> 0 | M42: =IF(AND(L42=0,I42<>""),1,0) -> 0 | N42: =IF(AND(L42=0,M42=0,K42<>""),1,0) -> 0 | O42: =IF(COUNTIF(L42:N42,0)=3,1,0) -> 1 | P42: =IF(D42<>"扶養","",IF(E42<>"確認待ち",1,IF(OR(AND(G42="本人の結婚",O42=1),AND(H42="減",OR(N42=1,O42=1))),1,0))) | Q42: =COUNTIF('責任職 企業局→市長部局'!A:A,SQLデータ!B42) -> 0 | R42: =COUNTIF('一般職員 企業局→市長部局'!A:F,SQLデータ!B42) -> 0
A43: 202530000479 | B43: 1181211 | C43: 46112 | D43: 児童（改定） | E43: 確認済 | F43: オペレータ保留 | G43: NULL | L43: =IF(ISBLANK(J43),0,1) -> 0 | M43: =IF(AND(L43=0,I43<>""),1,0) -> 0 | N43: =IF(AND(L43=0,M43=0,K43<>""),1,0) -> 0 | O43: =IF(COUNTIF(L43:N43,0)=3,1,0) -> 1 | P43: =IF(D43<>"扶養","",IF(E43<>"確認待ち",1,IF(OR(AND(G43="本人の結婚",O43=1),AND(H43="減",OR(N43=1,O43=1))),1,0))) | Q43: =COUNTIF('責任職 企業局→市長部局'!A:A,SQLデータ!B43) -> 0 | R43: =COUNTIF('一般職員 企業局→市長部局'!A:F,SQLデータ!B43) -> 0
A44: 202540000188 | B44: 1221176 | C44: 45770 | D44: 住居 | E44: 確認済 | F44: 7,3 | G44: NULL | L44: =IF(ISBLANK(J44),0,1) -> 0 | M44: =IF(AND(L44=0,I44<>""),1,0) -> 0 | N44: =IF(AND(L44=0,M44=0,K44<>""),1,0) -> 0 | O44: =IF(COUNTIF(L44:N44,0)=3,1,0) -> 1 | P44: =IF(D44<>"扶養","",IF(E44<>"確認待ち",1,IF(OR(AND(G44="本人の結婚",O44=1),AND(H44="減",OR(N44=1,O44=1))),1,0))) | Q44: =COUNTIF('責任職 企業局→市長部局'!A:A,SQLデータ!B44) -> 0 | R44: =COUNTIF('一般職員 企業局→市長部局'!A:F,SQLデータ!B44) -> 0
A45: 202540001533 | B45: 1231105 | C45: 46115 | D45: 住居 | E45: 確認待ち | F45: オペレータ保留 | G45: NULL | L45: =IF(ISBLANK(J45),0,1) -> 0 | M45: =IF(AND(L45=0,I45<>""),1,0) -> 0 | N45: =IF(AND(L45=0,M45=0,K45<>""),1,0) -> 0 | O45: =IF(COUNTIF(L45:N45,0)=3,1,0) -> 1 | P45: =IF(D45<>"扶養","",IF(E45<>"確認待ち",1,IF(OR(AND(G45="本人の結婚",O45=1),AND(H45="減",OR(N45=1,O45=1))),1,0))) | Q45: =COUNTIF('責任職 企業局→市長部局'!A:A,SQLデータ!B45) -> 0 | R45: =COUNTIF('一般職員 企業局→市長部局'!A:F,SQLデータ!B45) -> 0
A46: 202540001567 | B46: 1096099 | C46: 45955 | D46: 住居 | E46: 確認済 | F46: オペレータ保留 | G46: NULL | L46: =IF(ISBLANK(J46),0,1) -> 0 | M46: =IF(AND(L46=0,I46<>""),1,0) -> 0 | N46: =IF(AND(L46=0,M46=0,K46<>""),1,0) -> 0 | O46: =IF(COUNTIF(L46:N46,0)=3,1,0) -> 1 | P46: =IF(D46<>"扶養","",IF(E46<>"確認待ち",1,IF(OR(AND(G46="本人の結婚",O46=1),AND(H46="減",OR(N46=1,O46=1))),1,0))) | Q46: =COUNTIF('責任職 企業局→市長部局'!A:A,SQLデータ!B46) -> 0 | R46: =COUNTIF('一般職員 企業局→市長部局'!A:F,SQLデータ!B46) -> 0
A47: 202540001727 | B47: 1223027 | C47: 45971 | D47: 住居 | E47: ＳＶ確認中 | G47: NULL | L47: =IF(ISBLANK(J47),0,1) -> 0 | M47: =IF(AND(L47=0,I47<>""),1,0) -> 0 | N47: =IF(AND(L47=0,M47=0,K47<>""),1,0) -> 0 | O47: =IF(COUNTIF(L47:N47,0)=3,1,0) -> 1 | P47: =IF(D47<>"扶養","",IF(E47<>"確認待ち",1,IF(OR(AND(G47="本人の結婚",O47=1),AND(H47="減",OR(N47=1,O47=1))),1,0))) | Q47: =COUNTIF('責任職 企業局→市長部局'!A:A,SQLデータ!B47) -> 0 | R47: =COUNTIF('一般職員 企業局→市長部局'!A:F,SQLデータ!B47) -> 0
A48: 202540001858 | B48: 1241228 | C48: 46023 | D48: 住居 | E48: 確認待ち | F48: 保留中 | G48: NULL | L48: =IF(ISBLANK(J48),0,1) -> 0 | M48: =IF(AND(L48=0,I48<>""),1,0) -> 0 | N48: =IF(AND(L48=0,M48=0,K48<>""),1,0) -> 0 | O48: =IF(COUNTIF(L48:N48,0)=3,1,0) -> 1 | P48: =IF(D48<>"扶養","",IF(E48<>"確認待ち",1,IF(OR(AND(G48="本人の結婚",O48=1),AND(H48="減",OR(N48=1,O48=1))),1,0))) | Q48: =COUNTIF('責任職 企業局→市長部局'!A:A,SQLデータ!B48) -> 0 | R48: =COUNTIF('一般職員 企業局→市長部局'!A:F,SQLデータ!B48) -> 0
A49: 202540002042 | B49: 1234027 | C49: 46113 | D49: 住居 | E49: 確認待ち | G49: NULL | L49: =IF(ISBLANK(J49),0,1) -> 0 | M49: =IF(AND(L49=0,I49<>""),1,0) -> 0 | N49: =IF(AND(L49=0,M49=0,K49<>""),1,0) -> 0 | O49: =IF(COUNTIF(L49:N49,0)=3,1,0) -> 1 | P49: =IF(D49<>"扶養","",IF(E49<>"確認待ち",1,IF(OR(AND(G49="本人の結婚",O49=1),AND(H49="減",OR(N49=1,O49=1))),1,0))) | Q49: =COUNTIF('責任職 企業局→市長部局'!A:A,SQLデータ!B49) -> 0 | R49: =COUNTIF('一般職員 企業局→市長部局'!A:F,SQLデータ!B49) -> 0
A50: 202540002060 | B50: 1096099 | C50: 46002 | D50: 住居 | E50: 確認待ち | F50: 1,7 | G50: NULL | L50: =IF(ISBLANK(J50),0,1) -> 0 | M50: =IF(AND(L50=0,I50<>""),1,0) -> 0 | N50: =IF(AND(L50=0,M50=0,K50<>""),1,0) -> 0 | O50: =IF(COUNTIF(L50:N50,0)=3,1,0) -> 1 | P50: =IF(D50<>"扶養","",IF(E50<>"確認待ち",1,IF(OR(AND(G50="本人の結婚",O50=1),AND(H50="減",OR(N50=1,O50=1))),1,0))) | Q50: =COUNTIF('責任職 企業局→市長部局'!A:A,SQLデータ!B50) -> 0 | R50: =COUNTIF('一般職員 企業局→市長部局'!A:F,SQLデータ!B50) -> 0
A51: 202540002273 | B51: 1146049 | C51: 46038 | D51: 住居 | E51: 確認待ち | G51: NULL | L51: =IF(ISBLANK(J51),0,1) -> 0 | M51: =IF(AND(L51=0,I51<>""),1,0) -> 0 | N51: =IF(AND(L51=0,M51=0,K51<>""),1,0) -> 0 | O51: =IF(COUNTIF(L51:N51,0)=3,1,0) -> 1 | P51: =IF(D51<>"扶養","",IF(E51<>"確認待ち",1,IF(OR(AND(G51="本人の結婚",O51=1),AND(H51="減",OR(N51=1,O51=1))),1,0))) | Q51: =COUNTIF('責任職 企業局→市長部局'!A:A,SQLデータ!B51) -> 0 | R51: =COUNTIF('一般職員 企業局→市長部局'!A:F,SQLデータ!B51) -> 0
A52: 202540002292 | B52: 1182055 | C52: 46041 | D52: 住居 | E52: 確認済 | G52: NULL | L52: =IF(ISBLANK(J52),0,1) -> 0 | M52: =IF(AND(L52=0,I52<>""),1,0) -> 0 | N52: =IF(AND(L52=0,M52=0,K52<>""),1,0) -> 0 | O52: =IF(COUNTIF(L52:N52,0)=3,1,0) -> 1 | P52: =IF(D52<>"扶養","",IF(E52<>"確認待ち",1,IF(OR(AND(G52="本人の結婚",O52=1),AND(H52="減",OR(N52=1,O52=1))),1,0))) | Q52: =COUNTIF('責任職 企業局→市長部局'!A:A,SQLデータ!B52) -> 0 | R52: =COUNTIF('一般職員 企業局→市長部局'!A:F,SQLデータ!B52) -> 0
A53: 202540002373 | B53: 1221303 | C53: 46111 | D53: 住居 | E53: 確認待ち | F53: 添付待ち | G53: NULL | L53: =IF(ISBLANK(J53),0,1) -> 0 | M53: =IF(AND(L53=0,I53<>""),1,0) -> 0 | N53: =IF(AND(L53=0,M53=0,K53<>""),1,0) -> 0 | O53: =IF(COUNTIF(L53:N53,0)=3,1,0) -> 1 | P53: =IF(D53<>"扶養","",IF(E53<>"確認待ち",1,IF(OR(AND(G53="本人の結婚",O53=1),AND(H53="減",OR(N53=1,O53=1))),1,0))) | Q53: =COUNTIF('責任職 企業局→市長部局'!A:A,SQLデータ!B53) -> 0 | R53: =COUNTIF('一般職員 企業局→市長部局'!A:F,SQLデータ!B53) -> 0
A54: 202540002377 | B54: 1251086 | C54: 46127 | D54: 住居 | E54: 確認待ち | G54: NULL | L54: =IF(ISBLANK(J54),0,1) -> 0 | M54: =IF(AND(L54=0,I54<>""),1,0) -> 0 | N54: =IF(AND(L54=0,M54=0,K54<>""),1,0) -> 0 | O54: =IF(COUNTIF(L54:N54,0)=3,1,0) -> 1 | P54: =IF(D54<>"扶養","",IF(E54<>"確認待ち",1,IF(OR(AND(G54="本人の結婚",O54=1),AND(H54="減",OR(N54=1,O54=1))),1,0))) | Q54: =COUNTIF('責任職 企業局→市長部局'!A:A,SQLデータ!B54) -> 0 | R54: =COUNTIF('一般職員 企業局→市長部局'!A:F,SQLデータ!B54) -> 0
A55: 202540002394 | B55: 1221129 | C55: 46052 | D55: 住居 | E55: ＯＰ確認中 | F55: 添付待ち | G55: NULL | L55: =IF(ISBLANK(J55),0,1) -> 0 | M55: =IF(AND(L55=0,I55<>""),1,0) -> 0 | N55: =IF(AND(L55=0,M55=0,K55<>""),1,0) -> 0 | O55: =IF(COUNTIF(L55:N55,0)=3,1,0) -> 1 | P55: =IF(D55<>"扶養","",IF(E55<>"確認待ち",1,IF(OR(AND(G55="本人の結婚",O55=1),AND(H55="減",OR(N55=1,O55=1))),1,0))) | Q55: =COUNTIF('責任職 企業局→市長部局'!A:A,SQLデータ!B55) -> 0 | R55: =COUNTIF('一般職員 企業局→市長部局'!A:F,SQLデータ!B55) -> 0
A56: 202540002395 | B56: 1251145 | C56: 46084 | D56: 住居 | E56: 確認待ち | F56: 添付待ち | G56: NULL | L56: =IF(ISBLANK(J56),0,1) -> 0 | M56: =IF(AND(L56=0,I56<>""),1,0) -> 0 | N56: =IF(AND(L56=0,M56=0,K56<>""),1,0) -> 0 | O56: =IF(COUNTIF(L56:N56,0)=3,1,0) -> 1 | P56: =IF(D56<>"扶養","",IF(E56<>"確認待ち",1,IF(OR(AND(G56="本人の結婚",O56=1),AND(H56="減",OR(N56=1,O56=1))),1,0))) | Q56: =COUNTIF('責任職 企業局→市長部局'!A:A,SQLデータ!B56) -> 0 | R56: =COUNTIF('一般職員 企業局→市長部局'!A:F,SQLデータ!B56) -> 0
A57: 202540002480 | B57: 1131092 | C57: 46062 | D57: 住居 | E57: 確認待ち | F57: 添付待ち | G57: NULL | L57: =IF(ISBLANK(J57),0,1) -> 0 | M57: =IF(AND(L57=0,I57<>""),1,0) -> 0 | N57: =IF(AND(L57=0,M57=0,K57<>""),1,0) -> 0 | O57: =IF(COUNTIF(L57:N57,0)=3,1,0) -> 1 | P57: =IF(D57<>"扶養","",IF(E57<>"確認待ち",1,IF(OR(AND(G57="本人の結婚",O57=1),AND(H57="減",OR(N57=1,O57=1))),1,0))) | Q57: =COUNTIF('責任職 企業局→市長部局'!A:A,SQLデータ!B57) -> 0 | R57: =COUNTIF('一般職員 企業局→市長部局'!A:F,SQLデータ!B57) -> 0
A58: 202540002483 | B58: 1114002 | C58: 46060 | D58: 住居 | E58: 確認済 | G58: NULL | L58: =IF(ISBLANK(J58),0,1) -> 0 | M58: =IF(AND(L58=0,I58<>""),1,0) -> 0 | N58: =IF(AND(L58=0,M58=0,K58<>""),1,0) -> 0 | O58: =IF(COUNTIF(L58:N58,0)=3,1,0) -> 1 | P58: =IF(D58<>"扶養","",IF(E58<>"確認待ち",1,IF(OR(AND(G58="本人の結婚",O58=1),AND(H58="減",OR(N58=1,O58=1))),1,0))) | Q58: =COUNTIF('責任職 企業局→市長部局'!A:A,SQLデータ!B58) -> 0 | R58: =COUNTIF('一般職員 企業局→市長部局'!A:F,SQLデータ!B58) -> 0
A59: 202540002515 | B59: 1222023 | C59: 46066 | D59: 住居 | E59: ＳＶ確認中 | G59: NULL | L59: =IF(ISBLANK(J59),0,1) -> 0 | M59: =IF(AND(L59=0,I59<>""),1,0) -> 0 | N59: =IF(AND(L59=0,M59=0,K59<>""),1,0) -> 0 | O59: =IF(COUNTIF(L59:N59,0)=3,1,0) -> 1 | P59: =IF(D59<>"扶養","",IF(E59<>"確認待ち",1,IF(OR(AND(G59="本人の結婚",O59=1),AND(H59="減",OR(N59=1,O59=1))),1,0))) | Q59: =COUNTIF('責任職 企業局→市長部局'!A:A,SQLデータ!B59) -> 0 | R59: =COUNTIF('一般職員 企業局→市長部局'!A:F,SQLデータ!B59) -> 0
A60: 202540002523 | B60: 1252092 | C60: 46083 | D60: 住居 | E60: ＳＶ確認中 | G60: NULL | L60: =IF(ISBLANK(J60),0,1) -> 0 | M60: =IF(AND(L60=0,I60<>""),1,0) -> 0 | N60: =IF(AND(L60=0,M60=0,K60<>""),1,0) -> 0 | O60: =IF(COUNTIF(L60:N60,0)=3,1,0) -> 1 | P60: =IF(D60<>"扶養","",IF(E60<>"確認待ち",1,IF(OR(AND(G60="本人の結婚",O60=1),AND(H60="減",OR(N60=1,O60=1))),1,0))) | Q60: =COUNTIF('責任職 企業局→市長部局'!A:A,SQLデータ!B60) -> 0 | R60: =COUNTIF('一般職員 企業局→市長部局'!A:F,SQLデータ!B60) -> 0
A61: 202540002551 | B61: 1234067 | C61: 46073 | D61: 住居 | E61: 確認待ち | F61: 添付待ち | G61: NULL | L61: =IF(ISBLANK(J61),0,1) -> 0 | M61: =IF(AND(L61=0,I61<>""),1,0) -> 0 | N61: =IF(AND(L61=0,M61=0,K61<>""),1,0) -> 0 | O61: =IF(COUNTIF(L61:N61,0)=3,1,0) -> 1 | P61: =IF(D61<>"扶養","",IF(E61<>"確認待ち",1,IF(OR(AND(G61="本人の結婚",O61=1),AND(H61="減",OR(N61=1,O61=1))),1,0))) | Q61: =COUNTIF('責任職 企業局→市長部局'!A:A,SQLデータ!B61) -> 0 | R61: =COUNTIF('一般職員 企業局→市長部局'!A:F,SQLデータ!B61) -> 0
A62: 202540002587 | B62: 1234070 | C62: 46074 | D62: 住居 | E62: 確認待ち | F62: 1,7 | G62: NULL | L62: =IF(ISBLANK(J62),0,1) -> 0 | M62: =IF(AND(L62=0,I62<>""),1,0) -> 0 | N62: =IF(AND(L62=0,M62=0,K62<>""),1,0) -> 0 | O62: =IF(COUNTIF(L62:N62,0)=3,1,0) -> 1 | P62: =IF(D62<>"扶養","",IF(E62<>"確認待ち",1,IF(OR(AND(G62="本人の結婚",O62=1),AND(H62="減",OR(N62=1,O62=1))),1,0))) | Q62: =COUNTIF('責任職 企業局→市長部局'!A:A,SQLデータ!B62) -> 0 | R62: =COUNTIF('一般職員 企業局→市長部局'!A:F,SQLデータ!B62) -> 0
A63: 202540002621 | B63: 1191168 | C63: 46098 | D63: 住居 | E63: ＳＶ確認中 | G63: NULL | L63: =IF(ISBLANK(J63),0,1) -> 0 | M63: =IF(AND(L63=0,I63<>""),1,0) -> 0 | N63: =IF(AND(L63=0,M63=0,K63<>""),1,0) -> 0 | O63: =IF(COUNTIF(L63:N63,0)=3,1,0) -> 1 | P63: =IF(D63<>"扶養","",IF(E63<>"確認待ち",1,IF(OR(AND(G63="本人の結婚",O63=1),AND(H63="減",OR(N63=1,O63=1))),1,0))) | Q63: =COUNTIF('責任職 企業局→市長部局'!A:A,SQLデータ!B63) -> 0 | R63: =COUNTIF('一般職員 企業局→市長部局'!A:F,SQLデータ!B63) -> 0
A64: 202540002634 | B64: 1086105 | C64: 46090 | D64: 住居 | E64: 申請受付 | G64: NULL | L64: =IF(ISBLANK(J64),0,1) -> 0 | M64: =IF(AND(L64=0,I64<>""),1,0) -> 0 | N64: =IF(AND(L64=0,M64=0,K64<>""),1,0) -> 0 | O64: =IF(COUNTIF(L64:N64,0)=3,1,0) -> 1 | P64: =IF(D64<>"扶養","",IF(E64<>"確認待ち",1,IF(OR(AND(G64="本人の結婚",O64=1),AND(H64="減",OR(N64=1,O64=1))),1,0))) | Q64: =COUNTIF('責任職 企業局→市長部局'!A:A,SQLデータ!B64) -> 0 | R64: =COUNTIF('一般職員 企業局→市長部局'!A:F,SQLデータ!B64) -> 0
A65: 202540002647 | B65: 1191028 | C65: 46083 | D65: 住居 | E65: ＳＶ確認中 | G65: NULL | L65: =IF(ISBLANK(J65),0,1) -> 0 | M65: =IF(AND(L65=0,I65<>""),1,0) -> 0 | N65: =IF(AND(L65=0,M65=0,K65<>""),1,0) -> 0 | O65: =IF(COUNTIF(L65:N65,0)=3,1,0) -> 1 | P65: =IF(D65<>"扶養","",IF(E65<>"確認待ち",1,IF(OR(AND(G65="本人の結婚",O65=1),AND(H65="減",OR(N65=1,O65=1))),1,0))) | Q65: =COUNTIF('責任職 企業局→市長部局'!A:A,SQLデータ!B65) -> 0 | R65: =COUNTIF('一般職員 企業局→市長部局'!A:F,SQLデータ!B65) -> 0
A66: 202540002650 | B66: 1101204 | C66: 46083 | D66: 住居 | E66: ＳＶ確認中 | G66: NULL | L66: =IF(ISBLANK(J66),0,1) -> 0 | M66: =IF(AND(L66=0,I66<>""),1,0) -> 0 | N66: =IF(AND(L66=0,M66=0,K66<>""),1,0) -> 0 | O66: =IF(COUNTIF(L66:N66,0)=3,1,0) -> 1 | P66: =IF(D66<>"扶養","",IF(E66<>"確認待ち",1,IF(OR(AND(G66="本人の結婚",O66=1),AND(H66="減",OR(N66=1,O66=1))),1,0))) | Q66: =COUNTIF('責任職 企業局→市長部局'!A:A,SQLデータ!B66) -> 0 | R66: =COUNTIF('一般職員 企業局→市長部局'!A:F,SQLデータ!B66) -> 0
A67: 202540002655 | B67: 1166137 | C67: 46083 | D67: 住居 | E67: 確認待ち | F67: 添付待ち | G67: NULL | L67: =IF(ISBLANK(J67),0,1) -> 0 | M67: =IF(AND(L67=0,I67<>""),1,0) -> 0 | N67: =IF(AND(L67=0,M67=0,K67<>""),1,0) -> 0 | O67: =IF(COUNTIF(L67:N67,0)=3,1,0) -> 1 | P67: =IF(D67<>"扶養","",IF(E67<>"確認待ち",1,IF(OR(AND(G67="本人の結婚",O67=1),AND(H67="減",OR(N67=1,O67=1))),1,0))) | Q67: =COUNTIF('責任職 企業局→市長部局'!A:A,SQLデータ!B67) -> 0 | R67: =COUNTIF('一般職員 企業局→市長部局'!A:F,SQLデータ!B67) -> 0
A68: 202540002675 | B68: 1243005 | C68: 46085 | D68: 住居 | E68: ＳＶ確認中 | G68: NULL | L68: =IF(ISBLANK(J68),0,1) -> 0 | M68: =IF(AND(L68=0,I68<>""),1,0) -> 0 | N68: =IF(AND(L68=0,M68=0,K68<>""),1,0) -> 0 | O68: =IF(COUNTIF(L68:N68,0)=3,1,0) -> 1 | P68: =IF(D68<>"扶養","",IF(E68<>"確認待ち",1,IF(OR(AND(G68="本人の結婚",O68=1),AND(H68="減",OR(N68=1,O68=1))),1,0))) | Q68: =COUNTIF('責任職 企業局→市長部局'!A:A,SQLデータ!B68) -> 0 | R68: =COUNTIF('一般職員 企業局→市長部局'!A:F,SQLデータ!B68) -> 0
A69: 202540002685 | B69: 1201382 | C69: 46086 | D69: 住居 | E69: ＳＶ確認中 | G69: NULL | L69: =IF(ISBLANK(J69),0,1) -> 0 | M69: =IF(AND(L69=0,I69<>""),1,0) -> 0 | N69: =IF(AND(L69=0,M69=0,K69<>""),1,0) -> 0 | O69: =IF(COUNTIF(L69:N69,0)=3,1,0) -> 1 | P69: =IF(D69<>"扶養","",IF(E69<>"確認待ち",1,IF(OR(AND(G69="本人の結婚",O69=1),AND(H69="減",OR(N69=1,O69=1))),1,0))) | Q69: =COUNTIF('責任職 企業局→市長部局'!A:A,SQLデータ!B69) -> 0 | R69: =COUNTIF('一般職員 企業局→市長部局'!A:F,SQLデータ!B69) -> 0
A70: 202540002686 | B70: 1201057 | C70: 46085 | D70: 住居 | E70: ＳＶ確認中 | G70: NULL | L70: =IF(ISBLANK(J70),0,1) -> 0 | M70: =IF(AND(L70=0,I70<>""),1,0) -> 0 | N70: =IF(AND(L70=0,M70=0,K70<>""),1,0) -> 0 | O70: =IF(COUNTIF(L70:N70,0)=3,1,0) -> 1 | P70: =IF(D70<>"扶養","",IF(E70<>"確認待ち",1,IF(OR(AND(G70="本人の結婚",O70=1),AND(H70="減",OR(N70=1,O70=1))),1,0))) | Q70: =COUNTIF('責任職 企業局→市長部局'!A:A,SQLデータ!B70) -> 0 | R70: =COUNTIF('一般職員 企業局→市長部局'!A:F,SQLデータ!B70) -> 0
A71: 202540002703 | B71: 1081380 | C71: 46098 | D71: 住居 | E71: ＳＶ確認中 | G71: NULL | L71: =IF(ISBLANK(J71),0,1) -> 0 | M71: =IF(AND(L71=0,I71<>""),1,0) -> 0 | N71: =IF(AND(L71=0,M71=0,K71<>""),1,0) -> 0 | O71: =IF(COUNTIF(L71:N71,0)=3,1,0) -> 1 | P71: =IF(D71<>"扶養","",IF(E71<>"確認待ち",1,IF(OR(AND(G71="本人の結婚",O71=1),AND(H71="減",OR(N71=1,O71=1))),1,0))) | Q71: =COUNTIF('責任職 企業局→市長部局'!A:A,SQLデータ!B71) -> 0 | R71: =COUNTIF('一般職員 企業局→市長部局'!A:F,SQLデータ!B71) -> 0
A72: 202540002704 | B72: 1221154 | C72: 46087 | D72: 住居 | E72: ＳＶ確認中 | G72: NULL | L72: =IF(ISBLANK(J72),0,1) -> 0 | M72: =IF(AND(L72=0,I72<>""),1,0) -> 0 | N72: =IF(AND(L72=0,M72=0,K72<>""),1,0) -> 0 | O72: =IF(COUNTIF(L72:N72,0)=3,1,0) -> 1 | P72: =IF(D72<>"扶養","",IF(E72<>"確認待ち",1,IF(OR(AND(G72="本人の結婚",O72=1),AND(H72="減",OR(N72=1,O72=1))),1,0))) | Q72: =COUNTIF('責任職 企業局→市長部局'!A:A,SQLデータ!B72) -> 0 | R72: =COUNTIF('一般職員 企業局→市長部局'!A:F,SQLデータ!B72) -> 0
A73: 202540002706 | B73: 1201271 | C73: 46087 | D73: 住居 | E73: ＳＶ確認中 | G73: NULL | L73: =IF(ISBLANK(J73),0,1) -> 0 | M73: =IF(AND(L73=0,I73<>""),1,0) -> 0 | N73: =IF(AND(L73=0,M73=0,K73<>""),1,0) -> 0 | O73: =IF(COUNTIF(L73:N73,0)=3,1,0) -> 1 | P73: =IF(D73<>"扶養","",IF(E73<>"確認待ち",1,IF(OR(AND(G73="本人の結婚",O73=1),AND(H73="減",OR(N73=1,O73=1))),1,0))) | Q73: =COUNTIF('責任職 企業局→市長部局'!A:A,SQLデータ!B73) -> 0 | R73: =COUNTIF('一般職員 企業局→市長部局'!A:F,SQLデータ!B73) -> 0
A74: 202540002709 | B74: 1201519 | C74: 46087 | D74: 住居 | E74: 確認待ち | F74: 添付待ち | G74: NULL | L74: =IF(ISBLANK(J74),0,1) -> 0 | M74: =IF(AND(L74=0,I74<>""),1,0) -> 0 | N74: =IF(AND(L74=0,M74=0,K74<>""),1,0) -> 0 | O74: =IF(COUNTIF(L74:N74,0)=3,1,0) -> 1 | P74: =IF(D74<>"扶養","",IF(E74<>"確認待ち",1,IF(OR(AND(G74="本人の結婚",O74=1),AND(H74="減",OR(N74=1,O74=1))),1,0))) | Q74: =COUNTIF('責任職 企業局→市長部局'!A:A,SQLデータ!B74) -> 0 | R74: =COUNTIF('一般職員 企業局→市長部局'!A:F,SQLデータ!B74) -> 0
A75: 202540002710 | B75: 1191055 | C75: 46087 | D75: 住居 | E75: ＳＶ確認中 | G75: NULL | L75: =IF(ISBLANK(J75),0,1) -> 0 | M75: =IF(AND(L75=0,I75<>""),1,0) -> 0 | N75: =IF(AND(L75=0,M75=0,K75<>""),1,0) -> 0 | O75: =IF(COUNTIF(L75:N75,0)=3,1,0) -> 1 | P75: =IF(D75<>"扶養","",IF(E75<>"確認待ち",1,IF(OR(AND(G75="本人の結婚",O75=1),AND(H75="減",OR(N75=1,O75=1))),1,0))) | Q75: =COUNTIF('責任職 企業局→市長部局'!A:A,SQLデータ!B75) -> 0 | R75: =COUNTIF('一般職員 企業局→市長部局'!A:F,SQLデータ!B75) -> 0
A76: 202540002717 | B76: 1201328 | C76: 46090 | D76: 住居 | E76: ＳＶ確認中 | G76: NULL | L76: =IF(ISBLANK(J76),0,1) -> 0 | M76: =IF(AND(L76=0,I76<>""),1,0) -> 0 | N76: =IF(AND(L76=0,M76=0,K76<>""),1,0) -> 0 | O76: =IF(COUNTIF(L76:N76,0)=3,1,0) -> 1 | P76: =IF(D76<>"扶養","",IF(E76<>"確認待ち",1,IF(OR(AND(G76="本人の結婚",O76=1),AND(H76="減",OR(N76=1,O76=1))),1,0))) | Q76: =COUNTIF('責任職 企業局→市長部局'!A:A,SQLデータ!B76) -> 0 | R76: =COUNTIF('一般職員 企業局→市長部局'!A:F,SQLデータ!B76) -> 0
A77: 202540002718 | B77: 1254047 | C77: 46090 | D77: 住居 | E77: 申請受付 | G77: NULL | L77: =IF(ISBLANK(J77),0,1) -> 0 | M77: =IF(AND(L77=0,I77<>""),1,0) -> 0 | N77: =IF(AND(L77=0,M77=0,K77<>""),1,0) -> 0 | O77: =IF(COUNTIF(L77:N77,0)=3,1,0) -> 1 | P77: =IF(D77<>"扶養","",IF(E77<>"確認待ち",1,IF(OR(AND(G77="本人の結婚",O77=1),AND(H77="減",OR(N77=1,O77=1))),1,0))) | Q77: =COUNTIF('責任職 企業局→市長部局'!A:A,SQLデータ!B77) -> 0 | R77: =COUNTIF('一般職員 企業局→市長部局'!A:F,SQLデータ!B77) -> 0
A78: 202540002727 | B78: 1233006 | C78: 46090 | D78: 住居 | E78: ＳＶ確認中 | G78: NULL | L78: =IF(ISBLANK(J78),0,1) -> 0 | M78: =IF(AND(L78=0,I78<>""),1,0) -> 0 | N78: =IF(AND(L78=0,M78=0,K78<>""),1,0) -> 0 | O78: =IF(COUNTIF(L78:N78,0)=3,1,0) -> 1 | P78: =IF(D78<>"扶養","",IF(E78<>"確認待ち",1,IF(OR(AND(G78="本人の結婚",O78=1),AND(H78="減",OR(N78=1,O78=1))),1,0))) | Q78: =COUNTIF('責任職 企業局→市長部局'!A:A,SQLデータ!B78) -> 0 | R78: =COUNTIF('一般職員 企業局→市長部局'!A:F,SQLデータ!B78) -> 0
A79: 202540002731 | B79: 1211374 | C79: 46115 | D79: 住居 | E79: 申請受付 | F79: 保留中 | G79: NULL | L79: =IF(ISBLANK(J79),0,1) -> 0 | M79: =IF(AND(L79=0,I79<>""),1,0) -> 0 | N79: =IF(AND(L79=0,M79=0,K79<>""),1,0) -> 0 | O79: =IF(COUNTIF(L79:N79,0)=3,1,0) -> 1 | P79: =IF(D79<>"扶養","",IF(E79<>"確認待ち",1,IF(OR(AND(G79="本人の結婚",O79=1),AND(H79="減",OR(N79=1,O79=1))),1,0))) | Q79: =COUNTIF('責任職 企業局→市長部局'!A:A,SQLデータ!B79) -> 0 | R79: =COUNTIF('一般職員 企業局→市長部局'!A:F,SQLデータ!B79) -> 0
A80: 202540002733 | B80: 1226096 | C80: 46091 | D80: 住居 | E80: ＳＶ確認中 | G80: NULL | L80: =IF(ISBLANK(J80),0,1) -> 0 | M80: =IF(AND(L80=0,I80<>""),1,0) -> 0 | N80: =IF(AND(L80=0,M80=0,K80<>""),1,0) -> 0 | O80: =IF(COUNTIF(L80:N80,0)=3,1,0) -> 1 | P80: =IF(D80<>"扶養","",IF(E80<>"確認待ち",1,IF(OR(AND(G80="本人の結婚",O80=1),AND(H80="減",OR(N80=1,O80=1))),1,0))) | Q80: =COUNTIF('責任職 企業局→市長部局'!A:A,SQLデータ!B80) -> 0 | R80: =COUNTIF('一般職員 企業局→市長部局'!A:F,SQLデータ!B80) -> 0
A81: 202540002742 | B81: 1201070 | C81: 46091 | D81: 住居 | E81: 確認済 | G81: NULL | L81: =IF(ISBLANK(J81),0,1) -> 0 | M81: =IF(AND(L81=0,I81<>""),1,0) -> 0 | N81: =IF(AND(L81=0,M81=0,K81<>""),1,0) -> 0 | O81: =IF(COUNTIF(L81:N81,0)=3,1,0) -> 1 | P81: =IF(D81<>"扶養","",IF(E81<>"確認待ち",1,IF(OR(AND(G81="本人の結婚",O81=1),AND(H81="減",OR(N81=1,O81=1))),1,0))) | Q81: =COUNTIF('責任職 企業局→市長部局'!A:A,SQLデータ!B81) -> 0 | R81: =COUNTIF('一般職員 企業局→市長部局'!A:F,SQLデータ!B81) -> 0
A82: 202540002745 | B82: 1211467 | C82: 46092 | D82: 住居 | E82: ＳＶ確認中 | G82: NULL | L82: =IF(ISBLANK(J82),0,1) -> 0 | M82: =IF(AND(L82=0,I82<>""),1,0) -> 0 | N82: =IF(AND(L82=0,M82=0,K82<>""),1,0) -> 0 | O82: =IF(COUNTIF(L82:N82,0)=3,1,0) -> 1 | P82: =IF(D82<>"扶養","",IF(E82<>"確認待ち",1,IF(OR(AND(G82="本人の結婚",O82=1),AND(H82="減",OR(N82=1,O82=1))),1,0))) | Q82: =COUNTIF('責任職 企業局→市長部局'!A:A,SQLデータ!B82) -> 0 | R82: =COUNTIF('一般職員 企業局→市長部局'!A:F,SQLデータ!B82) -> 0
A83: 202540002755 | B83: 1186065 | C83: 46093 | D83: 住居 | E83: ＳＶ確認中 | G83: NULL | L83: =IF(ISBLANK(J83),0,1) -> 0 | M83: =IF(AND(L83=0,I83<>""),1,0) -> 0 | N83: =IF(AND(L83=0,M83=0,K83<>""),1,0) -> 0 | O83: =IF(COUNTIF(L83:N83,0)=3,1,0) -> 1 | P83: =IF(D83<>"扶養","",IF(E83<>"確認待ち",1,IF(OR(AND(G83="本人の結婚",O83=1),AND(H83="減",OR(N83=1,O83=1))),1,0))) | Q83: =COUNTIF('責任職 企業局→市長部局'!A:A,SQLデータ!B83) -> 0 | R83: =COUNTIF('一般職員 企業局→市長部局'!A:F,SQLデータ!B83) -> 0
A84: 202540002764 | B84: 910964 | C84: 46093 | D84: 住居 | E84: 申請受付 | F84: 保留中 | G84: NULL | L84: =IF(ISBLANK(J84),0,1) -> 0 | M84: =IF(AND(L84=0,I84<>""),1,0) -> 0 | N84: =IF(AND(L84=0,M84=0,K84<>""),1,0) -> 0 | O84: =IF(COUNTIF(L84:N84,0)=3,1,0) -> 1 | P84: =IF(D84<>"扶養","",IF(E84<>"確認待ち",1,IF(OR(AND(G84="本人の結婚",O84=1),AND(H84="減",OR(N84=1,O84=1))),1,0))) | Q84: =COUNTIF('責任職 企業局→市長部局'!A:A,SQLデータ!B84) -> 0 | R84: =COUNTIF('一般職員 企業局→市長部局'!A:F,SQLデータ!B84) -> 0
A85: 202540002776 | B85: 1226129 | C85: 46094 | D85: 住居 | E85: ＳＶ確認中 | G85: NULL | L85: =IF(ISBLANK(J85),0,1) -> 0 | M85: =IF(AND(L85=0,I85<>""),1,0) -> 0 | N85: =IF(AND(L85=0,M85=0,K85<>""),1,0) -> 0 | O85: =IF(COUNTIF(L85:N85,0)=3,1,0) -> 1 | P85: =IF(D85<>"扶養","",IF(E85<>"確認待ち",1,IF(OR(AND(G85="本人の結婚",O85=1),AND(H85="減",OR(N85=1,O85=1))),1,0))) | Q85: =COUNTIF('責任職 企業局→市長部局'!A:A,SQLデータ!B85) -> 0 | R85: =COUNTIF('一般職員 企業局→市長部局'!A:F,SQLデータ!B85) -> 0
A86: 202540002786 | B86: 1186154 | C86: 46098 | D86: 住居 | E86: ＳＶ確認中 | G86: NULL | L86: =IF(ISBLANK(J86),0,1) -> 0 | M86: =IF(AND(L86=0,I86<>""),1,0) -> 0 | N86: =IF(AND(L86=0,M86=0,K86<>""),1,0) -> 0 | O86: =IF(COUNTIF(L86:N86,0)=3,1,0) -> 1 | P86: =IF(D86<>"扶養","",IF(E86<>"確認待ち",1,IF(OR(AND(G86="本人の結婚",O86=1),AND(H86="減",OR(N86=1,O86=1))),1,0))) | Q86: =COUNTIF('責任職 企業局→市長部局'!A:A,SQLデータ!B86) -> 0 | R86: =COUNTIF('一般職員 企業局→市長部局'!A:F,SQLデータ!B86) -> 0
A87: 202540002792 | B87: 930600 | C87: 46125 | D87: 住居 | E87: ＯＰ確認中 | G87: NULL | L87: =IF(ISBLANK(J87),0,1) -> 0 | M87: =IF(AND(L87=0,I87<>""),1,0) -> 0 | N87: =IF(AND(L87=0,M87=0,K87<>""),1,0) -> 0 | O87: =IF(COUNTIF(L87:N87,0)=3,1,0) -> 1 | P87: =IF(D87<>"扶養","",IF(E87<>"確認待ち",1,IF(OR(AND(G87="本人の結婚",O87=1),AND(H87="減",OR(N87=1,O87=1))),1,0))) | Q87: =COUNTIF('責任職 企業局→市長部局'!A:A,SQLデータ!B87) -> 0 | R87: =COUNTIF('一般職員 企業局→市長部局'!A:F,SQLデータ!B87) -> 0
A88: 202540002794 | B88: 1191365 | C88: 46097 | D88: 住居 | E88: ＳＶ確認中 | G88: NULL | L88: =IF(ISBLANK(J88),0,1) -> 0 | M88: =IF(AND(L88=0,I88<>""),1,0) -> 0 | N88: =IF(AND(L88=0,M88=0,K88<>""),1,0) -> 0 | O88: =IF(COUNTIF(L88:N88,0)=3,1,0) -> 1 | P88: =IF(D88<>"扶養","",IF(E88<>"確認待ち",1,IF(OR(AND(G88="本人の結婚",O88=1),AND(H88="減",OR(N88=1,O88=1))),1,0))) | Q88: =COUNTIF('責任職 企業局→市長部局'!A:A,SQLデータ!B88) -> 0 | R88: =COUNTIF('一般職員 企業局→市長部局'!A:F,SQLデータ!B88) -> 0
A89: 202540002797 | B89: 1201456 | C89: 46097 | D89: 住居 | E89: ＳＶ確認中 | G89: NULL | L89: =IF(ISBLANK(J89),0,1) -> 0 | M89: =IF(AND(L89=0,I89<>""),1,0) -> 0 | N89: =IF(AND(L89=0,M89=0,K89<>""),1,0) -> 0 | O89: =IF(COUNTIF(L89:N89,0)=3,1,0) -> 1 | P89: =IF(D89<>"扶養","",IF(E89<>"確認待ち",1,IF(OR(AND(G89="本人の結婚",O89=1),AND(H89="減",OR(N89=1,O89=1))),1,0))) | Q89: =COUNTIF('責任職 企業局→市長部局'!A:A,SQLデータ!B89) -> 0 | R89: =COUNTIF('一般職員 企業局→市長部局'!A:F,SQLデータ!B89) -> 0
A90: 202540002801 | B90: 1102111 | C90: 46098 | D90: 住居 | E90: 確認待ち | F90: 添付待ち | G90: NULL | L90: =IF(ISBLANK(J90),0,1) -> 0 | M90: =IF(AND(L90=0,I90<>""),1,0) -> 0 | N90: =IF(AND(L90=0,M90=0,K90<>""),1,0) -> 0 | O90: =IF(COUNTIF(L90:N90,0)=3,1,0) -> 1 | P90: =IF(D90<>"扶養","",IF(E90<>"確認待ち",1,IF(OR(AND(G90="本人の結婚",O90=1),AND(H90="減",OR(N90=1,O90=1))),1,0))) | Q90: =COUNTIF('責任職 企業局→市長部局'!A:A,SQLデータ!B90) -> 0 | R90: =COUNTIF('一般職員 企業局→市長部局'!A:F,SQLデータ!B90) -> 0
A91: 202540002817 | B91: 1221491 | C91: 46098 | D91: 住居 | E91: ＳＶ確認中 | G91: NULL | L91: =IF(ISBLANK(J91),0,1) -> 0 | M91: =IF(AND(L91=0,I91<>""),1,0) -> 0 | N91: =IF(AND(L91=0,M91=0,K91<>""),1,0) -> 0 | O91: =IF(COUNTIF(L91:N91,0)=3,1,0) -> 1 | P91: =IF(D91<>"扶養","",IF(E91<>"確認待ち",1,IF(OR(AND(G91="本人の結婚",O91=1),AND(H91="減",OR(N91=1,O91=1))),1,0))) | Q91: =COUNTIF('責任職 企業局→市長部局'!A:A,SQLデータ!B91) -> 0 | R91: =COUNTIF('一般職員 企業局→市長部局'!A:F,SQLデータ!B91) -> 0
A92: 202540002818 | B92: 1232017 | C92: 46098 | D92: 住居 | E92: 確認待ち | F92: 添付待ち | G92: NULL | L92: =IF(ISBLANK(J92),0,1) -> 0 | M92: =IF(AND(L92=0,I92<>""),1,0) -> 0 | N92: =IF(AND(L92=0,M92=0,K92<>""),1,0) -> 0 | O92: =IF(COUNTIF(L92:N92,0)=3,1,0) -> 1 | P92: =IF(D92<>"扶養","",IF(E92<>"確認待ち",1,IF(OR(AND(G92="本人の結婚",O92=1),AND(H92="減",OR(N92=1,O92=1))),1,0))) | Q92: =COUNTIF('責任職 企業局→市長部局'!A:A,SQLデータ!B92) -> 0 | R92: =COUNTIF('一般職員 企業局→市長部局'!A:F,SQLデータ!B92) -> 0
A93: 202540002819 | B93: 1251296 | C93: 46098 | D93: 住居 | E93: ＳＶ確認中 | G93: NULL | L93: =IF(ISBLANK(J93),0,1) -> 0 | M93: =IF(AND(L93=0,I93<>""),1,0) -> 0 | N93: =IF(AND(L93=0,M93=0,K93<>""),1,0) -> 0 | O93: =IF(COUNTIF(L93:N93,0)=3,1,0) -> 1 | P93: =IF(D93<>"扶養","",IF(E93<>"確認待ち",1,IF(OR(AND(G93="本人の結婚",O93=1),AND(H93="減",OR(N93=1,O93=1))),1,0))) | Q93: =COUNTIF('責任職 企業局→市長部局'!A:A,SQLデータ!B93) -> 0 | R93: =COUNTIF('一般職員 企業局→市長部局'!A:F,SQLデータ!B93) -> 0
A94: 202540002821 | B94: 1206033 | C94: 46100 | D94: 住居 | E94: 確認待ち | F94: 添付待ち | G94: NULL | L94: =IF(ISBLANK(J94),0,1) -> 0 | M94: =IF(AND(L94=0,I94<>""),1,0) -> 0 | N94: =IF(AND(L94=0,M94=0,K94<>""),1,0) -> 0 | O94: =IF(COUNTIF(L94:N94,0)=3,1,0) -> 1 | P94: =IF(D94<>"扶養","",IF(E94<>"確認待ち",1,IF(OR(AND(G94="本人の結婚",O94=1),AND(H94="減",OR(N94=1,O94=1))),1,0))) | Q94: =COUNTIF('責任職 企業局→市長部局'!A:A,SQLデータ!B94) -> 0 | R94: =COUNTIF('一般職員 企業局→市長部局'!A:F,SQLデータ!B94) -> 0
A95: 202540002827 | B95: 1144034 | C95: 46100 | D95: 住居 | E95: 確認待ち | F95: 添付待ち | G95: NULL | L95: =IF(ISBLANK(J95),0,1) -> 0 | M95: =IF(AND(L95=0,I95<>""),1,0) -> 0 | N95: =IF(AND(L95=0,M95=0,K95<>""),1,0) -> 0 | O95: =IF(COUNTIF(L95:N95,0)=3,1,0) -> 1 | P95: =IF(D95<>"扶養","",IF(E95<>"確認待ち",1,IF(OR(AND(G95="本人の結婚",O95=1),AND(H95="減",OR(N95=1,O95=1))),1,0))) | Q95: =COUNTIF('責任職 企業局→市長部局'!A:A,SQLデータ!B95) -> 0 | R95: =COUNTIF('一般職員 企業局→市長部局'!A:F,SQLデータ!B95) -> 0
A96: 202540002828 | B96: 1226077 | C96: 46100 | D96: 住居 | E96: 申請受付 | G96: NULL | L96: =IF(ISBLANK(J96),0,1) -> 0 | M96: =IF(AND(L96=0,I96<>""),1,0) -> 0 | N96: =IF(AND(L96=0,M96=0,K96<>""),1,0) -> 0 | O96: =IF(COUNTIF(L96:N96,0)=3,1,0) -> 1 | P96: =IF(D96<>"扶養","",IF(E96<>"確認待ち",1,IF(OR(AND(G96="本人の結婚",O96=1),AND(H96="減",OR(N96=1,O96=1))),1,0))) | Q96: =COUNTIF('責任職 企業局→市長部局'!A:A,SQLデータ!B96) -> 0 | R96: =COUNTIF('一般職員 企業局→市長部局'!A:F,SQLデータ!B96) -> 0
A97: 202540002829 | B97: 1253013 | C97: 46100 | D97: 住居 | E97: 申請受付 | G97: NULL | L97: =IF(ISBLANK(J97),0,1) -> 0 | M97: =IF(AND(L97=0,I97<>""),1,0) -> 0 | N97: =IF(AND(L97=0,M97=0,K97<>""),1,0) -> 0 | O97: =IF(COUNTIF(L97:N97,0)=3,1,0) -> 1 | P97: =IF(D97<>"扶養","",IF(E97<>"確認待ち",1,IF(OR(AND(G97="本人の結婚",O97=1),AND(H97="減",OR(N97=1,O97=1))),1,0))) | Q97: =COUNTIF('責任職 企業局→市長部局'!A:A,SQLデータ!B97) -> 0 | R97: =COUNTIF('一般職員 企業局→市長部局'!A:F,SQLデータ!B97) -> 0
A98: 202540002838 | B98: 1106098 | C98: 46102 | D98: 住居 | E98: ＳＶ確認中 | G98: NULL | L98: =IF(ISBLANK(J98),0,1) -> 0 | M98: =IF(AND(L98=0,I98<>""),1,0) -> 0 | N98: =IF(AND(L98=0,M98=0,K98<>""),1,0) -> 0 | O98: =IF(COUNTIF(L98:N98,0)=3,1,0) -> 1 | P98: =IF(D98<>"扶養","",IF(E98<>"確認待ち",1,IF(OR(AND(G98="本人の結婚",O98=1),AND(H98="減",OR(N98=1,O98=1))),1,0))) | Q98: =COUNTIF('責任職 企業局→市長部局'!A:A,SQLデータ!B98) -> 0 | R98: =COUNTIF('一般職員 企業局→市長部局'!A:F,SQLデータ!B98) -> 0
A99: 202540002857 | B99: 1216111 | C99: 46104 | D99: 住居 | E99: 確認待ち | F99: 添付待ち | G99: NULL | L99: =IF(ISBLANK(J99),0,1) -> 0 | M99: =IF(AND(L99=0,I99<>""),1,0) -> 0 | N99: =IF(AND(L99=0,M99=0,K99<>""),1,0) -> 0 | O99: =IF(COUNTIF(L99:N99,0)=3,1,0) -> 1 | P99: =IF(D99<>"扶養","",IF(E99<>"確認待ち",1,IF(OR(AND(G99="本人の結婚",O99=1),AND(H99="減",OR(N99=1,O99=1))),1,0))) | Q99: =COUNTIF('責任職 企業局→市長部局'!A:A,SQLデータ!B99) -> 0 | R99: =COUNTIF('一般職員 企業局→市長部局'!A:F,SQLデータ!B99) -> 0
A100: 202540002861 | B100: 1234124 | C100: 46105 | D100: 住居 | E100: ＳＶ確認中 | F100: オペレータ保留 | G100: NULL | L100: =IF(ISBLANK(J100),0,1) -> 0 | M100: =IF(AND(L100=0,I100<>""),1,0) -> 0 | N100: =IF(AND(L100=0,M100=0,K100<>""),1,0) -> 0 | O100: =IF(COUNTIF(L100:N100,0)=3,1,0) -> 1 | P100: =IF(D100<>"扶養","",IF(E100<>"確認待ち",1,IF(OR(AND(G100="本人の結婚",O100=1),AND(H100="減",OR(N100=1,O100=1))),1,0))) | Q100: =COUNTIF('責任職 企業局→市長部局'!A:A,SQLデータ!B100) -> 0 | R100: =COUNTIF('一般職員 企業局→市長部局'!A:F,SQLデータ!B100) -> 0
...

Sheet 届出事由・区分・届出年月日ごと集計
A1: 増減 | B1: 届出事由 | C1: 区分 | D1: 申請件数 | E1: 開始日 | F1: 45658 | G1: 46111 | H1: =G1+7 -> 46118 | I1: =H1+7 -> 46125 | J1: =I1+7 -> 46132 | K1: =J1+7 -> 46139 | L1: =K1+7 -> 46146 | M1: =L1+7 -> 46153 | N1: =M1+7 -> 46160 | O1: =N1+7 -> 46167 | ... T1: =S1+7 -> 46202
E2: 終了日 | F2: 46110 | G2: 46117 | H2: =G2+7 -> 46124 | I2: =H2+7 -> 46131 | J2: =I2+7 -> 46138 | K2: =J2+7 -> 46145 | L2: =K2+7 -> 46152 | M2: =L2+7 -> 46159 | N2: =M2+7 -> 46166 | O2: =N2+7 -> 46173 | ... T2: =S2+7 -> 46208
A3: 増 | B3: 出生 | C3: 共済あり | D3: =COUNTIFS(SQLデータ!$D:$D,"扶養",SQLデータ!$H:$H,届出事由・区分・届出年月日ごと集計!$A3,SQLデータ!$G:$G,届出事由・区分・届出年月日ごと集計!$B3,SQLデータ!$L:$L,1) -> 17 | F3: =COUNTIFS(SQLデータ!$D:$D,"扶養",SQLデータ!$P:$P,1,SQLデータ!$H:$H,届出事由・区分・届出年月日ごと集計!$A3,SQLデータ!$G:$G,届出事由・区分・届出年月日ごと集計!$B3,SQLデータ!$L:$L,1,SQLデータ!$F:$F,"",SQLデータ!$C:$C,">="&届出事由・区分・届出年月日ごと集計!F$1,SQLデータ!$C:$C,"<="&届出事由・区分・届出年月日ごと集計!F$2) -> 1 | G3: =COUNTIFS(SQLデータ!$D:$D,"扶養",SQLデータ!$P:$P,1,SQLデータ!$H:$H,届出事由・区分・届出年月日ごと集計!$A3,SQLデータ!$G:$G,届出事由・区分・届出年月日ごと集計!$B3,SQLデータ!$L:$L,1,SQLデータ!$F:$F,"",SQLデータ!$C:$C,">="&届出事由・区分・届出年月日ごと集計!G$1,SQLデータ!$C:$C,"<="&届出事由・区分・届出年月日ごと集計!G$2) -> 0 | H3: =COUNTIFS(SQLデータ!$D:$D,"扶養",SQLデータ!$P:$P,1,SQLデータ!$H:$H,届出事由・区分・届出年月日ごと集計!$A3,SQLデータ!$G:$G,届出事由・区分・届出年月日ごと集計!$B3,SQLデータ!$L:$L,1,SQLデータ!$F:$F,"",SQLデータ!$C:$C,">="&届出事由・区分・届出年月日ごと集計!H$1,SQLデータ!$C:$C,"<="&届出事由・区分・届出年月日ごと集計!H$2) -> 0 | I3: =COUNTIFS(SQLデータ!$D:$D,"扶養",SQLデータ!$P:$P,1,SQLデータ!$H:$H,届出事由・区分・届出年月日ごと集計!$A3,SQLデータ!$G:$G,届出事由・区分・届出年月日ごと集計!$B3,SQLデータ!$L:$L,1,SQLデータ!$F:$F,"",SQLデータ!$C:$C,">="&届出事由・区分・届出年月日ごと集計!I$1,SQLデータ!$C:$C,"<="&届出事由・区分・届出年月日ごと集計!I$2) -> 1 | J3: =COUNTIFS(SQLデータ!$D:$D,"扶養",SQLデータ!$P:$P,1,SQLデータ!$H:$H,届出事由・区分・届出年月日ごと集計!$A3,SQLデータ!$G:$G,届出事由・区分・届出年月日ごと集計!$B3,SQLデータ!$L:$L,1,SQLデータ!$F:$F,"",SQLデータ!$C:$C,">="&届出事由・区分・届出年月日ごと集計!J$1,SQLデータ!$C:$C,"<="&届出事由・区分・届出年月日ごと集計!J$2) -> 0 | K3: =COUNTIFS(SQLデータ!$D:$D,"扶養",SQLデータ!$P:$P,1,SQLデータ!$H:$H,届出事由・区分・届出年月日ごと集計!$A3,SQLデータ!$G:$G,届出事由・区分・届出年月日ごと集計!$B3,SQLデータ!$L:$L,1,SQLデータ!$F:$F,"",SQLデータ!$C:$C,">="&届出事由・区分・届出年月日ごと集計!K$1,SQLデータ!$C:$C,"<="&届出事由・区分・届出年月日ごと集計!K$2) -> 0 | L3: =COUNTIFS(SQLデータ!$D:$D,"扶養",SQLデータ!$P:$P,1,SQLデータ!$H:$H,届出事由・区分・届出年月日ごと集計!$A3,SQLデータ!$G:$G,届出事由・区分・届出年月日ごと集計!$B3,SQLデータ!$L:$L,1,SQLデータ!$F:$F,"",SQLデータ!$C:$C,">="&届出事由・区分・届出年月日ごと集計!L$1,SQLデータ!$C:$C,"<="&届出事由・区分・届出年月日ごと集計!L$2) -> 0 | M3: =COUNTIFS(SQLデータ!$D:$D,"扶養",SQLデータ!$P:$P,1,SQLデータ!$H:$H,届出事由・区分・届出年月日ごと集計!$A3,SQLデータ!$G:$G,届出事由・区分・届出年月日ごと集計!$B3,SQLデータ!$L:$L,1,SQLデータ!$F:$F,"",SQLデータ!$C:$C,">="&届出事由・区分・届出年月日ごと集計!M$1,SQLデータ!$C:$C,"<="&届出事由・区分・届出年月日ごと集計!M$2) -> 0 | ... T3: =COUNTIFS(SQLデータ!$D:$D,"扶養",SQLデータ!$P:$P,1,SQLデータ!$H:$H,届出事由・区分・届出年月日ごと集計!$A3,SQLデータ!$G:$G,届出事由・区分・届出年月日ごと集計!$B3,SQLデータ!$L:$L,1,SQLデータ!$F:$F,"",SQLデータ!$C:$C,">="&届出事由・区分・届出年月日ごと集計!T$1,SQLデータ!$C:$C,"<="&届出事由・区分・届出年月日ごと集計!T$2) -> 0
A4: 増 | B4: 出生 | C4: 扶養手当あり | D4: =COUNTIFS(SQLデータ!$D:$D,"扶養",SQLデータ!$H:$H,届出事由・区分・届出年月日ごと集計!$A4,SQLデータ!$G:$G,届出事由・区分・届出年月日ごと集計!$B4,SQLデータ!$M:$M,1) -> 2 | F4: =COUNTIFS(SQLデータ!$D:$D,"扶養",SQLデータ!$P:$P,1,SQLデータ!$H:$H,届出事由・区分・届出年月日ごと集計!$A4,SQLデータ!$G:$G,届出事由・区分・届出年月日ごと集計!$B4,SQLデータ!$M:$M,1,SQLデータ!$F:$F,"",SQLデータ!$C:$C,">="&届出事由・区分・届出年月日ごと集計!F$1,SQLデータ!$C:$C,"<="&届出事由・区分・届出年月日ごと集計!F$2) -> 0 | G4: =COUNTIFS(SQLデータ!$D:$D,"扶養",SQLデータ!$P:$P,1,SQLデータ!$H:$H,届出事由・区分・届出年月日ごと集計!$A4,SQLデータ!$G:$G,届出事由・区分・届出年月日ごと集計!$B4,SQLデータ!$M:$M,1,SQLデータ!$F:$F,"",SQLデータ!$C:$C,">="&届出事由・区分・届出年月日ごと集計!G$1,SQLデータ!$C:$C,"<="&届出事由・区分・届出年月日ごと集計!G$2) -> 0 | H4: =COUNTIFS(SQLデータ!$D:$D,"扶養",SQLデータ!$P:$P,1,SQLデータ!$H:$H,届出事由・区分・届出年月日ごと集計!$A4,SQLデータ!$G:$G,届出事由・区分・届出年月日ごと集計!$B4,SQLデータ!$M:$M,1,SQLデータ!$F:$F,"",SQLデータ!$C:$C,">="&届出事由・区分・届出年月日ごと集計!H$1,SQLデータ!$C:$C,"<="&届出事由・区分・届出年月日ごと集計!H$2) -> 0 | I4: =COUNTIFS(SQLデータ!$D:$D,"扶養",SQLデータ!$P:$P,1,SQLデータ!$H:$H,届出事由・区分・届出年月日ごと集計!$A4,SQLデータ!$G:$G,届出事由・区分・届出年月日ごと集計!$B4,SQLデータ!$M:$M,1,SQLデータ!$F:$F,"",SQLデータ!$C:$C,">="&届出事由・区分・届出年月日ごと集計!I$1,SQLデータ!$C:$C,"<="&届出事由・区分・届出年月日ごと集計!I$2) -> 0 | J4: =COUNTIFS(SQLデータ!$D:$D,"扶養",SQLデータ!$P:$P,1,SQLデータ!$H:$H,届出事由・区分・届出年月日ごと集計!$A4,SQLデータ!$G:$G,届出事由・区分・届出年月日ごと集計!$B4,SQLデータ!$M:$M,1,SQLデータ!$F:$F,"",SQLデータ!$C:$C,">="&届出事由・区分・届出年月日ごと集計!J$1,SQLデータ!$C:$C,"<="&届出事由・区分・届出年月日ごと集計!J$2) -> 0 | K4: =COUNTIFS(SQLデータ!$D:$D,"扶養",SQLデータ!$P:$P,1,SQLデータ!$H:$H,届出事由・区分・届出年月日ごと集計!$A4,SQLデータ!$G:$G,届出事由・区分・届出年月日ごと集計!$B4,SQLデータ!$M:$M,1,SQLデータ!$F:$F,"",SQLデータ!$C:$C,">="&届出事由・区分・届出年月日ごと集計!K$1,SQLデータ!$C:$C,"<="&届出事由・区分・届出年月日ごと集計!K$2) -> 0 | L4: =COUNTIFS(SQLデータ!$D:$D,"扶養",SQLデータ!$P:$P,1,SQLデータ!$H:$H,届出事由・区分・届出年月日ごと集計!$A4,SQLデータ!$G:$G,届出事由・区分・届出年月日ごと集計!$B4,SQLデータ!$M:$M,1,SQLデータ!$F:$F,"",SQLデータ!$C:$C,">="&届出事由・区分・届出年月日ごと集計!L$1,SQLデータ!$C:$C,"<="&届出事由・区分・届出年月日ごと集計!L$2) -> 0 | M4: =COUNTIFS(SQLデータ!$D:$D,"扶養",SQLデータ!$P:$P,1,SQLデータ!$H:$H,届出事由・区分・届出年月日ごと集計!$A4,SQLデータ!$G:$G,届出事由・区分・届出年月日ごと集計!$B4,SQLデータ!$M:$M,1,SQLデータ!$F:$F,"",SQLデータ!$C:$C,">="&届出事由・区分・届出年月日ごと集計!M$1,SQLデータ!$C:$C,"<="&届出事由・区分・届出年月日ごと集計!M$2) -> 0 | ... T4: =COUNTIFS(SQLデータ!$D:$D,"扶養",SQLデータ!$P:$P,1,SQLデータ!$H:$H,届出事由・区分・届出年月日ごと集計!$A4,SQLデータ!$G:$G,届出事由・区分・届出年月日ごと集計!$B4,SQLデータ!$M:$M,1,SQLデータ!$F:$F,"",SQLデータ!$C:$C,">="&届出事由・区分・届出年月日ごと集計!T$1,SQLデータ!$C:$C,"<="&届出事由・区分・届出年月日ごと集計!T$2) -> 0
A5: 増 | B5: 出生 | C5: 税控除のみ | D5: =COUNTIFS(SQLデータ!$D:$D,"扶養",SQLデータ!$H:$H,届出事由・区分・届出年月日ごと集計!$A5,SQLデータ!$G:$G,届出事由・区分・届出年月日ごと集計!$B5,SQLデータ!$N:$N,1) -> 0 | F5: =COUNTIFS(SQLデータ!$D:$D,"扶養",SQLデータ!$P:$P,1,SQLデータ!$H:$H,届出事由・区分・届出年月日ごと集計!$A5,SQLデータ!$G:$G,届出事由・区分・届出年月日ごと集計!$B5,SQLデータ!$N:$N,1,SQLデータ!$F:$F,"",SQLデータ!$C:$C,">="&届出事由・区分・届出年月日ごと集計!F$1,SQLデータ!$C:$C,"<="&届出事由・区分・届出年月日ごと集計!F$2) -> 0 | G5: =COUNTIFS(SQLデータ!$D:$D,"扶養",SQLデータ!$P:$P,1,SQLデータ!$H:$H,届出事由・区分・届出年月日ごと集計!$A5,SQLデータ!$G:$G,届出事由・区分・届出年月日ごと集計!$B5,SQLデータ!$N:$N,1,SQLデータ!$F:$F,"",SQLデータ!$C:$C,">="&届出事由・区分・届出年月日ごと集計!G$1,SQLデータ!$C:$C,"<="&届出事由・区分・届出年月日ごと集計!G$2) -> 0 | H5: =COUNTIFS(SQLデータ!$D:$D,"扶養",SQLデータ!$P:$P,1,SQLデータ!$H:$H,届出事由・区分・届出年月日ごと集計!$A5,SQLデータ!$G:$G,届出事由・区分・届出年月日ごと集計!$B5,SQLデータ!$N:$N,1,SQLデータ!$F:$F,"",SQLデータ!$C:$C,">="&届出事由・区分・届出年月日ごと集計!H$1,SQLデータ!$C:$C,"<="&届出事由・区分・届出年月日ごと集計!H$2) -> 0 | I5: =COUNTIFS(SQLデータ!$D:$D,"扶養",SQLデータ!$P:$P,1,SQLデータ!$H:$H,届出事由・区分・届出年月日ごと集計!$A5,SQLデータ!$G:$G,届出事由・区分・届出年月日ごと集計!$B5,SQLデータ!$N:$N,1,SQLデータ!$F:$F,"",SQLデータ!$C:$C,">="&届出事由・区分・届出年月日ごと集計!I$1,SQLデータ!$C:$C,"<="&届出事由・区分・届出年月日ごと集計!I$2) -> 0 | J5: =COUNTIFS(SQLデータ!$D:$D,"扶養",SQLデータ!$P:$P,1,SQLデータ!$H:$H,届出事由・区分・届出年月日ごと集計!$A5,SQLデータ!$G:$G,届出事由・区分・届出年月日ごと集計!$B5,SQLデータ!$N:$N,1,SQLデータ!$F:$F,"",SQLデータ!$C:$C,">="&届出事由・区分・届出年月日ごと集計!J$1,SQLデータ!$C:$C,"<="&届出事由・区分・届出年月日ごと集計!J$2) -> 0 | K5: =COUNTIFS(SQLデータ!$D:$D,"扶養",SQLデータ!$P:$P,1,SQLデータ!$H:$H,届出事由・区分・届出年月日ごと集計!$A5,SQLデータ!$G:$G,届出事由・区分・届出年月日ごと集計!$B5,SQLデータ!$N:$N,1,SQLデータ!$F:$F,"",SQLデータ!$C:$C,">="&届出事由・区分・届出年月日ごと集計!K$1,SQLデータ!$C:$C,"<="&届出事由・区分・届出年月日ごと集計!K$2) -> 0 | L5: =COUNTIFS(SQLデータ!$D:$D,"扶養",SQLデータ!$P:$P,1,SQLデータ!$H:$H,届出事由・区分・届出年月日ごと集計!$A5,SQLデータ!$G:$G,届出事由・区分・届出年月日ごと集計!$B5,SQLデータ!$N:$N,1,SQLデータ!$F:$F,"",SQLデータ!$C:$C,">="&届出事由・区分・届出年月日ごと集計!L$1,SQLデータ!$C:$C,"<="&届出事由・区分・届出年月日ごと集計!L$2) -> 0 | M5: =COUNTIFS(SQLデータ!$D:$D,"扶養",SQLデータ!$P:$P,1,SQLデータ!$H:$H,届出事由・区分・届出年月日ごと集計!$A5,SQLデータ!$G:$G,届出事由・区分・届出年月日ごと集計!$B5,SQLデータ!$N:$N,1,SQLデータ!$F:$F,"",SQLデータ!$C:$C,">="&届出事由・区分・届出年月日ごと集計!M$1,SQLデータ!$C:$C,"<="&届出事由・区分・届出年月日ごと集計!M$2) -> 0 | ... T5: =COUNTIFS(SQLデータ!$D:$D,"扶養",SQLデータ!$P:$P,1,SQLデータ!$H:$H,届出事由・区分・届出年月日ごと集計!$A5,SQLデータ!$G:$G,届出事由・区分・届出年月日ごと集計!$B5,SQLデータ!$N:$N,1,SQLデータ!$F:$F,"",SQLデータ!$C:$C,">="&届出事由・区分・届出年月日ごと集計!T$1,SQLデータ!$C:$C,"<="&届出事由・区分・届出年月日ごと集計!T$2) -> 0
A6: 増 | B6: 出生 | C6: 本人税のみ | D6: =COUNTIFS(SQLデータ!$D:$D,"扶養",SQLデータ!$H:$H,届出事由・区分・届出年月日ごと集計!$A6,SQLデータ!$G:$G,届出事由・区分・届出年月日ごと集計!$B6,SQLデータ!$O:$O,1) -> 0 | F6: =COUNTIFS(SQLデータ!$D:$D,"扶養",SQLデータ!$P:$P,1,SQLデータ!$H:$H,届出事由・区分・届出年月日ごと集計!$A6,SQLデータ!$G:$G,届出事由・区分・届出年月日ごと集計!$B6,SQLデータ!$O:$O,1,SQLデータ!$F:$F,"",SQLデータ!$C:$C,">="&届出事由・区分・届出年月日ごと集計!F$1,SQLデータ!$C:$C,"<="&届出事由・区分・届出年月日ごと集計!F$2) -> 0 | G6: =COUNTIFS(SQLデータ!$D:$D,"扶養",SQLデータ!$P:$P,1,SQLデータ!$H:$H,届出事由・区分・届出年月日ごと集計!$A6,SQLデータ!$G:$G,届出事由・区分・届出年月日ごと集計!$B6,SQLデータ!$O:$O,1,SQLデータ!$F:$F,"",SQLデータ!$C:$C,">="&届出事由・区分・届出年月日ごと集計!G$1,SQLデータ!$C:$C,"<="&届出事由・区分・届出年月日ごと集計!G$2) -> 0 | H6: =COUNTIFS(SQLデータ!$D:$D,"扶養",SQLデータ!$P:$P,1,SQLデータ!$H:$H,届出事由・区分・届出年月日ごと集計!$A6,SQLデータ!$G:$G,届出事由・区分・届出年月日ごと集計!$B6,SQLデータ!$O:$O,1,SQLデータ!$F:$F,"",SQLデータ!$C:$C,">="&届出事由・区分・届出年月日ごと集計!H$1,SQLデータ!$C:$C,"<="&届出事由・区分・届出年月日ごと集計!H$2) -> 0 | I6: =COUNTIFS(SQLデータ!$D:$D,"扶養",SQLデータ!$P:$P,1,SQLデータ!$H:$H,届出事由・区分・届出年月日ごと集計!$A6,SQLデータ!$G:$G,届出事由・区分・届出年月日ごと集計!$B6,SQLデータ!$O:$O,1,SQLデータ!$F:$F,"",SQLデータ!$C:$C,">="&届出事由・区分・届出年月日ごと集計!I$1,SQLデータ!$C:$C,"<="&届出事由・区分・届出年月日ごと集計!I$2) -> 0 | J6: =COUNTIFS(SQLデータ!$D:$D,"扶養",SQLデータ!$P:$P,1,SQLデータ!$H:$H,届出事由・区分・届出年月日ごと集計!$A6,SQLデータ!$G:$G,届出事由・区分・届出年月日ごと集計!$B6,SQLデータ!$O:$O,1,SQLデータ!$F:$F,"",SQLデータ!$C:$C,">="&届出事由・区分・届出年月日ごと集計!J$1,SQLデータ!$C:$C,"<="&届出事由・区分・届出年月日ごと集計!J$2) -> 0 | K6: =COUNTIFS(SQLデータ!$D:$D,"扶養",SQLデータ!$P:$P,1,SQLデータ!$H:$H,届出事由・区分・届出年月日ごと集計!$A6,SQLデータ!$G:$G,届出事由・区分・届出年月日ごと集計!$B6,SQLデータ!$O:$O,1,SQLデータ!$F:$F,"",SQLデータ!$C:$C,">="&届出事由・区分・届出年月日ごと集計!K$1,SQLデータ!$C:$C,"<="&届出事由・区分・届出年月日ごと集計!K$2) -> 0 | L6: =COUNTIFS(SQLデータ!$D:$D,"扶養",SQLデータ!$P:$P,1,SQLデータ!$H:$H,届出事由・区分・届出年月日ごと集計!$A6,SQLデータ!$G:$G,届出事由・区分・届出年月日ごと集計!$B6,SQLデータ!$O:$O,1,SQLデータ!$F:$F,"",SQLデータ!$C:$C,">="&届出事由・区分・届出年月日ごと集計!L$1,SQLデータ!$C:$C,"<="&届出事由・区分・届出年月日ごと集計!L$2) -> 0 | M6: =COUNTIFS(SQLデータ!$D:$D,"扶養",SQLデータ!$P:$P,1,SQLデータ!$H:$H,届出事由・区分・届出年月日ごと集計!$A6,SQLデータ!$G:$G,届出事由・区分・届出年月日ごと集計!$B6,SQLデータ!$O:$O,1,SQLデータ!$F:$F,"",SQLデータ!$C:$C,">="&届出事由・区分・届出年月日ごと集計!M$1,SQLデータ!$C:$C,"<="&届出事由・区分・届出年月日ごと集計!M$2) -> 0 | ... T6: =COUNTIFS(SQLデータ!$D:$D,"扶養",SQLデータ!$P:$P,1,SQLデータ!$H:$H,届出事由・区分・届出年月日ごと集計!$A6,SQLデータ!$G:$G,届出事由・区分・届出年月日ごと集計!$B6,SQLデータ!$O:$O,1,SQLデータ!$F:$F,"",SQLデータ!$C:$C,">="&届出事由・区分・届出年月日ごと集計!T$1,SQLデータ!$C:$C,"<="&届出事由・区分・届出年月日ごと集計!T$2) -> 0
A7: 増 | B7: 扶養親族の退職 | C7: 共済あり | D7: =COUNTIFS(SQLデータ!$D:$D,"扶養",SQLデータ!$H:$H,届出事由・区分・届出年月日ごと集計!$A7,SQLデータ!$G:$G,届出事由・区分・届出年月日ごと集計!$B7,SQLデータ!$L:$L,1) -> 19 | F7: =COUNTIFS(SQLデータ!$D:$D,"扶養",SQLデータ!$P:$P,1,SQLデータ!$H:$H,届出事由・区分・届出年月日ごと集計!$A7,SQLデータ!$G:$G,届出事由・区分・届出年月日ごと集計!$B7,SQLデータ!$L:$L,1,SQLデータ!$F:$F,"",SQLデータ!$C:$C,">="&届出事由・区分・届出年月日ごと集計!F$1,SQLデータ!$C:$C,"<="&届出事由・区分・届出年月日ごと集計!F$2) -> 2 | G7: =COUNTIFS(SQLデータ!$D:$D,"扶養",SQLデータ!$P:$P,1,SQLデータ!$H:$H,届出事由・区分・届出年月日ごと集計!$A7,SQLデータ!$G:$G,届出事由・区分・届出年月日ごと集計!$B7,SQLデータ!$L:$L,1,SQLデータ!$F:$F,"",SQLデータ!$C:$C,">="&届出事由・区分・届出年月日ごと集計!G$1,SQLデータ!$C:$C,"<="&届出事由・区分・届出年月日ごと集計!G$2) -> 3 | H7: =COUNTIFS(SQLデータ!$D:$D,"扶養",SQLデータ!$P:$P,1,SQLデータ!$H:$H,届出事由・区分・届出年月日ごと集計!$A7,SQLデータ!$G:$G,届出事由・区分・届出年月日ごと集計!$B7,SQLデータ!$L:$L,1,SQLデータ!$F:$F,"",SQLデータ!$C:$C,">="&届出事由・区分・届出年月日ごと集計!H$1,SQLデータ!$C:$C,"<="&届出事由・区分・届出年月日ごと集計!H$2) -> 1 | I7: =COUNTIFS(SQLデータ!$D:$D,"扶養",SQLデータ!$P:$P,1,SQLデータ!$H:$H,届出事由・区分・届出年月日ごと集計!$A7,SQLデータ!$G:$G,届出事由・区分・届出年月日ごと集計!$B7,SQLデータ!$L:$L,1,SQLデータ!$F:$F,"",SQLデータ!$C:$C,">="&届出事由・区分・届出年月日ごと集計!I$1,SQLデータ!$C:$C,"<="&届出事由・区分・届出年月日ごと集計!I$2) -> 0 | J7: =COUNTIFS(SQLデータ!$D:$D,"扶養",SQLデータ!$P:$P,1,SQLデータ!$H:$H,届出事由・区分・届出年月日ごと集計!$A7,SQLデータ!$G:$G,届出事由・区分・届出年月日ごと集計!$B7,SQLデータ!$L:$L,1,SQLデータ!$F:$F,"",SQLデータ!$C:$C,">="&届出事由・区分・届出年月日ごと集計!J$1,SQLデータ!$C:$C,"<="&届出事由・区分・届出年月日ごと集計!J$2) -> 0 | K7: =COUNTIFS(SQLデータ!$D:$D,"扶養",SQLデータ!$P:$P,1,SQLデータ!$H:$H,届出事由・区分・届出年月日ごと集計!$A7,SQLデータ!$G:$G,届出事由・区分・届出年月日ごと集計!$B7,SQLデータ!$L:$L,1,SQLデータ!$F:$F,"",SQLデータ!$C:$C,">="&届出事由・区分・届出年月日ごと集計!K$1,SQLデータ!$C:$C,"<="&届出事由・区分・届出年月日ごと集計!K$2) -> 0 | L7: =COUNTIFS(SQLデータ!$D:$D,"扶養",SQLデータ!$P:$P,1,SQLデータ!$H:$H,届出事由・区分・届出年月日ごと集計!$A7,SQLデータ!$G:$G,届出事由・区分・届出年月日ごと集計!$B7,SQLデータ!$L:$L,1,SQLデータ!$F:$F,"",SQLデータ!$C:$C,">="&届出事由・区分・届出年月日ごと集計!L$1,SQLデータ!$C:$C,"<="&届出事由・区分・届出年月日ごと集計!L$2) -> 0 | M7: =COUNTIFS(SQLデータ!$D:$D,"扶養",SQLデータ!$P:$P,1,SQLデータ!$H:$H,届出事由・区分・届出年月日ごと集計!$A7,SQLデータ!$G:$G,届出事由・区分・届出年月日ごと集計!$B7,SQLデータ!$L:$L,1,SQLデータ!$F:$F,"",SQLデータ!$C:$C,">="&届出事由・区分・届出年月日ごと集計!M$1,SQLデータ!$C:$C,"<="&届出事由・区分・届出年月日ごと集計!M$2) -> 0 | ... T7: =COUNTIFS(SQLデータ!$D:$D,"扶養",SQLデータ!$P:$P,1,SQLデータ!$H:$H,届出事由・区分・届出年月日ごと集計!$A7,SQLデータ!$G:$G,届出事由・区分・届出年月日ごと集計!$B7,SQLデータ!$L:$L,1,SQLデータ!$F:$F,"",SQLデータ!$C:$C,">="&届出事由・区分・届出年月日ごと集計!T$1,SQLデータ!$C:$C,"<="&届出事由・区分・届出年月日ごと集計!T$2) -> 0
A8: 増 | B8: 扶養親族の退職 | C8: 扶養手当あり | D8: =COUNTIFS(SQLデータ!$D:$D,"扶養",SQLデータ!$H:$H,届出事由・区分・届出年月日ごと集計!$A8,SQLデータ!$G:$G,届出事由・区分・届出年月日ごと集計!$B8,SQLデータ!$M:$M,1) -> 0 | F8: =COUNTIFS(SQLデータ!$D:$D,"扶養",SQLデータ!$P:$P,1,SQLデータ!$H:$H,届出事由・区分・届出年月日ごと集計!$A8,SQLデータ!$G:$G,届出事由・区分・届出年月日ごと集計!$B8,SQLデータ!$M:$M,1,SQLデータ!$F:$F,"",SQLデータ!$C:$C,">="&届出事由・区分・届出年月日ごと集計!F$1,SQLデータ!$C:$C,"<="&届出事由・区分・届出年月日ごと集計!F$2) -> 0 | G8: =COUNTIFS(SQLデータ!$D:$D,"扶養",SQLデータ!$P:$P,1,SQLデータ!$H:$H,届出事由・区分・届出年月日ごと集計!$A8,SQLデータ!$G:$G,届出事由・区分・届出年月日ごと集計!$B8,SQLデータ!$M:$M,1,SQLデータ!$F:$F,"",SQLデータ!$C:$C,">="&届出事由・区分・届出年月日ごと集計!G$1,SQLデータ!$C:$C,"<="&届出事由・区分・届出年月日ごと集計!G$2) -> 0 | H8: =COUNTIFS(SQLデータ!$D:$D,"扶養",SQLデータ!$P:$P,1,SQLデータ!$H:$H,届出事由・区分・届出年月日ごと集計!$A8,SQLデータ!$G:$G,届出事由・区分・届出年月日ごと集計!$B8,SQLデータ!$M:$M,1,SQLデータ!$F:$F,"",SQLデータ!$C:$C,">="&届出事由・区分・届出年月日ごと集計!H$1,SQLデータ!$C:$C,"<="&届出事由・区分・届出年月日ごと集計!H$2) -> 0 | I8: =COUNTIFS(SQLデータ!$D:$D,"扶養",SQLデータ!$P:$P,1,SQLデータ!$H:$H,届出事由・区分・届出年月日ごと集計!$A8,SQLデータ!$G:$G,届出事由・区分・届出年月日ごと集計!$B8,SQLデータ!$M:$M,1,SQLデータ!$F:$F,"",SQLデータ!$C:$C,">="&届出事由・区分・届出年月日ごと集計!I$1,SQLデータ!$C:$C,"<="&届出事由・区分・届出年月日ごと集計!I$2) -> 0 | J8: =COUNTIFS(SQLデータ!$D:$D,"扶養",SQLデータ!$P:$P,1,SQLデータ!$H:$H,届出事由・区分・届出年月日ごと集計!$A8,SQLデータ!$G:$G,届出事由・区分・届出年月日ごと集計!$B8,SQLデータ!$M:$M,1,SQLデータ!$F:$F,"",SQLデータ!$C:$C,">="&届出事由・区分・届出年月日ごと集計!J$1,SQLデータ!$C:$C,"<="&届出事由・区分・届出年月日ごと集計!J$2) -> 0 | K8: =COUNTIFS(SQLデータ!$D:$D,"扶養",SQLデータ!$P:$P,1,SQLデータ!$H:$H,届出事由・区分・届出年月日ごと集計!$A8,SQLデータ!$G:$G,届出事由・区分・届出年月日ごと集計!$B8,SQLデータ!$M:$M,1,SQLデータ!$F:$F,"",SQLデータ!$C:$C,">="&届出事由・区分・届出年月日ごと集計!K$1,SQLデータ!$C:$C,"<="&届出事由・区分・届出年月日ごと集計!K$2) -> 0 | L8: =COUNTIFS(SQLデータ!$D:$D,"扶養",SQLデータ!$P:$P,1,SQLデータ!$H:$H,届出事由・区分・届出年月日ごと集計!$A8,SQLデータ!$G:$G,届出事由・区分・届出年月日ごと集計!$B8,SQLデータ!$M:$M,1,SQLデータ!$F:$F,"",SQLデータ!$C:$C,">="&届出事由・区分・届出年月日ごと集計!L$1,SQLデータ!$C:$C,"<="&届出事由・区分・届出年月日ごと集計!L$2) -> 0 | M8: =COUNTIFS(SQLデータ!$D:$D,"扶養",SQLデータ!$P:$P,1,SQLデータ!$H:$H,届出事由・区分・届出年月日ごと集計!$A8,SQLデータ!$G:$G,届出事由・区分・届出年月日ごと集計!$B8,SQLデータ!$M:$M,1,SQLデータ!$F:$F,"",SQLデータ!$C:$C,">="&届出事由・区分・届出年月日ごと集計!M$1,SQLデータ!$C:$C,"<="&届出事由・区分・届出年月日ごと集計!M$2) -> 0 | ... T8: =COUNTIFS(SQLデータ!$D:$D,"扶養",SQLデータ!$P:$P,1,SQLデータ!$H:$H,届出事由・区分・届出年月日ごと集計!$A8,SQLデータ!$G:$G,届出事由・区分・届出年月日ごと集計!$B8,SQLデータ!$M:$M,1,SQLデータ!$F:$F,"",SQLデータ!$C:$C,">="&届出事由・区分・届出年月日ごと集計!T$1,SQLデータ!$C:$C,"<="&届出事由・区分・届出年月日ごと集計!T$2) -> 0
A9: 増 | B9: 扶養親族の退職 | C9: 税控除のみ | D9: =COUNTIFS(SQLデータ!$D:$D,"扶養",SQLデータ!$H:$H,届出事由・区分・届出年月日ごと集計!$A9,SQLデータ!$G:$G,届出事由・区分・届出年月日ごと集計!$B9,SQLデータ!$N:$N,1) -> 0 | F9: =COUNTIFS(SQLデータ!$D:$D,"扶養",SQLデータ!$P:$P,1,SQLデータ!$H:$H,届出事由・区分・届出年月日ごと集計!$A9,SQLデータ!$G:$G,届出事由・区分・届出年月日ごと集計!$B9,SQLデータ!$N:$N,1,SQLデータ!$F:$F,"",SQLデータ!$C:$C,">="&届出事由・区分・届出年月日ごと集計!F$1,SQLデータ!$C:$C,"<="&届出事由・区分・届出年月日ごと集計!F$2) -> 0 | G9: =COUNTIFS(SQLデータ!$D:$D,"扶養",SQLデータ!$P:$P,1,SQLデータ!$H:$H,届出事由・区分・届出年月日ごと集計!$A9,SQLデータ!$G:$G,届出事由・区分・届出年月日ごと集計!$B9,SQLデータ!$N:$N,1,SQLデータ!$F:$F,"",SQLデータ!$C:$C,">="&届出事由・区分・届出年月日ごと集計!G$1,SQLデータ!$C:$C,"<="&届出事由・区分・届出年月日ごと集計!G$2) -> 0 | H9: =COUNTIFS(SQLデータ!$D:$D,"扶養",SQLデータ!$P:$P,1,SQLデータ!$H:$H,届出事由・区分・届出年月日ごと集計!$A9,SQLデータ!$G:$G,届出事由・区分・届出年月日ごと集計!$B9,SQLデータ!$N:$N,1,SQLデータ!$F:$F,"",SQLデータ!$C:$C,">="&届出事由・区分・届出年月日ごと集計!H$1,SQLデータ!$C:$C,"<="&届出事由・区分・届出年月日ごと集計!H$2) -> 0 | I9: =COUNTIFS(SQLデータ!$D:$D,"扶養",SQLデータ!$P:$P,1,SQLデータ!$H:$H,届出事由・区分・届出年月日ごと集計!$A9,SQLデータ!$G:$G,届出事由・区分・届出年月日ごと集計!$B9,SQLデータ!$N:$N,1,SQLデータ!$F:$F,"",SQLデータ!$C:$C,">="&届出事由・区分・届出年月日ごと集計!I$1,SQLデータ!$C:$C,"<="&届出事由・区分・届出年月日ごと集計!I$2) -> 0 | J9: =COUNTIFS(SQLデータ!$D:$D,"扶養",SQLデータ!$P:$P,1,SQLデータ!$H:$H,届出事由・区分・届出年月日ごと集計!$A9,SQLデータ!$G:$G,届出事由・区分・届出年月日ごと集計!$B9,SQLデータ!$N:$N,1,SQLデータ!$F:$F,"",SQLデータ!$C:$C,">="&届出事由・区分・届出年月日ごと集計!J$1,SQLデータ!$C:$C,"<="&届出事由・区分・届出年月日ごと集計!J$2) -> 0 | K9: =COUNTIFS(SQLデータ!$D:$D,"扶養",SQLデータ!$P:$P,1,SQLデータ!$H:$H,届出事由・区分・届出年月日ごと集計!$A9,SQLデータ!$G:$G,届出事由・区分・届出年月日ごと集計!$B9,SQLデータ!$N:$N,1,SQLデータ!$F:$F,"",SQLデータ!$C:$C,">="&届出事由・区分・届出年月日ごと集計!K$1,SQLデータ!$C:$C,"<="&届出事由・区分・届出年月日ごと集計!K$2) -> 0 | L9: =COUNTIFS(SQLデータ!$D:$D,"扶養",SQLデータ!$P:$P,1,SQLデータ!$H:$H,届出事由・区分・届出年月日ごと集計!$A9,SQLデータ!$G:$G,届出事由・区分・届出年月日ごと集計!$B9,SQLデータ!$N:$N,1,SQLデータ!$F:$F,"",SQLデータ!$C:$C,">="&届出事由・区分・届出年月日ごと集計!L$1,SQLデータ!$C:$C,"<="&届出事由・区分・届出年月日ごと集計!L$2) -> 0 | M9: =COUNTIFS(SQLデータ!$D:$D,"扶養",SQLデータ!$P:$P,1,SQLデータ!$H:$H,届出事由・区分・届出年月日ごと集計!$A9,SQLデータ!$G:$G,届出事由・区分・届出年月日ごと集計!$B9,SQLデータ!$N:$N,1,SQLデータ!$F:$F,"",SQLデータ!$C:$C,">="&届出事由・区分・届出年月日ごと集計!M$1,SQLデータ!$C:$C,"<="&届出事由・区分・届出年月日ごと集計!M$2) -> 0 | ... T9: =COUNTIFS(SQLデータ!$D:$D,"扶養",SQLデータ!$P:$P,1,SQLデータ!$H:$H,届出事由・区分・届出年月日ごと集計!$A9,SQLデータ!$G:$G,届出事由・区分・届出年月日ごと集計!$B9,SQLデータ!$N:$N,1,SQLデータ!$F:$F,"",SQLデータ!$C:$C,">="&届出事由・区分・届出年月日ごと集計!T$1,SQLデータ!$C:$C,"<="&届出事由・区分・届出年月日ごと集計!T$2) -> 0
A10: 増 | B10: 扶養親族の退職 | C10: 本人税のみ | D10: =COUNTIFS(SQLデータ!$D:$D,"扶養",SQLデータ!$H:$H,届出事由・区分・届出年月日ごと集計!$A10,SQLデータ!$G:$G,届出事由・区分・届出年月日ごと集計!$B10,SQLデータ!$O:$O,1) -> 0 | F10: =COUNTIFS(SQLデータ!$D:$D,"扶養",SQLデータ!$P:$P,1,SQLデータ!$H:$H,届出事由・区分・届出年月日ごと集計!$A10,SQLデータ!$G:$G,届出事由・区分・届出年月日ごと集計!$B10,SQLデータ!$O:$O,1,SQLデータ!$F:$F,"",SQLデータ!$C:$C,">="&届出事由・区分・届出年月日ごと集計!F$1,SQLデータ!$C:$C,"<="&届出事由・区分・届出年月日ごと集計!F$2) -> 0 | G10: =COUNTIFS(SQLデータ!$D:$D,"扶養",SQLデータ!$P:$P,1,SQLデータ!$H:$H,届出事由・区分・届出年月日ごと集計!$A10,SQLデータ!$G:$G,届出事由・区分・届出年月日ごと集計!$B10,SQLデータ!$O:$O,1,SQLデータ!$F:$F,"",SQLデータ!$C:$C,">="&届出事由・区分・届出年月日ごと集計!G$1,SQLデータ!$C:$C,"<="&届出事由・区分・届出年月日ごと集計!G$2) -> 0 | H10: =COUNTIFS(SQLデータ!$D:$D,"扶養",SQLデータ!$P:$P,1,SQLデータ!$H:$H,届出事由・区分・届出年月日ごと集計!$A10,SQLデータ!$G:$G,届出事由・区分・届出年月日ごと集計!$B10,SQLデータ!$O:$O,1,SQLデータ!$F:$F,"",SQLデータ!$C:$C,">="&届出事由・区分・届出年月日ごと集計!H$1,SQLデータ!$C:$C,"<="&届出事由・区分・届出年月日ごと集計!H$2) -> 0 | I10: =COUNTIFS(SQLデータ!$D:$D,"扶養",SQLデータ!$P:$P,1,SQLデータ!$H:$H,届出事由・区分・届出年月日ごと集計!$A10,SQLデータ!$G:$G,届出事由・区分・届出年月日ごと集計!$B10,SQLデータ!$O:$O,1,SQLデータ!$F:$F,"",SQLデータ!$C:$C,">="&届出事由・区分・届出年月日ごと集計!I$1,SQLデータ!$C:$C,"<="&届出事由・区分・届出年月日ごと集計!I$2) -> 0 | J10: =COUNTIFS(SQLデータ!$D:$D,"扶養",SQLデータ!$P:$P,1,SQLデータ!$H:$H,届出事由・区分・届出年月日ごと集計!$A10,SQLデータ!$G:$G,届出事由・区分・届出年月日ごと集計!$B10,SQLデータ!$O:$O,1,SQLデータ!$F:$F,"",SQLデータ!$C:$C,">="&届出事由・区分・届出年月日ごと集計!J$1,SQLデータ!$C:$C,"<="&届出事由・区分・届出年月日ごと集計!J$2) -> 0 | K10: =COUNTIFS(SQLデータ!$D:$D,"扶養",SQLデータ!$P:$P,1,SQLデータ!$H:$H,届出事由・区分・届出年月日ごと集計!$A10,SQLデータ!$G:$G,届出事由・区分・届出年月日ごと集計!$B10,SQLデータ!$O:$O,1,SQLデータ!$F:$F,"",SQLデータ!$C:$C,">="&届出事由・区分・届出年月日ごと集計!K$1,SQLデータ!$C:$C,"<="&届出事由・区分・届出年月日ごと集計!K$2) -> 0 | L10: =COUNTIFS(SQLデータ!$D:$D,"扶養",SQLデータ!$P:$P,1,SQLデータ!$H:$H,届出事由・区分・届出年月日ごと集計!$A10,SQLデータ!$G:$G,届出事由・区分・届出年月日ごと集計!$B10,SQLデータ!$O:$O,1,SQLデータ!$F:$F,"",SQLデータ!$C:$C,">="&届出事由・区分・届出年月日ごと集計!L$1,SQLデータ!$C:$C,"<="&届出事由・区分・届出年月日ごと集計!L$2) -> 0 | M10: =COUNTIFS(SQLデータ!$D:$D,"扶養",SQLデータ!$P:$P,1,SQLデータ!$H:$H,届出事由・区分・届出年月日ごと集計!$A10,SQLデータ!$G:$G,届出事由・区分・届出年月日ごと集計!$B10,SQLデータ!$O:$O,1,SQLデータ!$F:$F,"",SQLデータ!$C:$C,">="&届出事由・区分・届出年月日ごと集計!M$1,SQLデータ!$C:$C,"<="&届出事由・区分・届出年月日ごと集計!M$2) -> 0 | ... T10: =COUNTIFS(SQLデータ!$D:$D,"扶養",SQLデータ!$P:$P,1,SQLデータ!$H:$H,届出事由・区分・届出年月日ごと集計!$A10,SQLデータ!$G:$G,届出事由・区分・届出年月日ごと集計!$B10,SQLデータ!$O:$O,1,SQLデータ!$F:$F,"",SQLデータ!$C:$C,">="&届出事由・区分・届出年月日ごと集計!T$1,SQLデータ!$C:$C,"<="&届出事由・区分・届出年月日ごと集計!T$2) -> 0
A11: 増 | B11: 本人の結婚 | C11: 共済あり | D11: =COUNTIFS(SQLデータ!$D:$D,"扶養",SQLデータ!$H:$H,届出事由・区分・届出年月日ごと集計!$A11,SQLデータ!$G:$G,届出事由・区分・届出年月日ごと集計!$B11,SQLデータ!$L:$L,1) -> 3 | F11: =COUNTIFS(SQLデータ!$D:$D,"扶養",SQLデータ!$P:$P,1,SQLデータ!$H:$H,届出事由・区分・届出年月日ごと集計!$A11,SQLデータ!$G:$G,届出事由・区分・届出年月日ごと集計!$B11,SQLデータ!$L:$L,1,SQLデータ!$F:$F,"",SQLデータ!$C:$C,">="&届出事由・区分・届出年月日ごと集計!F$1,SQLデータ!$C:$C,"<="&届出事由・区分・届出年月日ごと集計!F$2) -> 0 | G11: =COUNTIFS(SQLデータ!$D:$D,"扶養",SQLデータ!$P:$P,1,SQLデータ!$H:$H,届出事由・区分・届出年月日ごと集計!$A11,SQLデータ!$G:$G,届出事由・区分・届出年月日ごと集計!$B11,SQLデータ!$L:$L,1,SQLデータ!$F:$F,"",SQLデータ!$C:$C,">="&届出事由・区分・届出年月日ごと集計!G$1,SQLデータ!$C:$C,"<="&届出事由・区分・届出年月日ごと集計!G$2) -> 1 | H11: =COUNTIFS(SQLデータ!$D:$D,"扶養",SQLデータ!$P:$P,1,SQLデータ!$H:$H,届出事由・区分・届出年月日ごと集計!$A11,SQLデータ!$G:$G,届出事由・区分・届出年月日ごと集計!$B11,SQLデータ!$L:$L,1,SQLデータ!$F:$F,"",SQLデータ!$C:$C,">="&届出事由・区分・届出年月日ごと集計!H$1,SQLデータ!$C:$C,"<="&届出事由・区分・届出年月日ごと集計!H$2) -> 0 | I11: =COUNTIFS(SQLデータ!$D:$D,"扶養",SQLデータ!$P:$P,1,SQLデータ!$H:$H,届出事由・区分・届出年月日ごと集計!$A11,SQLデータ!$G:$G,届出事由・区分・届出年月日ごと集計!$B11,SQLデータ!$L:$L,1,SQLデータ!$F:$F,"",SQLデータ!$C:$C,">="&届出事由・区分・届出年月日ごと集計!I$1,SQLデータ!$C:$C,"<="&届出事由・区分・届出年月日ごと集計!I$2) -> 0 | J11: =COUNTIFS(SQLデータ!$D:$D,"扶養",SQLデータ!$P:$P,1,SQLデータ!$H:$H,届出事由・区分・届出年月日ごと集計!$A11,SQLデータ!$G:$G,届出事由・区分・届出年月日ごと集計!$B11,SQLデータ!$L:$L,1,SQLデータ!$F:$F,"",SQLデータ!$C:$C,">="&届出事由・区分・届出年月日ごと集計!J$1,SQLデータ!$C:$C,"<="&届出事由・区分・届出年月日ごと集計!J$2) -> 0 | K11: =COUNTIFS(SQLデータ!$D:$D,"扶養",SQLデータ!$P:$P,1,SQLデータ!$H:$H,届出事由・区分・届出年月日ごと集計!$A11,SQLデータ!$G:$G,届出事由・区分・届出年月日ごと集計!$B11,SQLデータ!$L:$L,1,SQLデータ!$F:$F,"",SQLデータ!$C:$C,">="&届出事由・区分・届出年月日ごと集計!K$1,SQLデータ!$C:$C,"<="&届出事由・区分・届出年月日ごと集計!K$2) -> 0 | L11: =COUNTIFS(SQLデータ!$D:$D,"扶養",SQLデータ!$P:$P,1,SQLデータ!$H:$H,届出事由・区分・届出年月日ごと集計!$A11,SQLデータ!$G:$G,届出事由・区分・届出年月日ごと集計!$B11,SQLデータ!$L:$L,1,SQLデータ!$F:$F,"",SQLデータ!$C:$C,">="&届出事由・区分・届出年月日ごと集計!L$1,SQLデータ!$C:$C,"<="&届出事由・区分・届出年月日ごと集計!L$2) -> 0 | M11: =COUNTIFS(SQLデータ!$D:$D,"扶養",SQLデータ!$P:$P,1,SQLデータ!$H:$H,届出事由・区分・届出年月日ごと集計!$A11,SQLデータ!$G:$G,届出事由・区分・届出年月日ごと集計!$B11,SQLデータ!$L:$L,1,SQLデータ!$F:$F,"",SQLデータ!$C:$C,">="&届出事由・区分・届出年月日ごと集計!M$1,SQLデータ!$C:$C,"<="&届出事由・区分・届出年月日ごと集計!M$2) -> 0 | ... T11: =COUNTIFS(SQLデータ!$D:$D,"扶養",SQLデータ!$P:$P,1,SQLデータ!$H:$H,届出事由・区分・届出年月日ごと集計!$A11,SQLデータ!$G:$G,届出事由・区分・届出年月日ごと集計!$B11,SQLデータ!$L:$L,1,SQLデータ!$F:$F,"",SQLデータ!$C:$C,">="&届出事由・区分・届出年月日ごと集計!T$1,SQLデータ!$C:$C,"<="&届出事由・区分・届出年月日ごと集計!T$2) -> 0
A12: 増 | B12: 本人の結婚 | C12: 扶養手当あり | D12: =COUNTIFS(SQLデータ!$D:$D,"扶養",SQLデータ!$H:$H,届出事由・区分・届出年月日ごと集計!$A12,SQLデータ!$G:$G,届出事由・区分・届出年月日ごと集計!$B12,SQLデータ!$M:$M,1) -> 0 | F12: =COUNTIFS(SQLデータ!$D:$D,"扶養",SQLデータ!$P:$P,1,SQLデータ!$H:$H,届出事由・区分・届出年月日ごと集計!$A12,SQLデータ!$G:$G,届出事由・区分・届出年月日ごと集計!$B12,SQLデータ!$M:$M,1,SQLデータ!$F:$F,"",SQLデータ!$C:$C,">="&届出事由・区分・届出年月日ごと集計!F$1,SQLデータ!$C:$C,"<="&届出事由・区分・届出年月日ごと集計!F$2) -> 0 | G12: =COUNTIFS(SQLデータ!$D:$D,"扶養",SQLデータ!$P:$P,1,SQLデータ!$H:$H,届出事由・区分・届出年月日ごと集計!$A12,SQLデータ!$G:$G,届出事由・区分・届出年月日ごと集計!$B12,SQLデータ!$M:$M,1,SQLデータ!$F:$F,"",SQLデータ!$C:$C,">="&届出事由・区分・届出年月日ごと集計!G$1,SQLデータ!$C:$C,"<="&届出事由・区分・届出年月日ごと集計!G$2) -> 0 | H12: =COUNTIFS(SQLデータ!$D:$D,"扶養",SQLデータ!$P:$P,1,SQLデータ!$H:$H,届出事由・区分・届出年月日ごと集計!$A12,SQLデータ!$G:$G,届出事由・区分・届出年月日ごと集計!$B12,SQLデータ!$M:$M,1,SQLデータ!$F:$F,"",SQLデータ!$C:$C,">="&届出事由・区分・届出年月日ごと集計!H$1,SQLデータ!$C:$C,"<="&届出事由・区分・届出年月日ごと集計!H$2) -> 0 | I12: =COUNTIFS(SQLデータ!$D:$D,"扶養",SQLデータ!$P:$P,1,SQLデータ!$H:$H,届出事由・区分・届出年月日ごと集計!$A12,SQLデータ!$G:$G,届出事由・区分・届出年月日ごと集計!$B12,SQLデータ!$M:$M,1,SQLデータ!$F:$F,"",SQLデータ!$C:$C,">="&届出事由・区分・届出年月日ごと集計!I$1,SQLデータ!$C:$C,"<="&届出事由・区分・届出年月日ごと集計!I$2) -> 0 | J12: =COUNTIFS(SQLデータ!$D:$D,"扶養",SQLデータ!$P:$P,1,SQLデータ!$H:$H,届出事由・区分・届出年月日ごと集計!$A12,SQLデータ!$G:$G,届出事由・区分・届出年月日ごと集計!$B12,SQLデータ!$M:$M,1,SQLデータ!$F:$F,"",SQLデータ!$C:$C,">="&届出事由・区分・届出年月日ごと集計!J$1,SQLデータ!$C:$C,"<="&届出事由・区分・届出年月日ごと集計!J$2) -> 0 | K12: =COUNTIFS(SQLデータ!$D:$D,"扶養",SQLデータ!$P:$P,1,SQLデータ!$H:$H,届出事由・区分・届出年月日ごと集計!$A12,SQLデータ!$G:$G,届出事由・区分・届出年月日ごと集計!$B12,SQLデータ!$M:$M,1,SQLデータ!$F:$F,"",SQLデータ!$C:$C,">="&届出事由・区分・届出年月日ごと集計!K$1,SQLデータ!$C:$C,"<="&届出事由・区分・届出年月日ごと集計!K$2) -> 0 | L12: =COUNTIFS(SQLデータ!$D:$D,"扶養",SQLデータ!$P:$P,1,SQLデータ!$H:$H,届出事由・区分・届出年月日ごと集計!$A12,SQLデータ!$G:$G,届出事由・区分・届出年月日ごと集計!$B12,SQLデータ!$M:$M,1,SQLデータ!$F:$F,"",SQLデータ!$C:$C,">="&届出事由・区分・届出年月日ごと集計!L$1,SQLデータ!$C:$C,"<="&届出事由・区分・届出年月日ごと集計!L$2) -> 0 | M12: =COUNTIFS(SQLデータ!$D:$D,"扶養",SQLデータ!$P:$P,1,SQLデータ!$H:$H,届出事由・区分・届出年月日ごと集計!$A12,SQLデータ!$G:$G,届出事由・区分・届出年月日ごと集計!$B12,SQLデータ!$M:$M,1,SQLデータ!$F:$F,"",SQLデータ!$C:$C,">="&届出事由・区分・届出年月日ごと集計!M$1,SQLデータ!$C:$C,"<="&届出事由・区分・届出年月日ごと集計!M$2) -> 0 | ... T12: =COUNTIFS(SQLデータ!$D:$D,"扶養",SQLデータ!$P:$P,1,SQLデータ!$H:$H,届出事由・区分・届出年月日ごと集計!$A12,SQLデータ!$G:$G,届出事由・区分・届出年月日ごと集計!$B12,SQLデータ!$M:$M,1,SQLデータ!$F:$F,"",SQLデータ!$C:$C,">="&届出事由・区分・届出年月日ごと集計!T$1,SQLデータ!$C:$C,"<="&届出事由・区分・届出年月日ごと集計!T$2) -> 0
A13: 増 | B13: 本人の結婚 | C13: 税控除のみ | D13: =COUNTIFS(SQLデータ!$D:$D,"扶養",SQLデータ!$H:$H,届出事由・区分・届出年月日ごと集計!$A13,SQLデータ!$G:$G,届出事由・区分・届出年月日ごと集計!$B13,SQLデータ!$N:$N,1) -> 1 | F13: =COUNTIFS(SQLデータ!$D:$D,"扶養",SQLデータ!$P:$P,1,SQLデータ!$H:$H,届出事由・区分・届出年月日ごと集計!$A13,SQLデータ!$G:$G,届出事由・区分・届出年月日ごと集計!$B13,SQLデータ!$N:$N,1,SQLデータ!$F:$F,"",SQLデータ!$C:$C,">="&届出事由・区分・届出年月日ごと集計!F$1,SQLデータ!$C:$C,"<="&届出事由・区分・届出年月日ごと集計!F$2) -> 0 | G13: =COUNTIFS(SQLデータ!$D:$D,"扶養",SQLデータ!$P:$P,1,SQLデータ!$H:$H,届出事由・区分・届出年月日ごと集計!$A13,SQLデータ!$G:$G,届出事由・区分・届出年月日ごと集計!$B13,SQLデータ!$N:$N,1,SQLデータ!$F:$F,"",SQLデータ!$C:$C,">="&届出事由・区分・届出年月日ごと集計!G$1,SQLデータ!$C:$C,"<="&届出事由・区分・届出年月日ごと集計!G$2) -> 0 | H13: =COUNTIFS(SQLデータ!$D:$D,"扶養",SQLデータ!$P:$P,1,SQLデータ!$H:$H,届出事由・区分・届出年月日ごと集計!$A13,SQLデータ!$G:$G,届出事由・区分・届出年月日ごと集計!$B13,SQLデータ!$N:$N,1,SQLデータ!$F:$F,"",SQLデータ!$C:$C,">="&届出事由・区分・届出年月日ごと集計!H$1,SQLデータ!$C:$C,"<="&届出事由・区分・届出年月日ごと集計!H$2) -> 0 | I13: =COUNTIFS(SQLデータ!$D:$D,"扶養",SQLデータ!$P:$P,1,SQLデータ!$H:$H,届出事由・区分・届出年月日ごと集計!$A13,SQLデータ!$G:$G,届出事由・区分・届出年月日ごと集計!$B13,SQLデータ!$N:$N,1,SQLデータ!$F:$F,"",SQLデータ!$C:$C,">="&届出事由・区分・届出年月日ごと集計!I$1,SQLデータ!$C:$C,"<="&届出事由・区分・届出年月日ごと集計!I$2) -> 0 | J13: =COUNTIFS(SQLデータ!$D:$D,"扶養",SQLデータ!$P:$P,1,SQLデータ!$H:$H,届出事由・区分・届出年月日ごと集計!$A13,SQLデータ!$G:$G,届出事由・区分・届出年月日ごと集計!$B13,SQLデータ!$N:$N,1,SQLデータ!$F:$F,"",SQLデータ!$C:$C,">="&届出事由・区分・届出年月日ごと集計!J$1,SQLデータ!$C:$C,"<="&届出事由・区分・届出年月日ごと集計!J$2) -> 0 | K13: =COUNTIFS(SQLデータ!$D:$D,"扶養",SQLデータ!$P:$P,1,SQLデータ!$H:$H,届出事由・区分・届出年月日ごと集計!$A13,SQLデータ!$G:$G,届出事由・区分・届出年月日ごと集計!$B13,SQLデータ!$N:$N,1,SQLデータ!$F:$F,"",SQLデータ!$C:$C,">="&届出事由・区分・届出年月日ごと集計!K$1,SQLデータ!$C:$C,"<="&届出事由・区分・届出年月日ごと集計!K$2) -> 0 | L13: =COUNTIFS(SQLデータ!$D:$D,"扶養",SQLデータ!$P:$P,1,SQLデータ!$H:$H,届出事由・区分・届出年月日ごと集計!$A13,SQLデータ!$G:$G,届出事由・区分・届出年月日ごと集計!$B13,SQLデータ!$N:$N,1,SQLデータ!$F:$F,"",SQLデータ!$C:$C,">="&届出事由・区分・届出年月日ごと集計!L$1,SQLデータ!$C:$C,"<="&届出事由・区分・届出年月日ごと集計!L$2) -> 0 | M13: =COUNTIFS(SQLデータ!$D:$D,"扶養",SQLデータ!$P:$P,1,SQLデータ!$H:$H,届出事由・区分・届出年月日ごと集計!$A13,SQLデータ!$G:$G,届出事由・区分・届出年月日ごと集計!$B13,SQLデータ!$N:$N,1,SQLデータ!$F:$F,"",SQLデータ!$C:$C,">="&届出事由・区分・届出年月日ごと集計!M$1,SQLデータ!$C:$C,"<="&届出事由・区分・届出年月日ごと集計!M$2) -> 0 | ... T13: =COUNTIFS(SQLデータ!$D:$D,"扶養",SQLデータ!$P:$P,1,SQLデータ!$H:$H,届出事由・区分・届出年月日ごと集計!$A13,SQLデータ!$G:$G,届出事由・区分・届出年月日ごと集計!$B13,SQLデータ!$N:$N,1,SQLデータ!$F:$F,"",SQLデータ!$C:$C,">="&届出事由・区分・届出年月日ごと集計!T$1,SQLデータ!$C:$C,"<="&届出事由・区分・届出年月日ごと集計!T$2) -> 0
A14: 増 | B14: 本人の結婚 | C14: 本人税のみ | D14: =COUNTIFS(SQLデータ!$D:$D,"扶養",SQLデータ!$H:$H,届出事由・区分・届出年月日ごと集計!$A14,SQLデータ!$G:$G,届出事由・区分・届出年月日ごと集計!$B14,SQLデータ!$O:$O,1) -> 40 | F14: =COUNTIFS(SQLデータ!$D:$D,"扶養",SQLデータ!$P:$P,1,SQLデータ!$H:$H,届出事由・区分・届出年月日ごと集計!$A14,SQLデータ!$G:$G,届出事由・区分・届出年月日ごと集計!$B14,SQLデータ!$O:$O,1,SQLデータ!$F:$F,"",SQLデータ!$C:$C,">="&届出事由・区分・届出年月日ごと集計!F$1,SQLデータ!$C:$C,"<="&届出事由・区分・届出年月日ごと集計!F$2) -> 27 | G14: =COUNTIFS(SQLデータ!$D:$D,"扶養",SQLデータ!$P:$P,1,SQLデータ!$H:$H,届出事由・区分・届出年月日ごと集計!$A14,SQLデータ!$G:$G,届出事由・区分・届出年月日ごと集計!$B14,SQLデータ!$O:$O,1,SQLデータ!$F:$F,"",SQLデータ!$C:$C,">="&届出事由・区分・届出年月日ごと集計!G$1,SQLデータ!$C:$C,"<="&届出事由・区分・届出年月日ごと集計!G$2) -> 3 | H14: =COUNTIFS(SQLデータ!$D:$D,"扶養",SQLデータ!$P:$P,1,SQLデータ!$H:$H,届出事由・区分・届出年月日ごと集計!$A14,SQLデータ!$G:$G,届出事由・区分・届出年月日ごと集計!$B14,SQLデータ!$O:$O,1,SQLデータ!$F:$F,"",SQLデータ!$C:$C,">="&届出事由・区分・届出年月日ごと集計!H$1,SQLデータ!$C:$C,"<="&届出事由・区分・届出年月日ごと集計!H$2) -> 5 | I14: =COUNTIFS(SQLデータ!$D:$D,"扶養",SQLデータ!$P:$P,1,SQLデータ!$H:$H,届出事由・区分・届出年月日ごと集計!$A14,SQLデータ!$G:$G,届出事由・区分・届出年月日ごと集計!$B14,SQLデータ!$O:$O,1,SQLデータ!$F:$F,"",SQLデータ!$C:$C,">="&届出事由・区分・届出年月日ごと集計!I$1,SQLデータ!$C:$C,"<="&届出事由・区分・届出年月日ごと集計!I$2) -> 5 | J14: =COUNTIFS(SQLデータ!$D:$D,"扶養",SQLデータ!$P:$P,1,SQLデータ!$H:$H,届出事由・区分・届出年月日ごと集計!$A14,SQLデータ!$G:$G,届出事由・区分・届出年月日ごと集計!$B14,SQLデータ!$O:$O,1,SQLデータ!$F:$F,"",SQLデータ!$C:$C,">="&届出事由・区分・届出年月日ごと集計!J$1,SQLデータ!$C:$C,"<="&届出事由・区分・届出年月日ごと集計!J$2) -> 0 | K14: =COUNTIFS(SQLデータ!$D:$D,"扶養",SQLデータ!$P:$P,1,SQLデータ!$H:$H,届出事由・区分・届出年月日ごと集計!$A14,SQLデータ!$G:$G,届出事由・区分・届出年月日ごと集計!$B14,SQLデータ!$O:$O,1,SQLデータ!$F:$F,"",SQLデータ!$C:$C,">="&届出事由・区分・届出年月日ごと集計!K$1,SQLデータ!$C:$C,"<="&届出事由・区分・届出年月日ごと集計!K$2) -> 0 | L14: =COUNTIFS(SQLデータ!$D:$D,"扶養",SQLデータ!$P:$P,1,SQLデータ!$H:$H,届出事由・区分・届出年月日ごと集計!$A14,SQLデータ!$G:$G,届出事由・区分・届出年月日ごと集計!$B14,SQLデータ!$O:$O,1,SQLデータ!$F:$F,"",SQLデータ!$C:$C,">="&届出事由・区分・届出年月日ごと集計!L$1,SQLデータ!$C:$C,"<="&届出事由・区分・届出年月日ごと集計!L$2) -> 0 | M14: =COUNTIFS(SQLデータ!$D:$D,"扶養",SQLデータ!$P:$P,1,SQLデータ!$H:$H,届出事由・区分・届出年月日ごと集計!$A14,SQLデータ!$G:$G,届出事由・区分・届出年月日ごと集計!$B14,SQLデータ!$O:$O,1,SQLデータ!$F:$F,"",SQLデータ!$C:$C,">="&届出事由・区分・届出年月日ごと集計!M$1,SQLデータ!$C:$C,"<="&届出事由・区分・届出年月日ごと集計!M$2) -> 0 | ... T14: =COUNTIFS(SQLデータ!$D:$D,"扶養",SQLデータ!$P:$P,1,SQLデータ!$H:$H,届出事由・区分・届出年月日ごと集計!$A14,SQLデータ!$G:$G,届出事由・区分・届出年月日ごと集計!$B14,SQLデータ!$O:$O,1,SQLデータ!$F:$F,"",SQLデータ!$C:$C,">="&届出事由・区分・届出年月日ごと集計!T$1,SQLデータ!$C:$C,"<="&届出事由・区分・届出年月日ごと集計!T$2) -> 0
A15: 増 | B15: 雇用保険受給終了 | C15: 共済あり | D15: =COUNTIFS(SQLデータ!$D:$D,"扶養",SQLデータ!$H:$H,届出事由・区分・届出年月日ごと集計!$A15,SQLデータ!$G:$G,届出事由・区分・届出年月日ごと集計!$B15,SQLデータ!$L:$L,1) -> 3 | F15: =COUNTIFS(SQLデータ!$D:$D,"扶養",SQLデータ!$P:$P,1,SQLデータ!$H:$H,届出事由・区分・届出年月日ごと集計!$A15,SQLデータ!$G:$G,届出事由・区分・届出年月日ごと集計!$B15,SQLデータ!$L:$L,1,SQLデータ!$F:$F,"",SQLデータ!$C:$C,">="&届出事由・区分・届出年月日ごと集計!F$1,SQLデータ!$C:$C,"<="&届出事由・区分・届出年月日ごと集計!F$2) -> 1 | G15: =COUNTIFS(SQLデータ!$D:$D,"扶養",SQLデータ!$P:$P,1,SQLデータ!$H:$H,届出事由・区分・届出年月日ごと集計!$A15,SQLデータ!$G:$G,届出事由・区分・届出年月日ごと集計!$B15,SQLデータ!$L:$L,1,SQLデータ!$F:$F,"",SQLデータ!$C:$C,">="&届出事由・区分・届出年月日ごと集計!G$1,SQLデータ!$C:$C,"<="&届出事由・区分・届出年月日ごと集計!G$2) -> 0 | H15: =COUNTIFS(SQLデータ!$D:$D,"扶養",SQLデータ!$P:$P,1,SQLデータ!$H:$H,届出事由・区分・届出年月日ごと集計!$A15,SQLデータ!$G:$G,届出事由・区分・届出年月日ごと集計!$B15,SQLデータ!$L:$L,1,SQLデータ!$F:$F,"",SQLデータ!$C:$C,">="&届出事由・区分・届出年月日ごと集計!H$1,SQLデータ!$C:$C,"<="&届出事由・区分・届出年月日ごと集計!H$2) -> 0 | I15: =COUNTIFS(SQLデータ!$D:$D,"扶養",SQLデータ!$P:$P,1,SQLデータ!$H:$H,届出事由・区分・届出年月日ごと集計!$A15,SQLデータ!$G:$G,届出事由・区分・届出年月日ごと集計!$B15,SQLデータ!$L:$L,1,SQLデータ!$F:$F,"",SQLデータ!$C:$C,">="&届出事由・区分・届出年月日ごと集計!I$1,SQLデータ!$C:$C,"<="&届出事由・区分・届出年月日ごと集計!I$2) -> 0 | J15: =COUNTIFS(SQLデータ!$D:$D,"扶養",SQLデータ!$P:$P,1,SQLデータ!$H:$H,届出事由・区分・届出年月日ごと集計!$A15,SQLデータ!$G:$G,届出事由・区分・届出年月日ごと集計!$B15,SQLデータ!$L:$L,1,SQLデータ!$F:$F,"",SQLデータ!$C:$C,">="&届出事由・区分・届出年月日ごと集計!J$1,SQLデータ!$C:$C,"<="&届出事由・区分・届出年月日ごと集計!J$2) -> 0 | K15: =COUNTIFS(SQLデータ!$D:$D,"扶養",SQLデータ!$P:$P,1,SQLデータ!$H:$H,届出事由・区分・届出年月日ごと集計!$A15,SQLデータ!$G:$G,届出事由・区分・届出年月日ごと集計!$B15,SQLデータ!$L:$L,1,SQLデータ!$F:$F,"",SQLデータ!$C:$C,">="&届出事由・区分・届出年月日ごと集計!K$1,SQLデータ!$C:$C,"<="&届出事由・区分・届出年月日ごと集計!K$2) -> 0 | L15: =COUNTIFS(SQLデータ!$D:$D,"扶養",SQLデータ!$P:$P,1,SQLデータ!$H:$H,届出事由・区分・届出年月日ごと集計!$A15,SQLデータ!$G:$G,届出事由・区分・届出年月日ごと集計!$B15,SQLデータ!$L:$L,1,SQLデータ!$F:$F,"",SQLデータ!$C:$C,">="&届出事由・区分・届出年月日ごと集計!L$1,SQLデータ!$C:$C,"<="&届出事由・区分・届出年月日ごと集計!L$2) -> 0 | M15: =COUNTIFS(SQLデータ!$D:$D,"扶養",SQLデータ!$P:$P,1,SQLデータ!$H:$H,届出事由・区分・届出年月日ごと集計!$A15,SQLデータ!$G:$G,届出事由・区分・届出年月日ごと集計!$B15,SQLデータ!$L:$L,1,SQLデータ!$F:$F,"",SQLデータ!$C:$C,">="&届出事由・区分・届出年月日ごと集計!M$1,SQLデータ!$C:$C,"<="&届出事由・区分・届出年月日ごと集計!M$2) -> 0 | ... T15: =COUNTIFS(SQLデータ!$D:$D,"扶養",SQLデータ!$P:$P,1,SQLデータ!$H:$H,届出事由・区分・届出年月日ごと集計!$A15,SQLデータ!$G:$G,届出事由・区分・届出年月日ごと集計!$B15,SQLデータ!$L:$L,1,SQLデータ!$F:$F,"",SQLデータ!$C:$C,">="&届出事由・区分・届出年月日ごと集計!T$1,SQLデータ!$C:$C,"<="&届出事由・区分・届出年月日ごと集計!T$2) -> 0
A16: 増 | B16: 雇用保険受給終了 | C16: 扶養手当あり | D16: =COUNTIFS(SQLデータ!$D:$D,"扶養",SQLデータ!$H:$H,届出事由・区分・届出年月日ごと集計!$A16,SQLデータ!$G:$G,届出事由・区分・届出年月日ごと集計!$B16,SQLデータ!$M:$M,1) -> 0 | F16: =COUNTIFS(SQLデータ!$D:$D,"扶養",SQLデータ!$P:$P,1,SQLデータ!$H:$H,届出事由・区分・届出年月日ごと集計!$A16,SQLデータ!$G:$G,届出事由・区分・届出年月日ごと集計!$B16,SQLデータ!$M:$M,1,SQLデータ!$F:$F,"",SQLデータ!$C:$C,">="&届出事由・区分・届出年月日ごと集計!F$1,SQLデータ!$C:$C,"<="&届出事由・区分・届出年月日ごと集計!F$2) -> 0 | G16: =COUNTIFS(SQLデータ!$D:$D,"扶養",SQLデータ!$P:$P,1,SQLデータ!$H:$H,届出事由・区分・届出年月日ごと集計!$A16,SQLデータ!$G:$G,届出事由・区分・届出年月日ごと集計!$B16,SQLデータ!$M:$M,1,SQLデータ!$F:$F,"",SQLデータ!$C:$C,">="&届出事由・区分・届出年月日ごと集計!G$1,SQLデータ!$C:$C,"<="&届出事由・区分・届出年月日ごと集計!G$2) -> 0 | H16: =COUNTIFS(SQLデータ!$D:$D,"扶養",SQLデータ!$P:$P,1,SQLデータ!$H:$H,届出事由・区分・届出年月日ごと集計!$A16,SQLデータ!$G:$G,届出事由・区分・届出年月日ごと集計!$B16,SQLデータ!$M:$M,1,SQLデータ!$F:$F,"",SQLデータ!$C:$C,">="&届出事由・区分・届出年月日ごと集計!H$1,SQLデータ!$C:$C,"<="&届出事由・区分・届出年月日ごと集計!H$2) -> 0 | I16: =COUNTIFS(SQLデータ!$D:$D,"扶養",SQLデータ!$P:$P,1,SQLデータ!$H:$H,届出事由・区分・届出年月日ごと集計!$A16,SQLデータ!$G:$G,届出事由・区分・届出年月日ごと集計!$B16,SQLデータ!$M:$M,1,SQLデータ!$F:$F,"",SQLデータ!$C:$C,">="&届出事由・区分・届出年月日ごと集計!I$1,SQLデータ!$C:$C,"<="&届出事由・区分・届出年月日ごと集計!I$2) -> 0 | J16: =COUNTIFS(SQLデータ!$D:$D,"扶養",SQLデータ!$P:$P,1,SQLデータ!$H:$H,届出事由・区分・届出年月日ごと集計!$A16,SQLデータ!$G:$G,届出事由・区分・届出年月日ごと集計!$B16,SQLデータ!$M:$M,1,SQLデータ!$F:$F,"",SQLデータ!$C:$C,">="&届出事由・区分・届出年月日ごと集計!J$1,SQLデータ!$C:$C,"<="&届出事由・区分・届出年月日ごと集計!J$2) -> 0 | K16: =COUNTIFS(SQLデータ!$D:$D,"扶養",SQLデータ!$P:$P,1,SQLデータ!$H:$H,届出事由・区分・届出年月日ごと集計!$A16,SQLデータ!$G:$G,届出事由・区分・届出年月日ごと集計!$B16,SQLデータ!$M:$M,1,SQLデータ!$F:$F,"",SQLデータ!$C:$C,">="&届出事由・区分・届出年月日ごと集計!K$1,SQLデータ!$C:$C,"<="&届出事由・区分・届出年月日ごと集計!K$2) -> 0 | L16: =COUNTIFS(SQLデータ!$D:$D,"扶養",SQLデータ!$P:$P,1,SQLデータ!$H:$H,届出事由・区分・届出年月日ごと集計!$A16,SQLデータ!$G:$G,届出事由・区分・届出年月日ごと集計!$B16,SQLデータ!$M:$M,1,SQLデータ!$F:$F,"",SQLデータ!$C:$C,">="&届出事由・区分・届出年月日ごと集計!L$1,SQLデータ!$C:$C,"<="&届出事由・区分・届出年月日ごと集計!L$2) -> 0 | M16: =COUNTIFS(SQLデータ!$D:$D,"扶養",SQLデータ!$P:$P,1,SQLデータ!$H:$H,届出事由・区分・届出年月日ごと集計!$A16,SQLデータ!$G:$G,届出事由・区分・届出年月日ごと集計!$B16,SQLデータ!$M:$M,1,SQLデータ!$F:$F,"",SQLデータ!$C:$C,">="&届出事由・区分・届出年月日ごと集計!M$1,SQLデータ!$C:$C,"<="&届出事由・区分・届出年月日ごと集計!M$2) -> 0 | ... T16: =COUNTIFS(SQLデータ!$D:$D,"扶養",SQLデータ!$P:$P,1,SQLデータ!$H:$H,届出事由・区分・届出年月日ごと集計!$A16,SQLデータ!$G:$G,届出事由・区分・届出年月日ごと集計!$B16,SQLデータ!$M:$M,1,SQLデータ!$F:$F,"",SQLデータ!$C:$C,">="&届出事由・区分・届出年月日ごと集計!T$1,SQLデータ!$C:$C,"<="&届出事由・区分・届出年月日ごと集計!T$2) -> 0
A17: 増 | B17: 雇用保険受給終了 | C17: 税控除のみ | D17: =COUNTIFS(SQLデータ!$D:$D,"扶養",SQLデータ!$H:$H,届出事由・区分・届出年月日ごと集計!$A17,SQLデータ!$G:$G,届出事由・区分・届出年月日ごと集計!$B17,SQLデータ!$N:$N,1) -> 1 | F17: =COUNTIFS(SQLデータ!$D:$D,"扶養",SQLデータ!$P:$P,1,SQLデータ!$H:$H,届出事由・区分・届出年月日ごと集計!$A17,SQLデータ!$G:$G,届出事由・区分・届出年月日ごと集計!$B17,SQLデータ!$N:$N,1,SQLデータ!$F:$F,"",SQLデータ!$C:$C,">="&届出事由・区分・届出年月日ごと集計!F$1,SQLデータ!$C:$C,"<="&届出事由・区分・届出年月日ごと集計!F$2) -> 0 | G17: =COUNTIFS(SQLデータ!$D:$D,"扶養",SQLデータ!$P:$P,1,SQLデータ!$H:$H,届出事由・区分・届出年月日ごと集計!$A17,SQLデータ!$G:$G,届出事由・区分・届出年月日ごと集計!$B17,SQLデータ!$N:$N,1,SQLデータ!$F:$F,"",SQLデータ!$C:$C,">="&届出事由・区分・届出年月日ごと集計!G$1,SQLデータ!$C:$C,"<="&届出事由・区分・届出年月日ごと集計!G$2) -> 0 | H17: =COUNTIFS(SQLデータ!$D:$D,"扶養",SQLデータ!$P:$P,1,SQLデータ!$H:$H,届出事由・区分・届出年月日ごと集計!$A17,SQLデータ!$G:$G,届出事由・区分・届出年月日ごと集計!$B17,SQLデータ!$N:$N,1,SQLデータ!$F:$F,"",SQLデータ!$C:$C,">="&届出事由・区分・届出年月日ごと集計!H$1,SQLデータ!$C:$C,"<="&届出事由・区分・届出年月日ごと集計!H$2) -> 0 | I17: =COUNTIFS(SQLデータ!$D:$D,"扶養",SQLデータ!$P:$P,1,SQLデータ!$H:$H,届出事由・区分・届出年月日ごと集計!$A17,SQLデータ!$G:$G,届出事由・区分・届出年月日ごと集計!$B17,SQLデータ!$N:$N,1,SQLデータ!$F:$F,"",SQLデータ!$C:$C,">="&届出事由・区分・届出年月日ごと集計!I$1,SQLデータ!$C:$C,"<="&届出事由・区分・届出年月日ごと集計!I$2) -> 1 | J17: =COUNTIFS(SQLデータ!$D:$D,"扶養",SQLデータ!$P:$P,1,SQLデータ!$H:$H,届出事由・区分・届出年月日ごと集計!$A17,SQLデータ!$G:$G,届出事由・区分・届出年月日ごと集計!$B17,SQLデータ!$N:$N,1,SQLデータ!$F:$F,"",SQLデータ!$C:$C,">="&届出事由・区分・届出年月日ごと集計!J$1,SQLデータ!$C:$C,"<="&届出事由・区分・届出年月日ごと集計!J$2) -> 0 | K17: =COUNTIFS(SQLデータ!$D:$D,"扶養",SQLデータ!$P:$P,1,SQLデータ!$H:$H,届出事由・区分・届出年月日ごと集計!$A17,SQLデータ!$G:$G,届出事由・区分・届出年月日ごと集計!$B17,SQLデータ!$N:$N,1,SQLデータ!$F:$F,"",SQLデータ!$C:$C,">="&届出事由・区分・届出年月日ごと集計!K$1,SQLデータ!$C:$C,"<="&届出事由・区分・届出年月日ごと集計!K$2) -> 0 | L17: =COUNTIFS(SQLデータ!$D:$D,"扶養",SQLデータ!$P:$P,1,SQLデータ!$H:$H,届出事由・区分・届出年月日ごと集計!$A17,SQLデータ!$G:$G,届出事由・区分・届出年月日ごと集計!$B17,SQLデータ!$N:$N,1,SQLデータ!$F:$F,"",SQLデータ!$C:$C,">="&届出事由・区分・届出年月日ごと集計!L$1,SQLデータ!$C:$C,"<="&届出事由・区分・届出年月日ごと集計!L$2) -> 0 | M17: =COUNTIFS(SQLデータ!$D:$D,"扶養",SQLデータ!$P:$P,1,SQLデータ!$H:$H,届出事由・区分・届出年月日ごと集計!$A17,SQLデータ!$G:$G,届出事由・区分・届出年月日ごと集計!$B17,SQLデータ!$N:$N,1,SQLデータ!$F:$F,"",SQLデータ!$C:$C,">="&届出事由・区分・届出年月日ごと集計!M$1,SQLデータ!$C:$C,"<="&届出事由・区分・届出年月日ごと集計!M$2) -> 0 | ... T17: =COUNTIFS(SQLデータ!$D:$D,"扶養",SQLデータ!$P:$P,1,SQLデータ!$H:$H,届出事由・区分・届出年月日ごと集計!$A17,SQLデータ!$G:$G,届出事由・区分・届出年月日ごと集計!$B17,SQLデータ!$N:$N,1,SQLデータ!$F:$F,"",SQLデータ!$C:$C,">="&届出事由・区分・届出年月日ごと集計!T$1,SQLデータ!$C:$C,"<="&届出事由・区分・届出年月日ごと集計!T$2) -> 0
A18: 増 | B18: 雇用保険受給終了 | C18: 本人税のみ | D18: =COUNTIFS(SQLデータ!$D:$D,"扶養",SQLデータ!$H:$H,届出事由・区分・届出年月日ごと集計!$A18,SQLデータ!$G:$G,届出事由・区分・届出年月日ごと集計!$B18,SQLデータ!$O:$O,1) -> 0 | F18: =COUNTIFS(SQLデータ!$D:$D,"扶養",SQLデータ!$P:$P,1,SQLデータ!$H:$H,届出事由・区分・届出年月日ごと集計!$A18,SQLデータ!$G:$G,届出事由・区分・届出年月日ごと集計!$B18,SQLデータ!$O:$O,1,SQLデータ!$F:$F,"",SQLデータ!$C:$C,">="&届出事由・区分・届出年月日ごと集計!F$1,SQLデータ!$C:$C,"<="&届出事由・区分・届出年月日ごと集計!F$2) -> 0 | G18: =COUNTIFS(SQLデータ!$D:$D,"扶養",SQLデータ!$P:$P,1,SQLデータ!$H:$H,届出事由・区分・届出年月日ごと集計!$A18,SQLデータ!$G:$G,届出事由・区分・届出年月日ごと集計!$B18,SQLデータ!$O:$O,1,SQLデータ!$F:$F,"",SQLデータ!$C:$C,">="&届出事由・区分・届出年月日ごと集計!G$1,SQLデータ!$C:$C,"<="&届出事由・区分・届出年月日ごと集計!G$2) -> 0 | H18: =COUNTIFS(SQLデータ!$D:$D,"扶養",SQLデータ!$P:$P,1,SQLデータ!$H:$H,届出事由・区分・届出年月日ごと集計!$A18,SQLデータ!$G:$G,届出事由・区分・届出年月日ごと集計!$B18,SQLデータ!$O:$O,1,SQLデータ!$F:$F,"",SQLデータ!$C:$C,">="&届出事由・区分・届出年月日ごと集計!H$1,SQLデータ!$C:$C,"<="&届出事由・区分・届出年月日ごと集計!H$2) -> 0 | I18: =COUNTIFS(SQLデータ!$D:$D,"扶養",SQLデータ!$P:$P,1,SQLデータ!$H:$H,届出事由・区分・届出年月日ごと集計!$A18,SQLデータ!$G:$G,届出事由・区分・届出年月日ごと集計!$B18,SQLデータ!$O:$O,1,SQLデータ!$F:$F,"",SQLデータ!$C:$C,">="&届出事由・区分・届出年月日ごと集計!I$1,SQLデータ!$C:$C,"<="&届出事由・区分・届出年月日ごと集計!I$2) -> 0 | J18: =COUNTIFS(SQLデータ!$D:$D,"扶養",SQLデータ!$P:$P,1,SQLデータ!$H:$H,届出事由・区分・届出年月日ごと集計!$A18,SQLデータ!$G:$G,届出事由・区分・届出年月日ごと集計!$B18,SQLデータ!$O:$O,1,SQLデータ!$F:$F,"",SQLデータ!$C:$C,">="&届出事由・区分・届出年月日ごと集計!J$1,SQLデータ!$C:$C,"<="&届出事由・区分・届出年月日ごと集計!J$2) -> 0 | K18: =COUNTIFS(SQLデータ!$D:$D,"扶養",SQLデータ!$P:$P,1,SQLデータ!$H:$H,届出事由・区分・届出年月日ごと集計!$A18,SQLデータ!$G:$G,届出事由・区分・届出年月日ごと集計!$B18,SQLデータ!$O:$O,1,SQLデータ!$F:$F,"",SQLデータ!$C:$C,">="&届出事由・区分・届出年月日ごと集計!K$1,SQLデータ!$C:$C,"<="&届出事由・区分・届出年月日ごと集計!K$2) -> 0 | L18: =COUNTIFS(SQLデータ!$D:$D,"扶養",SQLデータ!$P:$P,1,SQLデータ!$H:$H,届出事由・区分・届出年月日ごと集計!$A18,SQLデータ!$G:$G,届出事由・区分・届出年月日ごと集計!$B18,SQLデータ!$O:$O,1,SQLデータ!$F:$F,"",SQLデータ!$C:$C,">="&届出事由・区分・届出年月日ごと集計!L$1,SQLデータ!$C:$C,"<="&届出事由・区分・届出年月日ごと集計!L$2) -> 0 | M18: =COUNTIFS(SQLデータ!$D:$D,"扶養",SQLデータ!$P:$P,1,SQLデータ!$H:$H,届出事由・区分・届出年月日ごと集計!$A18,SQLデータ!$G:$G,届出事由・区分・届出年月日ごと集計!$B18,SQLデータ!$O:$O,1,SQLデータ!$F:$F,"",SQLデータ!$C:$C,">="&届出事由・区分・届出年月日ごと集計!M$1,SQLデータ!$C:$C,"<="&届出事由・区分・届出年月日ごと集計!M$2) -> 0 | ... T18: =COUNTIFS(SQLデータ!$D:$D,"扶養",SQLデータ!$P:$P,1,SQLデータ!$H:$H,届出事由・区分・届出年月日ごと集計!$A18,SQLデータ!$G:$G,届出事由・区分・届出年月日ごと集計!$B18,SQLデータ!$O:$O,1,SQLデータ!$F:$F,"",SQLデータ!$C:$C,">="&届出事由・区分・届出年月日ごと集計!T$1,SQLデータ!$C:$C,"<="&届出事由・区分・届出年月日ごと集計!T$2) -> 0
A19: 増 | B19: 育休 | C19: 共済あり | D19: =COUNTIFS(SQLデータ!$D:$D,"扶養",SQLデータ!$H:$H,届出事由・区分・届出年月日ごと集計!$A19,SQLデータ!$G:$G,届出事由・区分・届出年月日ごと集計!$B19,SQLデータ!$L:$L,1) -> 0 | F19: =COUNTIFS(SQLデータ!$D:$D,"扶養",SQLデータ!$P:$P,1,SQLデータ!$H:$H,届出事由・区分・届出年月日ごと集計!$A19,SQLデータ!$G:$G,届出事由・区分・届出年月日ごと集計!$B19,SQLデータ!$L:$L,1,SQLデータ!$F:$F,"",SQLデータ!$C:$C,">="&届出事由・区分・届出年月日ごと集計!F$1,SQLデータ!$C:$C,"<="&届出事由・区分・届出年月日ごと集計!F$2) -> 0 | G19: =COUNTIFS(SQLデータ!$D:$D,"扶養",SQLデータ!$P:$P,1,SQLデータ!$H:$H,届出事由・区分・届出年月日ごと集計!$A19,SQLデータ!$G:$G,届出事由・区分・届出年月日ごと集計!$B19,SQLデータ!$L:$L,1,SQLデータ!$F:$F,"",SQLデータ!$C:$C,">="&届出事由・区分・届出年月日ごと集計!G$1,SQLデータ!$C:$C,"<="&届出事由・区分・届出年月日ごと集計!G$2) -> 0 | H19: =COUNTIFS(SQLデータ!$D:$D,"扶養",SQLデータ!$P:$P,1,SQLデータ!$H:$H,届出事由・区分・届出年月日ごと集計!$A19,SQLデータ!$G:$G,届出事由・区分・届出年月日ごと集計!$B19,SQLデータ!$L:$L,1,SQLデータ!$F:$F,"",SQLデータ!$C:$C,">="&届出事由・区分・届出年月日ごと集計!H$1,SQLデータ!$C:$C,"<="&届出事由・区分・届出年月日ごと集計!H$2) -> 0 | I19: =COUNTIFS(SQLデータ!$D:$D,"扶養",SQLデータ!$P:$P,1,SQLデータ!$H:$H,届出事由・区分・届出年月日ごと集計!$A19,SQLデータ!$G:$G,届出事由・区分・届出年月日ごと集計!$B19,SQLデータ!$L:$L,1,SQLデータ!$F:$F,"",SQLデータ!$C:$C,">="&届出事由・区分・届出年月日ごと集計!I$1,SQLデータ!$C:$C,"<="&届出事由・区分・届出年月日ごと集計!I$2) -> 0 | J19: =COUNTIFS(SQLデータ!$D:$D,"扶養",SQLデータ!$P:$P,1,SQLデータ!$H:$H,届出事由・区分・届出年月日ごと集計!$A19,SQLデータ!$G:$G,届出事由・区分・届出年月日ごと集計!$B19,SQLデータ!$L:$L,1,SQLデータ!$F:$F,"",SQLデータ!$C:$C,">="&届出事由・区分・届出年月日ごと集計!J$1,SQLデータ!$C:$C,"<="&届出事由・区分・届出年月日ごと集計!J$2) -> 0 | K19: =COUNTIFS(SQLデータ!$D:$D,"扶養",SQLデータ!$P:$P,1,SQLデータ!$H:$H,届出事由・区分・届出年月日ごと集計!$A19,SQLデータ!$G:$G,届出事由・区分・届出年月日ごと集計!$B19,SQLデータ!$L:$L,1,SQLデータ!$F:$F,"",SQLデータ!$C:$C,">="&届出事由・区分・届出年月日ごと集計!K$1,SQLデータ!$C:$C,"<="&届出事由・区分・届出年月日ごと集計!K$2) -> 0 | L19: =COUNTIFS(SQLデータ!$D:$D,"扶養",SQLデータ!$P:$P,1,SQLデータ!$H:$H,届出事由・区分・届出年月日ごと集計!$A19,SQLデータ!$G:$G,届出事由・区分・届出年月日ごと集計!$B19,SQLデータ!$L:$L,1,SQLデータ!$F:$F,"",SQLデータ!$C:$C,">="&届出事由・区分・届出年月日ごと集計!L$1,SQLデータ!$C:$C,"<="&届出事由・区分・届出年月日ごと集計!L$2) -> 0 | M19: =COUNTIFS(SQLデータ!$D:$D,"扶養",SQLデータ!$P:$P,1,SQLデータ!$H:$H,届出事由・区分・届出年月日ごと集計!$A19,SQLデータ!$G:$G,届出事由・区分・届出年月日ごと集計!$B19,SQLデータ!$L:$L,1,SQLデータ!$F:$F,"",SQLデータ!$C:$C,">="&届出事由・区分・届出年月日ごと集計!M$1,SQLデータ!$C:$C,"<="&届出事由・区分・届出年月日ごと集計!M$2) -> 0 | ... T19: =COUNTIFS(SQLデータ!$D:$D,"扶養",SQLデータ!$P:$P,1,SQLデータ!$H:$H,届出事由・区分・届出年月日ごと集計!$A19,SQLデータ!$G:$G,届出事由・区分・届出年月日ごと集計!$B19,SQLデータ!$L:$L,1,SQLデータ!$F:$F,"",SQLデータ!$C:$C,">="&届出事由・区分・届出年月日ごと集計!T$1,SQLデータ!$C:$C,"<="&届出事由・区分・届出年月日ごと集計!T$2) -> 0
A20: 増 | B20: 育休 | C20: 扶養手当あり | D20: =COUNTIFS(SQLデータ!$D:$D,"扶養",SQLデータ!$H:$H,届出事由・区分・届出年月日ごと集計!$A20,SQLデータ!$G:$G,届出事由・区分・届出年月日ごと集計!$B20,SQLデータ!$M:$M,1) -> 1 | F20: =COUNTIFS(SQLデータ!$D:$D,"扶養",SQLデータ!$P:$P,1,SQLデータ!$H:$H,届出事由・区分・届出年月日ごと集計!$A20,SQLデータ!$G:$G,届出事由・区分・届出年月日ごと集計!$B20,SQLデータ!$M:$M,1,SQLデータ!$F:$F,"",SQLデータ!$C:$C,">="&届出事由・区分・届出年月日ごと集計!F$1,SQLデータ!$C:$C,"<="&届出事由・区分・届出年月日ごと集計!F$2) -> 0 | G20: =COUNTIFS(SQLデータ!$D:$D,"扶養",SQLデータ!$P:$P,1,SQLデータ!$H:$H,届出事由・区分・届出年月日ごと集計!$A20,SQLデータ!$G:$G,届出事由・区分・届出年月日ごと集計!$B20,SQLデータ!$M:$M,1,SQLデータ!$F:$F,"",SQLデータ!$C:$C,">="&届出事由・区分・届出年月日ごと集計!G$1,SQLデータ!$C:$C,"<="&届出事由・区分・届出年月日ごと集計!G$2) -> 0 | H20: =COUNTIFS(SQLデータ!$D:$D,"扶養",SQLデータ!$P:$P,1,SQLデータ!$H:$H,届出事由・区分・届出年月日ごと集計!$A20,SQLデータ!$G:$G,届出事由・区分・届出年月日ごと集計!$B20,SQLデータ!$M:$M,1,SQLデータ!$F:$F,"",SQLデータ!$C:$C,">="&届出事由・区分・届出年月日ごと集計!H$1,SQLデータ!$C:$C,"<="&届出事由・区分・届出年月日ごと集計!H$2) -> 0 | I20: =COUNTIFS(SQLデータ!$D:$D,"扶養",SQLデータ!$P:$P,1,SQLデータ!$H:$H,届出事由・区分・届出年月日ごと集計!$A20,SQLデータ!$G:$G,届出事由・区分・届出年月日ごと集計!$B20,SQLデータ!$M:$M,1,SQLデータ!$F:$F,"",SQLデータ!$C:$C,">="&届出事由・区分・届出年月日ごと集計!I$1,SQLデータ!$C:$C,"<="&届出事由・区分・届出年月日ごと集計!I$2) -> 0 | J20: =COUNTIFS(SQLデータ!$D:$D,"扶養",SQLデータ!$P:$P,1,SQLデータ!$H:$H,届出事由・区分・届出年月日ごと集計!$A20,SQLデータ!$G:$G,届出事由・区分・届出年月日ごと集計!$B20,SQLデータ!$M:$M,1,SQLデータ!$F:$F,"",SQLデータ!$C:$C,">="&届出事由・区分・届出年月日ごと集計!J$1,SQLデータ!$C:$C,"<="&届出事由・区分・届出年月日ごと集計!J$2) -> 0 | K20: =COUNTIFS(SQLデータ!$D:$D,"扶養",SQLデータ!$P:$P,1,SQLデータ!$H:$H,届出事由・区分・届出年月日ごと集計!$A20,SQLデータ!$G:$G,届出事由・区分・届出年月日ごと集計!$B20,SQLデータ!$M:$M,1,SQLデータ!$F:$F,"",SQLデータ!$C:$C,">="&届出事由・区分・届出年月日ごと集計!K$1,SQLデータ!$C:$C,"<="&届出事由・区分・届出年月日ごと集計!K$2) -> 0 | L20: =COUNTIFS(SQLデータ!$D:$D,"扶養",SQLデータ!$P:$P,1,SQLデータ!$H:$H,届出事由・区分・届出年月日ごと集計!$A20,SQLデータ!$G:$G,届出事由・区分・届出年月日ごと集計!$B20,SQLデータ!$M:$M,1,SQLデータ!$F:$F,"",SQLデータ!$C:$C,">="&届出事由・区分・届出年月日ごと集計!L$1,SQLデータ!$C:$C,"<="&届出事由・区分・届出年月日ごと集計!L$2) -> 0 | M20: =COUNTIFS(SQLデータ!$D:$D,"扶養",SQLデータ!$P:$P,1,SQLデータ!$H:$H,届出事由・区分・届出年月日ごと集計!$A20,SQLデータ!$G:$G,届出事由・区分・届出年月日ごと集計!$B20,SQLデータ!$M:$M,1,SQLデータ!$F:$F,"",SQLデータ!$C:$C,">="&届出事由・区分・届出年月日ごと集計!M$1,SQLデータ!$C:$C,"<="&届出事由・区分・届出年月日ごと集計!M$2) -> 0 | ... T20: =COUNTIFS(SQLデータ!$D:$D,"扶養",SQLデータ!$P:$P,1,SQLデータ!$H:$H,届出事由・区分・届出年月日ごと集計!$A20,SQLデータ!$G:$G,届出事由・区分・届出年月日ごと集計!$B20,SQLデータ!$M:$M,1,SQLデータ!$F:$F,"",SQLデータ!$C:$C,">="&届出事由・区分・届出年月日ごと集計!T$1,SQLデータ!$C:$C,"<="&届出事由・区分・届出年月日ごと集計!T$2) -> 0
A21: 増 | B21: 育休 | C21: 税控除のみ | D21: =COUNTIFS(SQLデータ!$D:$D,"扶養",SQLデータ!$H:$H,届出事由・区分・届出年月日ごと集計!$A21,SQLデータ!$G:$G,届出事由・区分・届出年月日ごと集計!$B21,SQLデータ!$N:$N,1) -> 0 | F21: =COUNTIFS(SQLデータ!$D:$D,"扶養",SQLデータ!$P:$P,1,SQLデータ!$H:$H,届出事由・区分・届出年月日ごと集計!$A21,SQLデータ!$G:$G,届出事由・区分・届出年月日ごと集計!$B21,SQLデータ!$N:$N,1,SQLデータ!$F:$F,"",SQLデータ!$C:$C,">="&届出事由・区分・届出年月日ごと集計!F$1,SQLデータ!$C:$C,"<="&届出事由・区分・届出年月日ごと集計!F$2) -> 0 | G21: =COUNTIFS(SQLデータ!$D:$D,"扶養",SQLデータ!$P:$P,1,SQLデータ!$H:$H,届出事由・区分・届出年月日ごと集計!$A21,SQLデータ!$G:$G,届出事由・区分・届出年月日ごと集計!$B21,SQLデータ!$N:$N,1,SQLデータ!$F:$F,"",SQLデータ!$C:$C,">="&届出事由・区分・届出年月日ごと集計!G$1,SQLデータ!$C:$C,"<="&届出事由・区分・届出年月日ごと集計!G$2) -> 0 | H21: =COUNTIFS(SQLデータ!$D:$D,"扶養",SQLデータ!$P:$P,1,SQLデータ!$H:$H,届出事由・区分・届出年月日ごと集計!$A21,SQLデータ!$G:$G,届出事由・区分・届出年月日ごと集計!$B21,SQLデータ!$N:$N,1,SQLデータ!$F:$F,"",SQLデータ!$C:$C,">="&届出事由・区分・届出年月日ごと集計!H$1,SQLデータ!$C:$C,"<="&届出事由・区分・届出年月日ごと集計!H$2) -> 0 | I21: =COUNTIFS(SQLデータ!$D:$D,"扶養",SQLデータ!$P:$P,1,SQLデータ!$H:$H,届出事由・区分・届出年月日ごと集計!$A21,SQLデータ!$G:$G,届出事由・区分・届出年月日ごと集計!$B21,SQLデータ!$N:$N,1,SQLデータ!$F:$F,"",SQLデータ!$C:$C,">="&届出事由・区分・届出年月日ごと集計!I$1,SQLデータ!$C:$C,"<="&届出事由・区分・届出年月日ごと集計!I$2) -> 0 | J21: =COUNTIFS(SQLデータ!$D:$D,"扶養",SQLデータ!$P:$P,1,SQLデータ!$H:$H,届出事由・区分・届出年月日ごと集計!$A21,SQLデータ!$G:$G,届出事由・区分・届出年月日ごと集計!$B21,SQLデータ!$N:$N,1,SQLデータ!$F:$F,"",SQLデータ!$C:$C,">="&届出事由・区分・届出年月日ごと集計!J$1,SQLデータ!$C:$C,"<="&届出事由・区分・届出年月日ごと集計!J$2) -> 0 | K21: =COUNTIFS(SQLデータ!$D:$D,"扶養",SQLデータ!$P:$P,1,SQLデータ!$H:$H,届出事由・区分・届出年月日ごと集計!$A21,SQLデータ!$G:$G,届出事由・区分・届出年月日ごと集計!$B21,SQLデータ!$N:$N,1,SQLデータ!$F:$F,"",SQLデータ!$C:$C,">="&届出事由・区分・届出年月日ごと集計!K$1,SQLデータ!$C:$C,"<="&届出事由・区分・届出年月日ごと集計!K$2) -> 0 | L21: =COUNTIFS(SQLデータ!$D:$D,"扶養",SQLデータ!$P:$P,1,SQLデータ!$H:$H,届出事由・区分・届出年月日ごと集計!$A21,SQLデータ!$G:$G,届出事由・区分・届出年月日ごと集計!$B21,SQLデータ!$N:$N,1,SQLデータ!$F:$F,"",SQLデータ!$C:$C,">="&届出事由・区分・届出年月日ごと集計!L$1,SQLデータ!$C:$C,"<="&届出事由・区分・届出年月日ごと集計!L$2) -> 0 | M21: =COUNTIFS(SQLデータ!$D:$D,"扶養",SQLデータ!$P:$P,1,SQLデータ!$H:$H,届出事由・区分・届出年月日ごと集計!$A21,SQLデータ!$G:$G,届出事由・区分・届出年月日ごと集計!$B21,SQLデータ!$N:$N,1,SQLデータ!$F:$F,"",SQLデータ!$C:$C,">="&届出事由・区分・届出年月日ごと集計!M$1,SQLデータ!$C:$C,"<="&届出事由・区分・届出年月日ごと集計!M$2) -> 0 | ... T21: =COUNTIFS(SQLデータ!$D:$D,"扶養",SQLデータ!$P:$P,1,SQLデータ!$H:$H,届出事由・区分・届出年月日ごと集計!$A21,SQLデータ!$G:$G,届出事由・区分・届出年月日ごと集計!$B21,SQLデータ!$N:$N,1,SQLデータ!$F:$F,"",SQLデータ!$C:$C,">="&届出事由・区分・届出年月日ごと集計!T$1,SQLデータ!$C:$C,"<="&届出事由・区分・届出年月日ごと集計!T$2) -> 0
A22: 増 | B22: 育休 | C22: 本人税のみ | D22: =COUNTIFS(SQLデータ!$D:$D,"扶養",SQLデータ!$H:$H,届出事由・区分・届出年月日ごと集計!$A22,SQLデータ!$G:$G,届出事由・区分・届出年月日ごと集計!$B22,SQLデータ!$O:$O,1) -> 0 | F22: =COUNTIFS(SQLデータ!$D:$D,"扶養",SQLデータ!$P:$P,1,SQLデータ!$H:$H,届出事由・区分・届出年月日ごと集計!$A22,SQLデータ!$G:$G,届出事由・区分・届出年月日ごと集計!$B22,SQLデータ!$O:$O,1,SQLデータ!$F:$F,"",SQLデータ!$C:$C,">="&届出事由・区分・届出年月日ごと集計!F$1,SQLデータ!$C:$C,"<="&届出事由・区分・届出年月日ごと集計!F$2) -> 0 | G22: =COUNTIFS(SQLデータ!$D:$D,"扶養",SQLデータ!$P:$P,1,SQLデータ!$H:$H,届出事由・区分・届出年月日ごと集計!$A22,SQLデータ!$G:$G,届出事由・区分・届出年月日ごと集計!$B22,SQLデータ!$O:$O,1,SQLデータ!$F:$F,"",SQLデータ!$C:$C,">="&届出事由・区分・届出年月日ごと集計!G$1,SQLデータ!$C:$C,"<="&届出事由・区分・届出年月日ごと集計!G$2) -> 0 | H22: =COUNTIFS(SQLデータ!$D:$D,"扶養",SQLデータ!$P:$P,1,SQLデータ!$H:$H,届出事由・区分・届出年月日ごと集計!$A22,SQLデータ!$G:$G,届出事由・区分・届出年月日ごと集計!$B22,SQLデータ!$O:$O,1,SQLデータ!$F:$F,"",SQLデータ!$C:$C,">="&届出事由・区分・届出年月日ごと集計!H$1,SQLデータ!$C:$C,"<="&届出事由・区分・届出年月日ごと集計!H$2) -> 0 | I22: =COUNTIFS(SQLデータ!$D:$D,"扶養",SQLデータ!$P:$P,1,SQLデータ!$H:$H,届出事由・区分・届出年月日ごと集計!$A22,SQLデータ!$G:$G,届出事由・区分・届出年月日ごと集計!$B22,SQLデータ!$O:$O,1,SQLデータ!$F:$F,"",SQLデータ!$C:$C,">="&届出事由・区分・届出年月日ごと集計!I$1,SQLデータ!$C:$C,"<="&届出事由・区分・届出年月日ごと集計!I$2) -> 0 | J22: =COUNTIFS(SQLデータ!$D:$D,"扶養",SQLデータ!$P:$P,1,SQLデータ!$H:$H,届出事由・区分・届出年月日ごと集計!$A22,SQLデータ!$G:$G,届出事由・区分・届出年月日ごと集計!$B22,SQLデータ!$O:$O,1,SQLデータ!$F:$F,"",SQLデータ!$C:$C,">="&届出事由・区分・届出年月日ごと集計!J$1,SQLデータ!$C:$C,"<="&届出事由・区分・届出年月日ごと集計!J$2) -> 0 | K22: =COUNTIFS(SQLデータ!$D:$D,"扶養",SQLデータ!$P:$P,1,SQLデータ!$H:$H,届出事由・区分・届出年月日ごと集計!$A22,SQLデータ!$G:$G,届出事由・区分・届出年月日ごと集計!$B22,SQLデータ!$O:$O,1,SQLデータ!$F:$F,"",SQLデータ!$C:$C,">="&届出事由・区分・届出年月日ごと集計!K$1,SQLデータ!$C:$C,"<="&届出事由・区分・届出年月日ごと集計!K$2) -> 0 | L22: =COUNTIFS(SQLデータ!$D:$D,"扶養",SQLデータ!$P:$P,1,SQLデータ!$H:$H,届出事由・区分・届出年月日ごと集計!$A22,SQLデータ!$G:$G,届出事由・区分・届出年月日ごと集計!$B22,SQLデータ!$O:$O,1,SQLデータ!$F:$F,"",SQLデータ!$C:$C,">="&届出事由・区分・届出年月日ごと集計!L$1,SQLデータ!$C:$C,"<="&届出事由・区分・届出年月日ごと集計!L$2) -> 0 | M22: =COUNTIFS(SQLデータ!$D:$D,"扶養",SQLデータ!$P:$P,1,SQLデータ!$H:$H,届出事由・区分・届出年月日ごと集計!$A22,SQLデータ!$G:$G,届出事由・区分・届出年月日ごと集計!$B22,SQLデータ!$O:$O,1,SQLデータ!$F:$F,"",SQLデータ!$C:$C,">="&届出事由・区分・届出年月日ごと集計!M$1,SQLデータ!$C:$C,"<="&届出事由・区分・届出年月日ごと集計!M$2) -> 0 | ... T22: =COUNTIFS(SQLデータ!$D:$D,"扶養",SQLデータ!$P:$P,1,SQLデータ!$H:$H,届出事由・区分・届出年月日ごと集計!$A22,SQLデータ!$G:$G,届出事由・区分・届出年月日ごと集計!$B22,SQLデータ!$O:$O,1,SQLデータ!$F:$F,"",SQLデータ!$C:$C,">="&届出事由・区分・届出年月日ごと集計!T$1,SQLデータ!$C:$C,"<="&届出事由・区分・届出年月日ごと集計!T$2) -> 0
A23: 増 | B23: 扶養者の変更 | C23: 共済あり | D23: =COUNTIFS(SQLデータ!$D:$D,"扶養",SQLデータ!$H:$H,届出事由・区分・届出年月日ごと集計!$A23,SQLデータ!$G:$G,届出事由・区分・届出年月日ごと集計!$B23,SQLデータ!$L:$L,1) -> 8 | F23: =COUNTIFS(SQLデータ!$D:$D,"扶養",SQLデータ!$P:$P,1,SQLデータ!$H:$H,届出事由・区分・届出年月日ごと集計!$A23,SQLデータ!$G:$G,届出事由・区分・届出年月日ごと集計!$B23,SQLデータ!$L:$L,1,SQLデータ!$F:$F,"",SQLデータ!$C:$C,">="&届出事由・区分・届出年月日ごと集計!F$1,SQLデータ!$C:$C,"<="&届出事由・区分・届出年月日ごと集計!F$2) -> 0 | G23: =COUNTIFS(SQLデータ!$D:$D,"扶養",SQLデータ!$P:$P,1,SQLデータ!$H:$H,届出事由・区分・届出年月日ごと集計!$A23,SQLデータ!$G:$G,届出事由・区分・届出年月日ごと集計!$B23,SQLデータ!$L:$L,1,SQLデータ!$F:$F,"",SQLデータ!$C:$C,">="&届出事由・区分・届出年月日ごと集計!G$1,SQLデータ!$C:$C,"<="&届出事由・区分・届出年月日ごと集計!G$2) -> 1 | H23: =COUNTIFS(SQLデータ!$D:$D,"扶養",SQLデータ!$P:$P,1,SQLデータ!$H:$H,届出事由・区分・届出年月日ごと集計!$A23,SQLデータ!$G:$G,届出事由・区分・届出年月日ごと集計!$B23,SQLデータ!$L:$L,1,SQLデータ!$F:$F,"",SQLデータ!$C:$C,">="&届出事由・区分・届出年月日ごと集計!H$1,SQLデータ!$C:$C,"<="&届出事由・区分・届出年月日ごと集計!H$2) -> 2 | I23: =COUNTIFS(SQLデータ!$D:$D,"扶養",SQLデータ!$P:$P,1,SQLデータ!$H:$H,届出事由・区分・届出年月日ごと集計!$A23,SQLデータ!$G:$G,届出事由・区分・届出年月日ごと集計!$B23,SQLデータ!$L:$L,1,SQLデータ!$F:$F,"",SQLデータ!$C:$C,">="&届出事由・区分・届出年月日ごと集計!I$1,SQLデータ!$C:$C,"<="&届出事由・区分・届出年月日ごと集計!I$2) -> 2 | J23: =COUNTIFS(SQLデータ!$D:$D,"扶養",SQLデータ!$P:$P,1,SQLデータ!$H:$H,届出事由・区分・届出年月日ごと集計!$A23,SQLデータ!$G:$G,届出事由・区分・届出年月日ごと集計!$B23,SQLデータ!$L:$L,1,SQLデータ!$F:$F,"",SQLデータ!$C:$C,">="&届出事由・区分・届出年月日ごと集計!J$1,SQLデータ!$C:$C,"<="&届出事由・区分・届出年月日ごと集計!J$2) -> 0 | K23: =COUNTIFS(SQLデータ!$D:$D,"扶養",SQLデータ!$P:$P,1,SQLデータ!$H:$H,届出事由・区分・届出年月日ごと集計!$A23,SQLデータ!$G:$G,届出事由・区分・届出年月日ごと集計!$B23,SQLデータ!$L:$L,1,SQLデータ!$F:$F,"",SQLデータ!$C:$C,">="&届出事由・区分・届出年月日ごと集計!K$1,SQLデータ!$C:$C,"<="&届出事由・区分・届出年月日ごと集計!K$2) -> 0 | L23: =COUNTIFS(SQLデータ!$D:$D,"扶養",SQLデータ!$P:$P,1,SQLデータ!$H:$H,届出事由・区分・届出年月日ごと集計!$A23,SQLデータ!$G:$G,届出事由・区分・届出年月日ごと集計!$B23,SQLデータ!$L:$L,1,SQLデータ!$F:$F,"",SQLデータ!$C:$C,">="&届出事由・区分・届出年月日ごと集計!L$1,SQLデータ!$C:$C,"<="&届出事由・区分・届出年月日ごと集計!L$2) -> 0 | M23: =COUNTIFS(SQLデータ!$D:$D,"扶養",SQLデータ!$P:$P,1,SQLデータ!$H:$H,届出事由・区分・届出年月日ごと集計!$A23,SQLデータ!$G:$G,届出事由・区分・届出年月日ごと集計!$B23,SQLデータ!$L:$L,1,SQLデータ!$F:$F,"",SQLデータ!$C:$C,">="&届出事由・区分・届出年月日ごと集計!M$1,SQLデータ!$C:$C,"<="&届出事由・区分・届出年月日ごと集計!M$2) -> 0 | ... T23: =COUNTIFS(SQLデータ!$D:$D,"扶養",SQLデータ!$P:$P,1,SQLデータ!$H:$H,届出事由・区分・届出年月日ごと集計!$A23,SQLデータ!$G:$G,届出事由・区分・届出年月日ごと集計!$B23,SQLデータ!$L:$L,1,SQLデータ!$F:$F,"",SQLデータ!$C:$C,">="&届出事由・区分・届出年月日ごと集計!T$1,SQLデータ!$C:$C,"<="&届出事由・区分・届出年月日ごと集計!T$2) -> 0
A24: 増 | B24: 扶養者の変更 | C24: 扶養手当あり | D24: =COUNTIFS(SQLデータ!$D:$D,"扶養",SQLデータ!$H:$H,届出事由・区分・届出年月日ごと集計!$A24,SQLデータ!$G:$G,届出事由・区分・届出年月日ごと集計!$B24,SQLデータ!$M:$M,1) -> 2 | F24: =COUNTIFS(SQLデータ!$D:$D,"扶養",SQLデータ!$P:$P,1,SQLデータ!$H:$H,届出事由・区分・届出年月日ごと集計!$A24,SQLデータ!$G:$G,届出事由・区分・届出年月日ごと集計!$B24,SQLデータ!$M:$M,1,SQLデータ!$F:$F,"",SQLデータ!$C:$C,">="&届出事由・区分・届出年月日ごと集計!F$1,SQLデータ!$C:$C,"<="&届出事由・区分・届出年月日ごと集計!F$2) -> 0 | G24: =COUNTIFS(SQLデータ!$D:$D,"扶養",SQLデータ!$P:$P,1,SQLデータ!$H:$H,届出事由・区分・届出年月日ごと集計!$A24,SQLデータ!$G:$G,届出事由・区分・届出年月日ごと集計!$B24,SQLデータ!$M:$M,1,SQLデータ!$F:$F,"",SQLデータ!$C:$C,">="&届出事由・区分・届出年月日ごと集計!G$1,SQLデータ!$C:$C,"<="&届出事由・区分・届出年月日ごと集計!G$2) -> 0 | H24: =COUNTIFS(SQLデータ!$D:$D,"扶養",SQLデータ!$P:$P,1,SQLデータ!$H:$H,届出事由・区分・届出年月日ごと集計!$A24,SQLデータ!$G:$G,届出事由・区分・届出年月日ごと集計!$B24,SQLデータ!$M:$M,1,SQLデータ!$F:$F,"",SQLデータ!$C:$C,">="&届出事由・区分・届出年月日ごと集計!H$1,SQLデータ!$C:$C,"<="&届出事由・区分・届出年月日ごと集計!H$2) -> 0 | I24: =COUNTIFS(SQLデータ!$D:$D,"扶養",SQLデータ!$P:$P,1,SQLデータ!$H:$H,届出事由・区分・届出年月日ごと集計!$A24,SQLデータ!$G:$G,届出事由・区分・届出年月日ごと集計!$B24,SQLデータ!$M:$M,1,SQLデータ!$F:$F,"",SQLデータ!$C:$C,">="&届出事由・区分・届出年月日ごと集計!I$1,SQLデータ!$C:$C,"<="&届出事由・区分・届出年月日ごと集計!I$2) -> 0 | J24: =COUNTIFS(SQLデータ!$D:$D,"扶養",SQLデータ!$P:$P,1,SQLデータ!$H:$H,届出事由・区分・届出年月日ごと集計!$A24,SQLデータ!$G:$G,届出事由・区分・届出年月日ごと集計!$B24,SQLデータ!$M:$M,1,SQLデータ!$F:$F,"",SQLデータ!$C:$C,">="&届出事由・区分・届出年月日ごと集計!J$1,SQLデータ!$C:$C,"<="&届出事由・区分・届出年月日ごと集計!J$2) -> 0 | K24: =COUNTIFS(SQLデータ!$D:$D,"扶養",SQLデータ!$P:$P,1,SQLデータ!$H:$H,届出事由・区分・届出年月日ごと集計!$A24,SQLデータ!$G:$G,届出事由・区分・届出年月日ごと集計!$B24,SQLデータ!$M:$M,1,SQLデータ!$F:$F,"",SQLデータ!$C:$C,">="&届出事由・区分・届出年月日ごと集計!K$1,SQLデータ!$C:$C,"<="&届出事由・区分・届出年月日ごと集計!K$2) -> 0 | L24: =COUNTIFS(SQLデータ!$D:$D,"扶養",SQLデータ!$P:$P,1,SQLデータ!$H:$H,届出事由・区分・届出年月日ごと集計!$A24,SQLデータ!$G:$G,届出事由・区分・届出年月日ごと集計!$B24,SQLデータ!$M:$M,1,SQLデータ!$F:$F,"",SQLデータ!$C:$C,">="&届出事由・区分・届出年月日ごと集計!L$1,SQLデータ!$C:$C,"<="&届出事由・区分・届出年月日ごと集計!L$2) -> 0 | M24: =COUNTIFS(SQLデータ!$D:$D,"扶養",SQLデータ!$P:$P,1,SQLデータ!$H:$H,届出事由・区分・届出年月日ごと集計!$A24,SQLデータ!$G:$G,届出事由・区分・届出年月日ごと集計!$B24,SQLデータ!$M:$M,1,SQLデータ!$F:$F,"",SQLデータ!$C:$C,">="&届出事由・区分・届出年月日ごと集計!M$1,SQLデータ!$C:$C,"<="&届出事由・区分・届出年月日ごと集計!M$2) -> 0 | ... T24: =COUNTIFS(SQLデータ!$D:$D,"扶養",SQLデータ!$P:$P,1,SQLデータ!$H:$H,届出事由・区分・届出年月日ごと集計!$A24,SQLデータ!$G:$G,届出事由・区分・届出年月日ごと集計!$B24,SQLデータ!$M:$M,1,SQLデータ!$F:$F,"",SQLデータ!$C:$C,">="&届出事由・区分・届出年月日ごと集計!T$1,SQLデータ!$C:$C,"<="&届出事由・区分・届出年月日ごと集計!T$2) -> 0
A25: 増 | B25: 扶養者の変更 | C25: 税控除のみ | D25: =COUNTIFS(SQLデータ!$D:$D,"扶養",SQLデータ!$H:$H,届出事由・区分・届出年月日ごと集計!$A25,SQLデータ!$G:$G,届出事由・区分・届出年月日ごと集計!$B25,SQLデータ!$N:$N,1) -> 0 | F25: =COUNTIFS(SQLデータ!$D:$D,"扶養",SQLデータ!$P:$P,1,SQLデータ!$H:$H,届出事由・区分・届出年月日ごと集計!$A25,SQLデータ!$G:$G,届出事由・区分・届出年月日ごと集計!$B25,SQLデータ!$N:$N,1,SQLデータ!$F:$F,"",SQLデータ!$C:$C,">="&届出事由・区分・届出年月日ごと集計!F$1,SQLデータ!$C:$C,"<="&届出事由・区分・届出年月日ごと集計!F$2) -> 0 | G25: =COUNTIFS(SQLデータ!$D:$D,"扶養",SQLデータ!$P:$P,1,SQLデータ!$H:$H,届出事由・区分・届出年月日ごと集計!$A25,SQLデータ!$G:$G,届出事由・区分・届出年月日ごと集計!$B25,SQLデータ!$N:$N,1,SQLデータ!$F:$F,"",SQLデータ!$C:$C,">="&届出事由・区分・届出年月日ごと集計!G$1,SQLデータ!$C:$C,"<="&届出事由・区分・届出年月日ごと集計!G$2) -> 0 | H25: =COUNTIFS(SQLデータ!$D:$D,"扶養",SQLデータ!$P:$P,1,SQLデータ!$H:$H,届出事由・区分・届出年月日ごと集計!$A25,SQLデータ!$G:$G,届出事由・区分・届出年月日ごと集計!$B25,SQLデータ!$N:$N,1,SQLデータ!$F:$F,"",SQLデータ!$C:$C,">="&届出事由・区分・届出年月日ごと集計!H$1,SQLデータ!$C:$C,"<="&届出事由・区分・届出年月日ごと集計!H$2) -> 0 | I25: =COUNTIFS(SQLデータ!$D:$D,"扶養",SQLデータ!$P:$P,1,SQLデータ!$H:$H,届出事由・区分・届出年月日ごと集計!$A25,SQLデータ!$G:$G,届出事由・区分・届出年月日ごと集計!$B25,SQLデータ!$N:$N,1,SQLデータ!$F:$F,"",SQLデータ!$C:$C,">="&届出事由・区分・届出年月日ごと集計!I$1,SQLデータ!$C:$C,"<="&届出事由・区分・届出年月日ごと集計!I$2) -> 0 | J25: =COUNTIFS(SQLデータ!$D:$D,"扶養",SQLデータ!$P:$P,1,SQLデータ!$H:$H,届出事由・区分・届出年月日ごと集計!$A25,SQLデータ!$G:$G,届出事由・区分・届出年月日ごと集計!$B25,SQLデータ!$N:$N,1,SQLデータ!$F:$F,"",SQLデータ!$C:$C,">="&届出事由・区分・届出年月日ごと集計!J$1,SQLデータ!$C:$C,"<="&届出事由・区分・届出年月日ごと集計!J$2) -> 0 | K25: =COUNTIFS(SQLデータ!$D:$D,"扶養",SQLデータ!$P:$P,1,SQLデータ!$H:$H,届出事由・区分・届出年月日ごと集計!$A25,SQLデータ!$G:$G,届出事由・区分・届出年月日ごと集計!$B25,SQLデータ!$N:$N,1,SQLデータ!$F:$F,"",SQLデータ!$C:$C,">="&届出事由・区分・届出年月日ごと集計!K$1,SQLデータ!$C:$C,"<="&届出事由・区分・届出年月日ごと集計!K$2) -> 0 | L25: =COUNTIFS(SQLデータ!$D:$D,"扶養",SQLデータ!$P:$P,1,SQLデータ!$H:$H,届出事由・区分・届出年月日ごと集計!$A25,SQLデータ!$G:$G,届出事由・区分・届出年月日ごと集計!$B25,SQLデータ!$N:$N,1,SQLデータ!$F:$F,"",SQLデータ!$C:$C,">="&届出事由・区分・届出年月日ごと集計!L$1,SQLデータ!$C:$C,"<="&届出事由・区分・届出年月日ごと集計!L$2) -> 0 | M25: =COUNTIFS(SQLデータ!$D:$D,"扶養",SQLデータ!$P:$P,1,SQLデータ!$H:$H,届出事由・区分・届出年月日ごと集計!$A25,SQLデータ!$G:$G,届出事由・区分・届出年月日ごと集計!$B25,SQLデータ!$N:$N,1,SQLデータ!$F:$F,"",SQLデータ!$C:$C,">="&届出事由・区分・届出年月日ごと集計!M$1,SQLデータ!$C:$C,"<="&届出事由・区分・届出年月日ごと集計!M$2) -> 0 | ... T25: =COUNTIFS(SQLデータ!$D:$D,"扶養",SQLデータ!$P:$P,1,SQLデータ!$H:$H,届出事由・区分・届出年月日ごと集計!$A25,SQLデータ!$G:$G,届出事由・区分・届出年月日ごと集計!$B25,SQLデータ!$N:$N,1,SQLデータ!$F:$F,"",SQLデータ!$C:$C,">="&届出事由・区分・届出年月日ごと集計!T$1,SQLデータ!$C:$C,"<="&届出事由・区分・届出年月日ごと集計!T$2) -> 0
A26: 増 | B26: 扶養者の変更 | C26: 本人税のみ | D26: =COUNTIFS(SQLデータ!$D:$D,"扶養",SQLデータ!$H:$H,届出事由・区分・届出年月日ごと集計!$A26,SQLデータ!$G:$G,届出事由・区分・届出年月日ごと集計!$B26,SQLデータ!$O:$O,1) -> 0 | F26: =COUNTIFS(SQLデータ!$D:$D,"扶養",SQLデータ!$P:$P,1,SQLデータ!$H:$H,届出事由・区分・届出年月日ごと集計!$A26,SQLデータ!$G:$G,届出事由・区分・届出年月日ごと集計!$B26,SQLデータ!$O:$O,1,SQLデータ!$F:$F,"",SQLデータ!$C:$C,">="&届出事由・区分・届出年月日ごと集計!F$1,SQLデータ!$C:$C,"<="&届出事由・区分・届出年月日ごと集計!F$2) -> 0 | G26: =COUNTIFS(SQLデータ!$D:$D,"扶養",SQLデータ!$P:$P,1,SQLデータ!$H:$H,届出事由・区分・届出年月日ごと集計!$A26,SQLデータ!$G:$G,届出事由・区分・届出年月日ごと集計!$B26,SQLデータ!$O:$O,1,SQLデータ!$F:$F,"",SQLデータ!$C:$C,">="&届出事由・区分・届出年月日ごと集計!G$1,SQLデータ!$C:$C,"<="&届出事由・区分・届出年月日ごと集計!G$2) -> 0 | H26: =COUNTIFS(SQLデータ!$D:$D,"扶養",SQLデータ!$P:$P,1,SQLデータ!$H:$H,届出事由・区分・届出年月日ごと集計!$A26,SQLデータ!$G:$G,届出事由・区分・届出年月日ごと集計!$B26,SQLデータ!$O:$O,1,SQLデータ!$F:$F,"",SQLデータ!$C:$C,">="&届出事由・区分・届出年月日ごと集計!H$1,SQLデータ!$C:$C,"<="&届出事由・区分・届出年月日ごと集計!H$2) -> 0 | I26: =COUNTIFS(SQLデータ!$D:$D,"扶養",SQLデータ!$P:$P,1,SQLデータ!$H:$H,届出事由・区分・届出年月日ごと集計!$A26,SQLデータ!$G:$G,届出事由・区分・届出年月日ごと集計!$B26,SQLデータ!$O:$O,1,SQLデータ!$F:$F,"",SQLデータ!$C:$C,">="&届出事由・区分・届出年月日ごと集計!I$1,SQLデータ!$C:$C,"<="&届出事由・区分・届出年月日ごと集計!I$2) -> 0 | J26: =COUNTIFS(SQLデータ!$D:$D,"扶養",SQLデータ!$P:$P,1,SQLデータ!$H:$H,届出事由・区分・届出年月日ごと集計!$A26,SQLデータ!$G:$G,届出事由・区分・届出年月日ごと集計!$B26,SQLデータ!$O:$O,1,SQLデータ!$F:$F,"",SQLデータ!$C:$C,">="&届出事由・区分・届出年月日ごと集計!J$1,SQLデータ!$C:$C,"<="&届出事由・区分・届出年月日ごと集計!J$2) -> 0 | K26: =COUNTIFS(SQLデータ!$D:$D,"扶養",SQLデータ!$P:$P,1,SQLデータ!$H:$H,届出事由・区分・届出年月日ごと集計!$A26,SQLデータ!$G:$G,届出事由・区分・届出年月日ごと集計!$B26,SQLデータ!$O:$O,1,SQLデータ!$F:$F,"",SQLデータ!$C:$C,">="&届出事由・区分・届出年月日ごと集計!K$1,SQLデータ!$C:$C,"<="&届出事由・区分・届出年月日ごと集計!K$2) -> 0 | L26: =COUNTIFS(SQLデータ!$D:$D,"扶養",SQLデータ!$P:$P,1,SQLデータ!$H:$H,届出事由・区分・届出年月日ごと集計!$A26,SQLデータ!$G:$G,届出事由・区分・届出年月日ごと集計!$B26,SQLデータ!$O:$O,1,SQLデータ!$F:$F,"",SQLデータ!$C:$C,">="&届出事由・区分・届出年月日ごと集計!L$1,SQLデータ!$C:$C,"<="&届出事由・区分・届出年月日ごと集計!L$2) -> 0 | M26: =COUNTIFS(SQLデータ!$D:$D,"扶養",SQLデータ!$P:$P,1,SQLデータ!$H:$H,届出事由・区分・届出年月日ごと集計!$A26,SQLデータ!$G:$G,届出事由・区分・届出年月日ごと集計!$B26,SQLデータ!$O:$O,1,SQLデータ!$F:$F,"",SQLデータ!$C:$C,">="&届出事由・区分・届出年月日ごと集計!M$1,SQLデータ!$C:$C,"<="&届出事由・区分・届出年月日ごと集計!M$2) -> 0 | ... T26: =COUNTIFS(SQLデータ!$D:$D,"扶養",SQLデータ!$P:$P,1,SQLデータ!$H:$H,届出事由・区分・届出年月日ごと集計!$A26,SQLデータ!$G:$G,届出事由・区分・届出年月日ごと集計!$B26,SQLデータ!$O:$O,1,SQLデータ!$F:$F,"",SQLデータ!$C:$C,">="&届出事由・区分・届出年月日ごと集計!T$1,SQLデータ!$C:$C,"<="&届出事由・区分・届出年月日ごと集計!T$2) -> 0
A27: 増 | B27: 収入限度額以下 | C27: 共済あり | D27: =COUNTIFS(SQLデータ!$D:$D,"扶養",SQLデータ!$H:$H,届出事由・区分・届出年月日ごと集計!$A27,SQLデータ!$G:$G,届出事由・区分・届出年月日ごと集計!$B27,SQLデータ!$L:$L,1) -> 11 | F27: =COUNTIFS(SQLデータ!$D:$D,"扶養",SQLデータ!$P:$P,1,SQLデータ!$H:$H,届出事由・区分・届出年月日ごと集計!$A27,SQLデータ!$G:$G,届出事由・区分・届出年月日ごと集計!$B27,SQLデータ!$L:$L,1,SQLデータ!$F:$F,"",SQLデータ!$C:$C,">="&届出事由・区分・届出年月日ごと集計!F$1,SQLデータ!$C:$C,"<="&届出事由・区分・届出年月日ごと集計!F$2) -> 2 | G27: =COUNTIFS(SQLデータ!$D:$D,"扶養",SQLデータ!$P:$P,1,SQLデータ!$H:$H,届出事由・区分・届出年月日ごと集計!$A27,SQLデータ!$G:$G,届出事由・区分・届出年月日ごと集計!$B27,SQLデータ!$L:$L,1,SQLデータ!$F:$F,"",SQLデータ!$C:$C,">="&届出事由・区分・届出年月日ごと集計!G$1,SQLデータ!$C:$C,"<="&届出事由・区分・届出年月日ごと集計!G$2) -> 2 | H27: =COUNTIFS(SQLデータ!$D:$D,"扶養",SQLデータ!$P:$P,1,SQLデータ!$H:$H,届出事由・区分・届出年月日ごと集計!$A27,SQLデータ!$G:$G,届出事由・区分・届出年月日ごと集計!$B27,SQLデータ!$L:$L,1,SQLデータ!$F:$F,"",SQLデータ!$C:$C,">="&届出事由・区分・届出年月日ごと集計!H$1,SQLデータ!$C:$C,"<="&届出事由・区分・届出年月日ごと集計!H$2) -> 1 | I27: =COUNTIFS(SQLデータ!$D:$D,"扶養",SQLデータ!$P:$P,1,SQLデータ!$H:$H,届出事由・区分・届出年月日ごと集計!$A27,SQLデータ!$G:$G,届出事由・区分・届出年月日ごと集計!$B27,SQLデータ!$L:$L,1,SQLデータ!$F:$F,"",SQLデータ!$C:$C,">="&届出事由・区分・届出年月日ごと集計!I$1,SQLデータ!$C:$C,"<="&届出事由・区分・届出年月日ごと集計!I$2) -> 0 | J27: =COUNTIFS(SQLデータ!$D:$D,"扶養",SQLデータ!$P:$P,1,SQLデータ!$H:$H,届出事由・区分・届出年月日ごと集計!$A27,SQLデータ!$G:$G,届出事由・区分・届出年月日ごと集計!$B27,SQLデータ!$L:$L,1,SQLデータ!$F:$F,"",SQLデータ!$C:$C,">="&届出事由・区分・届出年月日ごと集計!J$1,SQLデータ!$C:$C,"<="&届出事由・区分・届出年月日ごと集計!J$2) -> 0 | K27: =COUNTIFS(SQLデータ!$D:$D,"扶養",SQLデータ!$P:$P,1,SQLデータ!$H:$H,届出事由・区分・届出年月日ごと集計!$A27,SQLデータ!$G:$G,届出事由・区分・届出年月日ごと集計!$B27,SQLデータ!$L:$L,1,SQLデータ!$F:$F,"",SQLデータ!$C:$C,">="&届出事由・区分・届出年月日ごと集計!K$1,SQLデータ!$C:$C,"<="&届出事由・区分・届出年月日ごと集計!K$2) -> 0 | L27: =COUNTIFS(SQLデータ!$D:$D,"扶養",SQLデータ!$P:$P,1,SQLデータ!$H:$H,届出事由・区分・届出年月日ごと集計!$A27,SQLデータ!$G:$G,届出事由・区分・届出年月日ごと集計!$B27,SQLデータ!$L:$L,1,SQLデータ!$F:$F,"",SQLデータ!$C:$C,">="&届出事由・区分・届出年月日ごと集計!L$1,SQLデータ!$C:$C,"<="&届出事由・区分・届出年月日ごと集計!L$2) -> 0 | M27: =COUNTIFS(SQLデータ!$D:$D,"扶養",SQLデータ!$P:$P,1,SQLデータ!$H:$H,届出事由・区分・届出年月日ごと集計!$A27,SQLデータ!$G:$G,届出事由・区分・届出年月日ごと集計!$B27,SQLデータ!$L:$L,1,SQLデータ!$F:$F,"",SQLデータ!$C:$C,">="&届出事由・区分・届出年月日ごと集計!M$1,SQLデータ!$C:$C,"<="&届出事由・区分・届出年月日ごと集計!M$2) -> 0 | ... T27: =COUNTIFS(SQLデータ!$D:$D,"扶養",SQLデータ!$P:$P,1,SQLデータ!$H:$H,届出事由・区分・届出年月日ごと集計!$A27,SQLデータ!$G:$G,届出事由・区分・届出年月日ごと集計!$B27,SQLデータ!$L:$L,1,SQLデータ!$F:$F,"",SQLデータ!$C:$C,">="&届出事由・区分・届出年月日ごと集計!T$1,SQLデータ!$C:$C,"<="&届出事由・区分・届出年月日ごと集計!T$2) -> 0
A28: 増 | B28: 収入限度額以下 | C28: 扶養手当あり | D28: =COUNTIFS(SQLデータ!$D:$D,"扶養",SQLデータ!$H:$H,届出事由・区分・届出年月日ごと集計!$A28,SQLデータ!$G:$G,届出事由・区分・届出年月日ごと集計!$B28,SQLデータ!$M:$M,1) -> 0 | F28: =COUNTIFS(SQLデータ!$D:$D,"扶養",SQLデータ!$P:$P,1,SQLデータ!$H:$H,届出事由・区分・届出年月日ごと集計!$A28,SQLデータ!$G:$G,届出事由・区分・届出年月日ごと集計!$B28,SQLデータ!$M:$M,1,SQLデータ!$F:$F,"",SQLデータ!$C:$C,">="&届出事由・区分・届出年月日ごと集計!F$1,SQLデータ!$C:$C,"<="&届出事由・区分・届出年月日ごと集計!F$2) -> 0 | G28: =COUNTIFS(SQLデータ!$D:$D,"扶養",SQLデータ!$P:$P,1,SQLデータ!$H:$H,届出事由・区分・届出年月日ごと集計!$A28,SQLデータ!$G:$G,届出事由・区分・届出年月日ごと集計!$B28,SQLデータ!$M:$M,1,SQLデータ!$F:$F,"",SQLデータ!$C:$C,">="&届出事由・区分・届出年月日ごと集計!G$1,SQLデータ!$C:$C,"<="&届出事由・区分・届出年月日ごと集計!G$2) -> 0 | H28: =COUNTIFS(SQLデータ!$D:$D,"扶養",SQLデータ!$P:$P,1,SQLデータ!$H:$H,届出事由・区分・届出年月日ごと集計!$A28,SQLデータ!$G:$G,届出事由・区分・届出年月日ごと集計!$B28,SQLデータ!$M:$M,1,SQLデータ!$F:$F,"",SQLデータ!$C:$C,">="&届出事由・区分・届出年月日ごと集計!H$1,SQLデータ!$C:$C,"<="&届出事由・区分・届出年月日ごと集計!H$2) -> 0 | I28: =COUNTIFS(SQLデータ!$D:$D,"扶養",SQLデータ!$P:$P,1,SQLデータ!$H:$H,届出事由・区分・届出年月日ごと集計!$A28,SQLデータ!$G:$G,届出事由・区分・届出年月日ごと集計!$B28,SQLデータ!$M:$M,1,SQLデータ!$F:$F,"",SQLデータ!$C:$C,">="&届出事由・区分・届出年月日ごと集計!I$1,SQLデータ!$C:$C,"<="&届出事由・区分・届出年月日ごと集計!I$2) -> 0 | J28: =COUNTIFS(SQLデータ!$D:$D,"扶養",SQLデータ!$P:$P,1,SQLデータ!$H:$H,届出事由・区分・届出年月日ごと集計!$A28,SQLデータ!$G:$G,届出事由・区分・届出年月日ごと集計!$B28,SQLデータ!$M:$M,1,SQLデータ!$F:$F,"",SQLデータ!$C:$C,">="&届出事由・区分・届出年月日ごと集計!J$1,SQLデータ!$C:$C,"<="&届出事由・区分・届出年月日ごと集計!J$2) -> 0 | K28: =COUNTIFS(SQLデータ!$D:$D,"扶養",SQLデータ!$P:$P,1,SQLデータ!$H:$H,届出事由・区分・届出年月日ごと集計!$A28,SQLデータ!$G:$G,届出事由・区分・届出年月日ごと集計!$B28,SQLデータ!$M:$M,1,SQLデータ!$F:$F,"",SQLデータ!$C:$C,">="&届出事由・区分・届出年月日ごと集計!K$1,SQLデータ!$C:$C,"<="&届出事由・区分・届出年月日ごと集計!K$2) -> 0 | L28: =COUNTIFS(SQLデータ!$D:$D,"扶養",SQLデータ!$P:$P,1,SQLデータ!$H:$H,届出事由・区分・届出年月日ごと集計!$A28,SQLデータ!$G:$G,届出事由・区分・届出年月日ごと集計!$B28,SQLデータ!$M:$M,1,SQLデータ!$F:$F,"",SQLデータ!$C:$C,">="&届出事由・区分・届出年月日ごと集計!L$1,SQLデータ!$C:$C,"<="&届出事由・区分・届出年月日ごと集計!L$2) -> 0 | M28: =COUNTIFS(SQLデータ!$D:$D,"扶養",SQLデータ!$P:$P,1,SQLデータ!$H:$H,届出事由・区分・届出年月日ごと集計!$A28,SQLデータ!$G:$G,届出事由・区分・届出年月日ごと集計!$B28,SQLデータ!$M:$M,1,SQLデータ!$F:$F,"",SQLデータ!$C:$C,">="&届出事由・区分・届出年月日ごと集計!M$1,SQLデータ!$C:$C,"<="&届出事由・区分・届出年月日ごと集計!M$2) -> 0 | ... T28: =COUNTIFS(SQLデータ!$D:$D,"扶養",SQLデータ!$P:$P,1,SQLデータ!$H:$H,届出事由・区分・届出年月日ごと集計!$A28,SQLデータ!$G:$G,届出事由・区分・届出年月日ごと集計!$B28,SQLデータ!$M:$M,1,SQLデータ!$F:$F,"",SQLデータ!$C:$C,">="&届出事由・区分・届出年月日ごと集計!T$1,SQLデータ!$C:$C,"<="&届出事由・区分・届出年月日ごと集計!T$2) -> 0
A29: 増 | B29: 収入限度額以下 | C29: 税控除のみ | D29: =COUNTIFS(SQLデータ!$D:$D,"扶養",SQLデータ!$H:$H,届出事由・区分・届出年月日ごと集計!$A29,SQLデータ!$G:$G,届出事由・区分・届出年月日ごと集計!$B29,SQLデータ!$N:$N,1) -> 0 | F29: =COUNTIFS(SQLデータ!$D:$D,"扶養",SQLデータ!$P:$P,1,SQLデータ!$H:$H,届出事由・区分・届出年月日ごと集計!$A29,SQLデータ!$G:$G,届出事由・区分・届出年月日ごと集計!$B29,SQLデータ!$N:$N,1,SQLデータ!$F:$F,"",SQLデータ!$C:$C,">="&届出事由・区分・届出年月日ごと集計!F$1,SQLデータ!$C:$C,"<="&届出事由・区分・届出年月日ごと集計!F$2) -> 0 | G29: =COUNTIFS(SQLデータ!$D:$D,"扶養",SQLデータ!$P:$P,1,SQLデータ!$H:$H,届出事由・区分・届出年月日ごと集計!$A29,SQLデータ!$G:$G,届出事由・区分・届出年月日ごと集計!$B29,SQLデータ!$N:$N,1,SQLデータ!$F:$F,"",SQLデータ!$C:$C,">="&届出事由・区分・届出年月日ごと集計!G$1,SQLデータ!$C:$C,"<="&届出事由・区分・届出年月日ごと集計!G$2) -> 0 | H29: =COUNTIFS(SQLデータ!$D:$D,"扶養",SQLデータ!$P:$P,1,SQLデータ!$H:$H,届出事由・区分・届出年月日ごと集計!$A29,SQLデータ!$G:$G,届出事由・区分・届出年月日ごと集計!$B29,SQLデータ!$N:$N,1,SQLデータ!$F:$F,"",SQLデータ!$C:$C,">="&届出事由・区分・届出年月日ごと集計!H$1,SQLデータ!$C:$C,"<="&届出事由・区分・届出年月日ごと集計!H$2) -> 0 | I29: =COUNTIFS(SQLデータ!$D:$D,"扶養",SQLデータ!$P:$P,1,SQLデータ!$H:$H,届出事由・区分・届出年月日ごと集計!$A29,SQLデータ!$G:$G,届出事由・区分・届出年月日ごと集計!$B29,SQLデータ!$N:$N,1,SQLデータ!$F:$F,"",SQLデータ!$C:$C,">="&届出事由・区分・届出年月日ごと集計!I$1,SQLデータ!$C:$C,"<="&届出事由・区分・届出年月日ごと集計!I$2) -> 0 | J29: =COUNTIFS(SQLデータ!$D:$D,"扶養",SQLデータ!$P:$P,1,SQLデータ!$H:$H,届出事由・区分・届出年月日ごと集計!$A29,SQLデータ!$G:$G,届出事由・区分・届出年月日ごと集計!$B29,SQLデータ!$N:$N,1,SQLデータ!$F:$F,"",SQLデータ!$C:$C,">="&届出事由・区分・届出年月日ごと集計!J$1,SQLデータ!$C:$C,"<="&届出事由・区分・届出年月日ごと集計!J$2) -> 0 | K29: =COUNTIFS(SQLデータ!$D:$D,"扶養",SQLデータ!$P:$P,1,SQLデータ!$H:$H,届出事由・区分・届出年月日ごと集計!$A29,SQLデータ!$G:$G,届出事由・区分・届出年月日ごと集計!$B29,SQLデータ!$N:$N,1,SQLデータ!$F:$F,"",SQLデータ!$C:$C,">="&届出事由・区分・届出年月日ごと集計!K$1,SQLデータ!$C:$C,"<="&届出事由・区分・届出年月日ごと集計!K$2) -> 0 | L29: =COUNTIFS(SQLデータ!$D:$D,"扶養",SQLデータ!$P:$P,1,SQLデータ!$H:$H,届出事由・区分・届出年月日ごと集計!$A29,SQLデータ!$G:$G,届出事由・区分・届出年月日ごと集計!$B29,SQLデータ!$N:$N,1,SQLデータ!$F:$F,"",SQLデータ!$C:$C,">="&届出事由・区分・届出年月日ごと集計!L$1,SQLデータ!$C:$C,"<="&届出事由・区分・届出年月日ごと集計!L$2) -> 0 | M29: =COUNTIFS(SQLデータ!$D:$D,"扶養",SQLデータ!$P:$P,1,SQLデータ!$H:$H,届出事由・区分・届出年月日ごと集計!$A29,SQLデータ!$G:$G,届出事由・区分・届出年月日ごと集計!$B29,SQLデータ!$N:$N,1,SQLデータ!$F:$F,"",SQLデータ!$C:$C,">="&届出事由・区分・届出年月日ごと集計!M$1,SQLデータ!$C:$C,"<="&届出事由・区分・届出年月日ごと集計!M$2) -> 0 | ... T29: =COUNTIFS(SQLデータ!$D:$D,"扶養",SQLデータ!$P:$P,1,SQLデータ!$H:$H,届出事由・区分・届出年月日ごと集計!$A29,SQLデータ!$G:$G,届出事由・区分・届出年月日ごと集計!$B29,SQLデータ!$N:$N,1,SQLデータ!$F:$F,"",SQLデータ!$C:$C,">="&届出事由・区分・届出年月日ごと集計!T$1,SQLデータ!$C:$C,"<="&届出事由・区分・届出年月日ごと集計!T$2) -> 0
A30: 増 | B30: 収入限度額以下 | C30: 本人税のみ | D30: =COUNTIFS(SQLデータ!$D:$D,"扶養",SQLデータ!$H:$H,届出事由・区分・届出年月日ごと集計!$A30,SQLデータ!$G:$G,届出事由・区分・届出年月日ごと集計!$B30,SQLデータ!$O:$O,1) -> 0 | F30: =COUNTIFS(SQLデータ!$D:$D,"扶養",SQLデータ!$P:$P,1,SQLデータ!$H:$H,届出事由・区分・届出年月日ごと集計!$A30,SQLデータ!$G:$G,届出事由・区分・届出年月日ごと集計!$B30,SQLデータ!$O:$O,1,SQLデータ!$F:$F,"",SQLデータ!$C:$C,">="&届出事由・区分・届出年月日ごと集計!F$1,SQLデータ!$C:$C,"<="&届出事由・区分・届出年月日ごと集計!F$2) -> 0 | G30: =COUNTIFS(SQLデータ!$D:$D,"扶養",SQLデータ!$P:$P,1,SQLデータ!$H:$H,届出事由・区分・届出年月日ごと集計!$A30,SQLデータ!$G:$G,届出事由・区分・届出年月日ごと集計!$B30,SQLデータ!$O:$O,1,SQLデータ!$F:$F,"",SQLデータ!$C:$C,">="&届出事由・区分・届出年月日ごと集計!G$1,SQLデータ!$C:$C,"<="&届出事由・区分・届出年月日ごと集計!G$2) -> 0 | H30: =COUNTIFS(SQLデータ!$D:$D,"扶養",SQLデータ!$P:$P,1,SQLデータ!$H:$H,届出事由・区分・届出年月日ごと集計!$A30,SQLデータ!$G:$G,届出事由・区分・届出年月日ごと集計!$B30,SQLデータ!$O:$O,1,SQLデータ!$F:$F,"",SQLデータ!$C:$C,">="&届出事由・区分・届出年月日ごと集計!H$1,SQLデータ!$C:$C,"<="&届出事由・区分・届出年月日ごと集計!H$2) -> 0 | I30: =COUNTIFS(SQLデータ!$D:$D,"扶養",SQLデータ!$P:$P,1,SQLデータ!$H:$H,届出事由・区分・届出年月日ごと集計!$A30,SQLデータ!$G:$G,届出事由・区分・届出年月日ごと集計!$B30,SQLデータ!$O:$O,1,SQLデータ!$F:$F,"",SQLデータ!$C:$C,">="&届出事由・区分・届出年月日ごと集計!I$1,SQLデータ!$C:$C,"<="&届出事由・区分・届出年月日ごと集計!I$2) -> 0 | J30: =COUNTIFS(SQLデータ!$D:$D,"扶養",SQLデータ!$P:$P,1,SQLデータ!$H:$H,届出事由・区分・届出年月日ごと集計!$A30,SQLデータ!$G:$G,届出事由・区分・届出年月日ごと集計!$B30,SQLデータ!$O:$O,1,SQLデータ!$F:$F,"",SQLデータ!$C:$C,">="&届出事由・区分・届出年月日ごと集計!J$1,SQLデータ!$C:$C,"<="&届出事由・区分・届出年月日ごと集計!J$2) -> 0 | K30: =COUNTIFS(SQLデータ!$D:$D,"扶養",SQLデータ!$P:$P,1,SQLデータ!$H:$H,届出事由・区分・届出年月日ごと集計!$A30,SQLデータ!$G:$G,届出事由・区分・届出年月日ごと集計!$B30,SQLデータ!$O:$O,1,SQLデータ!$F:$F,"",SQLデータ!$C:$C,">="&届出事由・区分・届出年月日ごと集計!K$1,SQLデータ!$C:$C,"<="&届出事由・区分・届出年月日ごと集計!K$2) -> 0 | L30: =COUNTIFS(SQLデータ!$D:$D,"扶養",SQLデータ!$P:$P,1,SQLデータ!$H:$H,届出事由・区分・届出年月日ごと集計!$A30,SQLデータ!$G:$G,届出事由・区分・届出年月日ごと集計!$B30,SQLデータ!$O:$O,1,SQLデータ!$F:$F,"",SQLデータ!$C:$C,">="&届出事由・区分・届出年月日ごと集計!L$1,SQLデータ!$C:$C,"<="&届出事由・区分・届出年月日ごと集計!L$2) -> 0 | M30: =COUNTIFS(SQLデータ!$D:$D,"扶養",SQLデータ!$P:$P,1,SQLデータ!$H:$H,届出事由・区分・届出年月日ごと集計!$A30,SQLデータ!$G:$G,届出事由・区分・届出年月日ごと集計!$B30,SQLデータ!$O:$O,1,SQLデータ!$F:$F,"",SQLデータ!$C:$C,">="&届出事由・区分・届出年月日ごと集計!M$1,SQLデータ!$C:$C,"<="&届出事由・区分・届出年月日ごと集計!M$2) -> 0 | ... T30: =COUNTIFS(SQLデータ!$D:$D,"扶養",SQLデータ!$P:$P,1,SQLデータ!$H:$H,届出事由・区分・届出年月日ごと集計!$A30,SQLデータ!$G:$G,届出事由・区分・届出年月日ごと集計!$B30,SQLデータ!$O:$O,1,SQLデータ!$F:$F,"",SQLデータ!$C:$C,">="&届出事由・区分・届出年月日ごと集計!T$1,SQLデータ!$C:$C,"<="&届出事由・区分・届出年月日ごと集計!T$2) -> 0
A31: 増 | B31: 障害程度の変更 | C31: 共済あり | D31: =COUNTIFS(SQLデータ!$D:$D,"扶養",SQLデータ!$H:$H,届出事由・区分・届出年月日ごと集計!$A31,SQLデータ!$G:$G,届出事由・区分・届出年月日ごと集計!$B31,SQLデータ!$L:$L,1) -> 0 | F31: =COUNTIFS(SQLデータ!$D:$D,"扶養",SQLデータ!$P:$P,1,SQLデータ!$H:$H,届出事由・区分・届出年月日ごと集計!$A31,SQLデータ!$G:$G,届出事由・区分・届出年月日ごと集計!$B31,SQLデータ!$L:$L,1,SQLデータ!$F:$F,"",SQLデータ!$C:$C,">="&届出事由・区分・届出年月日ごと集計!F$1,SQLデータ!$C:$C,"<="&届出事由・区分・届出年月日ごと集計!F$2) -> 0 | G31: =COUNTIFS(SQLデータ!$D:$D,"扶養",SQLデータ!$P:$P,1,SQLデータ!$H:$H,届出事由・区分・届出年月日ごと集計!$A31,SQLデータ!$G:$G,届出事由・区分・届出年月日ごと集計!$B31,SQLデータ!$L:$L,1,SQLデータ!$F:$F,"",SQLデータ!$C:$C,">="&届出事由・区分・届出年月日ごと集計!G$1,SQLデータ!$C:$C,"<="&届出事由・区分・届出年月日ごと集計!G$2) -> 0 | H31: =COUNTIFS(SQLデータ!$D:$D,"扶養",SQLデータ!$P:$P,1,SQLデータ!$H:$H,届出事由・区分・届出年月日ごと集計!$A31,SQLデータ!$G:$G,届出事由・区分・届出年月日ごと集計!$B31,SQLデータ!$L:$L,1,SQLデータ!$F:$F,"",SQLデータ!$C:$C,">="&届出事由・区分・届出年月日ごと集計!H$1,SQLデータ!$C:$C,"<="&届出事由・区分・届出年月日ごと集計!H$2) -> 0 | I31: =COUNTIFS(SQLデータ!$D:$D,"扶養",SQLデータ!$P:$P,1,SQLデータ!$H:$H,届出事由・区分・届出年月日ごと集計!$A31,SQLデータ!$G:$G,届出事由・区分・届出年月日ごと集計!$B31,SQLデータ!$L:$L,1,SQLデータ!$F:$F,"",SQLデータ!$C:$C,">="&届出事由・区分・届出年月日ごと集計!I$1,SQLデータ!$C:$C,"<="&届出事由・区分・届出年月日ごと集計!I$2) -> 0 | J31: =COUNTIFS(SQLデータ!$D:$D,"扶養",SQLデータ!$P:$P,1,SQLデータ!$H:$H,届出事由・区分・届出年月日ごと集計!$A31,SQLデータ!$G:$G,届出事由・区分・届出年月日ごと集計!$B31,SQLデータ!$L:$L,1,SQLデータ!$F:$F,"",SQLデータ!$C:$C,">="&届出事由・区分・届出年月日ごと集計!J$1,SQLデータ!$C:$C,"<="&届出事由・区分・届出年月日ごと集計!J$2) -> 0 | K31: =COUNTIFS(SQLデータ!$D:$D,"扶養",SQLデータ!$P:$P,1,SQLデータ!$H:$H,届出事由・区分・届出年月日ごと集計!$A31,SQLデータ!$G:$G,届出事由・区分・届出年月日ごと集計!$B31,SQLデータ!$L:$L,1,SQLデータ!$F:$F,"",SQLデータ!$C:$C,">="&届出事由・区分・届出年月日ごと集計!K$1,SQLデータ!$C:$C,"<="&届出事由・区分・届出年月日ごと集計!K$2) -> 0 | L31: =COUNTIFS(SQLデータ!$D:$D,"扶養",SQLデータ!$P:$P,1,SQLデータ!$H:$H,届出事由・区分・届出年月日ごと集計!$A31,SQLデータ!$G:$G,届出事由・区分・届出年月日ごと集計!$B31,SQLデータ!$L:$L,1,SQLデータ!$F:$F,"",SQLデータ!$C:$C,">="&届出事由・区分・届出年月日ごと集計!L$1,SQLデータ!$C:$C,"<="&届出事由・区分・届出年月日ごと集計!L$2) -> 0 | M31: =COUNTIFS(SQLデータ!$D:$D,"扶養",SQLデータ!$P:$P,1,SQLデータ!$H:$H,届出事由・区分・届出年月日ごと集計!$A31,SQLデータ!$G:$G,届出事由・区分・届出年月日ごと集計!$B31,SQLデータ!$L:$L,1,SQLデータ!$F:$F,"",SQLデータ!$C:$C,">="&届出事由・区分・届出年月日ごと集計!M$1,SQLデータ!$C:$C,"<="&届出事由・区分・届出年月日ごと集計!M$2) -> 0 | ... T31: =COUNTIFS(SQLデータ!$D:$D,"扶養",SQLデータ!$P:$P,1,SQLデータ!$H:$H,届出事由・区分・届出年月日ごと集計!$A31,SQLデータ!$G:$G,届出事由・区分・届出年月日ごと集計!$B31,SQLデータ!$L:$L,1,SQLデータ!$F:$F,"",SQLデータ!$C:$C,">="&届出事由・区分・届出年月日ごと集計!T$1,SQLデータ!$C:$C,"<="&届出事由・区分・届出年月日ごと集計!T$2) -> 0
A32: 増 | B32: 障害程度の変更 | C32: 扶養手当あり | D32: =COUNTIFS(SQLデータ!$D:$D,"扶養",SQLデータ!$H:$H,届出事由・区分・届出年月日ごと集計!$A32,SQLデータ!$G:$G,届出事由・区分・届出年月日ごと集計!$B32,SQLデータ!$M:$M,1) -> 0 | F32: =COUNTIFS(SQLデータ!$D:$D,"扶養",SQLデータ!$P:$P,1,SQLデータ!$H:$H,届出事由・区分・届出年月日ごと集計!$A32,SQLデータ!$G:$G,届出事由・区分・届出年月日ごと集計!$B32,SQLデータ!$M:$M,1,SQLデータ!$F:$F,"",SQLデータ!$C:$C,">="&届出事由・区分・届出年月日ごと集計!F$1,SQLデータ!$C:$C,"<="&届出事由・区分・届出年月日ごと集計!F$2) -> 0 | G32: =COUNTIFS(SQLデータ!$D:$D,"扶養",SQLデータ!$P:$P,1,SQLデータ!$H:$H,届出事由・区分・届出年月日ごと集計!$A32,SQLデータ!$G:$G,届出事由・区分・届出年月日ごと集計!$B32,SQLデータ!$M:$M,1,SQLデータ!$F:$F,"",SQLデータ!$C:$C,">="&届出事由・区分・届出年月日ごと集計!G$1,SQLデータ!$C:$C,"<="&届出事由・区分・届出年月日ごと集計!G$2) -> 0 | H32: =COUNTIFS(SQLデータ!$D:$D,"扶養",SQLデータ!$P:$P,1,SQLデータ!$H:$H,届出事由・区分・届出年月日ごと集計!$A32,SQLデータ!$G:$G,届出事由・区分・届出年月日ごと集計!$B32,SQLデータ!$M:$M,1,SQLデータ!$F:$F,"",SQLデータ!$C:$C,">="&届出事由・区分・届出年月日ごと集計!H$1,SQLデータ!$C:$C,"<="&届出事由・区分・届出年月日ごと集計!H$2) -> 0 | I32: =COUNTIFS(SQLデータ!$D:$D,"扶養",SQLデータ!$P:$P,1,SQLデータ!$H:$H,届出事由・区分・届出年月日ごと集計!$A32,SQLデータ!$G:$G,届出事由・区分・届出年月日ごと集計!$B32,SQLデータ!$M:$M,1,SQLデータ!$F:$F,"",SQLデータ!$C:$C,">="&届出事由・区分・届出年月日ごと集計!I$1,SQLデータ!$C:$C,"<="&届出事由・区分・届出年月日ごと集計!I$2) -> 0 | J32: =COUNTIFS(SQLデータ!$D:$D,"扶養",SQLデータ!$P:$P,1,SQLデータ!$H:$H,届出事由・区分・届出年月日ごと集計!$A32,SQLデータ!$G:$G,届出事由・区分・届出年月日ごと集計!$B32,SQLデータ!$M:$M,1,SQLデータ!$F:$F,"",SQLデータ!$C:$C,">="&届出事由・区分・届出年月日ごと集計!J$1,SQLデータ!$C:$C,"<="&届出事由・区分・届出年月日ごと集計!J$2) -> 0 | K32: =COUNTIFS(SQLデータ!$D:$D,"扶養",SQLデータ!$P:$P,1,SQLデータ!$H:$H,届出事由・区分・届出年月日ごと集計!$A32,SQLデータ!$G:$G,届出事由・区分・届出年月日ごと集計!$B32,SQLデータ!$M:$M,1,SQLデータ!$F:$F,"",SQLデータ!$C:$C,">="&届出事由・区分・届出年月日ごと集計!K$1,SQLデータ!$C:$C,"<="&届出事由・区分・届出年月日ごと集計!K$2) -> 0 | L32: =COUNTIFS(SQLデータ!$D:$D,"扶養",SQLデータ!$P:$P,1,SQLデータ!$H:$H,届出事由・区分・届出年月日ごと集計!$A32,SQLデータ!$G:$G,届出事由・区分・届出年月日ごと集計!$B32,SQLデータ!$M:$M,1,SQLデータ!$F:$F,"",SQLデータ!$C:$C,">="&届出事由・区分・届出年月日ごと集計!L$1,SQLデータ!$C:$C,"<="&届出事由・区分・届出年月日ごと集計!L$2) -> 0 | M32: =COUNTIFS(SQLデータ!$D:$D,"扶養",SQLデータ!$P:$P,1,SQLデータ!$H:$H,届出事由・区分・届出年月日ごと集計!$A32,SQLデータ!$G:$G,届出事由・区分・届出年月日ごと集計!$B32,SQLデータ!$M:$M,1,SQLデータ!$F:$F,"",SQLデータ!$C:$C,">="&届出事由・区分・届出年月日ごと集計!M$1,SQLデータ!$C:$C,"<="&届出事由・区分・届出年月日ごと集計!M$2) -> 0 | ... T32: =COUNTIFS(SQLデータ!$D:$D,"扶養",SQLデータ!$P:$P,1,SQLデータ!$H:$H,届出事由・区分・届出年月日ごと集計!$A32,SQLデータ!$G:$G,届出事由・区分・届出年月日ごと集計!$B32,SQLデータ!$M:$M,1,SQLデータ!$F:$F,"",SQLデータ!$C:$C,">="&届出事由・区分・届出年月日ごと集計!T$1,SQLデータ!$C:$C,"<="&届出事由・区分・届出年月日ごと集計!T$2) -> 0
A33: 増 | B33: 障害程度の変更 | C33: 税控除のみ | D33: =COUNTIFS(SQLデータ!$D:$D,"扶養",SQLデータ!$H:$H,届出事由・区分・届出年月日ごと集計!$A33,SQLデータ!$G:$G,届出事由・区分・届出年月日ごと集計!$B33,SQLデータ!$N:$N,1) -> 0 | F33: =COUNTIFS(SQLデータ!$D:$D,"扶養",SQLデータ!$P:$P,1,SQLデータ!$H:$H,届出事由・区分・届出年月日ごと集計!$A33,SQLデータ!$G:$G,届出事由・区分・届出年月日ごと集計!$B33,SQLデータ!$N:$N,1,SQLデータ!$F:$F,"",SQLデータ!$C:$C,">="&届出事由・区分・届出年月日ごと集計!F$1,SQLデータ!$C:$C,"<="&届出事由・区分・届出年月日ごと集計!F$2) -> 0 | G33: =COUNTIFS(SQLデータ!$D:$D,"扶養",SQLデータ!$P:$P,1,SQLデータ!$H:$H,届出事由・区分・届出年月日ごと集計!$A33,SQLデータ!$G:$G,届出事由・区分・届出年月日ごと集計!$B33,SQLデータ!$N:$N,1,SQLデータ!$F:$F,"",SQLデータ!$C:$C,">="&届出事由・区分・届出年月日ごと集計!G$1,SQLデータ!$C:$C,"<="&届出事由・区分・届出年月日ごと集計!G$2) -> 0 | H33: =COUNTIFS(SQLデータ!$D:$D,"扶養",SQLデータ!$P:$P,1,SQLデータ!$H:$H,届出事由・区分・届出年月日ごと集計!$A33,SQLデータ!$G:$G,届出事由・区分・届出年月日ごと集計!$B33,SQLデータ!$N:$N,1,SQLデータ!$F:$F,"",SQLデータ!$C:$C,">="&届出事由・区分・届出年月日ごと集計!H$1,SQLデータ!$C:$C,"<="&届出事由・区分・届出年月日ごと集計!H$2) -> 0 | I33: =COUNTIFS(SQLデータ!$D:$D,"扶養",SQLデータ!$P:$P,1,SQLデータ!$H:$H,届出事由・区分・届出年月日ごと集計!$A33,SQLデータ!$G:$G,届出事由・区分・届出年月日ごと集計!$B33,SQLデータ!$N:$N,1,SQLデータ!$F:$F,"",SQLデータ!$C:$C,">="&届出事由・区分・届出年月日ごと集計!I$1,SQLデータ!$C:$C,"<="&届出事由・区分・届出年月日ごと集計!I$2) -> 0 | J33: =COUNTIFS(SQLデータ!$D:$D,"扶養",SQLデータ!$P:$P,1,SQLデータ!$H:$H,届出事由・区分・届出年月日ごと集計!$A33,SQLデータ!$G:$G,届出事由・区分・届出年月日ごと集計!$B33,SQLデータ!$N:$N,1,SQLデータ!$F:$F,"",SQLデータ!$C:$C,">="&届出事由・区分・届出年月日ごと集計!J$1,SQLデータ!$C:$C,"<="&届出事由・区分・届出年月日ごと集計!J$2) -> 0 | K33: =COUNTIFS(SQLデータ!$D:$D,"扶養",SQLデータ!$P:$P,1,SQLデータ!$H:$H,届出事由・区分・届出年月日ごと集計!$A33,SQLデータ!$G:$G,届出事由・区分・届出年月日ごと集計!$B33,SQLデータ!$N:$N,1,SQLデータ!$F:$F,"",SQLデータ!$C:$C,">="&届出事由・区分・届出年月日ごと集計!K$1,SQLデータ!$C:$C,"<="&届出事由・区分・届出年月日ごと集計!K$2) -> 0 | L33: =COUNTIFS(SQLデータ!$D:$D,"扶養",SQLデータ!$P:$P,1,SQLデータ!$H:$H,届出事由・区分・届出年月日ごと集計!$A33,SQLデータ!$G:$G,届出事由・区分・届出年月日ごと集計!$B33,SQLデータ!$N:$N,1,SQLデータ!$F:$F,"",SQLデータ!$C:$C,">="&届出事由・区分・届出年月日ごと集計!L$1,SQLデータ!$C:$C,"<="&届出事由・区分・届出年月日ごと集計!L$2) -> 0 | M33: =COUNTIFS(SQLデータ!$D:$D,"扶養",SQLデータ!$P:$P,1,SQLデータ!$H:$H,届出事由・区分・届出年月日ごと集計!$A33,SQLデータ!$G:$G,届出事由・区分・届出年月日ごと集計!$B33,SQLデータ!$N:$N,1,SQLデータ!$F:$F,"",SQLデータ!$C:$C,">="&届出事由・区分・届出年月日ごと集計!M$1,SQLデータ!$C:$C,"<="&届出事由・区分・届出年月日ごと集計!M$2) -> 0 | ... T33: =COUNTIFS(SQLデータ!$D:$D,"扶養",SQLデータ!$P:$P,1,SQLデータ!$H:$H,届出事由・区分・届出年月日ごと集計!$A33,SQLデータ!$G:$G,届出事由・区分・届出年月日ごと集計!$B33,SQLデータ!$N:$N,1,SQLデータ!$F:$F,"",SQLデータ!$C:$C,">="&届出事由・区分・届出年月日ごと集計!T$1,SQLデータ!$C:$C,"<="&届出事由・区分・届出年月日ごと集計!T$2) -> 0
A34: 増 | B34: 障害程度の変更 | C34: 本人税のみ | D34: =COUNTIFS(SQLデータ!$D:$D,"扶養",SQLデータ!$H:$H,届出事由・区分・届出年月日ごと集計!$A34,SQLデータ!$G:$G,届出事由・区分・届出年月日ごと集計!$B34,SQLデータ!$O:$O,1) -> 1 | F34: =COUNTIFS(SQLデータ!$D:$D,"扶養",SQLデータ!$P:$P,1,SQLデータ!$H:$H,届出事由・区分・届出年月日ごと集計!$A34,SQLデータ!$G:$G,届出事由・区分・届出年月日ごと集計!$B34,SQLデータ!$O:$O,1,SQLデータ!$F:$F,"",SQLデータ!$C:$C,">="&届出事由・区分・届出年月日ごと集計!F$1,SQLデータ!$C:$C,"<="&届出事由・区分・届出年月日ごと集計!F$2) -> 1 | G34: =COUNTIFS(SQLデータ!$D:$D,"扶養",SQLデータ!$P:$P,1,SQLデータ!$H:$H,届出事由・区分・届出年月日ごと集計!$A34,SQLデータ!$G:$G,届出事由・区分・届出年月日ごと集計!$B34,SQLデータ!$O:$O,1,SQLデータ!$F:$F,"",SQLデータ!$C:$C,">="&届出事由・区分・届出年月日ごと集計!G$1,SQLデータ!$C:$C,"<="&届出事由・区分・届出年月日ごと集計!G$2) -> 0 | H34: =COUNTIFS(SQLデータ!$D:$D,"扶養",SQLデータ!$P:$P,1,SQLデータ!$H:$H,届出事由・区分・届出年月日ごと集計!$A34,SQLデータ!$G:$G,届出事由・区分・届出年月日ごと集計!$B34,SQLデータ!$O:$O,1,SQLデータ!$F:$F,"",SQLデータ!$C:$C,">="&届出事由・区分・届出年月日ごと集計!H$1,SQLデータ!$C:$C,"<="&届出事由・区分・届出年月日ごと集計!H$2) -> 0 | I34: =COUNTIFS(SQLデータ!$D:$D,"扶養",SQLデータ!$P:$P,1,SQLデータ!$H:$H,届出事由・区分・届出年月日ごと集計!$A34,SQLデータ!$G:$G,届出事由・区分・届出年月日ごと集計!$B34,SQLデータ!$O:$O,1,SQLデータ!$F:$F,"",SQLデータ!$C:$C,">="&届出事由・区分・届出年月日ごと集計!I$1,SQLデータ!$C:$C,"<="&届出事由・区分・届出年月日ごと集計!I$2) -> 0 | J34: =COUNTIFS(SQLデータ!$D:$D,"扶養",SQLデータ!$P:$P,1,SQLデータ!$H:$H,届出事由・区分・届出年月日ごと集計!$A34,SQLデータ!$G:$G,届出事由・区分・届出年月日ごと集計!$B34,SQLデータ!$O:$O,1,SQLデータ!$F:$F,"",SQLデータ!$C:$C,">="&届出事由・区分・届出年月日ごと集計!J$1,SQLデータ!$C:$C,"<="&届出事由・区分・届出年月日ごと集計!J$2) -> 0 | K34: =COUNTIFS(SQLデータ!$D:$D,"扶養",SQLデータ!$P:$P,1,SQLデータ!$H:$H,届出事由・区分・届出年月日ごと集計!$A34,SQLデータ!$G:$G,届出事由・区分・届出年月日ごと集計!$B34,SQLデータ!$O:$O,1,SQLデータ!$F:$F,"",SQLデータ!$C:$C,">="&届出事由・区分・届出年月日ごと集計!K$1,SQLデータ!$C:$C,"<="&届出事由・区分・届出年月日ごと集計!K$2) -> 0 | L34: =COUNTIFS(SQLデータ!$D:$D,"扶養",SQLデータ!$P:$P,1,SQLデータ!$H:$H,届出事由・区分・届出年月日ごと集計!$A34,SQLデータ!$G:$G,届出事由・区分・届出年月日ごと集計!$B34,SQLデータ!$O:$O,1,SQLデータ!$F:$F,"",SQLデータ!$C:$C,">="&届出事由・区分・届出年月日ごと集計!L$1,SQLデータ!$C:$C,"<="&届出事由・区分・届出年月日ごと集計!L$2) -> 0 | M34: =COUNTIFS(SQLデータ!$D:$D,"扶養",SQLデータ!$P:$P,1,SQLデータ!$H:$H,届出事由・区分・届出年月日ごと集計!$A34,SQLデータ!$G:$G,届出事由・区分・届出年月日ごと集計!$B34,SQLデータ!$O:$O,1,SQLデータ!$F:$F,"",SQLデータ!$C:$C,">="&届出事由・区分・届出年月日ごと集計!M$1,SQLデータ!$C:$C,"<="&届出事由・区分・届出年月日ごと集計!M$2) -> 0 | ... T34: =COUNTIFS(SQLデータ!$D:$D,"扶養",SQLデータ!$P:$P,1,SQLデータ!$H:$H,届出事由・区分・届出年月日ごと集計!$A34,SQLデータ!$G:$G,届出事由・区分・届出年月日ごと集計!$B34,SQLデータ!$O:$O,1,SQLデータ!$F:$F,"",SQLデータ!$C:$C,">="&届出事由・区分・届出年月日ごと集計!T$1,SQLデータ!$C:$C,"<="&届出事由・区分・届出年月日ごと集計!T$2) -> 0
A35: 増 | B35: 養子縁組 | C35: 共済あり | D35: =COUNTIFS(SQLデータ!$D:$D,"扶養",SQLデータ!$H:$H,届出事由・区分・届出年月日ごと集計!$A35,SQLデータ!$G:$G,届出事由・区分・届出年月日ごと集計!$B35,SQLデータ!$L:$L,1) -> 1 | F35: =COUNTIFS(SQLデータ!$D:$D,"扶養",SQLデータ!$P:$P,1,SQLデータ!$H:$H,届出事由・区分・届出年月日ごと集計!$A35,SQLデータ!$G:$G,届出事由・区分・届出年月日ごと集計!$B35,SQLデータ!$L:$L,1,SQLデータ!$F:$F,"",SQLデータ!$C:$C,">="&届出事由・区分・届出年月日ごと集計!F$1,SQLデータ!$C:$C,"<="&届出事由・区分・届出年月日ごと集計!F$2) -> 0 | G35: =COUNTIFS(SQLデータ!$D:$D,"扶養",SQLデータ!$P:$P,1,SQLデータ!$H:$H,届出事由・区分・届出年月日ごと集計!$A35,SQLデータ!$G:$G,届出事由・区分・届出年月日ごと集計!$B35,SQLデータ!$L:$L,1,SQLデータ!$F:$F,"",SQLデータ!$C:$C,">="&届出事由・区分・届出年月日ごと集計!G$1,SQLデータ!$C:$C,"<="&届出事由・区分・届出年月日ごと集計!G$2) -> 0 | H35: =COUNTIFS(SQLデータ!$D:$D,"扶養",SQLデータ!$P:$P,1,SQLデータ!$H:$H,届出事由・区分・届出年月日ごと集計!$A35,SQLデータ!$G:$G,届出事由・区分・届出年月日ごと集計!$B35,SQLデータ!$L:$L,1,SQLデータ!$F:$F,"",SQLデータ!$C:$C,">="&届出事由・区分・届出年月日ごと集計!H$1,SQLデータ!$C:$C,"<="&届出事由・区分・届出年月日ごと集計!H$2) -> 0 | I35: =COUNTIFS(SQLデータ!$D:$D,"扶養",SQLデータ!$P:$P,1,SQLデータ!$H:$H,届出事由・区分・届出年月日ごと集計!$A35,SQLデータ!$G:$G,届出事由・区分・届出年月日ごと集計!$B35,SQLデータ!$L:$L,1,SQLデータ!$F:$F,"",SQLデータ!$C:$C,">="&届出事由・区分・届出年月日ごと集計!I$1,SQLデータ!$C:$C,"<="&届出事由・区分・届出年月日ごと集計!I$2) -> 0 | J35: =COUNTIFS(SQLデータ!$D:$D,"扶養",SQLデータ!$P:$P,1,SQLデータ!$H:$H,届出事由・区分・届出年月日ごと集計!$A35,SQLデータ!$G:$G,届出事由・区分・届出年月日ごと集計!$B35,SQLデータ!$L:$L,1,SQLデータ!$F:$F,"",SQLデータ!$C:$C,">="&届出事由・区分・届出年月日ごと集計!J$1,SQLデータ!$C:$C,"<="&届出事由・区分・届出年月日ごと集計!J$2) -> 0 | K35: =COUNTIFS(SQLデータ!$D:$D,"扶養",SQLデータ!$P:$P,1,SQLデータ!$H:$H,届出事由・区分・届出年月日ごと集計!$A35,SQLデータ!$G:$G,届出事由・区分・届出年月日ごと集計!$B35,SQLデータ!$L:$L,1,SQLデータ!$F:$F,"",SQLデータ!$C:$C,">="&届出事由・区分・届出年月日ごと集計!K$1,SQLデータ!$C:$C,"<="&届出事由・区分・届出年月日ごと集計!K$2) -> 0 | L35: =COUNTIFS(SQLデータ!$D:$D,"扶養",SQLデータ!$P:$P,1,SQLデータ!$H:$H,届出事由・区分・届出年月日ごと集計!$A35,SQLデータ!$G:$G,届出事由・区分・届出年月日ごと集計!$B35,SQLデータ!$L:$L,1,SQLデータ!$F:$F,"",SQLデータ!$C:$C,">="&届出事由・区分・届出年月日ごと集計!L$1,SQLデータ!$C:$C,"<="&届出事由・区分・届出年月日ごと集計!L$2) -> 0 | M35: =COUNTIFS(SQLデータ!$D:$D,"扶養",SQLデータ!$P:$P,1,SQLデータ!$H:$H,届出事由・区分・届出年月日ごと集計!$A35,SQLデータ!$G:$G,届出事由・区分・届出年月日ごと集計!$B35,SQLデータ!$L:$L,1,SQLデータ!$F:$F,"",SQLデータ!$C:$C,">="&届出事由・区分・届出年月日ごと集計!M$1,SQLデータ!$C:$C,"<="&届出事由・区分・届出年月日ごと集計!M$2) -> 0 | ... T35: =COUNTIFS(SQLデータ!$D:$D,"扶養",SQLデータ!$P:$P,1,SQLデータ!$H:$H,届出事由・区分・届出年月日ごと集計!$A35,SQLデータ!$G:$G,届出事由・区分・届出年月日ごと集計!$B35,SQLデータ!$L:$L,1,SQLデータ!$F:$F,"",SQLデータ!$C:$C,">="&届出事由・区分・届出年月日ごと集計!T$1,SQLデータ!$C:$C,"<="&届出事由・区分・届出年月日ごと集計!T$2) -> 0
A36: 増 | B36: 養子縁組 | C36: 扶養手当あり | D36: =COUNTIFS(SQLデータ!$D:$D,"扶養",SQLデータ!$H:$H,届出事由・区分・届出年月日ごと集計!$A36,SQLデータ!$G:$G,届出事由・区分・届出年月日ごと集計!$B36,SQLデータ!$M:$M,1) -> 0 | F36: =COUNTIFS(SQLデータ!$D:$D,"扶養",SQLデータ!$P:$P,1,SQLデータ!$H:$H,届出事由・区分・届出年月日ごと集計!$A36,SQLデータ!$G:$G,届出事由・区分・届出年月日ごと集計!$B36,SQLデータ!$M:$M,1,SQLデータ!$F:$F,"",SQLデータ!$C:$C,">="&届出事由・区分・届出年月日ごと集計!F$1,SQLデータ!$C:$C,"<="&届出事由・区分・届出年月日ごと集計!F$2) -> 0 | G36: =COUNTIFS(SQLデータ!$D:$D,"扶養",SQLデータ!$P:$P,1,SQLデータ!$H:$H,届出事由・区分・届出年月日ごと集計!$A36,SQLデータ!$G:$G,届出事由・区分・届出年月日ごと集計!$B36,SQLデータ!$M:$M,1,SQLデータ!$F:$F,"",SQLデータ!$C:$C,">="&届出事由・区分・届出年月日ごと集計!G$1,SQLデータ!$C:$C,"<="&届出事由・区分・届出年月日ごと集計!G$2) -> 0 | H36: =COUNTIFS(SQLデータ!$D:$D,"扶養",SQLデータ!$P:$P,1,SQLデータ!$H:$H,届出事由・区分・届出年月日ごと集計!$A36,SQLデータ!$G:$G,届出事由・区分・届出年月日ごと集計!$B36,SQLデータ!$M:$M,1,SQLデータ!$F:$F,"",SQLデータ!$C:$C,">="&届出事由・区分・届出年月日ごと集計!H$1,SQLデータ!$C:$C,"<="&届出事由・区分・届出年月日ごと集計!H$2) -> 0 | I36: =COUNTIFS(SQLデータ!$D:$D,"扶養",SQLデータ!$P:$P,1,SQLデータ!$H:$H,届出事由・区分・届出年月日ごと集計!$A36,SQLデータ!$G:$G,届出事由・区分・届出年月日ごと集計!$B36,SQLデータ!$M:$M,1,SQLデータ!$F:$F,"",SQLデータ!$C:$C,">="&届出事由・区分・届出年月日ごと集計!I$1,SQLデータ!$C:$C,"<="&届出事由・区分・届出年月日ごと集計!I$2) -> 0 | J36: =COUNTIFS(SQLデータ!$D:$D,"扶養",SQLデータ!$P:$P,1,SQLデータ!$H:$H,届出事由・区分・届出年月日ごと集計!$A36,SQLデータ!$G:$G,届出事由・区分・届出年月日ごと集計!$B36,SQLデータ!$M:$M,1,SQLデータ!$F:$F,"",SQLデータ!$C:$C,">="&届出事由・区分・届出年月日ごと集計!J$1,SQLデータ!$C:$C,"<="&届出事由・区分・届出年月日ごと集計!J$2) -> 0 | K36: =COUNTIFS(SQLデータ!$D:$D,"扶養",SQLデータ!$P:$P,1,SQLデータ!$H:$H,届出事由・区分・届出年月日ごと集計!$A36,SQLデータ!$G:$G,届出事由・区分・届出年月日ごと集計!$B36,SQLデータ!$M:$M,1,SQLデータ!$F:$F,"",SQLデータ!$C:$C,">="&届出事由・区分・届出年月日ごと集計!K$1,SQLデータ!$C:$C,"<="&届出事由・区分・届出年月日ごと集計!K$2) -> 0 | L36: =COUNTIFS(SQLデータ!$D:$D,"扶養",SQLデータ!$P:$P,1,SQLデータ!$H:$H,届出事由・区分・届出年月日ごと集計!$A36,SQLデータ!$G:$G,届出事由・区分・届出年月日ごと集計!$B36,SQLデータ!$M:$M,1,SQLデータ!$F:$F,"",SQLデータ!$C:$C,">="&届出事由・区分・届出年月日ごと集計!L$1,SQLデータ!$C:$C,"<="&届出事由・区分・届出年月日ごと集計!L$2) -> 0 | M36: =COUNTIFS(SQLデータ!$D:$D,"扶養",SQLデータ!$P:$P,1,SQLデータ!$H:$H,届出事由・区分・届出年月日ごと集計!$A36,SQLデータ!$G:$G,届出事由・区分・届出年月日ごと集計!$B36,SQLデータ!$M:$M,1,SQLデータ!$F:$F,"",SQLデータ!$C:$C,">="&届出事由・区分・届出年月日ごと集計!M$1,SQLデータ!$C:$C,"<="&届出事由・区分・届出年月日ごと集計!M$2) -> 0 | ... T36: =COUNTIFS(SQLデータ!$D:$D,"扶養",SQLデータ!$P:$P,1,SQLデータ!$H:$H,届出事由・区分・届出年月日ごと集計!$A36,SQLデータ!$G:$G,届出事由・区分・届出年月日ごと集計!$B36,SQLデータ!$M:$M,1,SQLデータ!$F:$F,"",SQLデータ!$C:$C,">="&届出事由・区分・届出年月日ごと集計!T$1,SQLデータ!$C:$C,"<="&届出事由・区分・届出年月日ごと集計!T$2) -> 0
A37: 増 | B37: 養子縁組 | C37: 税控除のみ | D37: =COUNTIFS(SQLデータ!$D:$D,"扶養",SQLデータ!$H:$H,届出事由・区分・届出年月日ごと集計!$A37,SQLデータ!$G:$G,届出事由・区分・届出年月日ごと集計!$B37,SQLデータ!$N:$N,1) -> 0 | F37: =COUNTIFS(SQLデータ!$D:$D,"扶養",SQLデータ!$P:$P,1,SQLデータ!$H:$H,届出事由・区分・届出年月日ごと集計!$A37,SQLデータ!$G:$G,届出事由・区分・届出年月日ごと集計!$B37,SQLデータ!$N:$N,1,SQLデータ!$F:$F,"",SQLデータ!$C:$C,">="&届出事由・区分・届出年月日ごと集計!F$1,SQLデータ!$C:$C,"<="&届出事由・区分・届出年月日ごと集計!F$2) -> 0 | G37: =COUNTIFS(SQLデータ!$D:$D,"扶養",SQLデータ!$P:$P,1,SQLデータ!$H:$H,届出事由・区分・届出年月日ごと集計!$A37,SQLデータ!$G:$G,届出事由・区分・届出年月日ごと集計!$B37,SQLデータ!$N:$N,1,SQLデータ!$F:$F,"",SQLデータ!$C:$C,">="&届出事由・区分・届出年月日ごと集計!G$1,SQLデータ!$C:$C,"<="&届出事由・区分・届出年月日ごと集計!G$2) -> 0 | H37: =COUNTIFS(SQLデータ!$D:$D,"扶養",SQLデータ!$P:$P,1,SQLデータ!$H:$H,届出事由・区分・届出年月日ごと集計!$A37,SQLデータ!$G:$G,届出事由・区分・届出年月日ごと集計!$B37,SQLデータ!$N:$N,1,SQLデータ!$F:$F,"",SQLデータ!$C:$C,">="&届出事由・区分・届出年月日ごと集計!H$1,SQLデータ!$C:$C,"<="&届出事由・区分・届出年月日ごと集計!H$2) -> 0 | I37: =COUNTIFS(SQLデータ!$D:$D,"扶養",SQLデータ!$P:$P,1,SQLデータ!$H:$H,届出事由・区分・届出年月日ごと集計!$A37,SQLデータ!$G:$G,届出事由・区分・届出年月日ごと集計!$B37,SQLデータ!$N:$N,1,SQLデータ!$F:$F,"",SQLデータ!$C:$C,">="&届出事由・区分・届出年月日ごと集計!I$1,SQLデータ!$C:$C,"<="&届出事由・区分・届出年月日ごと集計!I$2) -> 0 | J37: =COUNTIFS(SQLデータ!$D:$D,"扶養",SQLデータ!$P:$P,1,SQLデータ!$H:$H,届出事由・区分・届出年月日ごと集計!$A37,SQLデータ!$G:$G,届出事由・区分・届出年月日ごと集計!$B37,SQLデータ!$N:$N,1,SQLデータ!$F:$F,"",SQLデータ!$C:$C,">="&届出事由・区分・届出年月日ごと集計!J$1,SQLデータ!$C:$C,"<="&届出事由・区分・届出年月日ごと集計!J$2) -> 0 | K37: =COUNTIFS(SQLデータ!$D:$D,"扶養",SQLデータ!$P:$P,1,SQLデータ!$H:$H,届出事由・区分・届出年月日ごと集計!$A37,SQLデータ!$G:$G,届出事由・区分・届出年月日ごと集計!$B37,SQLデータ!$N:$N,1,SQLデータ!$F:$F,"",SQLデータ!$C:$C,">="&届出事由・区分・届出年月日ごと集計!K$1,SQLデータ!$C:$C,"<="&届出事由・区分・届出年月日ごと集計!K$2) -> 0 | L37: =COUNTIFS(SQLデータ!$D:$D,"扶養",SQLデータ!$P:$P,1,SQLデータ!$H:$H,届出事由・区分・届出年月日ごと集計!$A37,SQLデータ!$G:$G,届出事由・区分・届出年月日ごと集計!$B37,SQLデータ!$N:$N,1,SQLデータ!$F:$F,"",SQLデータ!$C:$C,">="&届出事由・区分・届出年月日ごと集計!L$1,SQLデータ!$C:$C,"<="&届出事由・区分・届出年月日ごと集計!L$2) -> 0 | M37: =COUNTIFS(SQLデータ!$D:$D,"扶養",SQLデータ!$P:$P,1,SQLデータ!$H:$H,届出事由・区分・届出年月日ごと集計!$A37,SQLデータ!$G:$G,届出事由・区分・届出年月日ごと集計!$B37,SQLデータ!$N:$N,1,SQLデータ!$F:$F,"",SQLデータ!$C:$C,">="&届出事由・区分・届出年月日ごと集計!M$1,SQLデータ!$C:$C,"<="&届出事由・区分・届出年月日ごと集計!M$2) -> 0 | ... T37: =COUNTIFS(SQLデータ!$D:$D,"扶養",SQLデータ!$P:$P,1,SQLデータ!$H:$H,届出事由・区分・届出年月日ごと集計!$A37,SQLデータ!$G:$G,届出事由・区分・届出年月日ごと集計!$B37,SQLデータ!$N:$N,1,SQLデータ!$F:$F,"",SQLデータ!$C:$C,">="&届出事由・区分・届出年月日ごと集計!T$1,SQLデータ!$C:$C,"<="&届出事由・区分・届出年月日ごと集計!T$2) -> 0
A38: 増 | B38: 養子縁組 | C38: 本人税のみ | D38: =COUNTIFS(SQLデータ!$D:$D,"扶養",SQLデータ!$H:$H,届出事由・区分・届出年月日ごと集計!$A38,SQLデータ!$G:$G,届出事由・区分・届出年月日ごと集計!$B38,SQLデータ!$O:$O,1) -> 0 | F38: =COUNTIFS(SQLデータ!$D:$D,"扶養",SQLデータ!$P:$P,1,SQLデータ!$H:$H,届出事由・区分・届出年月日ごと集計!$A38,SQLデータ!$G:$G,届出事由・区分・届出年月日ごと集計!$B38,SQLデータ!$O:$O,1,SQLデータ!$F:$F,"",SQLデータ!$C:$C,">="&届出事由・区分・届出年月日ごと集計!F$1,SQLデータ!$C:$C,"<="&届出事由・区分・届出年月日ごと集計!F$2) -> 0 | G38: =COUNTIFS(SQLデータ!$D:$D,"扶養",SQLデータ!$P:$P,1,SQLデータ!$H:$H,届出事由・区分・届出年月日ごと集計!$A38,SQLデータ!$G:$G,届出事由・区分・届出年月日ごと集計!$B38,SQLデータ!$O:$O,1,SQLデータ!$F:$F,"",SQLデータ!$C:$C,">="&届出事由・区分・届出年月日ごと集計!G$1,SQLデータ!$C:$C,"<="&届出事由・区分・届出年月日ごと集計!G$2) -> 0 | H38: =COUNTIFS(SQLデータ!$D:$D,"扶養",SQLデータ!$P:$P,1,SQLデータ!$H:$H,届出事由・区分・届出年月日ごと集計!$A38,SQLデータ!$G:$G,届出事由・区分・届出年月日ごと集計!$B38,SQLデータ!$O:$O,1,SQLデータ!$F:$F,"",SQLデータ!$C:$C,">="&届出事由・区分・届出年月日ごと集計!H$1,SQLデータ!$C:$C,"<="&届出事由・区分・届出年月日ごと集計!H$2) -> 0 | I38: =COUNTIFS(SQLデータ!$D:$D,"扶養",SQLデータ!$P:$P,1,SQLデータ!$H:$H,届出事由・区分・届出年月日ごと集計!$A38,SQLデータ!$G:$G,届出事由・区分・届出年月日ごと集計!$B38,SQLデータ!$O:$O,1,SQLデータ!$F:$F,"",SQLデータ!$C:$C,">="&届出事由・区分・届出年月日ごと集計!I$1,SQLデータ!$C:$C,"<="&届出事由・区分・届出年月日ごと集計!I$2) -> 0 | J38: =COUNTIFS(SQLデータ!$D:$D,"扶養",SQLデータ!$P:$P,1,SQLデータ!$H:$H,届出事由・区分・届出年月日ごと集計!$A38,SQLデータ!$G:$G,届出事由・区分・届出年月日ごと集計!$B38,SQLデータ!$O:$O,1,SQLデータ!$F:$F,"",SQLデータ!$C:$C,">="&届出事由・区分・届出年月日ごと集計!J$1,SQLデータ!$C:$C,"<="&届出事由・区分・届出年月日ごと集計!J$2) -> 0 | K38: =COUNTIFS(SQLデータ!$D:$D,"扶養",SQLデータ!$P:$P,1,SQLデータ!$H:$H,届出事由・区分・届出年月日ごと集計!$A38,SQLデータ!$G:$G,届出事由・区分・届出年月日ごと集計!$B38,SQLデータ!$O:$O,1,SQLデータ!$F:$F,"",SQLデータ!$C:$C,">="&届出事由・区分・届出年月日ごと集計!K$1,SQLデータ!$C:$C,"<="&届出事由・区分・届出年月日ごと集計!K$2) -> 0 | L38: =COUNTIFS(SQLデータ!$D:$D,"扶養",SQLデータ!$P:$P,1,SQLデータ!$H:$H,届出事由・区分・届出年月日ごと集計!$A38,SQLデータ!$G:$G,届出事由・区分・届出年月日ごと集計!$B38,SQLデータ!$O:$O,1,SQLデータ!$F:$F,"",SQLデータ!$C:$C,">="&届出事由・区分・届出年月日ごと集計!L$1,SQLデータ!$C:$C,"<="&届出事由・区分・届出年月日ごと集計!L$2) -> 0 | M38: =COUNTIFS(SQLデータ!$D:$D,"扶養",SQLデータ!$P:$P,1,SQLデータ!$H:$H,届出事由・区分・届出年月日ごと集計!$A38,SQLデータ!$G:$G,届出事由・区分・届出年月日ごと集計!$B38,SQLデータ!$O:$O,1,SQLデータ!$F:$F,"",SQLデータ!$C:$C,">="&届出事由・区分・届出年月日ごと集計!M$1,SQLデータ!$C:$C,"<="&届出事由・区分・届出年月日ごと集計!M$2) -> 0 | ... T38: =COUNTIFS(SQLデータ!$D:$D,"扶養",SQLデータ!$P:$P,1,SQLデータ!$H:$H,届出事由・区分・届出年月日ごと集計!$A38,SQLデータ!$G:$G,届出事由・区分・届出年月日ごと集計!$B38,SQLデータ!$O:$O,1,SQLデータ!$F:$F,"",SQLデータ!$C:$C,">="&届出事由・区分・届出年月日ごと集計!T$1,SQLデータ!$C:$C,"<="&届出事由・区分・届出年月日ごと集計!T$2) -> 0
A39: 増 | B39: 扶養親族の同別居変更 | C39: 共済あり | D39: =COUNTIFS(SQLデータ!$D:$D,"扶養",SQLデータ!$H:$H,届出事由・区分・届出年月日ごと集計!$A39,SQLデータ!$G:$G,届出事由・区分・届出年月日ごと集計!$B39,SQLデータ!$L:$L,1) -> 6 | F39: =COUNTIFS(SQLデータ!$D:$D,"扶養",SQLデータ!$P:$P,1,SQLデータ!$H:$H,届出事由・区分・届出年月日ごと集計!$A39,SQLデータ!$G:$G,届出事由・区分・届出年月日ごと集計!$B39,SQLデータ!$L:$L,1,SQLデータ!$F:$F,"",SQLデータ!$C:$C,">="&届出事由・区分・届出年月日ごと集計!F$1,SQLデータ!$C:$C,"<="&届出事由・区分・届出年月日ごと集計!F$2) -> 0 | G39: =COUNTIFS(SQLデータ!$D:$D,"扶養",SQLデータ!$P:$P,1,SQLデータ!$H:$H,届出事由・区分・届出年月日ごと集計!$A39,SQLデータ!$G:$G,届出事由・区分・届出年月日ごと集計!$B39,SQLデータ!$L:$L,1,SQLデータ!$F:$F,"",SQLデータ!$C:$C,">="&届出事由・区分・届出年月日ごと集計!G$1,SQLデータ!$C:$C,"<="&届出事由・区分・届出年月日ごと集計!G$2) -> 1 | H39: =COUNTIFS(SQLデータ!$D:$D,"扶養",SQLデータ!$P:$P,1,SQLデータ!$H:$H,届出事由・区分・届出年月日ごと集計!$A39,SQLデータ!$G:$G,届出事由・区分・届出年月日ごと集計!$B39,SQLデータ!$L:$L,1,SQLデータ!$F:$F,"",SQLデータ!$C:$C,">="&届出事由・区分・届出年月日ごと集計!H$1,SQLデータ!$C:$C,"<="&届出事由・区分・届出年月日ごと集計!H$2) -> 3 | I39: =COUNTIFS(SQLデータ!$D:$D,"扶養",SQLデータ!$P:$P,1,SQLデータ!$H:$H,届出事由・区分・届出年月日ごと集計!$A39,SQLデータ!$G:$G,届出事由・区分・届出年月日ごと集計!$B39,SQLデータ!$L:$L,1,SQLデータ!$F:$F,"",SQLデータ!$C:$C,">="&届出事由・区分・届出年月日ごと集計!I$1,SQLデータ!$C:$C,"<="&届出事由・区分・届出年月日ごと集計!I$2) -> 1 | J39: =COUNTIFS(SQLデータ!$D:$D,"扶養",SQLデータ!$P:$P,1,SQLデータ!$H:$H,届出事由・区分・届出年月日ごと集計!$A39,SQLデータ!$G:$G,届出事由・区分・届出年月日ごと集計!$B39,SQLデータ!$L:$L,1,SQLデータ!$F:$F,"",SQLデータ!$C:$C,">="&届出事由・区分・届出年月日ごと集計!J$1,SQLデータ!$C:$C,"<="&届出事由・区分・届出年月日ごと集計!J$2) -> 0 | K39: =COUNTIFS(SQLデータ!$D:$D,"扶養",SQLデータ!$P:$P,1,SQLデータ!$H:$H,届出事由・区分・届出年月日ごと集計!$A39,SQLデータ!$G:$G,届出事由・区分・届出年月日ごと集計!$B39,SQLデータ!$L:$L,1,SQLデータ!$F:$F,"",SQLデータ!$C:$C,">="&届出事由・区分・届出年月日ごと集計!K$1,SQLデータ!$C:$C,"<="&届出事由・区分・届出年月日ごと集計!K$2) -> 0 | L39: =COUNTIFS(SQLデータ!$D:$D,"扶養",SQLデータ!$P:$P,1,SQLデータ!$H:$H,届出事由・区分・届出年月日ごと集計!$A39,SQLデータ!$G:$G,届出事由・区分・届出年月日ごと集計!$B39,SQLデータ!$L:$L,1,SQLデータ!$F:$F,"",SQLデータ!$C:$C,">="&届出事由・区分・届出年月日ごと集計!L$1,SQLデータ!$C:$C,"<="&届出事由・区分・届出年月日ごと集計!L$2) -> 0 | M39: =COUNTIFS(SQLデータ!$D:$D,"扶養",SQLデータ!$P:$P,1,SQLデータ!$H:$H,届出事由・区分・届出年月日ごと集計!$A39,SQLデータ!$G:$G,届出事由・区分・届出年月日ごと集計!$B39,SQLデータ!$L:$L,1,SQLデータ!$F:$F,"",SQLデータ!$C:$C,">="&届出事由・区分・届出年月日ごと集計!M$1,SQLデータ!$C:$C,"<="&届出事由・区分・届出年月日ごと集計!M$2) -> 0 | ... T39: =COUNTIFS(SQLデータ!$D:$D,"扶養",SQLデータ!$P:$P,1,SQLデータ!$H:$H,届出事由・区分・届出年月日ごと集計!$A39,SQLデータ!$G:$G,届出事由・区分・届出年月日ごと集計!$B39,SQLデータ!$L:$L,1,SQLデータ!$F:$F,"",SQLデータ!$C:$C,">="&届出事由・区分・届出年月日ごと集計!T$1,SQLデータ!$C:$C,"<="&届出事由・区分・届出年月日ごと集計!T$2) -> 0
A40: 増 | B40: 扶養親族の同別居変更 | C40: 扶養手当あり | D40: =COUNTIFS(SQLデータ!$D:$D,"扶養",SQLデータ!$H:$H,届出事由・区分・届出年月日ごと集計!$A40,SQLデータ!$G:$G,届出事由・区分・届出年月日ごと集計!$B40,SQLデータ!$M:$M,1) -> 1 | F40: =COUNTIFS(SQLデータ!$D:$D,"扶養",SQLデータ!$P:$P,1,SQLデータ!$H:$H,届出事由・区分・届出年月日ごと集計!$A40,SQLデータ!$G:$G,届出事由・区分・届出年月日ごと集計!$B40,SQLデータ!$M:$M,1,SQLデータ!$F:$F,"",SQLデータ!$C:$C,">="&届出事由・区分・届出年月日ごと集計!F$1,SQLデータ!$C:$C,"<="&届出事由・区分・届出年月日ごと集計!F$2) -> 0 | G40: =COUNTIFS(SQLデータ!$D:$D,"扶養",SQLデータ!$P:$P,1,SQLデータ!$H:$H,届出事由・区分・届出年月日ごと集計!$A40,SQLデータ!$G:$G,届出事由・区分・届出年月日ごと集計!$B40,SQLデータ!$M:$M,1,SQLデータ!$F:$F,"",SQLデータ!$C:$C,">="&届出事由・区分・届出年月日ごと集計!G$1,SQLデータ!$C:$C,"<="&届出事由・区分・届出年月日ごと集計!G$2) -> 0 | H40: =COUNTIFS(SQLデータ!$D:$D,"扶養",SQLデータ!$P:$P,1,SQLデータ!$H:$H,届出事由・区分・届出年月日ごと集計!$A40,SQLデータ!$G:$G,届出事由・区分・届出年月日ごと集計!$B40,SQLデータ!$M:$M,1,SQLデータ!$F:$F,"",SQLデータ!$C:$C,">="&届出事由・区分・届出年月日ごと集計!H$1,SQLデータ!$C:$C,"<="&届出事由・区分・届出年月日ごと集計!H$2) -> 0 | I40: =COUNTIFS(SQLデータ!$D:$D,"扶養",SQLデータ!$P:$P,1,SQLデータ!$H:$H,届出事由・区分・届出年月日ごと集計!$A40,SQLデータ!$G:$G,届出事由・区分・届出年月日ごと集計!$B40,SQLデータ!$M:$M,1,SQLデータ!$F:$F,"",SQLデータ!$C:$C,">="&届出事由・区分・届出年月日ごと集計!I$1,SQLデータ!$C:$C,"<="&届出事由・区分・届出年月日ごと集計!I$2) -> 0 | J40: =COUNTIFS(SQLデータ!$D:$D,"扶養",SQLデータ!$P:$P,1,SQLデータ!$H:$H,届出事由・区分・届出年月日ごと集計!$A40,SQLデータ!$G:$G,届出事由・区分・届出年月日ごと集計!$B40,SQLデータ!$M:$M,1,SQLデータ!$F:$F,"",SQLデータ!$C:$C,">="&届出事由・区分・届出年月日ごと集計!J$1,SQLデータ!$C:$C,"<="&届出事由・区分・届出年月日ごと集計!J$2) -> 0 | K40: =COUNTIFS(SQLデータ!$D:$D,"扶養",SQLデータ!$P:$P,1,SQLデータ!$H:$H,届出事由・区分・届出年月日ごと集計!$A40,SQLデータ!$G:$G,届出事由・区分・届出年月日ごと集計!$B40,SQLデータ!$M:$M,1,SQLデータ!$F:$F,"",SQLデータ!$C:$C,">="&届出事由・区分・届出年月日ごと集計!K$1,SQLデータ!$C:$C,"<="&届出事由・区分・届出年月日ごと集計!K$2) -> 0 | L40: =COUNTIFS(SQLデータ!$D:$D,"扶養",SQLデータ!$P:$P,1,SQLデータ!$H:$H,届出事由・区分・届出年月日ごと集計!$A40,SQLデータ!$G:$G,届出事由・区分・届出年月日ごと集計!$B40,SQLデータ!$M:$M,1,SQLデータ!$F:$F,"",SQLデータ!$C:$C,">="&届出事由・区分・届出年月日ごと集計!L$1,SQLデータ!$C:$C,"<="&届出事由・区分・届出年月日ごと集計!L$2) -> 0 | M40: =COUNTIFS(SQLデータ!$D:$D,"扶養",SQLデータ!$P:$P,1,SQLデータ!$H:$H,届出事由・区分・届出年月日ごと集計!$A40,SQLデータ!$G:$G,届出事由・区分・届出年月日ごと集計!$B40,SQLデータ!$M:$M,1,SQLデータ!$F:$F,"",SQLデータ!$C:$C,">="&届出事由・区分・届出年月日ごと集計!M$1,SQLデータ!$C:$C,"<="&届出事由・区分・届出年月日ごと集計!M$2) -> 0 | ... T40: =COUNTIFS(SQLデータ!$D:$D,"扶養",SQLデータ!$P:$P,1,SQLデータ!$H:$H,届出事由・区分・届出年月日ごと集計!$A40,SQLデータ!$G:$G,届出事由・区分・届出年月日ごと集計!$B40,SQLデータ!$M:$M,1,SQLデータ!$F:$F,"",SQLデータ!$C:$C,">="&届出事由・区分・届出年月日ごと集計!T$1,SQLデータ!$C:$C,"<="&届出事由・区分・届出年月日ごと集計!T$2) -> 0
A41: 増 | B41: 扶養親族の同別居変更 | C41: 税控除のみ | D41: =COUNTIFS(SQLデータ!$D:$D,"扶養",SQLデータ!$H:$H,届出事由・区分・届出年月日ごと集計!$A41,SQLデータ!$G:$G,届出事由・区分・届出年月日ごと集計!$B41,SQLデータ!$N:$N,1) -> 0 | F41: =COUNTIFS(SQLデータ!$D:$D,"扶養",SQLデータ!$P:$P,1,SQLデータ!$H:$H,届出事由・区分・届出年月日ごと集計!$A41,SQLデータ!$G:$G,届出事由・区分・届出年月日ごと集計!$B41,SQLデータ!$N:$N,1,SQLデータ!$F:$F,"",SQLデータ!$C:$C,">="&届出事由・区分・届出年月日ごと集計!F$1,SQLデータ!$C:$C,"<="&届出事由・区分・届出年月日ごと集計!F$2) -> 0 | G41: =COUNTIFS(SQLデータ!$D:$D,"扶養",SQLデータ!$P:$P,1,SQLデータ!$H:$H,届出事由・区分・届出年月日ごと集計!$A41,SQLデータ!$G:$G,届出事由・区分・届出年月日ごと集計!$B41,SQLデータ!$N:$N,1,SQLデータ!$F:$F,"",SQLデータ!$C:$C,">="&届出事由・区分・届出年月日ごと集計!G$1,SQLデータ!$C:$C,"<="&届出事由・区分・届出年月日ごと集計!G$2) -> 0 | H41: =COUNTIFS(SQLデータ!$D:$D,"扶養",SQLデータ!$P:$P,1,SQLデータ!$H:$H,届出事由・区分・届出年月日ごと集計!$A41,SQLデータ!$G:$G,届出事由・区分・届出年月日ごと集計!$B41,SQLデータ!$N:$N,1,SQLデータ!$F:$F,"",SQLデータ!$C:$C,">="&届出事由・区分・届出年月日ごと集計!H$1,SQLデータ!$C:$C,"<="&届出事由・区分・届出年月日ごと集計!H$2) -> 0 | I41: =COUNTIFS(SQLデータ!$D:$D,"扶養",SQLデータ!$P:$P,1,SQLデータ!$H:$H,届出事由・区分・届出年月日ごと集計!$A41,SQLデータ!$G:$G,届出事由・区分・届出年月日ごと集計!$B41,SQLデータ!$N:$N,1,SQLデータ!$F:$F,"",SQLデータ!$C:$C,">="&届出事由・区分・届出年月日ごと集計!I$1,SQLデータ!$C:$C,"<="&届出事由・区分・届出年月日ごと集計!I$2) -> 0 | J41: =COUNTIFS(SQLデータ!$D:$D,"扶養",SQLデータ!$P:$P,1,SQLデータ!$H:$H,届出事由・区分・届出年月日ごと集計!$A41,SQLデータ!$G:$G,届出事由・区分・届出年月日ごと集計!$B41,SQLデータ!$N:$N,1,SQLデータ!$F:$F,"",SQLデータ!$C:$C,">="&届出事由・区分・届出年月日ごと集計!J$1,SQLデータ!$C:$C,"<="&届出事由・区分・届出年月日ごと集計!J$2) -> 0 | K41: =COUNTIFS(SQLデータ!$D:$D,"扶養",SQLデータ!$P:$P,1,SQLデータ!$H:$H,届出事由・区分・届出年月日ごと集計!$A41,SQLデータ!$G:$G,届出事由・区分・届出年月日ごと集計!$B41,SQLデータ!$N:$N,1,SQLデータ!$F:$F,"",SQLデータ!$C:$C,">="&届出事由・区分・届出年月日ごと集計!K$1,SQLデータ!$C:$C,"<="&届出事由・区分・届出年月日ごと集計!K$2) -> 0 | L41: =COUNTIFS(SQLデータ!$D:$D,"扶養",SQLデータ!$P:$P,1,SQLデータ!$H:$H,届出事由・区分・届出年月日ごと集計!$A41,SQLデータ!$G:$G,届出事由・区分・届出年月日ごと集計!$B41,SQLデータ!$N:$N,1,SQLデータ!$F:$F,"",SQLデータ!$C:$C,">="&届出事由・区分・届出年月日ごと集計!L$1,SQLデータ!$C:$C,"<="&届出事由・区分・届出年月日ごと集計!L$2) -> 0 | M41: =COUNTIFS(SQLデータ!$D:$D,"扶養",SQLデータ!$P:$P,1,SQLデータ!$H:$H,届出事由・区分・届出年月日ごと集計!$A41,SQLデータ!$G:$G,届出事由・区分・届出年月日ごと集計!$B41,SQLデータ!$N:$N,1,SQLデータ!$F:$F,"",SQLデータ!$C:$C,">="&届出事由・区分・届出年月日ごと集計!M$1,SQLデータ!$C:$C,"<="&届出事由・区分・届出年月日ごと集計!M$2) -> 0 | ... T41: =COUNTIFS(SQLデータ!$D:$D,"扶養",SQLデータ!$P:$P,1,SQLデータ!$H:$H,届出事由・区分・届出年月日ごと集計!$A41,SQLデータ!$G:$G,届出事由・区分・届出年月日ごと集計!$B41,SQLデータ!$N:$N,1,SQLデータ!$F:$F,"",SQLデータ!$C:$C,">="&届出事由・区分・届出年月日ごと集計!T$1,SQLデータ!$C:$C,"<="&届出事由・区分・届出年月日ごと集計!T$2) -> 0
A42: 増 | B42: 扶養親族の同別居変更 | C42: 本人税のみ | D42: =COUNTIFS(SQLデータ!$D:$D,"扶養",SQLデータ!$H:$H,届出事由・区分・届出年月日ごと集計!$A42,SQLデータ!$G:$G,届出事由・区分・届出年月日ごと集計!$B42,SQLデータ!$O:$O,1) -> 0 | F42: =COUNTIFS(SQLデータ!$D:$D,"扶養",SQLデータ!$P:$P,1,SQLデータ!$H:$H,届出事由・区分・届出年月日ごと集計!$A42,SQLデータ!$G:$G,届出事由・区分・届出年月日ごと集計!$B42,SQLデータ!$O:$O,1,SQLデータ!$F:$F,"",SQLデータ!$C:$C,">="&届出事由・区分・届出年月日ごと集計!F$1,SQLデータ!$C:$C,"<="&届出事由・区分・届出年月日ごと集計!F$2) -> 0 | G42: =COUNTIFS(SQLデータ!$D:$D,"扶養",SQLデータ!$P:$P,1,SQLデータ!$H:$H,届出事由・区分・届出年月日ごと集計!$A42,SQLデータ!$G:$G,届出事由・区分・届出年月日ごと集計!$B42,SQLデータ!$O:$O,1,SQLデータ!$F:$F,"",SQLデータ!$C:$C,">="&届出事由・区分・届出年月日ごと集計!G$1,SQLデータ!$C:$C,"<="&届出事由・区分・届出年月日ごと集計!G$2) -> 0 | H42: =COUNTIFS(SQLデータ!$D:$D,"扶養",SQLデータ!$P:$P,1,SQLデータ!$H:$H,届出事由・区分・届出年月日ごと集計!$A42,SQLデータ!$G:$G,届出事由・区分・届出年月日ごと集計!$B42,SQLデータ!$O:$O,1,SQLデータ!$F:$F,"",SQLデータ!$C:$C,">="&届出事由・区分・届出年月日ごと集計!H$1,SQLデータ!$C:$C,"<="&届出事由・区分・届出年月日ごと集計!H$2) -> 0 | I42: =COUNTIFS(SQLデータ!$D:$D,"扶養",SQLデータ!$P:$P,1,SQLデータ!$H:$H,届出事由・区分・届出年月日ごと集計!$A42,SQLデータ!$G:$G,届出事由・区分・届出年月日ごと集計!$B42,SQLデータ!$O:$O,1,SQLデータ!$F:$F,"",SQLデータ!$C:$C,">="&届出事由・区分・届出年月日ごと集計!I$1,SQLデータ!$C:$C,"<="&届出事由・区分・届出年月日ごと集計!I$2) -> 0 | J42: =COUNTIFS(SQLデータ!$D:$D,"扶養",SQLデータ!$P:$P,1,SQLデータ!$H:$H,届出事由・区分・届出年月日ごと集計!$A42,SQLデータ!$G:$G,届出事由・区分・届出年月日ごと集計!$B42,SQLデータ!$O:$O,1,SQLデータ!$F:$F,"",SQLデータ!$C:$C,">="&届出事由・区分・届出年月日ごと集計!J$1,SQLデータ!$C:$C,"<="&届出事由・区分・届出年月日ごと集計!J$2) -> 0 | K42: =COUNTIFS(SQLデータ!$D:$D,"扶養",SQLデータ!$P:$P,1,SQLデータ!$H:$H,届出事由・区分・届出年月日ごと集計!$A42,SQLデータ!$G:$G,届出事由・区分・届出年月日ごと集計!$B42,SQLデータ!$O:$O,1,SQLデータ!$F:$F,"",SQLデータ!$C:$C,">="&届出事由・区分・届出年月日ごと集計!K$1,SQLデータ!$C:$C,"<="&届出事由・区分・届出年月日ごと集計!K$2) -> 0 | L42: =COUNTIFS(SQLデータ!$D:$D,"扶養",SQLデータ!$P:$P,1,SQLデータ!$H:$H,届出事由・区分・届出年月日ごと集計!$A42,SQLデータ!$G:$G,届出事由・区分・届出年月日ごと集計!$B42,SQLデータ!$O:$O,1,SQLデータ!$F:$F,"",SQLデータ!$C:$C,">="&届出事由・区分・届出年月日ごと集計!L$1,SQLデータ!$C:$C,"<="&届出事由・区分・届出年月日ごと集計!L$2) -> 0 | M42: =COUNTIFS(SQLデータ!$D:$D,"扶養",SQLデータ!$P:$P,1,SQLデータ!$H:$H,届出事由・区分・届出年月日ごと集計!$A42,SQLデータ!$G:$G,届出事由・区分・届出年月日ごと集計!$B42,SQLデータ!$O:$O,1,SQLデータ!$F:$F,"",SQLデータ!$C:$C,">="&届出事由・区分・届出年月日ごと集計!M$1,SQLデータ!$C:$C,"<="&届出事由・区分・届出年月日ごと集計!M$2) -> 0 | ... T42: =COUNTIFS(SQLデータ!$D:$D,"扶養",SQLデータ!$P:$P,1,SQLデータ!$H:$H,届出事由・区分・届出年月日ごと集計!$A42,SQLデータ!$G:$G,届出事由・区分・届出年月日ごと集計!$B42,SQLデータ!$O:$O,1,SQLデータ!$F:$F,"",SQLデータ!$C:$C,">="&届出事由・区分・届出年月日ごと集計!T$1,SQLデータ!$C:$C,"<="&届出事由・区分・届出年月日ごと集計!T$2) -> 0
A43: 増 | B43: 同居 | C43: 共済あり | D43: =COUNTIFS(SQLデータ!$D:$D,"扶養",SQLデータ!$H:$H,届出事由・区分・届出年月日ごと集計!$A43,SQLデータ!$G:$G,届出事由・区分・届出年月日ごと集計!$B43,SQLデータ!$L:$L,1) -> 1 | F43: =COUNTIFS(SQLデータ!$D:$D,"扶養",SQLデータ!$P:$P,1,SQLデータ!$H:$H,届出事由・区分・届出年月日ごと集計!$A43,SQLデータ!$G:$G,届出事由・区分・届出年月日ごと集計!$B43,SQLデータ!$L:$L,1,SQLデータ!$F:$F,"",SQLデータ!$C:$C,">="&届出事由・区分・届出年月日ごと集計!F$1,SQLデータ!$C:$C,"<="&届出事由・区分・届出年月日ごと集計!F$2) -> 0 | G43: =COUNTIFS(SQLデータ!$D:$D,"扶養",SQLデータ!$P:$P,1,SQLデータ!$H:$H,届出事由・区分・届出年月日ごと集計!$A43,SQLデータ!$G:$G,届出事由・区分・届出年月日ごと集計!$B43,SQLデータ!$L:$L,1,SQLデータ!$F:$F,"",SQLデータ!$C:$C,">="&届出事由・区分・届出年月日ごと集計!G$1,SQLデータ!$C:$C,"<="&届出事由・区分・届出年月日ごと集計!G$2) -> 0 | H43: =COUNTIFS(SQLデータ!$D:$D,"扶養",SQLデータ!$P:$P,1,SQLデータ!$H:$H,届出事由・区分・届出年月日ごと集計!$A43,SQLデータ!$G:$G,届出事由・区分・届出年月日ごと集計!$B43,SQLデータ!$L:$L,1,SQLデータ!$F:$F,"",SQLデータ!$C:$C,">="&届出事由・区分・届出年月日ごと集計!H$1,SQLデータ!$C:$C,"<="&届出事由・区分・届出年月日ごと集計!H$2) -> 0 | I43: =COUNTIFS(SQLデータ!$D:$D,"扶養",SQLデータ!$P:$P,1,SQLデータ!$H:$H,届出事由・区分・届出年月日ごと集計!$A43,SQLデータ!$G:$G,届出事由・区分・届出年月日ごと集計!$B43,SQLデータ!$L:$L,1,SQLデータ!$F:$F,"",SQLデータ!$C:$C,">="&届出事由・区分・届出年月日ごと集計!I$1,SQLデータ!$C:$C,"<="&届出事由・区分・届出年月日ごと集計!I$2) -> 0 | J43: =COUNTIFS(SQLデータ!$D:$D,"扶養",SQLデータ!$P:$P,1,SQLデータ!$H:$H,届出事由・区分・届出年月日ごと集計!$A43,SQLデータ!$G:$G,届出事由・区分・届出年月日ごと集計!$B43,SQLデータ!$L:$L,1,SQLデータ!$F:$F,"",SQLデータ!$C:$C,">="&届出事由・区分・届出年月日ごと集計!J$1,SQLデータ!$C:$C,"<="&届出事由・区分・届出年月日ごと集計!J$2) -> 0 | K43: =COUNTIFS(SQLデータ!$D:$D,"扶養",SQLデータ!$P:$P,1,SQLデータ!$H:$H,届出事由・区分・届出年月日ごと集計!$A43,SQLデータ!$G:$G,届出事由・区分・届出年月日ごと集計!$B43,SQLデータ!$L:$L,1,SQLデータ!$F:$F,"",SQLデータ!$C:$C,">="&届出事由・区分・届出年月日ごと集計!K$1,SQLデータ!$C:$C,"<="&届出事由・区分・届出年月日ごと集計!K$2) -> 0 | L43: =COUNTIFS(SQLデータ!$D:$D,"扶養",SQLデータ!$P:$P,1,SQLデータ!$H:$H,届出事由・区分・届出年月日ごと集計!$A43,SQLデータ!$G:$G,届出事由・区分・届出年月日ごと集計!$B43,SQLデータ!$L:$L,1,SQLデータ!$F:$F,"",SQLデータ!$C:$C,">="&届出事由・区分・届出年月日ごと集計!L$1,SQLデータ!$C:$C,"<="&届出事由・区分・届出年月日ごと集計!L$2) -> 0 | M43: =COUNTIFS(SQLデータ!$D:$D,"扶養",SQLデータ!$P:$P,1,SQLデータ!$H:$H,届出事由・区分・届出年月日ごと集計!$A43,SQLデータ!$G:$G,届出事由・区分・届出年月日ごと集計!$B43,SQLデータ!$L:$L,1,SQLデータ!$F:$F,"",SQLデータ!$C:$C,">="&届出事由・区分・届出年月日ごと集計!M$1,SQLデータ!$C:$C,"<="&届出事由・区分・届出年月日ごと集計!M$2) -> 0 | ... T43: =COUNTIFS(SQLデータ!$D:$D,"扶養",SQLデータ!$P:$P,1,SQLデータ!$H:$H,届出事由・区分・届出年月日ごと集計!$A43,SQLデータ!$G:$G,届出事由・区分・届出年月日ごと集計!$B43,SQLデータ!$L:$L,1,SQLデータ!$F:$F,"",SQLデータ!$C:$C,">="&届出事由・区分・届出年月日ごと集計!T$1,SQLデータ!$C:$C,"<="&届出事由・区分・届出年月日ごと集計!T$2) -> 0
A44: 増 | B44: 同居 | C44: 扶養手当あり | D44: =COUNTIFS(SQLデータ!$D:$D,"扶養",SQLデータ!$H:$H,届出事由・区分・届出年月日ごと集計!$A44,SQLデータ!$G:$G,届出事由・区分・届出年月日ごと集計!$B44,SQLデータ!$M:$M,1) -> 0 | F44: =COUNTIFS(SQLデータ!$D:$D,"扶養",SQLデータ!$P:$P,1,SQLデータ!$H:$H,届出事由・区分・届出年月日ごと集計!$A44,SQLデータ!$G:$G,届出事由・区分・届出年月日ごと集計!$B44,SQLデータ!$M:$M,1,SQLデータ!$F:$F,"",SQLデータ!$C:$C,">="&届出事由・区分・届出年月日ごと集計!F$1,SQLデータ!$C:$C,"<="&届出事由・区分・届出年月日ごと集計!F$2) -> 0 | G44: =COUNTIFS(SQLデータ!$D:$D,"扶養",SQLデータ!$P:$P,1,SQLデータ!$H:$H,届出事由・区分・届出年月日ごと集計!$A44,SQLデータ!$G:$G,届出事由・区分・届出年月日ごと集計!$B44,SQLデータ!$M:$M,1,SQLデータ!$F:$F,"",SQLデータ!$C:$C,">="&届出事由・区分・届出年月日ごと集計!G$1,SQLデータ!$C:$C,"<="&届出事由・区分・届出年月日ごと集計!G$2) -> 0 | H44: =COUNTIFS(SQLデータ!$D:$D,"扶養",SQLデータ!$P:$P,1,SQLデータ!$H:$H,届出事由・区分・届出年月日ごと集計!$A44,SQLデータ!$G:$G,届出事由・区分・届出年月日ごと集計!$B44,SQLデータ!$M:$M,1,SQLデータ!$F:$F,"",SQLデータ!$C:$C,">="&届出事由・区分・届出年月日ごと集計!H$1,SQLデータ!$C:$C,"<="&届出事由・区分・届出年月日ごと集計!H$2) -> 0 | I44: =COUNTIFS(SQLデータ!$D:$D,"扶養",SQLデータ!$P:$P,1,SQLデータ!$H:$H,届出事由・区分・届出年月日ごと集計!$A44,SQLデータ!$G:$G,届出事由・区分・届出年月日ごと集計!$B44,SQLデータ!$M:$M,1,SQLデータ!$F:$F,"",SQLデータ!$C:$C,">="&届出事由・区分・届出年月日ごと集計!I$1,SQLデータ!$C:$C,"<="&届出事由・区分・届出年月日ごと集計!I$2) -> 0 | J44: =COUNTIFS(SQLデータ!$D:$D,"扶養",SQLデータ!$P:$P,1,SQLデータ!$H:$H,届出事由・区分・届出年月日ごと集計!$A44,SQLデータ!$G:$G,届出事由・区分・届出年月日ごと集計!$B44,SQLデータ!$M:$M,1,SQLデータ!$F:$F,"",SQLデータ!$C:$C,">="&届出事由・区分・届出年月日ごと集計!J$1,SQLデータ!$C:$C,"<="&届出事由・区分・届出年月日ごと集計!J$2) -> 0 | K44: =COUNTIFS(SQLデータ!$D:$D,"扶養",SQLデータ!$P:$P,1,SQLデータ!$H:$H,届出事由・区分・届出年月日ごと集計!$A44,SQLデータ!$G:$G,届出事由・区分・届出年月日ごと集計!$B44,SQLデータ!$M:$M,1,SQLデータ!$F:$F,"",SQLデータ!$C:$C,">="&届出事由・区分・届出年月日ごと集計!K$1,SQLデータ!$C:$C,"<="&届出事由・区分・届出年月日ごと集計!K$2) -> 0 | L44: =COUNTIFS(SQLデータ!$D:$D,"扶養",SQLデータ!$P:$P,1,SQLデータ!$H:$H,届出事由・区分・届出年月日ごと集計!$A44,SQLデータ!$G:$G,届出事由・区分・届出年月日ごと集計!$B44,SQLデータ!$M:$M,1,SQLデータ!$F:$F,"",SQLデータ!$C:$C,">="&届出事由・区分・届出年月日ごと集計!L$1,SQLデータ!$C:$C,"<="&届出事由・区分・届出年月日ごと集計!L$2) -> 0 | M44: =COUNTIFS(SQLデータ!$D:$D,"扶養",SQLデータ!$P:$P,1,SQLデータ!$H:$H,届出事由・区分・届出年月日ごと集計!$A44,SQLデータ!$G:$G,届出事由・区分・届出年月日ごと集計!$B44,SQLデータ!$M:$M,1,SQLデータ!$F:$F,"",SQLデータ!$C:$C,">="&届出事由・区分・届出年月日ごと集計!M$1,SQLデータ!$C:$C,"<="&届出事由・区分・届出年月日ごと集計!M$2) -> 0 | ... T44: =COUNTIFS(SQLデータ!$D:$D,"扶養",SQLデータ!$P:$P,1,SQLデータ!$H:$H,届出事由・区分・届出年月日ごと集計!$A44,SQLデータ!$G:$G,届出事由・区分・届出年月日ごと集計!$B44,SQLデータ!$M:$M,1,SQLデータ!$F:$F,"",SQLデータ!$C:$C,">="&届出事由・区分・届出年月日ごと集計!T$1,SQLデータ!$C:$C,"<="&届出事由・区分・届出年月日ごと集計!T$2) -> 0
A45: 増 | B45: 同居 | C45: 税控除のみ | D45: =COUNTIFS(SQLデータ!$D:$D,"扶養",SQLデータ!$H:$H,届出事由・区分・届出年月日ごと集計!$A45,SQLデータ!$G:$G,届出事由・区分・届出年月日ごと集計!$B45,SQLデータ!$N:$N,1) -> 0 | F45: =COUNTIFS(SQLデータ!$D:$D,"扶養",SQLデータ!$P:$P,1,SQLデータ!$H:$H,届出事由・区分・届出年月日ごと集計!$A45,SQLデータ!$G:$G,届出事由・区分・届出年月日ごと集計!$B45,SQLデータ!$N:$N,1,SQLデータ!$F:$F,"",SQLデータ!$C:$C,">="&届出事由・区分・届出年月日ごと集計!F$1,SQLデータ!$C:$C,"<="&届出事由・区分・届出年月日ごと集計!F$2) -> 0 | G45: =COUNTIFS(SQLデータ!$D:$D,"扶養",SQLデータ!$P:$P,1,SQLデータ!$H:$H,届出事由・区分・届出年月日ごと集計!$A45,SQLデータ!$G:$G,届出事由・区分・届出年月日ごと集計!$B45,SQLデータ!$N:$N,1,SQLデータ!$F:$F,"",SQLデータ!$C:$C,">="&届出事由・区分・届出年月日ごと集計!G$1,SQLデータ!$C:$C,"<="&届出事由・区分・届出年月日ごと集計!G$2) -> 0 | H45: =COUNTIFS(SQLデータ!$D:$D,"扶養",SQLデータ!$P:$P,1,SQLデータ!$H:$H,届出事由・区分・届出年月日ごと集計!$A45,SQLデータ!$G:$G,届出事由・区分・届出年月日ごと集計!$B45,SQLデータ!$N:$N,1,SQLデータ!$F:$F,"",SQLデータ!$C:$C,">="&届出事由・区分・届出年月日ごと集計!H$1,SQLデータ!$C:$C,"<="&届出事由・区分・届出年月日ごと集計!H$2) -> 0 | I45: =COUNTIFS(SQLデータ!$D:$D,"扶養",SQLデータ!$P:$P,1,SQLデータ!$H:$H,届出事由・区分・届出年月日ごと集計!$A45,SQLデータ!$G:$G,届出事由・区分・届出年月日ごと集計!$B45,SQLデータ!$N:$N,1,SQLデータ!$F:$F,"",SQLデータ!$C:$C,">="&届出事由・区分・届出年月日ごと集計!I$1,SQLデータ!$C:$C,"<="&届出事由・区分・届出年月日ごと集計!I$2) -> 0 | J45: =COUNTIFS(SQLデータ!$D:$D,"扶養",SQLデータ!$P:$P,1,SQLデータ!$H:$H,届出事由・区分・届出年月日ごと集計!$A45,SQLデータ!$G:$G,届出事由・区分・届出年月日ごと集計!$B45,SQLデータ!$N:$N,1,SQLデータ!$F:$F,"",SQLデータ!$C:$C,">="&届出事由・区分・届出年月日ごと集計!J$1,SQLデータ!$C:$C,"<="&届出事由・区分・届出年月日ごと集計!J$2) -> 0 | K45: =COUNTIFS(SQLデータ!$D:$D,"扶養",SQLデータ!$P:$P,1,SQLデータ!$H:$H,届出事由・区分・届出年月日ごと集計!$A45,SQLデータ!$G:$G,届出事由・区分・届出年月日ごと集計!$B45,SQLデータ!$N:$N,1,SQLデータ!$F:$F,"",SQLデータ!$C:$C,">="&届出事由・区分・届出年月日ごと集計!K$1,SQLデータ!$C:$C,"<="&届出事由・区分・届出年月日ごと集計!K$2) -> 0 | L45: =COUNTIFS(SQLデータ!$D:$D,"扶養",SQLデータ!$P:$P,1,SQLデータ!$H:$H,届出事由・区分・届出年月日ごと集計!$A45,SQLデータ!$G:$G,届出事由・区分・届出年月日ごと集計!$B45,SQLデータ!$N:$N,1,SQLデータ!$F:$F,"",SQLデータ!$C:$C,">="&届出事由・区分・届出年月日ごと集計!L$1,SQLデータ!$C:$C,"<="&届出事由・区分・届出年月日ごと集計!L$2) -> 0 | M45: =COUNTIFS(SQLデータ!$D:$D,"扶養",SQLデータ!$P:$P,1,SQLデータ!$H:$H,届出事由・区分・届出年月日ごと集計!$A45,SQLデータ!$G:$G,届出事由・区分・届出年月日ごと集計!$B45,SQLデータ!$N:$N,1,SQLデータ!$F:$F,"",SQLデータ!$C:$C,">="&届出事由・区分・届出年月日ごと集計!M$1,SQLデータ!$C:$C,"<="&届出事由・区分・届出年月日ごと集計!M$2) -> 0 | ... T45: =COUNTIFS(SQLデータ!$D:$D,"扶養",SQLデータ!$P:$P,1,SQLデータ!$H:$H,届出事由・区分・届出年月日ごと集計!$A45,SQLデータ!$G:$G,届出事由・区分・届出年月日ごと集計!$B45,SQLデータ!$N:$N,1,SQLデータ!$F:$F,"",SQLデータ!$C:$C,">="&届出事由・区分・届出年月日ごと集計!T$1,SQLデータ!$C:$C,"<="&届出事由・区分・届出年月日ごと集計!T$2) -> 0
A46: 増 | B46: 同居 | C46: 本人税のみ | D46: =COUNTIFS(SQLデータ!$D:$D,"扶養",SQLデータ!$H:$H,届出事由・区分・届出年月日ごと集計!$A46,SQLデータ!$G:$G,届出事由・区分・届出年月日ごと集計!$B46,SQLデータ!$O:$O,1) -> 0 | F46: =COUNTIFS(SQLデータ!$D:$D,"扶養",SQLデータ!$P:$P,1,SQLデータ!$H:$H,届出事由・区分・届出年月日ごと集計!$A46,SQLデータ!$G:$G,届出事由・区分・届出年月日ごと集計!$B46,SQLデータ!$O:$O,1,SQLデータ!$F:$F,"",SQLデータ!$C:$C,">="&届出事由・区分・届出年月日ごと集計!F$1,SQLデータ!$C:$C,"<="&届出事由・区分・届出年月日ごと集計!F$2) -> 0 | G46: =COUNTIFS(SQLデータ!$D:$D,"扶養",SQLデータ!$P:$P,1,SQLデータ!$H:$H,届出事由・区分・届出年月日ごと集計!$A46,SQLデータ!$G:$G,届出事由・区分・届出年月日ごと集計!$B46,SQLデータ!$O:$O,1,SQLデータ!$F:$F,"",SQLデータ!$C:$C,">="&届出事由・区分・届出年月日ごと集計!G$1,SQLデータ!$C:$C,"<="&届出事由・区分・届出年月日ごと集計!G$2) -> 0 | H46: =COUNTIFS(SQLデータ!$D:$D,"扶養",SQLデータ!$P:$P,1,SQLデータ!$H:$H,届出事由・区分・届出年月日ごと集計!$A46,SQLデータ!$G:$G,届出事由・区分・届出年月日ごと集計!$B46,SQLデータ!$O:$O,1,SQLデータ!$F:$F,"",SQLデータ!$C:$C,">="&届出事由・区分・届出年月日ごと集計!H$1,SQLデータ!$C:$C,"<="&届出事由・区分・届出年月日ごと集計!H$2) -> 0 | I46: =COUNTIFS(SQLデータ!$D:$D,"扶養",SQLデータ!$P:$P,1,SQLデータ!$H:$H,届出事由・区分・届出年月日ごと集計!$A46,SQLデータ!$G:$G,届出事由・区分・届出年月日ごと集計!$B46,SQLデータ!$O:$O,1,SQLデータ!$F:$F,"",SQLデータ!$C:$C,">="&届出事由・区分・届出年月日ごと集計!I$1,SQLデータ!$C:$C,"<="&届出事由・区分・届出年月日ごと集計!I$2) -> 0 | J46: =COUNTIFS(SQLデータ!$D:$D,"扶養",SQLデータ!$P:$P,1,SQLデータ!$H:$H,届出事由・区分・届出年月日ごと集計!$A46,SQLデータ!$G:$G,届出事由・区分・届出年月日ごと集計!$B46,SQLデータ!$O:$O,1,SQLデータ!$F:$F,"",SQLデータ!$C:$C,">="&届出事由・区分・届出年月日ごと集計!J$1,SQLデータ!$C:$C,"<="&届出事由・区分・届出年月日ごと集計!J$2) -> 0 | K46: =COUNTIFS(SQLデータ!$D:$D,"扶養",SQLデータ!$P:$P,1,SQLデータ!$H:$H,届出事由・区分・届出年月日ごと集計!$A46,SQLデータ!$G:$G,届出事由・区分・届出年月日ごと集計!$B46,SQLデータ!$O:$O,1,SQLデータ!$F:$F,"",SQLデータ!$C:$C,">="&届出事由・区分・届出年月日ごと集計!K$1,SQLデータ!$C:$C,"<="&届出事由・区分・届出年月日ごと集計!K$2) -> 0 | L46: =COUNTIFS(SQLデータ!$D:$D,"扶養",SQLデータ!$P:$P,1,SQLデータ!$H:$H,届出事由・区分・届出年月日ごと集計!$A46,SQLデータ!$G:$G,届出事由・区分・届出年月日ごと集計!$B46,SQLデータ!$O:$O,1,SQLデータ!$F:$F,"",SQLデータ!$C:$C,">="&届出事由・区分・届出年月日ごと集計!L$1,SQLデータ!$C:$C,"<="&届出事由・区分・届出年月日ごと集計!L$2) -> 0 | M46: =COUNTIFS(SQLデータ!$D:$D,"扶養",SQLデータ!$P:$P,1,SQLデータ!$H:$H,届出事由・区分・届出年月日ごと集計!$A46,SQLデータ!$G:$G,届出事由・区分・届出年月日ごと集計!$B46,SQLデータ!$O:$O,1,SQLデータ!$F:$F,"",SQLデータ!$C:$C,">="&届出事由・区分・届出年月日ごと集計!M$1,SQLデータ!$C:$C,"<="&届出事由・区分・届出年月日ごと集計!M$2) -> 0 | ... T46: =COUNTIFS(SQLデータ!$D:$D,"扶養",SQLデータ!$P:$P,1,SQLデータ!$H:$H,届出事由・区分・届出年月日ごと集計!$A46,SQLデータ!$G:$G,届出事由・区分・届出年月日ごと集計!$B46,SQLデータ!$O:$O,1,SQLデータ!$F:$F,"",SQLデータ!$C:$C,">="&届出事由・区分・届出年月日ごと集計!T$1,SQLデータ!$C:$C,"<="&届出事由・区分・届出年月日ごと集計!T$2) -> 0
A47: 増 | B47: 扶養親族の離婚 | C47: 共済あり | D47: =COUNTIFS(SQLデータ!$D:$D,"扶養",SQLデータ!$H:$H,届出事由・区分・届出年月日ごと集計!$A47,SQLデータ!$G:$G,届出事由・区分・届出年月日ごと集計!$B47,SQLデータ!$L:$L,1) -> 1 | F47: =COUNTIFS(SQLデータ!$D:$D,"扶養",SQLデータ!$P:$P,1,SQLデータ!$H:$H,届出事由・区分・届出年月日ごと集計!$A47,SQLデータ!$G:$G,届出事由・区分・届出年月日ごと集計!$B47,SQLデータ!$L:$L,1,SQLデータ!$F:$F,"",SQLデータ!$C:$C,">="&届出事由・区分・届出年月日ごと集計!F$1,SQLデータ!$C:$C,"<="&届出事由・区分・届出年月日ごと集計!F$2) -> 0 | G47: =COUNTIFS(SQLデータ!$D:$D,"扶養",SQLデータ!$P:$P,1,SQLデータ!$H:$H,届出事由・区分・届出年月日ごと集計!$A47,SQLデータ!$G:$G,届出事由・区分・届出年月日ごと集計!$B47,SQLデータ!$L:$L,1,SQLデータ!$F:$F,"",SQLデータ!$C:$C,">="&届出事由・区分・届出年月日ごと集計!G$1,SQLデータ!$C:$C,"<="&届出事由・区分・届出年月日ごと集計!G$2) -> 0 | H47: =COUNTIFS(SQLデータ!$D:$D,"扶養",SQLデータ!$P:$P,1,SQLデータ!$H:$H,届出事由・区分・届出年月日ごと集計!$A47,SQLデータ!$G:$G,届出事由・区分・届出年月日ごと集計!$B47,SQLデータ!$L:$L,1,SQLデータ!$F:$F,"",SQLデータ!$C:$C,">="&届出事由・区分・届出年月日ごと集計!H$1,SQLデータ!$C:$C,"<="&届出事由・区分・届出年月日ごと集計!H$2) -> 0 | I47: =COUNTIFS(SQLデータ!$D:$D,"扶養",SQLデータ!$P:$P,1,SQLデータ!$H:$H,届出事由・区分・届出年月日ごと集計!$A47,SQLデータ!$G:$G,届出事由・区分・届出年月日ごと集計!$B47,SQLデータ!$L:$L,1,SQLデータ!$F:$F,"",SQLデータ!$C:$C,">="&届出事由・区分・届出年月日ごと集計!I$1,SQLデータ!$C:$C,"<="&届出事由・区分・届出年月日ごと集計!I$2) -> 0 | J47: =COUNTIFS(SQLデータ!$D:$D,"扶養",SQLデータ!$P:$P,1,SQLデータ!$H:$H,届出事由・区分・届出年月日ごと集計!$A47,SQLデータ!$G:$G,届出事由・区分・届出年月日ごと集計!$B47,SQLデータ!$L:$L,1,SQLデータ!$F:$F,"",SQLデータ!$C:$C,">="&届出事由・区分・届出年月日ごと集計!J$1,SQLデータ!$C:$C,"<="&届出事由・区分・届出年月日ごと集計!J$2) -> 0 | K47: =COUNTIFS(SQLデータ!$D:$D,"扶養",SQLデータ!$P:$P,1,SQLデータ!$H:$H,届出事由・区分・届出年月日ごと集計!$A47,SQLデータ!$G:$G,届出事由・区分・届出年月日ごと集計!$B47,SQLデータ!$L:$L,1,SQLデータ!$F:$F,"",SQLデータ!$C:$C,">="&届出事由・区分・届出年月日ごと集計!K$1,SQLデータ!$C:$C,"<="&届出事由・区分・届出年月日ごと集計!K$2) -> 0 | L47: =COUNTIFS(SQLデータ!$D:$D,"扶養",SQLデータ!$P:$P,1,SQLデータ!$H:$H,届出事由・区分・届出年月日ごと集計!$A47,SQLデータ!$G:$G,届出事由・区分・届出年月日ごと集計!$B47,SQLデータ!$L:$L,1,SQLデータ!$F:$F,"",SQLデータ!$C:$C,">="&届出事由・区分・届出年月日ごと集計!L$1,SQLデータ!$C:$C,"<="&届出事由・区分・届出年月日ごと集計!L$2) -> 0 | M47: =COUNTIFS(SQLデータ!$D:$D,"扶養",SQLデータ!$P:$P,1,SQLデータ!$H:$H,届出事由・区分・届出年月日ごと集計!$A47,SQLデータ!$G:$G,届出事由・区分・届出年月日ごと集計!$B47,SQLデータ!$L:$L,1,SQLデータ!$F:$F,"",SQLデータ!$C:$C,">="&届出事由・区分・届出年月日ごと集計!M$1,SQLデータ!$C:$C,"<="&届出事由・区分・届出年月日ごと集計!M$2) -> 0 | ... T47: =COUNTIFS(SQLデータ!$D:$D,"扶養",SQLデータ!$P:$P,1,SQLデータ!$H:$H,届出事由・区分・届出年月日ごと集計!$A47,SQLデータ!$G:$G,届出事由・区分・届出年月日ごと集計!$B47,SQLデータ!$L:$L,1,SQLデータ!$F:$F,"",SQLデータ!$C:$C,">="&届出事由・区分・届出年月日ごと集計!T$1,SQLデータ!$C:$C,"<="&届出事由・区分・届出年月日ごと集計!T$2) -> 0
A48: 増 | B48: 扶養親族の離婚 | C48: 扶養手当あり | D48: =COUNTIFS(SQLデータ!$D:$D,"扶養",SQLデータ!$H:$H,届出事由・区分・届出年月日ごと集計!$A48,SQLデータ!$G:$G,届出事由・区分・届出年月日ごと集計!$B48,SQLデータ!$M:$M,1) -> 0 | F48: =COUNTIFS(SQLデータ!$D:$D,"扶養",SQLデータ!$P:$P,1,SQLデータ!$H:$H,届出事由・区分・届出年月日ごと集計!$A48,SQLデータ!$G:$G,届出事由・区分・届出年月日ごと集計!$B48,SQLデータ!$M:$M,1,SQLデータ!$F:$F,"",SQLデータ!$C:$C,">="&届出事由・区分・届出年月日ごと集計!F$1,SQLデータ!$C:$C,"<="&届出事由・区分・届出年月日ごと集計!F$2) -> 0 | G48: =COUNTIFS(SQLデータ!$D:$D,"扶養",SQLデータ!$P:$P,1,SQLデータ!$H:$H,届出事由・区分・届出年月日ごと集計!$A48,SQLデータ!$G:$G,届出事由・区分・届出年月日ごと集計!$B48,SQLデータ!$M:$M,1,SQLデータ!$F:$F,"",SQLデータ!$C:$C,">="&届出事由・区分・届出年月日ごと集計!G$1,SQLデータ!$C:$C,"<="&届出事由・区分・届出年月日ごと集計!G$2) -> 0 | H48: =COUNTIFS(SQLデータ!$D:$D,"扶養",SQLデータ!$P:$P,1,SQLデータ!$H:$H,届出事由・区分・届出年月日ごと集計!$A48,SQLデータ!$G:$G,届出事由・区分・届出年月日ごと集計!$B48,SQLデータ!$M:$M,1,SQLデータ!$F:$F,"",SQLデータ!$C:$C,">="&届出事由・区分・届出年月日ごと集計!H$1,SQLデータ!$C:$C,"<="&届出事由・区分・届出年月日ごと集計!H$2) -> 0 | I48: =COUNTIFS(SQLデータ!$D:$D,"扶養",SQLデータ!$P:$P,1,SQLデータ!$H:$H,届出事由・区分・届出年月日ごと集計!$A48,SQLデータ!$G:$G,届出事由・区分・届出年月日ごと集計!$B48,SQLデータ!$M:$M,1,SQLデータ!$F:$F,"",SQLデータ!$C:$C,">="&届出事由・区分・届出年月日ごと集計!I$1,SQLデータ!$C:$C,"<="&届出事由・区分・届出年月日ごと集計!I$2) -> 0 | J48: =COUNTIFS(SQLデータ!$D:$D,"扶養",SQLデータ!$P:$P,1,SQLデータ!$H:$H,届出事由・区分・届出年月日ごと集計!$A48,SQLデータ!$G:$G,届出事由・区分・届出年月日ごと集計!$B48,SQLデータ!$M:$M,1,SQLデータ!$F:$F,"",SQLデータ!$C:$C,">="&届出事由・区分・届出年月日ごと集計!J$1,SQLデータ!$C:$C,"<="&届出事由・区分・届出年月日ごと集計!J$2) -> 0 | K48: =COUNTIFS(SQLデータ!$D:$D,"扶養",SQLデータ!$P:$P,1,SQLデータ!$H:$H,届出事由・区分・届出年月日ごと集計!$A48,SQLデータ!$G:$G,届出事由・区分・届出年月日ごと集計!$B48,SQLデータ!$M:$M,1,SQLデータ!$F:$F,"",SQLデータ!$C:$C,">="&届出事由・区分・届出年月日ごと集計!K$1,SQLデータ!$C:$C,"<="&届出事由・区分・届出年月日ごと集計!K$2) -> 0 | L48: =COUNTIFS(SQLデータ!$D:$D,"扶養",SQLデータ!$P:$P,1,SQLデータ!$H:$H,届出事由・区分・届出年月日ごと集計!$A48,SQLデータ!$G:$G,届出事由・区分・届出年月日ごと集計!$B48,SQLデータ!$M:$M,1,SQLデータ!$F:$F,"",SQLデータ!$C:$C,">="&届出事由・区分・届出年月日ごと集計!L$1,SQLデータ!$C:$C,"<="&届出事由・区分・届出年月日ごと集計!L$2) -> 0 | M48: =COUNTIFS(SQLデータ!$D:$D,"扶養",SQLデータ!$P:$P,1,SQLデータ!$H:$H,届出事由・区分・届出年月日ごと集計!$A48,SQLデータ!$G:$G,届出事由・区分・届出年月日ごと集計!$B48,SQLデータ!$M:$M,1,SQLデータ!$F:$F,"",SQLデータ!$C:$C,">="&届出事由・区分・届出年月日ごと集計!M$1,SQLデータ!$C:$C,"<="&届出事由・区分・届出年月日ごと集計!M$2) -> 0 | ... T48: =COUNTIFS(SQLデータ!$D:$D,"扶養",SQLデータ!$P:$P,1,SQLデータ!$H:$H,届出事由・区分・届出年月日ごと集計!$A48,SQLデータ!$G:$G,届出事由・区分・届出年月日ごと集計!$B48,SQLデータ!$M:$M,1,SQLデータ!$F:$F,"",SQLデータ!$C:$C,">="&届出事由・区分・届出年月日ごと集計!T$1,SQLデータ!$C:$C,"<="&届出事由・区分・届出年月日ごと集計!T$2) -> 0
A49: 増 | B49: 扶養親族の離婚 | C49: 税控除のみ | D49: =COUNTIFS(SQLデータ!$D:$D,"扶養",SQLデータ!$H:$H,届出事由・区分・届出年月日ごと集計!$A49,SQLデータ!$G:$G,届出事由・区分・届出年月日ごと集計!$B49,SQLデータ!$N:$N,1) -> 0 | F49: =COUNTIFS(SQLデータ!$D:$D,"扶養",SQLデータ!$P:$P,1,SQLデータ!$H:$H,届出事由・区分・届出年月日ごと集計!$A49,SQLデータ!$G:$G,届出事由・区分・届出年月日ごと集計!$B49,SQLデータ!$N:$N,1,SQLデータ!$F:$F,"",SQLデータ!$C:$C,">="&届出事由・区分・届出年月日ごと集計!F$1,SQLデータ!$C:$C,"<="&届出事由・区分・届出年月日ごと集計!F$2) -> 0 | G49: =COUNTIFS(SQLデータ!$D:$D,"扶養",SQLデータ!$P:$P,1,SQLデータ!$H:$H,届出事由・区分・届出年月日ごと集計!$A49,SQLデータ!$G:$G,届出事由・区分・届出年月日ごと集計!$B49,SQLデータ!$N:$N,1,SQLデータ!$F:$F,"",SQLデータ!$C:$C,">="&届出事由・区分・届出年月日ごと集計!G$1,SQLデータ!$C:$C,"<="&届出事由・区分・届出年月日ごと集計!G$2) -> 0 | H49: =COUNTIFS(SQLデータ!$D:$D,"扶養",SQLデータ!$P:$P,1,SQLデータ!$H:$H,届出事由・区分・届出年月日ごと集計!$A49,SQLデータ!$G:$G,届出事由・区分・届出年月日ごと集計!$B49,SQLデータ!$N:$N,1,SQLデータ!$F:$F,"",SQLデータ!$C:$C,">="&届出事由・区分・届出年月日ごと集計!H$1,SQLデータ!$C:$C,"<="&届出事由・区分・届出年月日ごと集計!H$2) -> 0 | I49: =COUNTIFS(SQLデータ!$D:$D,"扶養",SQLデータ!$P:$P,1,SQLデータ!$H:$H,届出事由・区分・届出年月日ごと集計!$A49,SQLデータ!$G:$G,届出事由・区分・届出年月日ごと集計!$B49,SQLデータ!$N:$N,1,SQLデータ!$F:$F,"",SQLデータ!$C:$C,">="&届出事由・区分・届出年月日ごと集計!I$1,SQLデータ!$C:$C,"<="&届出事由・区分・届出年月日ごと集計!I$2) -> 0 | J49: =COUNTIFS(SQLデータ!$D:$D,"扶養",SQLデータ!$P:$P,1,SQLデータ!$H:$H,届出事由・区分・届出年月日ごと集計!$A49,SQLデータ!$G:$G,届出事由・区分・届出年月日ごと集計!$B49,SQLデータ!$N:$N,1,SQLデータ!$F:$F,"",SQLデータ!$C:$C,">="&届出事由・区分・届出年月日ごと集計!J$1,SQLデータ!$C:$C,"<="&届出事由・区分・届出年月日ごと集計!J$2) -> 0 | K49: =COUNTIFS(SQLデータ!$D:$D,"扶養",SQLデータ!$P:$P,1,SQLデータ!$H:$H,届出事由・区分・届出年月日ごと集計!$A49,SQLデータ!$G:$G,届出事由・区分・届出年月日ごと集計!$B49,SQLデータ!$N:$N,1,SQLデータ!$F:$F,"",SQLデータ!$C:$C,">="&届出事由・区分・届出年月日ごと集計!K$1,SQLデータ!$C:$C,"<="&届出事由・区分・届出年月日ごと集計!K$2) -> 0 | L49: =COUNTIFS(SQLデータ!$D:$D,"扶養",SQLデータ!$P:$P,1,SQLデータ!$H:$H,届出事由・区分・届出年月日ごと集計!$A49,SQLデータ!$G:$G,届出事由・区分・届出年月日ごと集計!$B49,SQLデータ!$N:$N,1,SQLデータ!$F:$F,"",SQLデータ!$C:$C,">="&届出事由・区分・届出年月日ごと集計!L$1,SQLデータ!$C:$C,"<="&届出事由・区分・届出年月日ごと集計!L$2) -> 0 | M49: =COUNTIFS(SQLデータ!$D:$D,"扶養",SQLデータ!$P:$P,1,SQLデータ!$H:$H,届出事由・区分・届出年月日ごと集計!$A49,SQLデータ!$G:$G,届出事由・区分・届出年月日ごと集計!$B49,SQLデータ!$N:$N,1,SQLデータ!$F:$F,"",SQLデータ!$C:$C,">="&届出事由・区分・届出年月日ごと集計!M$1,SQLデータ!$C:$C,"<="&届出事由・区分・届出年月日ごと集計!M$2) -> 0 | ... T49: =COUNTIFS(SQLデータ!$D:$D,"扶養",SQLデータ!$P:$P,1,SQLデータ!$H:$H,届出事由・区分・届出年月日ごと集計!$A49,SQLデータ!$G:$G,届出事由・区分・届出年月日ごと集計!$B49,SQLデータ!$N:$N,1,SQLデータ!$F:$F,"",SQLデータ!$C:$C,">="&届出事由・区分・届出年月日ごと集計!T$1,SQLデータ!$C:$C,"<="&届出事由・区分・届出年月日ごと集計!T$2) -> 0
A50: 増 | B50: 扶養親族の離婚 | C50: 本人税のみ | D50: =COUNTIFS(SQLデータ!$D:$D,"扶養",SQLデータ!$H:$H,届出事由・区分・届出年月日ごと集計!$A50,SQLデータ!$G:$G,届出事由・区分・届出年月日ごと集計!$B50,SQLデータ!$O:$O,1) -> 0 | F50: =COUNTIFS(SQLデータ!$D:$D,"扶養",SQLデータ!$P:$P,1,SQLデータ!$H:$H,届出事由・区分・届出年月日ごと集計!$A50,SQLデータ!$G:$G,届出事由・区分・届出年月日ごと集計!$B50,SQLデータ!$O:$O,1,SQLデータ!$F:$F,"",SQLデータ!$C:$C,">="&届出事由・区分・届出年月日ごと集計!F$1,SQLデータ!$C:$C,"<="&届出事由・区分・届出年月日ごと集計!F$2) -> 0 | G50: =COUNTIFS(SQLデータ!$D:$D,"扶養",SQLデータ!$P:$P,1,SQLデータ!$H:$H,届出事由・区分・届出年月日ごと集計!$A50,SQLデータ!$G:$G,届出事由・区分・届出年月日ごと集計!$B50,SQLデータ!$O:$O,1,SQLデータ!$F:$F,"",SQLデータ!$C:$C,">="&届出事由・区分・届出年月日ごと集計!G$1,SQLデータ!$C:$C,"<="&届出事由・区分・届出年月日ごと集計!G$2) -> 0 | H50: =COUNTIFS(SQLデータ!$D:$D,"扶養",SQLデータ!$P:$P,1,SQLデータ!$H:$H,届出事由・区分・届出年月日ごと集計!$A50,SQLデータ!$G:$G,届出事由・区分・届出年月日ごと集計!$B50,SQLデータ!$O:$O,1,SQLデータ!$F:$F,"",SQLデータ!$C:$C,">="&届出事由・区分・届出年月日ごと集計!H$1,SQLデータ!$C:$C,"<="&届出事由・区分・届出年月日ごと集計!H$2) -> 0 | I50: =COUNTIFS(SQLデータ!$D:$D,"扶養",SQLデータ!$P:$P,1,SQLデータ!$H:$H,届出事由・区分・届出年月日ごと集計!$A50,SQLデータ!$G:$G,届出事由・区分・届出年月日ごと集計!$B50,SQLデータ!$O:$O,1,SQLデータ!$F:$F,"",SQLデータ!$C:$C,">="&届出事由・区分・届出年月日ごと集計!I$1,SQLデータ!$C:$C,"<="&届出事由・区分・届出年月日ごと集計!I$2) -> 0 | J50: =COUNTIFS(SQLデータ!$D:$D,"扶養",SQLデータ!$P:$P,1,SQLデータ!$H:$H,届出事由・区分・届出年月日ごと集計!$A50,SQLデータ!$G:$G,届出事由・区分・届出年月日ごと集計!$B50,SQLデータ!$O:$O,1,SQLデータ!$F:$F,"",SQLデータ!$C:$C,">="&届出事由・区分・届出年月日ごと集計!J$1,SQLデータ!$C:$C,"<="&届出事由・区分・届出年月日ごと集計!J$2) -> 0 | K50: =COUNTIFS(SQLデータ!$D:$D,"扶養",SQLデータ!$P:$P,1,SQLデータ!$H:$H,届出事由・区分・届出年月日ごと集計!$A50,SQLデータ!$G:$G,届出事由・区分・届出年月日ごと集計!$B50,SQLデータ!$O:$O,1,SQLデータ!$F:$F,"",SQLデータ!$C:$C,">="&届出事由・区分・届出年月日ごと集計!K$1,SQLデータ!$C:$C,"<="&届出事由・区分・届出年月日ごと集計!K$2) -> 0 | L50: =COUNTIFS(SQLデータ!$D:$D,"扶養",SQLデータ!$P:$P,1,SQLデータ!$H:$H,届出事由・区分・届出年月日ごと集計!$A50,SQLデータ!$G:$G,届出事由・区分・届出年月日ごと集計!$B50,SQLデータ!$O:$O,1,SQLデータ!$F:$F,"",SQLデータ!$C:$C,">="&届出事由・区分・届出年月日ごと集計!L$1,SQLデータ!$C:$C,"<="&届出事由・区分・届出年月日ごと集計!L$2) -> 0 | M50: =COUNTIFS(SQLデータ!$D:$D,"扶養",SQLデータ!$P:$P,1,SQLデータ!$H:$H,届出事由・区分・届出年月日ごと集計!$A50,SQLデータ!$G:$G,届出事由・区分・届出年月日ごと集計!$B50,SQLデータ!$O:$O,1,SQLデータ!$F:$F,"",SQLデータ!$C:$C,">="&届出事由・区分・届出年月日ごと集計!M$1,SQLデータ!$C:$C,"<="&届出事由・区分・届出年月日ごと集計!M$2) -> 0 | ... T50: =COUNTIFS(SQLデータ!$D:$D,"扶養",SQLデータ!$P:$P,1,SQLデータ!$H:$H,届出事由・区分・届出年月日ごと集計!$A50,SQLデータ!$G:$G,届出事由・区分・届出年月日ごと集計!$B50,SQLデータ!$O:$O,1,SQLデータ!$F:$F,"",SQLデータ!$C:$C,">="&届出事由・区分・届出年月日ごと集計!T$1,SQLデータ!$C:$C,"<="&届出事由・区分・届出年月日ごと集計!T$2) -> 0
A51: 増 | B51: 事実婚 | C51: 共済あり | D51: =COUNTIFS(SQLデータ!$D:$D,"扶養",SQLデータ!$H:$H,届出事由・区分・届出年月日ごと集計!$A51,SQLデータ!$G:$G,届出事由・区分・届出年月日ごと集計!$B51,SQLデータ!$L:$L,1) -> 0 | F51: =COUNTIFS(SQLデータ!$D:$D,"扶養",SQLデータ!$P:$P,1,SQLデータ!$H:$H,届出事由・区分・届出年月日ごと集計!$A51,SQLデータ!$G:$G,届出事由・区分・届出年月日ごと集計!$B51,SQLデータ!$L:$L,1,SQLデータ!$F:$F,"",SQLデータ!$C:$C,">="&届出事由・区分・届出年月日ごと集計!F$1,SQLデータ!$C:$C,"<="&届出事由・区分・届出年月日ごと集計!F$2) -> 0 | G51: =COUNTIFS(SQLデータ!$D:$D,"扶養",SQLデータ!$P:$P,1,SQLデータ!$H:$H,届出事由・区分・届出年月日ごと集計!$A51,SQLデータ!$G:$G,届出事由・区分・届出年月日ごと集計!$B51,SQLデータ!$L:$L,1,SQLデータ!$F:$F,"",SQLデータ!$C:$C,">="&届出事由・区分・届出年月日ごと集計!G$1,SQLデータ!$C:$C,"<="&届出事由・区分・届出年月日ごと集計!G$2) -> 0 | H51: =COUNTIFS(SQLデータ!$D:$D,"扶養",SQLデータ!$P:$P,1,SQLデータ!$H:$H,届出事由・区分・届出年月日ごと集計!$A51,SQLデータ!$G:$G,届出事由・区分・届出年月日ごと集計!$B51,SQLデータ!$L:$L,1,SQLデータ!$F:$F,"",SQLデータ!$C:$C,">="&届出事由・区分・届出年月日ごと集計!H$1,SQLデータ!$C:$C,"<="&届出事由・区分・届出年月日ごと集計!H$2) -> 0 | I51: =COUNTIFS(SQLデータ!$D:$D,"扶養",SQLデータ!$P:$P,1,SQLデータ!$H:$H,届出事由・区分・届出年月日ごと集計!$A51,SQLデータ!$G:$G,届出事由・区分・届出年月日ごと集計!$B51,SQLデータ!$L:$L,1,SQLデータ!$F:$F,"",SQLデータ!$C:$C,">="&届出事由・区分・届出年月日ごと集計!I$1,SQLデータ!$C:$C,"<="&届出事由・区分・届出年月日ごと集計!I$2) -> 0 | J51: =COUNTIFS(SQLデータ!$D:$D,"扶養",SQLデータ!$P:$P,1,SQLデータ!$H:$H,届出事由・区分・届出年月日ごと集計!$A51,SQLデータ!$G:$G,届出事由・区分・届出年月日ごと集計!$B51,SQLデータ!$L:$L,1,SQLデータ!$F:$F,"",SQLデータ!$C:$C,">="&届出事由・区分・届出年月日ごと集計!J$1,SQLデータ!$C:$C,"<="&届出事由・区分・届出年月日ごと集計!J$2) -> 0 | K51: =COUNTIFS(SQLデータ!$D:$D,"扶養",SQLデータ!$P:$P,1,SQLデータ!$H:$H,届出事由・区分・届出年月日ごと集計!$A51,SQLデータ!$G:$G,届出事由・区分・届出年月日ごと集計!$B51,SQLデータ!$L:$L,1,SQLデータ!$F:$F,"",SQLデータ!$C:$C,">="&届出事由・区分・届出年月日ごと集計!K$1,SQLデータ!$C:$C,"<="&届出事由・区分・届出年月日ごと集計!K$2) -> 0 | L51: =COUNTIFS(SQLデータ!$D:$D,"扶養",SQLデータ!$P:$P,1,SQLデータ!$H:$H,届出事由・区分・届出年月日ごと集計!$A51,SQLデータ!$G:$G,届出事由・区分・届出年月日ごと集計!$B51,SQLデータ!$L:$L,1,SQLデータ!$F:$F,"",SQLデータ!$C:$C,">="&届出事由・区分・届出年月日ごと集計!L$1,SQLデータ!$C:$C,"<="&届出事由・区分・届出年月日ごと集計!L$2) -> 0 | M51: =COUNTIFS(SQLデータ!$D:$D,"扶養",SQLデータ!$P:$P,1,SQLデータ!$H:$H,届出事由・区分・届出年月日ごと集計!$A51,SQLデータ!$G:$G,届出事由・区分・届出年月日ごと集計!$B51,SQLデータ!$L:$L,1,SQLデータ!$F:$F,"",SQLデータ!$C:$C,">="&届出事由・区分・届出年月日ごと集計!M$1,SQLデータ!$C:$C,"<="&届出事由・区分・届出年月日ごと集計!M$2) -> 0 | ... T51: =COUNTIFS(SQLデータ!$D:$D,"扶養",SQLデータ!$P:$P,1,SQLデータ!$H:$H,届出事由・区分・届出年月日ごと集計!$A51,SQLデータ!$G:$G,届出事由・区分・届出年月日ごと集計!$B51,SQLデータ!$L:$L,1,SQLデータ!$F:$F,"",SQLデータ!$C:$C,">="&届出事由・区分・届出年月日ごと集計!T$1,SQLデータ!$C:$C,"<="&届出事由・区分・届出年月日ごと集計!T$2) -> 0
A52: 増 | B52: 事実婚 | C52: 扶養手当あり | D52: =COUNTIFS(SQLデータ!$D:$D,"扶養",SQLデータ!$H:$H,届出事由・区分・届出年月日ごと集計!$A52,SQLデータ!$G:$G,届出事由・区分・届出年月日ごと集計!$B52,SQLデータ!$M:$M,1) -> 0 | F52: =COUNTIFS(SQLデータ!$D:$D,"扶養",SQLデータ!$P:$P,1,SQLデータ!$H:$H,届出事由・区分・届出年月日ごと集計!$A52,SQLデータ!$G:$G,届出事由・区分・届出年月日ごと集計!$B52,SQLデータ!$M:$M,1,SQLデータ!$F:$F,"",SQLデータ!$C:$C,">="&届出事由・区分・届出年月日ごと集計!F$1,SQLデータ!$C:$C,"<="&届出事由・区分・届出年月日ごと集計!F$2) -> 0 | G52: =COUNTIFS(SQLデータ!$D:$D,"扶養",SQLデータ!$P:$P,1,SQLデータ!$H:$H,届出事由・区分・届出年月日ごと集計!$A52,SQLデータ!$G:$G,届出事由・区分・届出年月日ごと集計!$B52,SQLデータ!$M:$M,1,SQLデータ!$F:$F,"",SQLデータ!$C:$C,">="&届出事由・区分・届出年月日ごと集計!G$1,SQLデータ!$C:$C,"<="&届出事由・区分・届出年月日ごと集計!G$2) -> 0 | H52: =COUNTIFS(SQLデータ!$D:$D,"扶養",SQLデータ!$P:$P,1,SQLデータ!$H:$H,届出事由・区分・届出年月日ごと集計!$A52,SQLデータ!$G:$G,届出事由・区分・届出年月日ごと集計!$B52,SQLデータ!$M:$M,1,SQLデータ!$F:$F,"",SQLデータ!$C:$C,">="&届出事由・区分・届出年月日ごと集計!H$1,SQLデータ!$C:$C,"<="&届出事由・区分・届出年月日ごと集計!H$2) -> 0 | I52: =COUNTIFS(SQLデータ!$D:$D,"扶養",SQLデータ!$P:$P,1,SQLデータ!$H:$H,届出事由・区分・届出年月日ごと集計!$A52,SQLデータ!$G:$G,届出事由・区分・届出年月日ごと集計!$B52,SQLデータ!$M:$M,1,SQLデータ!$F:$F,"",SQLデータ!$C:$C,">="&届出事由・区分・届出年月日ごと集計!I$1,SQLデータ!$C:$C,"<="&届出事由・区分・届出年月日ごと集計!I$2) -> 0 | J52: =COUNTIFS(SQLデータ!$D:$D,"扶養",SQLデータ!$P:$P,1,SQLデータ!$H:$H,届出事由・区分・届出年月日ごと集計!$A52,SQLデータ!$G:$G,届出事由・区分・届出年月日ごと集計!$B52,SQLデータ!$M:$M,1,SQLデータ!$F:$F,"",SQLデータ!$C:$C,">="&届出事由・区分・届出年月日ごと集計!J$1,SQLデータ!$C:$C,"<="&届出事由・区分・届出年月日ごと集計!J$2) -> 0 | K52: =COUNTIFS(SQLデータ!$D:$D,"扶養",SQLデータ!$P:$P,1,SQLデータ!$H:$H,届出事由・区分・届出年月日ごと集計!$A52,SQLデータ!$G:$G,届出事由・区分・届出年月日ごと集計!$B52,SQLデータ!$M:$M,1,SQLデータ!$F:$F,"",SQLデータ!$C:$C,">="&届出事由・区分・届出年月日ごと集計!K$1,SQLデータ!$C:$C,"<="&届出事由・区分・届出年月日ごと集計!K$2) -> 0 | L52: =COUNTIFS(SQLデータ!$D:$D,"扶養",SQLデータ!$P:$P,1,SQLデータ!$H:$H,届出事由・区分・届出年月日ごと集計!$A52,SQLデータ!$G:$G,届出事由・区分・届出年月日ごと集計!$B52,SQLデータ!$M:$M,1,SQLデータ!$F:$F,"",SQLデータ!$C:$C,">="&届出事由・区分・届出年月日ごと集計!L$1,SQLデータ!$C:$C,"<="&届出事由・区分・届出年月日ごと集計!L$2) -> 0 | M52: =COUNTIFS(SQLデータ!$D:$D,"扶養",SQLデータ!$P:$P,1,SQLデータ!$H:$H,届出事由・区分・届出年月日ごと集計!$A52,SQLデータ!$G:$G,届出事由・区分・届出年月日ごと集計!$B52,SQLデータ!$M:$M,1,SQLデータ!$F:$F,"",SQLデータ!$C:$C,">="&届出事由・区分・届出年月日ごと集計!M$1,SQLデータ!$C:$C,"<="&届出事由・区分・届出年月日ごと集計!M$2) -> 0 | ... T52: =COUNTIFS(SQLデータ!$D:$D,"扶養",SQLデータ!$P:$P,1,SQLデータ!$H:$H,届出事由・区分・届出年月日ごと集計!$A52,SQLデータ!$G:$G,届出事由・区分・届出年月日ごと集計!$B52,SQLデータ!$M:$M,1,SQLデータ!$F:$F,"",SQLデータ!$C:$C,">="&届出事由・区分・届出年月日ごと集計!T$1,SQLデータ!$C:$C,"<="&届出事由・区分・届出年月日ごと集計!T$2) -> 0
A53: 増 | B53: 事実婚 | C53: 税控除のみ | D53: =COUNTIFS(SQLデータ!$D:$D,"扶養",SQLデータ!$H:$H,届出事由・区分・届出年月日ごと集計!$A53,SQLデータ!$G:$G,届出事由・区分・届出年月日ごと集計!$B53,SQLデータ!$N:$N,1) -> 0 | F53: =COUNTIFS(SQLデータ!$D:$D,"扶養",SQLデータ!$P:$P,1,SQLデータ!$H:$H,届出事由・区分・届出年月日ごと集計!$A53,SQLデータ!$G:$G,届出事由・区分・届出年月日ごと集計!$B53,SQLデータ!$N:$N,1,SQLデータ!$F:$F,"",SQLデータ!$C:$C,">="&届出事由・区分・届出年月日ごと集計!F$1,SQLデータ!$C:$C,"<="&届出事由・区分・届出年月日ごと集計!F$2) -> 0 | G53: =COUNTIFS(SQLデータ!$D:$D,"扶養",SQLデータ!$P:$P,1,SQLデータ!$H:$H,届出事由・区分・届出年月日ごと集計!$A53,SQLデータ!$G:$G,届出事由・区分・届出年月日ごと集計!$B53,SQLデータ!$N:$N,1,SQLデータ!$F:$F,"",SQLデータ!$C:$C,">="&届出事由・区分・届出年月日ごと集計!G$1,SQLデータ!$C:$C,"<="&届出事由・区分・届出年月日ごと集計!G$2) -> 0 | H53: =COUNTIFS(SQLデータ!$D:$D,"扶養",SQLデータ!$P:$P,1,SQLデータ!$H:$H,届出事由・区分・届出年月日ごと集計!$A53,SQLデータ!$G:$G,届出事由・区分・届出年月日ごと集計!$B53,SQLデータ!$N:$N,1,SQLデータ!$F:$F,"",SQLデータ!$C:$C,">="&届出事由・区分・届出年月日ごと集計!H$1,SQLデータ!$C:$C,"<="&届出事由・区分・届出年月日ごと集計!H$2) -> 0 | I53: =COUNTIFS(SQLデータ!$D:$D,"扶養",SQLデータ!$P:$P,1,SQLデータ!$H:$H,届出事由・区分・届出年月日ごと集計!$A53,SQLデータ!$G:$G,届出事由・区分・届出年月日ごと集計!$B53,SQLデータ!$N:$N,1,SQLデータ!$F:$F,"",SQLデータ!$C:$C,">="&届出事由・区分・届出年月日ごと集計!I$1,SQLデータ!$C:$C,"<="&届出事由・区分・届出年月日ごと集計!I$2) -> 0 | J53: =COUNTIFS(SQLデータ!$D:$D,"扶養",SQLデータ!$P:$P,1,SQLデータ!$H:$H,届出事由・区分・届出年月日ごと集計!$A53,SQLデータ!$G:$G,届出事由・区分・届出年月日ごと集計!$B53,SQLデータ!$N:$N,1,SQLデータ!$F:$F,"",SQLデータ!$C:$C,">="&届出事由・区分・届出年月日ごと集計!J$1,SQLデータ!$C:$C,"<="&届出事由・区分・届出年月日ごと集計!J$2) -> 0 | K53: =COUNTIFS(SQLデータ!$D:$D,"扶養",SQLデータ!$P:$P,1,SQLデータ!$H:$H,届出事由・区分・届出年月日ごと集計!$A53,SQLデータ!$G:$G,届出事由・区分・届出年月日ごと集計!$B53,SQLデータ!$N:$N,1,SQLデータ!$F:$F,"",SQLデータ!$C:$C,">="&届出事由・区分・届出年月日ごと集計!K$1,SQLデータ!$C:$C,"<="&届出事由・区分・届出年月日ごと集計!K$2) -> 0 | L53: =COUNTIFS(SQLデータ!$D:$D,"扶養",SQLデータ!$P:$P,1,SQLデータ!$H:$H,届出事由・区分・届出年月日ごと集計!$A53,SQLデータ!$G:$G,届出事由・区分・届出年月日ごと集計!$B53,SQLデータ!$N:$N,1,SQLデータ!$F:$F,"",SQLデータ!$C:$C,">="&届出事由・区分・届出年月日ごと集計!L$1,SQLデータ!$C:$C,"<="&届出事由・区分・届出年月日ごと集計!L$2) -> 0 | M53: =COUNTIFS(SQLデータ!$D:$D,"扶養",SQLデータ!$P:$P,1,SQLデータ!$H:$H,届出事由・区分・届出年月日ごと集計!$A53,SQLデータ!$G:$G,届出事由・区分・届出年月日ごと集計!$B53,SQLデータ!$N:$N,1,SQLデータ!$F:$F,"",SQLデータ!$C:$C,">="&届出事由・区分・届出年月日ごと集計!M$1,SQLデータ!$C:$C,"<="&届出事由・区分・届出年月日ごと集計!M$2) -> 0 | ... T53: =COUNTIFS(SQLデータ!$D:$D,"扶養",SQLデータ!$P:$P,1,SQLデータ!$H:$H,届出事由・区分・届出年月日ごと集計!$A53,SQLデータ!$G:$G,届出事由・区分・届出年月日ごと集計!$B53,SQLデータ!$N:$N,1,SQLデータ!$F:$F,"",SQLデータ!$C:$C,">="&届出事由・区分・届出年月日ごと集計!T$1,SQLデータ!$C:$C,"<="&届出事由・区分・届出年月日ごと集計!T$2) -> 0
A54: 増 | B54: 事実婚 | C54: 本人税のみ | D54: =COUNTIFS(SQLデータ!$D:$D,"扶養",SQLデータ!$H:$H,届出事由・区分・届出年月日ごと集計!$A54,SQLデータ!$G:$G,届出事由・区分・届出年月日ごと集計!$B54,SQLデータ!$O:$O,1) -> 0 | F54: =COUNTIFS(SQLデータ!$D:$D,"扶養",SQLデータ!$P:$P,1,SQLデータ!$H:$H,届出事由・区分・届出年月日ごと集計!$A54,SQLデータ!$G:$G,届出事由・区分・届出年月日ごと集計!$B54,SQLデータ!$O:$O,1,SQLデータ!$F:$F,"",SQLデータ!$C:$C,">="&届出事由・区分・届出年月日ごと集計!F$1,SQLデータ!$C:$C,"<="&届出事由・区分・届出年月日ごと集計!F$2) -> 0 | G54: =COUNTIFS(SQLデータ!$D:$D,"扶養",SQLデータ!$P:$P,1,SQLデータ!$H:$H,届出事由・区分・届出年月日ごと集計!$A54,SQLデータ!$G:$G,届出事由・区分・届出年月日ごと集計!$B54,SQLデータ!$O:$O,1,SQLデータ!$F:$F,"",SQLデータ!$C:$C,">="&届出事由・区分・届出年月日ごと集計!G$1,SQLデータ!$C:$C,"<="&届出事由・区分・届出年月日ごと集計!G$2) -> 0 | H54: =COUNTIFS(SQLデータ!$D:$D,"扶養",SQLデータ!$P:$P,1,SQLデータ!$H:$H,届出事由・区分・届出年月日ごと集計!$A54,SQLデータ!$G:$G,届出事由・区分・届出年月日ごと集計!$B54,SQLデータ!$O:$O,1,SQLデータ!$F:$F,"",SQLデータ!$C:$C,">="&届出事由・区分・届出年月日ごと集計!H$1,SQLデータ!$C:$C,"<="&届出事由・区分・届出年月日ごと集計!H$2) -> 0 | I54: =COUNTIFS(SQLデータ!$D:$D,"扶養",SQLデータ!$P:$P,1,SQLデータ!$H:$H,届出事由・区分・届出年月日ごと集計!$A54,SQLデータ!$G:$G,届出事由・区分・届出年月日ごと集計!$B54,SQLデータ!$O:$O,1,SQLデータ!$F:$F,"",SQLデータ!$C:$C,">="&届出事由・区分・届出年月日ごと集計!I$1,SQLデータ!$C:$C,"<="&届出事由・区分・届出年月日ごと集計!I$2) -> 0 | J54: =COUNTIFS(SQLデータ!$D:$D,"扶養",SQLデータ!$P:$P,1,SQLデータ!$H:$H,届出事由・区分・届出年月日ごと集計!$A54,SQLデータ!$G:$G,届出事由・区分・届出年月日ごと集計!$B54,SQLデータ!$O:$O,1,SQLデータ!$F:$F,"",SQLデータ!$C:$C,">="&届出事由・区分・届出年月日ごと集計!J$1,SQLデータ!$C:$C,"<="&届出事由・区分・届出年月日ごと集計!J$2) -> 0 | K54: =COUNTIFS(SQLデータ!$D:$D,"扶養",SQLデータ!$P:$P,1,SQLデータ!$H:$H,届出事由・区分・届出年月日ごと集計!$A54,SQLデータ!$G:$G,届出事由・区分・届出年月日ごと集計!$B54,SQLデータ!$O:$O,1,SQLデータ!$F:$F,"",SQLデータ!$C:$C,">="&届出事由・区分・届出年月日ごと集計!K$1,SQLデータ!$C:$C,"<="&届出事由・区分・届出年月日ごと集計!K$2) -> 0 | L54: =COUNTIFS(SQLデータ!$D:$D,"扶養",SQLデータ!$P:$P,1,SQLデータ!$H:$H,届出事由・区分・届出年月日ごと集計!$A54,SQLデータ!$G:$G,届出事由・区分・届出年月日ごと集計!$B54,SQLデータ!$O:$O,1,SQLデータ!$F:$F,"",SQLデータ!$C:$C,">="&届出事由・区分・届出年月日ごと集計!L$1,SQLデータ!$C:$C,"<="&届出事由・区分・届出年月日ごと集計!L$2) -> 0 | M54: =COUNTIFS(SQLデータ!$D:$D,"扶養",SQLデータ!$P:$P,1,SQLデータ!$H:$H,届出事由・区分・届出年月日ごと集計!$A54,SQLデータ!$G:$G,届出事由・区分・届出年月日ごと集計!$B54,SQLデータ!$O:$O,1,SQLデータ!$F:$F,"",SQLデータ!$C:$C,">="&届出事由・区分・届出年月日ごと集計!M$1,SQLデータ!$C:$C,"<="&届出事由・区分・届出年月日ごと集計!M$2) -> 0 | ... T54: =COUNTIFS(SQLデータ!$D:$D,"扶養",SQLデータ!$P:$P,1,SQLデータ!$H:$H,届出事由・区分・届出年月日ごと集計!$A54,SQLデータ!$G:$G,届出事由・区分・届出年月日ごと集計!$B54,SQLデータ!$O:$O,1,SQLデータ!$F:$F,"",SQLデータ!$C:$C,">="&届出事由・区分・届出年月日ごと集計!T$1,SQLデータ!$C:$C,"<="&届出事由・区分・届出年月日ごと集計!T$2) -> 0
A55: 増 | B55: 廃業 | C55: 共済あり | D55: =COUNTIFS(SQLデータ!$D:$D,"扶養",SQLデータ!$H:$H,届出事由・区分・届出年月日ごと集計!$A55,SQLデータ!$G:$G,届出事由・区分・届出年月日ごと集計!$B55,SQLデータ!$L:$L,1) -> 0 | F55: =COUNTIFS(SQLデータ!$D:$D,"扶養",SQLデータ!$P:$P,1,SQLデータ!$H:$H,届出事由・区分・届出年月日ごと集計!$A55,SQLデータ!$G:$G,届出事由・区分・届出年月日ごと集計!$B55,SQLデータ!$L:$L,1,SQLデータ!$F:$F,"",SQLデータ!$C:$C,">="&届出事由・区分・届出年月日ごと集計!F$1,SQLデータ!$C:$C,"<="&届出事由・区分・届出年月日ごと集計!F$2) -> 0 | G55: =COUNTIFS(SQLデータ!$D:$D,"扶養",SQLデータ!$P:$P,1,SQLデータ!$H:$H,届出事由・区分・届出年月日ごと集計!$A55,SQLデータ!$G:$G,届出事由・区分・届出年月日ごと集計!$B55,SQLデータ!$L:$L,1,SQLデータ!$F:$F,"",SQLデータ!$C:$C,">="&届出事由・区分・届出年月日ごと集計!G$1,SQLデータ!$C:$C,"<="&届出事由・区分・届出年月日ごと集計!G$2) -> 0 | H55: =COUNTIFS(SQLデータ!$D:$D,"扶養",SQLデータ!$P:$P,1,SQLデータ!$H:$H,届出事由・区分・届出年月日ごと集計!$A55,SQLデータ!$G:$G,届出事由・区分・届出年月日ごと集計!$B55,SQLデータ!$L:$L,1,SQLデータ!$F:$F,"",SQLデータ!$C:$C,">="&届出事由・区分・届出年月日ごと集計!H$1,SQLデータ!$C:$C,"<="&届出事由・区分・届出年月日ごと集計!H$2) -> 0 | I55: =COUNTIFS(SQLデータ!$D:$D,"扶養",SQLデータ!$P:$P,1,SQLデータ!$H:$H,届出事由・区分・届出年月日ごと集計!$A55,SQLデータ!$G:$G,届出事由・区分・届出年月日ごと集計!$B55,SQLデータ!$L:$L,1,SQLデータ!$F:$F,"",SQLデータ!$C:$C,">="&届出事由・区分・届出年月日ごと集計!I$1,SQLデータ!$C:$C,"<="&届出事由・区分・届出年月日ごと集計!I$2) -> 0 | J55: =COUNTIFS(SQLデータ!$D:$D,"扶養",SQLデータ!$P:$P,1,SQLデータ!$H:$H,届出事由・区分・届出年月日ごと集計!$A55,SQLデータ!$G:$G,届出事由・区分・届出年月日ごと集計!$B55,SQLデータ!$L:$L,1,SQLデータ!$F:$F,"",SQLデータ!$C:$C,">="&届出事由・区分・届出年月日ごと集計!J$1,SQLデータ!$C:$C,"<="&届出事由・区分・届出年月日ごと集計!J$2) -> 0 | K55: =COUNTIFS(SQLデータ!$D:$D,"扶養",SQLデータ!$P:$P,1,SQLデータ!$H:$H,届出事由・区分・届出年月日ごと集計!$A55,SQLデータ!$G:$G,届出事由・区分・届出年月日ごと集計!$B55,SQLデータ!$L:$L,1,SQLデータ!$F:$F,"",SQLデータ!$C:$C,">="&届出事由・区分・届出年月日ごと集計!K$1,SQLデータ!$C:$C,"<="&届出事由・区分・届出年月日ごと集計!K$2) -> 0 | L55: =COUNTIFS(SQLデータ!$D:$D,"扶養",SQLデータ!$P:$P,1,SQLデータ!$H:$H,届出事由・区分・届出年月日ごと集計!$A55,SQLデータ!$G:$G,届出事由・区分・届出年月日ごと集計!$B55,SQLデータ!$L:$L,1,SQLデータ!$F:$F,"",SQLデータ!$C:$C,">="&届出事由・区分・届出年月日ごと集計!L$1,SQLデータ!$C:$C,"<="&届出事由・区分・届出年月日ごと集計!L$2) -> 0 | M55: =COUNTIFS(SQLデータ!$D:$D,"扶養",SQLデータ!$P:$P,1,SQLデータ!$H:$H,届出事由・区分・届出年月日ごと集計!$A55,SQLデータ!$G:$G,届出事由・区分・届出年月日ごと集計!$B55,SQLデータ!$L:$L,1,SQLデータ!$F:$F,"",SQLデータ!$C:$C,">="&届出事由・区分・届出年月日ごと集計!M$1,SQLデータ!$C:$C,"<="&届出事由・区分・届出年月日ごと集計!M$2) -> 0 | ... T55: =COUNTIFS(SQLデータ!$D:$D,"扶養",SQLデータ!$P:$P,1,SQLデータ!$H:$H,届出事由・区分・届出年月日ごと集計!$A55,SQLデータ!$G:$G,届出事由・区分・届出年月日ごと集計!$B55,SQLデータ!$L:$L,1,SQLデータ!$F:$F,"",SQLデータ!$C:$C,">="&届出事由・区分・届出年月日ごと集計!T$1,SQLデータ!$C:$C,"<="&届出事由・区分・届出年月日ごと集計!T$2) -> 0
A56: 増 | B56: 廃業 | C56: 扶養手当あり | D56: =COUNTIFS(SQLデータ!$D:$D,"扶養",SQLデータ!$H:$H,届出事由・区分・届出年月日ごと集計!$A56,SQLデータ!$G:$G,届出事由・区分・届出年月日ごと集計!$B56,SQLデータ!$M:$M,1) -> 0 | F56: =COUNTIFS(SQLデータ!$D:$D,"扶養",SQLデータ!$P:$P,1,SQLデータ!$H:$H,届出事由・区分・届出年月日ごと集計!$A56,SQLデータ!$G:$G,届出事由・区分・届出年月日ごと集計!$B56,SQLデータ!$M:$M,1,SQLデータ!$F:$F,"",SQLデータ!$C:$C,">="&届出事由・区分・届出年月日ごと集計!F$1,SQLデータ!$C:$C,"<="&届出事由・区分・届出年月日ごと集計!F$2) -> 0 | G56: =COUNTIFS(SQLデータ!$D:$D,"扶養",SQLデータ!$P:$P,1,SQLデータ!$H:$H,届出事由・区分・届出年月日ごと集計!$A56,SQLデータ!$G:$G,届出事由・区分・届出年月日ごと集計!$B56,SQLデータ!$M:$M,1,SQLデータ!$F:$F,"",SQLデータ!$C:$C,">="&届出事由・区分・届出年月日ごと集計!G$1,SQLデータ!$C:$C,"<="&届出事由・区分・届出年月日ごと集計!G$2) -> 0 | H56: =COUNTIFS(SQLデータ!$D:$D,"扶養",SQLデータ!$P:$P,1,SQLデータ!$H:$H,届出事由・区分・届出年月日ごと集計!$A56,SQLデータ!$G:$G,届出事由・区分・届出年月日ごと集計!$B56,SQLデータ!$M:$M,1,SQLデータ!$F:$F,"",SQLデータ!$C:$C,">="&届出事由・区分・届出年月日ごと集計!H$1,SQLデータ!$C:$C,"<="&届出事由・区分・届出年月日ごと集計!H$2) -> 0 | I56: =COUNTIFS(SQLデータ!$D:$D,"扶養",SQLデータ!$P:$P,1,SQLデータ!$H:$H,届出事由・区分・届出年月日ごと集計!$A56,SQLデータ!$G:$G,届出事由・区分・届出年月日ごと集計!$B56,SQLデータ!$M:$M,1,SQLデータ!$F:$F,"",SQLデータ!$C:$C,">="&届出事由・区分・届出年月日ごと集計!I$1,SQLデータ!$C:$C,"<="&届出事由・区分・届出年月日ごと集計!I$2) -> 0 | J56: =COUNTIFS(SQLデータ!$D:$D,"扶養",SQLデータ!$P:$P,1,SQLデータ!$H:$H,届出事由・区分・届出年月日ごと集計!$A56,SQLデータ!$G:$G,届出事由・区分・届出年月日ごと集計!$B56,SQLデータ!$M:$M,1,SQLデータ!$F:$F,"",SQLデータ!$C:$C,">="&届出事由・区分・届出年月日ごと集計!J$1,SQLデータ!$C:$C,"<="&届出事由・区分・届出年月日ごと集計!J$2) -> 0 | K56: =COUNTIFS(SQLデータ!$D:$D,"扶養",SQLデータ!$P:$P,1,SQLデータ!$H:$H,届出事由・区分・届出年月日ごと集計!$A56,SQLデータ!$G:$G,届出事由・区分・届出年月日ごと集計!$B56,SQLデータ!$M:$M,1,SQLデータ!$F:$F,"",SQLデータ!$C:$C,">="&届出事由・区分・届出年月日ごと集計!K$1,SQLデータ!$C:$C,"<="&届出事由・区分・届出年月日ごと集計!K$2) -> 0 | L56: =COUNTIFS(SQLデータ!$D:$D,"扶養",SQLデータ!$P:$P,1,SQLデータ!$H:$H,届出事由・区分・届出年月日ごと集計!$A56,SQLデータ!$G:$G,届出事由・区分・届出年月日ごと集計!$B56,SQLデータ!$M:$M,1,SQLデータ!$F:$F,"",SQLデータ!$C:$C,">="&届出事由・区分・届出年月日ごと集計!L$1,SQLデータ!$C:$C,"<="&届出事由・区分・届出年月日ごと集計!L$2) -> 0 | M56: =COUNTIFS(SQLデータ!$D:$D,"扶養",SQLデータ!$P:$P,1,SQLデータ!$H:$H,届出事由・区分・届出年月日ごと集計!$A56,SQLデータ!$G:$G,届出事由・区分・届出年月日ごと集計!$B56,SQLデータ!$M:$M,1,SQLデータ!$F:$F,"",SQLデータ!$C:$C,">="&届出事由・区分・届出年月日ごと集計!M$1,SQLデータ!$C:$C,"<="&届出事由・区分・届出年月日ごと集計!M$2) -> 0 | ... T56: =COUNTIFS(SQLデータ!$D:$D,"扶養",SQLデータ!$P:$P,1,SQLデータ!$H:$H,届出事由・区分・届出年月日ごと集計!$A56,SQLデータ!$G:$G,届出事由・区分・届出年月日ごと集計!$B56,SQLデータ!$M:$M,1,SQLデータ!$F:$F,"",SQLデータ!$C:$C,">="&届出事由・区分・届出年月日ごと集計!T$1,SQLデータ!$C:$C,"<="&届出事由・区分・届出年月日ごと集計!T$2) -> 0
A57: 増 | B57: 廃業 | C57: 税控除のみ | D57: =COUNTIFS(SQLデータ!$D:$D,"扶養",SQLデータ!$H:$H,届出事由・区分・届出年月日ごと集計!$A57,SQLデータ!$G:$G,届出事由・区分・届出年月日ごと集計!$B57,SQLデータ!$N:$N,1) -> 0 | F57: =COUNTIFS(SQLデータ!$D:$D,"扶養",SQLデータ!$P:$P,1,SQLデータ!$H:$H,届出事由・区分・届出年月日ごと集計!$A57,SQLデータ!$G:$G,届出事由・区分・届出年月日ごと集計!$B57,SQLデータ!$N:$N,1,SQLデータ!$F:$F,"",SQLデータ!$C:$C,">="&届出事由・区分・届出年月日ごと集計!F$1,SQLデータ!$C:$C,"<="&届出事由・区分・届出年月日ごと集計!F$2) -> 0 | G57: =COUNTIFS(SQLデータ!$D:$D,"扶養",SQLデータ!$P:$P,1,SQLデータ!$H:$H,届出事由・区分・届出年月日ごと集計!$A57,SQLデータ!$G:$G,届出事由・区分・届出年月日ごと集計!$B57,SQLデータ!$N:$N,1,SQLデータ!$F:$F,"",SQLデータ!$C:$C,">="&届出事由・区分・届出年月日ごと集計!G$1,SQLデータ!$C:$C,"<="&届出事由・区分・届出年月日ごと集計!G$2) -> 0 | H57: =COUNTIFS(SQLデータ!$D:$D,"扶養",SQLデータ!$P:$P,1,SQLデータ!$H:$H,届出事由・区分・届出年月日ごと集計!$A57,SQLデータ!$G:$G,届出事由・区分・届出年月日ごと集計!$B57,SQLデータ!$N:$N,1,SQLデータ!$F:$F,"",SQLデータ!$C:$C,">="&届出事由・区分・届出年月日ごと集計!H$1,SQLデータ!$C:$C,"<="&届出事由・区分・届出年月日ごと集計!H$2) -> 0 | I57: =COUNTIFS(SQLデータ!$D:$D,"扶養",SQLデータ!$P:$P,1,SQLデータ!$H:$H,届出事由・区分・届出年月日ごと集計!$A57,SQLデータ!$G:$G,届出事由・区分・届出年月日ごと集計!$B57,SQLデータ!$N:$N,1,SQLデータ!$F:$F,"",SQLデータ!$C:$C,">="&届出事由・区分・届出年月日ごと集計!I$1,SQLデータ!$C:$C,"<="&届出事由・区分・届出年月日ごと集計!I$2) -> 0 | J57: =COUNTIFS(SQLデータ!$D:$D,"扶養",SQLデータ!$P:$P,1,SQLデータ!$H:$H,届出事由・区分・届出年月日ごと集計!$A57,SQLデータ!$G:$G,届出事由・区分・届出年月日ごと集計!$B57,SQLデータ!$N:$N,1,SQLデータ!$F:$F,"",SQLデータ!$C:$C,">="&届出事由・区分・届出年月日ごと集計!J$1,SQLデータ!$C:$C,"<="&届出事由・区分・届出年月日ごと集計!J$2) -> 0 | K57: =COUNTIFS(SQLデータ!$D:$D,"扶養",SQLデータ!$P:$P,1,SQLデータ!$H:$H,届出事由・区分・届出年月日ごと集計!$A57,SQLデータ!$G:$G,届出事由・区分・届出年月日ごと集計!$B57,SQLデータ!$N:$N,1,SQLデータ!$F:$F,"",SQLデータ!$C:$C,">="&届出事由・区分・届出年月日ごと集計!K$1,SQLデータ!$C:$C,"<="&届出事由・区分・届出年月日ごと集計!K$2) -> 0 | L57: =COUNTIFS(SQLデータ!$D:$D,"扶養",SQLデータ!$P:$P,1,SQLデータ!$H:$H,届出事由・区分・届出年月日ごと集計!$A57,SQLデータ!$G:$G,届出事由・区分・届出年月日ごと集計!$B57,SQLデータ!$N:$N,1,SQLデータ!$F:$F,"",SQLデータ!$C:$C,">="&届出事由・区分・届出年月日ごと集計!L$1,SQLデータ!$C:$C,"<="&届出事由・区分・届出年月日ごと集計!L$2) -> 0 | M57: =COUNTIFS(SQLデータ!$D:$D,"扶養",SQLデータ!$P:$P,1,SQLデータ!$H:$H,届出事由・区分・届出年月日ごと集計!$A57,SQLデータ!$G:$G,届出事由・区分・届出年月日ごと集計!$B57,SQLデータ!$N:$N,1,SQLデータ!$F:$F,"",SQLデータ!$C:$C,">="&届出事由・区分・届出年月日ごと集計!M$1,SQLデータ!$C:$C,"<="&届出事由・区分・届出年月日ごと集計!M$2) -> 0 | ... T57: =COUNTIFS(SQLデータ!$D:$D,"扶養",SQLデータ!$P:$P,1,SQLデータ!$H:$H,届出事由・区分・届出年月日ごと集計!$A57,SQLデータ!$G:$G,届出事由・区分・届出年月日ごと集計!$B57,SQLデータ!$N:$N,1,SQLデータ!$F:$F,"",SQLデータ!$C:$C,">="&届出事由・区分・届出年月日ごと集計!T$1,SQLデータ!$C:$C,"<="&届出事由・区分・届出年月日ごと集計!T$2) -> 0
A58: 増 | B58: 廃業 | C58: 本人税のみ | D58: =COUNTIFS(SQLデータ!$D:$D,"扶養",SQLデータ!$H:$H,届出事由・区分・届出年月日ごと集計!$A58,SQLデータ!$G:$G,届出事由・区分・届出年月日ごと集計!$B58,SQLデータ!$O:$O,1) -> 0 | F58: =COUNTIFS(SQLデータ!$D:$D,"扶養",SQLデータ!$P:$P,1,SQLデータ!$H:$H,届出事由・区分・届出年月日ごと集計!$A58,SQLデータ!$G:$G,届出事由・区分・届出年月日ごと集計!$B58,SQLデータ!$O:$O,1,SQLデータ!$F:$F,"",SQLデータ!$C:$C,">="&届出事由・区分・届出年月日ごと集計!F$1,SQLデータ!$C:$C,"<="&届出事由・区分・届出年月日ごと集計!F$2) -> 0 | G58: =COUNTIFS(SQLデータ!$D:$D,"扶養",SQLデータ!$P:$P,1,SQLデータ!$H:$H,届出事由・区分・届出年月日ごと集計!$A58,SQLデータ!$G:$G,届出事由・区分・届出年月日ごと集計!$B58,SQLデータ!$O:$O,1,SQLデータ!$F:$F,"",SQLデータ!$C:$C,">="&届出事由・区分・届出年月日ごと集計!G$1,SQLデータ!$C:$C,"<="&届出事由・区分・届出年月日ごと集計!G$2) -> 0 | H58: =COUNTIFS(SQLデータ!$D:$D,"扶養",SQLデータ!$P:$P,1,SQLデータ!$H:$H,届出事由・区分・届出年月日ごと集計!$A58,SQLデータ!$G:$G,届出事由・区分・届出年月日ごと集計!$B58,SQLデータ!$O:$O,1,SQLデータ!$F:$F,"",SQLデータ!$C:$C,">="&届出事由・区分・届出年月日ごと集計!H$1,SQLデータ!$C:$C,"<="&届出事由・区分・届出年月日ごと集計!H$2) -> 0 | I58: =COUNTIFS(SQLデータ!$D:$D,"扶養",SQLデータ!$P:$P,1,SQLデータ!$H:$H,届出事由・区分・届出年月日ごと集計!$A58,SQLデータ!$G:$G,届出事由・区分・届出年月日ごと集計!$B58,SQLデータ!$O:$O,1,SQLデータ!$F:$F,"",SQLデータ!$C:$C,">="&届出事由・区分・届出年月日ごと集計!I$1,SQLデータ!$C:$C,"<="&届出事由・区分・届出年月日ごと集計!I$2) -> 0 | J58: =COUNTIFS(SQLデータ!$D:$D,"扶養",SQLデータ!$P:$P,1,SQLデータ!$H:$H,届出事由・区分・届出年月日ごと集計!$A58,SQLデータ!$G:$G,届出事由・区分・届出年月日ごと集計!$B58,SQLデータ!$O:$O,1,SQLデータ!$F:$F,"",SQLデータ!$C:$C,">="&届出事由・区分・届出年月日ごと集計!J$1,SQLデータ!$C:$C,"<="&届出事由・区分・届出年月日ごと集計!J$2) -> 0 | K58: =COUNTIFS(SQLデータ!$D:$D,"扶養",SQLデータ!$P:$P,1,SQLデータ!$H:$H,届出事由・区分・届出年月日ごと集計!$A58,SQLデータ!$G:$G,届出事由・区分・届出年月日ごと集計!$B58,SQLデータ!$O:$O,1,SQLデータ!$F:$F,"",SQLデータ!$C:$C,">="&届出事由・区分・届出年月日ごと集計!K$1,SQLデータ!$C:$C,"<="&届出事由・区分・届出年月日ごと集計!K$2) -> 0 | L58: =COUNTIFS(SQLデータ!$D:$D,"扶養",SQLデータ!$P:$P,1,SQLデータ!$H:$H,届出事由・区分・届出年月日ごと集計!$A58,SQLデータ!$G:$G,届出事由・区分・届出年月日ごと集計!$B58,SQLデータ!$O:$O,1,SQLデータ!$F:$F,"",SQLデータ!$C:$C,">="&届出事由・区分・届出年月日ごと集計!L$1,SQLデータ!$C:$C,"<="&届出事由・区分・届出年月日ごと集計!L$2) -> 0 | M58: =COUNTIFS(SQLデータ!$D:$D,"扶養",SQLデータ!$P:$P,1,SQLデータ!$H:$H,届出事由・区分・届出年月日ごと集計!$A58,SQLデータ!$G:$G,届出事由・区分・届出年月日ごと集計!$B58,SQLデータ!$O:$O,1,SQLデータ!$F:$F,"",SQLデータ!$C:$C,">="&届出事由・区分・届出年月日ごと集計!M$1,SQLデータ!$C:$C,"<="&届出事由・区分・届出年月日ごと集計!M$2) -> 0 | ... T58: =COUNTIFS(SQLデータ!$D:$D,"扶養",SQLデータ!$P:$P,1,SQLデータ!$H:$H,届出事由・区分・届出年月日ごと集計!$A58,SQLデータ!$G:$G,届出事由・区分・届出年月日ごと集計!$B58,SQLデータ!$O:$O,1,SQLデータ!$F:$F,"",SQLデータ!$C:$C,">="&届出事由・区分・届出年月日ごと集計!T$1,SQLデータ!$C:$C,"<="&届出事由・区分・届出年月日ごと集計!T$2) -> 0
A59: 増 | B59: 心身に著しい障害者 | C59: 共済あり | D59: =COUNTIFS(SQLデータ!$D:$D,"扶養",SQLデータ!$H:$H,届出事由・区分・届出年月日ごと集計!$A59,SQLデータ!$G:$G,届出事由・区分・届出年月日ごと集計!$B59,SQLデータ!$L:$L,1) -> 0 | F59: =COUNTIFS(SQLデータ!$D:$D,"扶養",SQLデータ!$P:$P,1,SQLデータ!$H:$H,届出事由・区分・届出年月日ごと集計!$A59,SQLデータ!$G:$G,届出事由・区分・届出年月日ごと集計!$B59,SQLデータ!$L:$L,1,SQLデータ!$F:$F,"",SQLデータ!$C:$C,">="&届出事由・区分・届出年月日ごと集計!F$1,SQLデータ!$C:$C,"<="&届出事由・区分・届出年月日ごと集計!F$2) -> 0 | G59: =COUNTIFS(SQLデータ!$D:$D,"扶養",SQLデータ!$P:$P,1,SQLデータ!$H:$H,届出事由・区分・届出年月日ごと集計!$A59,SQLデータ!$G:$G,届出事由・区分・届出年月日ごと集計!$B59,SQLデータ!$L:$L,1,SQLデータ!$F:$F,"",SQLデータ!$C:$C,">="&届出事由・区分・届出年月日ごと集計!G$1,SQLデータ!$C:$C,"<="&届出事由・区分・届出年月日ごと集計!G$2) -> 0 | H59: =COUNTIFS(SQLデータ!$D:$D,"扶養",SQLデータ!$P:$P,1,SQLデータ!$H:$H,届出事由・区分・届出年月日ごと集計!$A59,SQLデータ!$G:$G,届出事由・区分・届出年月日ごと集計!$B59,SQLデータ!$L:$L,1,SQLデータ!$F:$F,"",SQLデータ!$C:$C,">="&届出事由・区分・届出年月日ごと集計!H$1,SQLデータ!$C:$C,"<="&届出事由・区分・届出年月日ごと集計!H$2) -> 0 | I59: =COUNTIFS(SQLデータ!$D:$D,"扶養",SQLデータ!$P:$P,1,SQLデータ!$H:$H,届出事由・区分・届出年月日ごと集計!$A59,SQLデータ!$G:$G,届出事由・区分・届出年月日ごと集計!$B59,SQLデータ!$L:$L,1,SQLデータ!$F:$F,"",SQLデータ!$C:$C,">="&届出事由・区分・届出年月日ごと集計!I$1,SQLデータ!$C:$C,"<="&届出事由・区分・届出年月日ごと集計!I$2) -> 0 | J59: =COUNTIFS(SQLデータ!$D:$D,"扶養",SQLデータ!$P:$P,1,SQLデータ!$H:$H,届出事由・区分・届出年月日ごと集計!$A59,SQLデータ!$G:$G,届出事由・区分・届出年月日ごと集計!$B59,SQLデータ!$L:$L,1,SQLデータ!$F:$F,"",SQLデータ!$C:$C,">="&届出事由・区分・届出年月日ごと集計!J$1,SQLデータ!$C:$C,"<="&届出事由・区分・届出年月日ごと集計!J$2) -> 0 | K59: =COUNTIFS(SQLデータ!$D:$D,"扶養",SQLデータ!$P:$P,1,SQLデータ!$H:$H,届出事由・区分・届出年月日ごと集計!$A59,SQLデータ!$G:$G,届出事由・区分・届出年月日ごと集計!$B59,SQLデータ!$L:$L,1,SQLデータ!$F:$F,"",SQLデータ!$C:$C,">="&届出事由・区分・届出年月日ごと集計!K$1,SQLデータ!$C:$C,"<="&届出事由・区分・届出年月日ごと集計!K$2) -> 0 | L59: =COUNTIFS(SQLデータ!$D:$D,"扶養",SQLデータ!$P:$P,1,SQLデータ!$H:$H,届出事由・区分・届出年月日ごと集計!$A59,SQLデータ!$G:$G,届出事由・区分・届出年月日ごと集計!$B59,SQLデータ!$L:$L,1,SQLデータ!$F:$F,"",SQLデータ!$C:$C,">="&届出事由・区分・届出年月日ごと集計!L$1,SQLデータ!$C:$C,"<="&届出事由・区分・届出年月日ごと集計!L$2) -> 0 | M59: =COUNTIFS(SQLデータ!$D:$D,"扶養",SQLデータ!$P:$P,1,SQLデータ!$H:$H,届出事由・区分・届出年月日ごと集計!$A59,SQLデータ!$G:$G,届出事由・区分・届出年月日ごと集計!$B59,SQLデータ!$L:$L,1,SQLデータ!$F:$F,"",SQLデータ!$C:$C,">="&届出事由・区分・届出年月日ごと集計!M$1,SQLデータ!$C:$C,"<="&届出事由・区分・届出年月日ごと集計!M$2) -> 0 | ... T59: =COUNTIFS(SQLデータ!$D:$D,"扶養",SQLデータ!$P:$P,1,SQLデータ!$H:$H,届出事由・区分・届出年月日ごと集計!$A59,SQLデータ!$G:$G,届出事由・区分・届出年月日ごと集計!$B59,SQLデータ!$L:$L,1,SQLデータ!$F:$F,"",SQLデータ!$C:$C,">="&届出事由・区分・届出年月日ごと集計!T$1,SQLデータ!$C:$C,"<="&届出事由・区分・届出年月日ごと集計!T$2) -> 0
A60: 増 | B60: 心身に著しい障害者 | C60: 扶養手当あり | D60: =COUNTIFS(SQLデータ!$D:$D,"扶養",SQLデータ!$H:$H,届出事由・区分・届出年月日ごと集計!$A60,SQLデータ!$G:$G,届出事由・区分・届出年月日ごと集計!$B60,SQLデータ!$M:$M,1) -> 0 | F60: =COUNTIFS(SQLデータ!$D:$D,"扶養",SQLデータ!$P:$P,1,SQLデータ!$H:$H,届出事由・区分・届出年月日ごと集計!$A60,SQLデータ!$G:$G,届出事由・区分・届出年月日ごと集計!$B60,SQLデータ!$M:$M,1,SQLデータ!$F:$F,"",SQLデータ!$C:$C,">="&届出事由・区分・届出年月日ごと集計!F$1,SQLデータ!$C:$C,"<="&届出事由・区分・届出年月日ごと集計!F$2) -> 0 | G60: =COUNTIFS(SQLデータ!$D:$D,"扶養",SQLデータ!$P:$P,1,SQLデータ!$H:$H,届出事由・区分・届出年月日ごと集計!$A60,SQLデータ!$G:$G,届出事由・区分・届出年月日ごと集計!$B60,SQLデータ!$M:$M,1,SQLデータ!$F:$F,"",SQLデータ!$C:$C,">="&届出事由・区分・届出年月日ごと集計!G$1,SQLデータ!$C:$C,"<="&届出事由・区分・届出年月日ごと集計!G$2) -> 0 | H60: =COUNTIFS(SQLデータ!$D:$D,"扶養",SQLデータ!$P:$P,1,SQLデータ!$H:$H,届出事由・区分・届出年月日ごと集計!$A60,SQLデータ!$G:$G,届出事由・区分・届出年月日ごと集計!$B60,SQLデータ!$M:$M,1,SQLデータ!$F:$F,"",SQLデータ!$C:$C,">="&届出事由・区分・届出年月日ごと集計!H$1,SQLデータ!$C:$C,"<="&届出事由・区分・届出年月日ごと集計!H$2) -> 0 | I60: =COUNTIFS(SQLデータ!$D:$D,"扶養",SQLデータ!$P:$P,1,SQLデータ!$H:$H,届出事由・区分・届出年月日ごと集計!$A60,SQLデータ!$G:$G,届出事由・区分・届出年月日ごと集計!$B60,SQLデータ!$M:$M,1,SQLデータ!$F:$F,"",SQLデータ!$C:$C,">="&届出事由・区分・届出年月日ごと集計!I$1,SQLデータ!$C:$C,"<="&届出事由・区分・届出年月日ごと集計!I$2) -> 0 | J60: =COUNTIFS(SQLデータ!$D:$D,"扶養",SQLデータ!$P:$P,1,SQLデータ!$H:$H,届出事由・区分・届出年月日ごと集計!$A60,SQLデータ!$G:$G,届出事由・区分・届出年月日ごと集計!$B60,SQLデータ!$M:$M,1,SQLデータ!$F:$F,"",SQLデータ!$C:$C,">="&届出事由・区分・届出年月日ごと集計!J$1,SQLデータ!$C:$C,"<="&届出事由・区分・届出年月日ごと集計!J$2) -> 0 | K60: =COUNTIFS(SQLデータ!$D:$D,"扶養",SQLデータ!$P:$P,1,SQLデータ!$H:$H,届出事由・区分・届出年月日ごと集計!$A60,SQLデータ!$G:$G,届出事由・区分・届出年月日ごと集計!$B60,SQLデータ!$M:$M,1,SQLデータ!$F:$F,"",SQLデータ!$C:$C,">="&届出事由・区分・届出年月日ごと集計!K$1,SQLデータ!$C:$C,"<="&届出事由・区分・届出年月日ごと集計!K$2) -> 0 | L60: =COUNTIFS(SQLデータ!$D:$D,"扶養",SQLデータ!$P:$P,1,SQLデータ!$H:$H,届出事由・区分・届出年月日ごと集計!$A60,SQLデータ!$G:$G,届出事由・区分・届出年月日ごと集計!$B60,SQLデータ!$M:$M,1,SQLデータ!$F:$F,"",SQLデータ!$C:$C,">="&届出事由・区分・届出年月日ごと集計!L$1,SQLデータ!$C:$C,"<="&届出事由・区分・届出年月日ごと集計!L$2) -> 0 | M60: =COUNTIFS(SQLデータ!$D:$D,"扶養",SQLデータ!$P:$P,1,SQLデータ!$H:$H,届出事由・区分・届出年月日ごと集計!$A60,SQLデータ!$G:$G,届出事由・区分・届出年月日ごと集計!$B60,SQLデータ!$M:$M,1,SQLデータ!$F:$F,"",SQLデータ!$C:$C,">="&届出事由・区分・届出年月日ごと集計!M$1,SQLデータ!$C:$C,"<="&届出事由・区分・届出年月日ごと集計!M$2) -> 0 | ... T60: =COUNTIFS(SQLデータ!$D:$D,"扶養",SQLデータ!$P:$P,1,SQLデータ!$H:$H,届出事由・区分・届出年月日ごと集計!$A60,SQLデータ!$G:$G,届出事由・区分・届出年月日ごと集計!$B60,SQLデータ!$M:$M,1,SQLデータ!$F:$F,"",SQLデータ!$C:$C,">="&届出事由・区分・届出年月日ごと集計!T$1,SQLデータ!$C:$C,"<="&届出事由・区分・届出年月日ごと集計!T$2) -> 0
A61: 増 | B61: 心身に著しい障害者 | C61: 税控除のみ | D61: =COUNTIFS(SQLデータ!$D:$D,"扶養",SQLデータ!$H:$H,届出事由・区分・届出年月日ごと集計!$A61,SQLデータ!$G:$G,届出事由・区分・届出年月日ごと集計!$B61,SQLデータ!$N:$N,1) -> 0 | F61: =COUNTIFS(SQLデータ!$D:$D,"扶養",SQLデータ!$P:$P,1,SQLデータ!$H:$H,届出事由・区分・届出年月日ごと集計!$A61,SQLデータ!$G:$G,届出事由・区分・届出年月日ごと集計!$B61,SQLデータ!$N:$N,1,SQLデータ!$F:$F,"",SQLデータ!$C:$C,">="&届出事由・区分・届出年月日ごと集計!F$1,SQLデータ!$C:$C,"<="&届出事由・区分・届出年月日ごと集計!F$2) -> 0 | G61: =COUNTIFS(SQLデータ!$D:$D,"扶養",SQLデータ!$P:$P,1,SQLデータ!$H:$H,届出事由・区分・届出年月日ごと集計!$A61,SQLデータ!$G:$G,届出事由・区分・届出年月日ごと集計!$B61,SQLデータ!$N:$N,1,SQLデータ!$F:$F,"",SQLデータ!$C:$C,">="&届出事由・区分・届出年月日ごと集計!G$1,SQLデータ!$C:$C,"<="&届出事由・区分・届出年月日ごと集計!G$2) -> 0 | H61: =COUNTIFS(SQLデータ!$D:$D,"扶養",SQLデータ!$P:$P,1,SQLデータ!$H:$H,届出事由・区分・届出年月日ごと集計!$A61,SQLデータ!$G:$G,届出事由・区分・届出年月日ごと集計!$B61,SQLデータ!$N:$N,1,SQLデータ!$F:$F,"",SQLデータ!$C:$C,">="&届出事由・区分・届出年月日ごと集計!H$1,SQLデータ!$C:$C,"<="&届出事由・区分・届出年月日ごと集計!H$2) -> 0 | I61: =COUNTIFS(SQLデータ!$D:$D,"扶養",SQLデータ!$P:$P,1,SQLデータ!$H:$H,届出事由・区分・届出年月日ごと集計!$A61,SQLデータ!$G:$G,届出事由・区分・届出年月日ごと集計!$B61,SQLデータ!$N:$N,1,SQLデータ!$F:$F,"",SQLデータ!$C:$C,">="&届出事由・区分・届出年月日ごと集計!I$1,SQLデータ!$C:$C,"<="&届出事由・区分・届出年月日ごと集計!I$2) -> 0 | J61: =COUNTIFS(SQLデータ!$D:$D,"扶養",SQLデータ!$P:$P,1,SQLデータ!$H:$H,届出事由・区分・届出年月日ごと集計!$A61,SQLデータ!$G:$G,届出事由・区分・届出年月日ごと集計!$B61,SQLデータ!$N:$N,1,SQLデータ!$F:$F,"",SQLデータ!$C:$C,">="&届出事由・区分・届出年月日ごと集計!J$1,SQLデータ!$C:$C,"<="&届出事由・区分・届出年月日ごと集計!J$2) -> 0 | K61: =COUNTIFS(SQLデータ!$D:$D,"扶養",SQLデータ!$P:$P,1,SQLデータ!$H:$H,届出事由・区分・届出年月日ごと集計!$A61,SQLデータ!$G:$G,届出事由・区分・届出年月日ごと集計!$B61,SQLデータ!$N:$N,1,SQLデータ!$F:$F,"",SQLデータ!$C:$C,">="&届出事由・区分・届出年月日ごと集計!K$1,SQLデータ!$C:$C,"<="&届出事由・区分・届出年月日ごと集計!K$2) -> 0 | L61: =COUNTIFS(SQLデータ!$D:$D,"扶養",SQLデータ!$P:$P,1,SQLデータ!$H:$H,届出事由・区分・届出年月日ごと集計!$A61,SQLデータ!$G:$G,届出事由・区分・届出年月日ごと集計!$B61,SQLデータ!$N:$N,1,SQLデータ!$F:$F,"",SQLデータ!$C:$C,">="&届出事由・区分・届出年月日ごと集計!L$1,SQLデータ!$C:$C,"<="&届出事由・区分・届出年月日ごと集計!L$2) -> 0 | M61: =COUNTIFS(SQLデータ!$D:$D,"扶養",SQLデータ!$P:$P,1,SQLデータ!$H:$H,届出事由・区分・届出年月日ごと集計!$A61,SQLデータ!$G:$G,届出事由・区分・届出年月日ごと集計!$B61,SQLデータ!$N:$N,1,SQLデータ!$F:$F,"",SQLデータ!$C:$C,">="&届出事由・区分・届出年月日ごと集計!M$1,SQLデータ!$C:$C,"<="&届出事由・区分・届出年月日ごと集計!M$2) -> 0 | ... T61: =COUNTIFS(SQLデータ!$D:$D,"扶養",SQLデータ!$P:$P,1,SQLデータ!$H:$H,届出事由・区分・届出年月日ごと集計!$A61,SQLデータ!$G:$G,届出事由・区分・届出年月日ごと集計!$B61,SQLデータ!$N:$N,1,SQLデータ!$F:$F,"",SQLデータ!$C:$C,">="&届出事由・区分・届出年月日ごと集計!T$1,SQLデータ!$C:$C,"<="&届出事由・区分・届出年月日ごと集計!T$2) -> 0
A62: 増 | B62: 心身に著しい障害者 | C62: 本人税のみ | D62: =COUNTIFS(SQLデータ!$D:$D,"扶養",SQLデータ!$H:$H,届出事由・区分・届出年月日ごと集計!$A62,SQLデータ!$G:$G,届出事由・区分・届出年月日ごと集計!$B62,SQLデータ!$O:$O,1) -> 0 | F62: =COUNTIFS(SQLデータ!$D:$D,"扶養",SQLデータ!$P:$P,1,SQLデータ!$H:$H,届出事由・区分・届出年月日ごと集計!$A62,SQLデータ!$G:$G,届出事由・区分・届出年月日ごと集計!$B62,SQLデータ!$O:$O,1,SQLデータ!$F:$F,"",SQLデータ!$C:$C,">="&届出事由・区分・届出年月日ごと集計!F$1,SQLデータ!$C:$C,"<="&届出事由・区分・届出年月日ごと集計!F$2) -> 0 | G62: =COUNTIFS(SQLデータ!$D:$D,"扶養",SQLデータ!$P:$P,1,SQLデータ!$H:$H,届出事由・区分・届出年月日ごと集計!$A62,SQLデータ!$G:$G,届出事由・区分・届出年月日ごと集計!$B62,SQLデータ!$O:$O,1,SQLデータ!$F:$F,"",SQLデータ!$C:$C,">="&届出事由・区分・届出年月日ごと集計!G$1,SQLデータ!$C:$C,"<="&届出事由・区分・届出年月日ごと集計!G$2) -> 0 | H62: =COUNTIFS(SQLデータ!$D:$D,"扶養",SQLデータ!$P:$P,1,SQLデータ!$H:$H,届出事由・区分・届出年月日ごと集計!$A62,SQLデータ!$G:$G,届出事由・区分・届出年月日ごと集計!$B62,SQLデータ!$O:$O,1,SQLデータ!$F:$F,"",SQLデータ!$C:$C,">="&届出事由・区分・届出年月日ごと集計!H$1,SQLデータ!$C:$C,"<="&届出事由・区分・届出年月日ごと集計!H$2) -> 0 | I62: =COUNTIFS(SQLデータ!$D:$D,"扶養",SQLデータ!$P:$P,1,SQLデータ!$H:$H,届出事由・区分・届出年月日ごと集計!$A62,SQLデータ!$G:$G,届出事由・区分・届出年月日ごと集計!$B62,SQLデータ!$O:$O,1,SQLデータ!$F:$F,"",SQLデータ!$C:$C,">="&届出事由・区分・届出年月日ごと集計!I$1,SQLデータ!$C:$C,"<="&届出事由・区分・届出年月日ごと集計!I$2) -> 0 | J62: =COUNTIFS(SQLデータ!$D:$D,"扶養",SQLデータ!$P:$P,1,SQLデータ!$H:$H,届出事由・区分・届出年月日ごと集計!$A62,SQLデータ!$G:$G,届出事由・区分・届出年月日ごと集計!$B62,SQLデータ!$O:$O,1,SQLデータ!$F:$F,"",SQLデータ!$C:$C,">="&届出事由・区分・届出年月日ごと集計!J$1,SQLデータ!$C:$C,"<="&届出事由・区分・届出年月日ごと集計!J$2) -> 0 | K62: =COUNTIFS(SQLデータ!$D:$D,"扶養",SQLデータ!$P:$P,1,SQLデータ!$H:$H,届出事由・区分・届出年月日ごと集計!$A62,SQLデータ!$G:$G,届出事由・区分・届出年月日ごと集計!$B62,SQLデータ!$O:$O,1,SQLデータ!$F:$F,"",SQLデータ!$C:$C,">="&届出事由・区分・届出年月日ごと集計!K$1,SQLデータ!$C:$C,"<="&届出事由・区分・届出年月日ごと集計!K$2) -> 0 | L62: =COUNTIFS(SQLデータ!$D:$D,"扶養",SQLデータ!$P:$P,1,SQLデータ!$H:$H,届出事由・区分・届出年月日ごと集計!$A62,SQLデータ!$G:$G,届出事由・区分・届出年月日ごと集計!$B62,SQLデータ!$O:$O,1,SQLデータ!$F:$F,"",SQLデータ!$C:$C,">="&届出事由・区分・届出年月日ごと集計!L$1,SQLデータ!$C:$C,"<="&届出事由・区分・届出年月日ごと集計!L$2) -> 0 | M62: =COUNTIFS(SQLデータ!$D:$D,"扶養",SQLデータ!$P:$P,1,SQLデータ!$H:$H,届出事由・区分・届出年月日ごと集計!$A62,SQLデータ!$G:$G,届出事由・区分・届出年月日ごと集計!$B62,SQLデータ!$O:$O,1,SQLデータ!$F:$F,"",SQLデータ!$C:$C,">="&届出事由・区分・届出年月日ごと集計!M$1,SQLデータ!$C:$C,"<="&届出事由・区分・届出年月日ごと集計!M$2) -> 0 | ... T62: =COUNTIFS(SQLデータ!$D:$D,"扶養",SQLデータ!$P:$P,1,SQLデータ!$H:$H,届出事由・区分・届出年月日ごと集計!$A62,SQLデータ!$G:$G,届出事由・区分・届出年月日ごと集計!$B62,SQLデータ!$O:$O,1,SQLデータ!$F:$F,"",SQLデータ!$C:$C,">="&届出事由・区分・届出年月日ごと集計!T$1,SQLデータ!$C:$C,"<="&届出事由・区分・届出年月日ごと集計!T$2) -> 0
A63: 増 | B63: その他 | C63: 共済あり | D63: =COUNTIFS(SQLデータ!$D:$D,"扶養",SQLデータ!$H:$H,届出事由・区分・届出年月日ごと集計!$A63,SQLデータ!$G:$G,届出事由・区分・届出年月日ごと集計!$B63,SQLデータ!$L:$L,1) -> 2 | F63: =COUNTIFS(SQLデータ!$D:$D,"扶養",SQLデータ!$P:$P,1,SQLデータ!$H:$H,届出事由・区分・届出年月日ごと集計!$A63,SQLデータ!$G:$G,届出事由・区分・届出年月日ごと集計!$B63,SQLデータ!$L:$L,1,SQLデータ!$F:$F,"",SQLデータ!$C:$C,">="&届出事由・区分・届出年月日ごと集計!F$1,SQLデータ!$C:$C,"<="&届出事由・区分・届出年月日ごと集計!F$2) -> 0 | G63: =COUNTIFS(SQLデータ!$D:$D,"扶養",SQLデータ!$P:$P,1,SQLデータ!$H:$H,届出事由・区分・届出年月日ごと集計!$A63,SQLデータ!$G:$G,届出事由・区分・届出年月日ごと集計!$B63,SQLデータ!$L:$L,1,SQLデータ!$F:$F,"",SQLデータ!$C:$C,">="&届出事由・区分・届出年月日ごと集計!G$1,SQLデータ!$C:$C,"<="&届出事由・区分・届出年月日ごと集計!G$2) -> 0 | H63: =COUNTIFS(SQLデータ!$D:$D,"扶養",SQLデータ!$P:$P,1,SQLデータ!$H:$H,届出事由・区分・届出年月日ごと集計!$A63,SQLデータ!$G:$G,届出事由・区分・届出年月日ごと集計!$B63,SQLデータ!$L:$L,1,SQLデータ!$F:$F,"",SQLデータ!$C:$C,">="&届出事由・区分・届出年月日ごと集計!H$1,SQLデータ!$C:$C,"<="&届出事由・区分・届出年月日ごと集計!H$2) -> 0 | I63: =COUNTIFS(SQLデータ!$D:$D,"扶養",SQLデータ!$P:$P,1,SQLデータ!$H:$H,届出事由・区分・届出年月日ごと集計!$A63,SQLデータ!$G:$G,届出事由・区分・届出年月日ごと集計!$B63,SQLデータ!$L:$L,1,SQLデータ!$F:$F,"",SQLデータ!$C:$C,">="&届出事由・区分・届出年月日ごと集計!I$1,SQLデータ!$C:$C,"<="&届出事由・区分・届出年月日ごと集計!I$2) -> 0 | J63: =COUNTIFS(SQLデータ!$D:$D,"扶養",SQLデータ!$P:$P,1,SQLデータ!$H:$H,届出事由・区分・届出年月日ごと集計!$A63,SQLデータ!$G:$G,届出事由・区分・届出年月日ごと集計!$B63,SQLデータ!$L:$L,1,SQLデータ!$F:$F,"",SQLデータ!$C:$C,">="&届出事由・区分・届出年月日ごと集計!J$1,SQLデータ!$C:$C,"<="&届出事由・区分・届出年月日ごと集計!J$2) -> 0 | K63: =COUNTIFS(SQLデータ!$D:$D,"扶養",SQLデータ!$P:$P,1,SQLデータ!$H:$H,届出事由・区分・届出年月日ごと集計!$A63,SQLデータ!$G:$G,届出事由・区分・届出年月日ごと集計!$B63,SQLデータ!$L:$L,1,SQLデータ!$F:$F,"",SQLデータ!$C:$C,">="&届出事由・区分・届出年月日ごと集計!K$1,SQLデータ!$C:$C,"<="&届出事由・区分・届出年月日ごと集計!K$2) -> 0 | L63: =COUNTIFS(SQLデータ!$D:$D,"扶養",SQLデータ!$P:$P,1,SQLデータ!$H:$H,届出事由・区分・届出年月日ごと集計!$A63,SQLデータ!$G:$G,届出事由・区分・届出年月日ごと集計!$B63,SQLデータ!$L:$L,1,SQLデータ!$F:$F,"",SQLデータ!$C:$C,">="&届出事由・区分・届出年月日ごと集計!L$1,SQLデータ!$C:$C,"<="&届出事由・区分・届出年月日ごと集計!L$2) -> 0 | M63: =COUNTIFS(SQLデータ!$D:$D,"扶養",SQLデータ!$P:$P,1,SQLデータ!$H:$H,届出事由・区分・届出年月日ごと集計!$A63,SQLデータ!$G:$G,届出事由・区分・届出年月日ごと集計!$B63,SQLデータ!$L:$L,1,SQLデータ!$F:$F,"",SQLデータ!$C:$C,">="&届出事由・区分・届出年月日ごと集計!M$1,SQLデータ!$C:$C,"<="&届出事由・区分・届出年月日ごと集計!M$2) -> 0 | ... T63: =COUNTIFS(SQLデータ!$D:$D,"扶養",SQLデータ!$P:$P,1,SQLデータ!$H:$H,届出事由・区分・届出年月日ごと集計!$A63,SQLデータ!$G:$G,届出事由・区分・届出年月日ごと集計!$B63,SQLデータ!$L:$L,1,SQLデータ!$F:$F,"",SQLデータ!$C:$C,">="&届出事由・区分・届出年月日ごと集計!T$1,SQLデータ!$C:$C,"<="&届出事由・区分・届出年月日ごと集計!T$2) -> 0
A64: 増 | B64: その他 | C64: 扶養手当あり | D64: =COUNTIFS(SQLデータ!$D:$D,"扶養",SQLデータ!$H:$H,届出事由・区分・届出年月日ごと集計!$A64,SQLデータ!$G:$G,届出事由・区分・届出年月日ごと集計!$B64,SQLデータ!$M:$M,1) -> 1 | F64: =COUNTIFS(SQLデータ!$D:$D,"扶養",SQLデータ!$P:$P,1,SQLデータ!$H:$H,届出事由・区分・届出年月日ごと集計!$A64,SQLデータ!$G:$G,届出事由・区分・届出年月日ごと集計!$B64,SQLデータ!$M:$M,1,SQLデータ!$F:$F,"",SQLデータ!$C:$C,">="&届出事由・区分・届出年月日ごと集計!F$1,SQLデータ!$C:$C,"<="&届出事由・区分・届出年月日ごと集計!F$2) -> 0 | G64: =COUNTIFS(SQLデータ!$D:$D,"扶養",SQLデータ!$P:$P,1,SQLデータ!$H:$H,届出事由・区分・届出年月日ごと集計!$A64,SQLデータ!$G:$G,届出事由・区分・届出年月日ごと集計!$B64,SQLデータ!$M:$M,1,SQLデータ!$F:$F,"",SQLデータ!$C:$C,">="&届出事由・区分・届出年月日ごと集計!G$1,SQLデータ!$C:$C,"<="&届出事由・区分・届出年月日ごと集計!G$2) -> 0 | H64: =COUNTIFS(SQLデータ!$D:$D,"扶養",SQLデータ!$P:$P,1,SQLデータ!$H:$H,届出事由・区分・届出年月日ごと集計!$A64,SQLデータ!$G:$G,届出事由・区分・届出年月日ごと集計!$B64,SQLデータ!$M:$M,1,SQLデータ!$F:$F,"",SQLデータ!$C:$C,">="&届出事由・区分・届出年月日ごと集計!H$1,SQLデータ!$C:$C,"<="&届出事由・区分・届出年月日ごと集計!H$2) -> 1 | I64: =COUNTIFS(SQLデータ!$D:$D,"扶養",SQLデータ!$P:$P,1,SQLデータ!$H:$H,届出事由・区分・届出年月日ごと集計!$A64,SQLデータ!$G:$G,届出事由・区分・届出年月日ごと集計!$B64,SQLデータ!$M:$M,1,SQLデータ!$F:$F,"",SQLデータ!$C:$C,">="&届出事由・区分・届出年月日ごと集計!I$1,SQLデータ!$C:$C,"<="&届出事由・区分・届出年月日ごと集計!I$2) -> 0 | J64: =COUNTIFS(SQLデータ!$D:$D,"扶養",SQLデータ!$P:$P,1,SQLデータ!$H:$H,届出事由・区分・届出年月日ごと集計!$A64,SQLデータ!$G:$G,届出事由・区分・届出年月日ごと集計!$B64,SQLデータ!$M:$M,1,SQLデータ!$F:$F,"",SQLデータ!$C:$C,">="&届出事由・区分・届出年月日ごと集計!J$1,SQLデータ!$C:$C,"<="&届出事由・区分・届出年月日ごと集計!J$2) -> 0 | K64: =COUNTIFS(SQLデータ!$D:$D,"扶養",SQLデータ!$P:$P,1,SQLデータ!$H:$H,届出事由・区分・届出年月日ごと集計!$A64,SQLデータ!$G:$G,届出事由・区分・届出年月日ごと集計!$B64,SQLデータ!$M:$M,1,SQLデータ!$F:$F,"",SQLデータ!$C:$C,">="&届出事由・区分・届出年月日ごと集計!K$1,SQLデータ!$C:$C,"<="&届出事由・区分・届出年月日ごと集計!K$2) -> 0 | L64: =COUNTIFS(SQLデータ!$D:$D,"扶養",SQLデータ!$P:$P,1,SQLデータ!$H:$H,届出事由・区分・届出年月日ごと集計!$A64,SQLデータ!$G:$G,届出事由・区分・届出年月日ごと集計!$B64,SQLデータ!$M:$M,1,SQLデータ!$F:$F,"",SQLデータ!$C:$C,">="&届出事由・区分・届出年月日ごと集計!L$1,SQLデータ!$C:$C,"<="&届出事由・区分・届出年月日ごと集計!L$2) -> 0 | M64: =COUNTIFS(SQLデータ!$D:$D,"扶養",SQLデータ!$P:$P,1,SQLデータ!$H:$H,届出事由・区分・届出年月日ごと集計!$A64,SQLデータ!$G:$G,届出事由・区分・届出年月日ごと集計!$B64,SQLデータ!$M:$M,1,SQLデータ!$F:$F,"",SQLデータ!$C:$C,">="&届出事由・区分・届出年月日ごと集計!M$1,SQLデータ!$C:$C,"<="&届出事由・区分・届出年月日ごと集計!M$2) -> 0 | ... T64: =COUNTIFS(SQLデータ!$D:$D,"扶養",SQLデータ!$P:$P,1,SQLデータ!$H:$H,届出事由・区分・届出年月日ごと集計!$A64,SQLデータ!$G:$G,届出事由・区分・届出年月日ごと集計!$B64,SQLデータ!$M:$M,1,SQLデータ!$F:$F,"",SQLデータ!$C:$C,">="&届出事由・区分・届出年月日ごと集計!T$1,SQLデータ!$C:$C,"<="&届出事由・区分・届出年月日ごと集計!T$2) -> 0
A65: 増 | B65: その他 | C65: 税控除のみ | D65: =COUNTIFS(SQLデータ!$D:$D,"扶養",SQLデータ!$H:$H,届出事由・区分・届出年月日ごと集計!$A65,SQLデータ!$G:$G,届出事由・区分・届出年月日ごと集計!$B65,SQLデータ!$N:$N,1) -> 1 | F65: =COUNTIFS(SQLデータ!$D:$D,"扶養",SQLデータ!$P:$P,1,SQLデータ!$H:$H,届出事由・区分・届出年月日ごと集計!$A65,SQLデータ!$G:$G,届出事由・区分・届出年月日ごと集計!$B65,SQLデータ!$N:$N,1,SQLデータ!$F:$F,"",SQLデータ!$C:$C,">="&届出事由・区分・届出年月日ごと集計!F$1,SQLデータ!$C:$C,"<="&届出事由・区分・届出年月日ごと集計!F$2) -> 0 | G65: =COUNTIFS(SQLデータ!$D:$D,"扶養",SQLデータ!$P:$P,1,SQLデータ!$H:$H,届出事由・区分・届出年月日ごと集計!$A65,SQLデータ!$G:$G,届出事由・区分・届出年月日ごと集計!$B65,SQLデータ!$N:$N,1,SQLデータ!$F:$F,"",SQLデータ!$C:$C,">="&届出事由・区分・届出年月日ごと集計!G$1,SQLデータ!$C:$C,"<="&届出事由・区分・届出年月日ごと集計!G$2) -> 0 | H65: =COUNTIFS(SQLデータ!$D:$D,"扶養",SQLデータ!$P:$P,1,SQLデータ!$H:$H,届出事由・区分・届出年月日ごと集計!$A65,SQLデータ!$G:$G,届出事由・区分・届出年月日ごと集計!$B65,SQLデータ!$N:$N,1,SQLデータ!$F:$F,"",SQLデータ!$C:$C,">="&届出事由・区分・届出年月日ごと集計!H$1,SQLデータ!$C:$C,"<="&届出事由・区分・届出年月日ごと集計!H$2) -> 0 | I65: =COUNTIFS(SQLデータ!$D:$D,"扶養",SQLデータ!$P:$P,1,SQLデータ!$H:$H,届出事由・区分・届出年月日ごと集計!$A65,SQLデータ!$G:$G,届出事由・区分・届出年月日ごと集計!$B65,SQLデータ!$N:$N,1,SQLデータ!$F:$F,"",SQLデータ!$C:$C,">="&届出事由・区分・届出年月日ごと集計!I$1,SQLデータ!$C:$C,"<="&届出事由・区分・届出年月日ごと集計!I$2) -> 0 | J65: =COUNTIFS(SQLデータ!$D:$D,"扶養",SQLデータ!$P:$P,1,SQLデータ!$H:$H,届出事由・区分・届出年月日ごと集計!$A65,SQLデータ!$G:$G,届出事由・区分・届出年月日ごと集計!$B65,SQLデータ!$N:$N,1,SQLデータ!$F:$F,"",SQLデータ!$C:$C,">="&届出事由・区分・届出年月日ごと集計!J$1,SQLデータ!$C:$C,"<="&届出事由・区分・届出年月日ごと集計!J$2) -> 0 | K65: =COUNTIFS(SQLデータ!$D:$D,"扶養",SQLデータ!$P:$P,1,SQLデータ!$H:$H,届出事由・区分・届出年月日ごと集計!$A65,SQLデータ!$G:$G,届出事由・区分・届出年月日ごと集計!$B65,SQLデータ!$N:$N,1,SQLデータ!$F:$F,"",SQLデータ!$C:$C,">="&届出事由・区分・届出年月日ごと集計!K$1,SQLデータ!$C:$C,"<="&届出事由・区分・届出年月日ごと集計!K$2) -> 0 | L65: =COUNTIFS(SQLデータ!$D:$D,"扶養",SQLデータ!$P:$P,1,SQLデータ!$H:$H,届出事由・区分・届出年月日ごと集計!$A65,SQLデータ!$G:$G,届出事由・区分・届出年月日ごと集計!$B65,SQLデータ!$N:$N,1,SQLデータ!$F:$F,"",SQLデータ!$C:$C,">="&届出事由・区分・届出年月日ごと集計!L$1,SQLデータ!$C:$C,"<="&届出事由・区分・届出年月日ごと集計!L$2) -> 0 | M65: =COUNTIFS(SQLデータ!$D:$D,"扶養",SQLデータ!$P:$P,1,SQLデータ!$H:$H,届出事由・区分・届出年月日ごと集計!$A65,SQLデータ!$G:$G,届出事由・区分・届出年月日ごと集計!$B65,SQLデータ!$N:$N,1,SQLデータ!$F:$F,"",SQLデータ!$C:$C,">="&届出事由・区分・届出年月日ごと集計!M$1,SQLデータ!$C:$C,"<="&届出事由・区分・届出年月日ごと集計!M$2) -> 0 | ... T65: =COUNTIFS(SQLデータ!$D:$D,"扶養",SQLデータ!$P:$P,1,SQLデータ!$H:$H,届出事由・区分・届出年月日ごと集計!$A65,SQLデータ!$G:$G,届出事由・区分・届出年月日ごと集計!$B65,SQLデータ!$N:$N,1,SQLデータ!$F:$F,"",SQLデータ!$C:$C,">="&届出事由・区分・届出年月日ごと集計!T$1,SQLデータ!$C:$C,"<="&届出事由・区分・届出年月日ごと集計!T$2) -> 0
A66: 増 | B66: その他 | C66: 本人税のみ | D66: =COUNTIFS(SQLデータ!$D:$D,"扶養",SQLデータ!$H:$H,届出事由・区分・届出年月日ごと集計!$A66,SQLデータ!$G:$G,届出事由・区分・届出年月日ごと集計!$B66,SQLデータ!$O:$O,1) -> 0 | F66: =COUNTIFS(SQLデータ!$D:$D,"扶養",SQLデータ!$P:$P,1,SQLデータ!$H:$H,届出事由・区分・届出年月日ごと集計!$A66,SQLデータ!$G:$G,届出事由・区分・届出年月日ごと集計!$B66,SQLデータ!$O:$O,1,SQLデータ!$F:$F,"",SQLデータ!$C:$C,">="&届出事由・区分・届出年月日ごと集計!F$1,SQLデータ!$C:$C,"<="&届出事由・区分・届出年月日ごと集計!F$2) -> 0 | G66: =COUNTIFS(SQLデータ!$D:$D,"扶養",SQLデータ!$P:$P,1,SQLデータ!$H:$H,届出事由・区分・届出年月日ごと集計!$A66,SQLデータ!$G:$G,届出事由・区分・届出年月日ごと集計!$B66,SQLデータ!$O:$O,1,SQLデータ!$F:$F,"",SQLデータ!$C:$C,">="&届出事由・区分・届出年月日ごと集計!G$1,SQLデータ!$C:$C,"<="&届出事由・区分・届出年月日ごと集計!G$2) -> 0 | H66: =COUNTIFS(SQLデータ!$D:$D,"扶養",SQLデータ!$P:$P,1,SQLデータ!$H:$H,届出事由・区分・届出年月日ごと集計!$A66,SQLデータ!$G:$G,届出事由・区分・届出年月日ごと集計!$B66,SQLデータ!$O:$O,1,SQLデータ!$F:$F,"",SQLデータ!$C:$C,">="&届出事由・区分・届出年月日ごと集計!H$1,SQLデータ!$C:$C,"<="&届出事由・区分・届出年月日ごと集計!H$2) -> 0 | I66: =COUNTIFS(SQLデータ!$D:$D,"扶養",SQLデータ!$P:$P,1,SQLデータ!$H:$H,届出事由・区分・届出年月日ごと集計!$A66,SQLデータ!$G:$G,届出事由・区分・届出年月日ごと集計!$B66,SQLデータ!$O:$O,1,SQLデータ!$F:$F,"",SQLデータ!$C:$C,">="&届出事由・区分・届出年月日ごと集計!I$1,SQLデータ!$C:$C,"<="&届出事由・区分・届出年月日ごと集計!I$2) -> 0 | J66: =COUNTIFS(SQLデータ!$D:$D,"扶養",SQLデータ!$P:$P,1,SQLデータ!$H:$H,届出事由・区分・届出年月日ごと集計!$A66,SQLデータ!$G:$G,届出事由・区分・届出年月日ごと集計!$B66,SQLデータ!$O:$O,1,SQLデータ!$F:$F,"",SQLデータ!$C:$C,">="&届出事由・区分・届出年月日ごと集計!J$1,SQLデータ!$C:$C,"<="&届出事由・区分・届出年月日ごと集計!J$2) -> 0 | K66: =COUNTIFS(SQLデータ!$D:$D,"扶養",SQLデータ!$P:$P,1,SQLデータ!$H:$H,届出事由・区分・届出年月日ごと集計!$A66,SQLデータ!$G:$G,届出事由・区分・届出年月日ごと集計!$B66,SQLデータ!$O:$O,1,SQLデータ!$F:$F,"",SQLデータ!$C:$C,">="&届出事由・区分・届出年月日ごと集計!K$1,SQLデータ!$C:$C,"<="&届出事由・区分・届出年月日ごと集計!K$2) -> 0 | L66: =COUNTIFS(SQLデータ!$D:$D,"扶養",SQLデータ!$P:$P,1,SQLデータ!$H:$H,届出事由・区分・届出年月日ごと集計!$A66,SQLデータ!$G:$G,届出事由・区分・届出年月日ごと集計!$B66,SQLデータ!$O:$O,1,SQLデータ!$F:$F,"",SQLデータ!$C:$C,">="&届出事由・区分・届出年月日ごと集計!L$1,SQLデータ!$C:$C,"<="&届出事由・区分・届出年月日ごと集計!L$2) -> 0 | M66: =COUNTIFS(SQLデータ!$D:$D,"扶養",SQLデータ!$P:$P,1,SQLデータ!$H:$H,届出事由・区分・届出年月日ごと集計!$A66,SQLデータ!$G:$G,届出事由・区分・届出年月日ごと集計!$B66,SQLデータ!$O:$O,1,SQLデータ!$F:$F,"",SQLデータ!$C:$C,">="&届出事由・区分・届出年月日ごと集計!M$1,SQLデータ!$C:$C,"<="&届出事由・区分・届出年月日ごと集計!M$2) -> 0 | ... T66: =COUNTIFS(SQLデータ!$D:$D,"扶養",SQLデータ!$P:$P,1,SQLデータ!$H:$H,届出事由・区分・届出年月日ごと集計!$A66,SQLデータ!$G:$G,届出事由・区分・届出年月日ごと集計!$B66,SQLデータ!$O:$O,1,SQLデータ!$F:$F,"",SQLデータ!$C:$C,">="&届出事由・区分・届出年月日ごと集計!T$1,SQLデータ!$C:$C,"<="&届出事由・区分・届出年月日ごと集計!T$2) -> 0
A67: 減 | B67: 離婚 | C67: 共済あり | D67: =COUNTIFS(SQLデータ!$D:$D,"扶養",SQLデータ!$H:$H,届出事由・区分・届出年月日ごと集計!$A67,SQLデータ!$G:$G,届出事由・区分・届出年月日ごと集計!$B67,SQLデータ!$L:$L,1) -> 2 | F67: =COUNTIFS(SQLデータ!$D:$D,"扶養",SQLデータ!$P:$P,1,SQLデータ!$H:$H,届出事由・区分・届出年月日ごと集計!$A67,SQLデータ!$G:$G,届出事由・区分・届出年月日ごと集計!$B67,SQLデータ!$L:$L,1,SQLデータ!$F:$F,"",SQLデータ!$C:$C,">="&届出事由・区分・届出年月日ごと集計!F$1,SQLデータ!$C:$C,"<="&届出事由・区分・届出年月日ごと集計!F$2) -> 1 | G67: =COUNTIFS(SQLデータ!$D:$D,"扶養",SQLデータ!$P:$P,1,SQLデータ!$H:$H,届出事由・区分・届出年月日ごと集計!$A67,SQLデータ!$G:$G,届出事由・区分・届出年月日ごと集計!$B67,SQLデータ!$L:$L,1,SQLデータ!$F:$F,"",SQLデータ!$C:$C,">="&届出事由・区分・届出年月日ごと集計!G$1,SQLデータ!$C:$C,"<="&届出事由・区分・届出年月日ごと集計!G$2) -> 1 | H67: =COUNTIFS(SQLデータ!$D:$D,"扶養",SQLデータ!$P:$P,1,SQLデータ!$H:$H,届出事由・区分・届出年月日ごと集計!$A67,SQLデータ!$G:$G,届出事由・区分・届出年月日ごと集計!$B67,SQLデータ!$L:$L,1,SQLデータ!$F:$F,"",SQLデータ!$C:$C,">="&届出事由・区分・届出年月日ごと集計!H$1,SQLデータ!$C:$C,"<="&届出事由・区分・届出年月日ごと集計!H$2) -> 0 | I67: =COUNTIFS(SQLデータ!$D:$D,"扶養",SQLデータ!$P:$P,1,SQLデータ!$H:$H,届出事由・区分・届出年月日ごと集計!$A67,SQLデータ!$G:$G,届出事由・区分・届出年月日ごと集計!$B67,SQLデータ!$L:$L,1,SQLデータ!$F:$F,"",SQLデータ!$C:$C,">="&届出事由・区分・届出年月日ごと集計!I$1,SQLデータ!$C:$C,"<="&届出事由・区分・届出年月日ごと集計!I$2) -> 0 | J67: =COUNTIFS(SQLデータ!$D:$D,"扶養",SQLデータ!$P:$P,1,SQLデータ!$H:$H,届出事由・区分・届出年月日ごと集計!$A67,SQLデータ!$G:$G,届出事由・区分・届出年月日ごと集計!$B67,SQLデータ!$L:$L,1,SQLデータ!$F:$F,"",SQLデータ!$C:$C,">="&届出事由・区分・届出年月日ごと集計!J$1,SQLデータ!$C:$C,"<="&届出事由・区分・届出年月日ごと集計!J$2) -> 0 | K67: =COUNTIFS(SQLデータ!$D:$D,"扶養",SQLデータ!$P:$P,1,SQLデータ!$H:$H,届出事由・区分・届出年月日ごと集計!$A67,SQLデータ!$G:$G,届出事由・区分・届出年月日ごと集計!$B67,SQLデータ!$L:$L,1,SQLデータ!$F:$F,"",SQLデータ!$C:$C,">="&届出事由・区分・届出年月日ごと集計!K$1,SQLデータ!$C:$C,"<="&届出事由・区分・届出年月日ごと集計!K$2) -> 0 | L67: =COUNTIFS(SQLデータ!$D:$D,"扶養",SQLデータ!$P:$P,1,SQLデータ!$H:$H,届出事由・区分・届出年月日ごと集計!$A67,SQLデータ!$G:$G,届出事由・区分・届出年月日ごと集計!$B67,SQLデータ!$L:$L,1,SQLデータ!$F:$F,"",SQLデータ!$C:$C,">="&届出事由・区分・届出年月日ごと集計!L$1,SQLデータ!$C:$C,"<="&届出事由・区分・届出年月日ごと集計!L$2) -> 0 | M67: =COUNTIFS(SQLデータ!$D:$D,"扶養",SQLデータ!$P:$P,1,SQLデータ!$H:$H,届出事由・区分・届出年月日ごと集計!$A67,SQLデータ!$G:$G,届出事由・区分・届出年月日ごと集計!$B67,SQLデータ!$L:$L,1,SQLデータ!$F:$F,"",SQLデータ!$C:$C,">="&届出事由・区分・届出年月日ごと集計!M$1,SQLデータ!$C:$C,"<="&届出事由・区分・届出年月日ごと集計!M$2) -> 0 | ... T67: =COUNTIFS(SQLデータ!$D:$D,"扶養",SQLデータ!$P:$P,1,SQLデータ!$H:$H,届出事由・区分・届出年月日ごと集計!$A67,SQLデータ!$G:$G,届出事由・区分・届出年月日ごと集計!$B67,SQLデータ!$L:$L,1,SQLデータ!$F:$F,"",SQLデータ!$C:$C,">="&届出事由・区分・届出年月日ごと集計!T$1,SQLデータ!$C:$C,"<="&届出事由・区分・届出年月日ごと集計!T$2) -> 0
A68: 減 | B68: 離婚 | C68: 扶養手当あり | D68: =COUNTIFS(SQLデータ!$D:$D,"扶養",SQLデータ!$H:$H,届出事由・区分・届出年月日ごと集計!$A68,SQLデータ!$G:$G,届出事由・区分・届出年月日ごと集計!$B68,SQLデータ!$M:$M,1) -> 0 | F68: =COUNTIFS(SQLデータ!$D:$D,"扶養",SQLデータ!$P:$P,1,SQLデータ!$H:$H,届出事由・区分・届出年月日ごと集計!$A68,SQLデータ!$G:$G,届出事由・区分・届出年月日ごと集計!$B68,SQLデータ!$M:$M,1,SQLデータ!$F:$F,"",SQLデータ!$C:$C,">="&届出事由・区分・届出年月日ごと集計!F$1,SQLデータ!$C:$C,"<="&届出事由・区分・届出年月日ごと集計!F$2) -> 0 | G68: =COUNTIFS(SQLデータ!$D:$D,"扶養",SQLデータ!$P:$P,1,SQLデータ!$H:$H,届出事由・区分・届出年月日ごと集計!$A68,SQLデータ!$G:$G,届出事由・区分・届出年月日ごと集計!$B68,SQLデータ!$M:$M,1,SQLデータ!$F:$F,"",SQLデータ!$C:$C,">="&届出事由・区分・届出年月日ごと集計!G$1,SQLデータ!$C:$C,"<="&届出事由・区分・届出年月日ごと集計!G$2) -> 0 | H68: =COUNTIFS(SQLデータ!$D:$D,"扶養",SQLデータ!$P:$P,1,SQLデータ!$H:$H,届出事由・区分・届出年月日ごと集計!$A68,SQLデータ!$G:$G,届出事由・区分・届出年月日ごと集計!$B68,SQLデータ!$M:$M,1,SQLデータ!$F:$F,"",SQLデータ!$C:$C,">="&届出事由・区分・届出年月日ごと集計!H$1,SQLデータ!$C:$C,"<="&届出事由・区分・届出年月日ごと集計!H$2) -> 0 | I68: =COUNTIFS(SQLデータ!$D:$D,"扶養",SQLデータ!$P:$P,1,SQLデータ!$H:$H,届出事由・区分・届出年月日ごと集計!$A68,SQLデータ!$G:$G,届出事由・区分・届出年月日ごと集計!$B68,SQLデータ!$M:$M,1,SQLデータ!$F:$F,"",SQLデータ!$C:$C,">="&届出事由・区分・届出年月日ごと集計!I$1,SQLデータ!$C:$C,"<="&届出事由・区分・届出年月日ごと集計!I$2) -> 0 | J68: =COUNTIFS(SQLデータ!$D:$D,"扶養",SQLデータ!$P:$P,1,SQLデータ!$H:$H,届出事由・区分・届出年月日ごと集計!$A68,SQLデータ!$G:$G,届出事由・区分・届出年月日ごと集計!$B68,SQLデータ!$M:$M,1,SQLデータ!$F:$F,"",SQLデータ!$C:$C,">="&届出事由・区分・届出年月日ごと集計!J$1,SQLデータ!$C:$C,"<="&届出事由・区分・届出年月日ごと集計!J$2) -> 0 | K68: =COUNTIFS(SQLデータ!$D:$D,"扶養",SQLデータ!$P:$P,1,SQLデータ!$H:$H,届出事由・区分・届出年月日ごと集計!$A68,SQLデータ!$G:$G,届出事由・区分・届出年月日ごと集計!$B68,SQLデータ!$M:$M,1,SQLデータ!$F:$F,"",SQLデータ!$C:$C,">="&届出事由・区分・届出年月日ごと集計!K$1,SQLデータ!$C:$C,"<="&届出事由・区分・届出年月日ごと集計!K$2) -> 0 | L68: =COUNTIFS(SQLデータ!$D:$D,"扶養",SQLデータ!$P:$P,1,SQLデータ!$H:$H,届出事由・区分・届出年月日ごと集計!$A68,SQLデータ!$G:$G,届出事由・区分・届出年月日ごと集計!$B68,SQLデータ!$M:$M,1,SQLデータ!$F:$F,"",SQLデータ!$C:$C,">="&届出事由・区分・届出年月日ごと集計!L$1,SQLデータ!$C:$C,"<="&届出事由・区分・届出年月日ごと集計!L$2) -> 0 | M68: =COUNTIFS(SQLデータ!$D:$D,"扶養",SQLデータ!$P:$P,1,SQLデータ!$H:$H,届出事由・区分・届出年月日ごと集計!$A68,SQLデータ!$G:$G,届出事由・区分・届出年月日ごと集計!$B68,SQLデータ!$M:$M,1,SQLデータ!$F:$F,"",SQLデータ!$C:$C,">="&届出事由・区分・届出年月日ごと集計!M$1,SQLデータ!$C:$C,"<="&届出事由・区分・届出年月日ごと集計!M$2) -> 0 | ... T68: =COUNTIFS(SQLデータ!$D:$D,"扶養",SQLデータ!$P:$P,1,SQLデータ!$H:$H,届出事由・区分・届出年月日ごと集計!$A68,SQLデータ!$G:$G,届出事由・区分・届出年月日ごと集計!$B68,SQLデータ!$M:$M,1,SQLデータ!$F:$F,"",SQLデータ!$C:$C,">="&届出事由・区分・届出年月日ごと集計!T$1,SQLデータ!$C:$C,"<="&届出事由・区分・届出年月日ごと集計!T$2) -> 0
